Workbook

Sheet Assumption
B1: 센텀C부지 복합개발사업 재무모델 | I1: 입력값 | J1: 파란 글씨 = 입력(하드코딩)
B2: Assumption (단위: 백만원) | I2: 수식 | J2: 검정 = 계산 수식
C3: =IF(ABS(CF!$C$159)<1,"OK","Error") -> OK | D3: =IF(SUMPRODUCT(ABS($F$544:$F$553))<1,"OK","Run Macro") -> OK | E3: =IF(MIN(CF!$E$159:$EF$159)>-0.5,"OK","Shortage") -> OK | F3: =IF(SUM(CF!$E$153:$EF$153)-SUM(CF!$E$116:$EF$116)<1,"OK","PF한도부족") -> OK | I3: 연결 | J3: 초록 = CF 시트 연결
C4: Balance Check | D4: Macro Check | E4: Shortage Check | F4: Cash Check | I4: Macro | J4: 노랑 = Macro Paste 값(순환참조 차단)
A6: 프로젝트 일정 (계획)
B8: 리츠설립일 | D8: Date | E8: 46112
B9: 매매계약체결 준비기간 | D9: Months | E9: 3
B10: 토지매매계약체결일 | D10: Date | E10: =EOMONTH($E$8,$E$9) -> 46203
B11: 인허가 준비기간 | D11: Months | E11: 14
B12: 인허가 완료일 | D12: Date | E12: =EOMONTH($E$10,$E$11) -> 46630
B13: 공사준비기간 | D13: Months | E13: 1
B14: 착공일 | D14: Date | E14: =EOMONTH($E$12,$E$13) -> 46660
B15: 공사기간 | D15: Months | E15: 42
B16: 준공일 | D16: Date | E16: =EOMONTH($E$14,$E$15-1) -> 47907
B17: 운영준비기간 | D17: Months | E17: 1
B18: 운영개시일 | D18: Date | E18: =EOMONTH($E$16,$E$17) -> 47938
B19: 운영기간 | D19: Months | E19: 60
B20: 운영종료일 | D20: Date | E20: =EOMONTH($E$18,$E$19-1) -> 49734
B21: 처분준비기간 | D21: Months | E21: 0
B22: 처분일 | D22: Date | E22: =EOMONTH($E$20,$E$21) -> 49734
B23: 청산준비기간 | D23: Months | E23: 3
B24: 리츠청산일 | D24: Date | E24: =EOMONTH($E$22,$E$23) -> 49826
B25: 개발기간(설립~준공) | D25: Years | E25: =((YEAR($E$16)-YEAR($E$8))*12+MONTH($E$16)-MONTH($E$8)+1)/12 -> 5
B26: 리츠운용기간(운영개시~청산) | D26: Years | E26: =((YEAR($E$24)-YEAR($E$18))*12+MONTH($E$24)-MONTH($E$18)+1)/12 -> 5.25
A28: Results
B30: IRR On Equity (보통주) | E30: =CF!$C$171 -> 0.20392787
B31: IRR On Equity (우선주) | E31: =CF!$C$172 -> 0.05
B32: IRR On Equity (전체) | E32: =CF!$C$173 -> 0.12111635
A34: 사업개요
B36: (1) 사 업 명 | D36: 센텀C부지 복합개발사업
B37: (2) 대 지 위 치 | D37: 부산광역시 해운대 우동 1492
B38: (3) 지 역 지 구 | D38: 중심상업지역/지구단위계획구역
B39: (4) 용 도 | D39: 관광숙박시설(호텔, 콘도), 노유자시설(시니어레지던스), 문화집회시설(공연장 등), 판매시설
B40: (5) 건축연면적 | E40: 평 환산계수 | F40: 0.3025
B42: 연면적 | C42: 지상연면적 | D42: 178919.43 | E42: =$D$42*$F$40 -> 54123.128
C43: 지하연면적 | D43: 91531.54 | E43: =$D$43*$F$40 -> 27688.291
C44: 전체연면적 | D44: =$D$42+$D$43 -> 270450.97 | E44: =$D$44*$F$40 -> 81811.418 | F44: =ABS($D$44-$C$56)<1 -> TRUE | G44: =ABS($D$44*$F$40-$C$55)<1 -> TRUE
B46: 용도별 연면적 | C46: 시니어 레지던스 | D46: =SUMIF($D$53:$W$53,"시니어 레지던스",$D$56:$W$56) -> 76060.08 | E46: =SUMIF($D$53:$W$53,"시니어 레지던스",$D$55:$W$55) -> 23008.174
C47: 레지던스 | D47: =SUMIF($D$53:$W$53,"레지던스",$D$56:$W$56) -> 44693.91 | E47: =SUMIF($D$53:$W$53,"레지던스",$D$55:$W$55) -> 13519.908
C48: 호텔 | D48: =SUMIF($D$53:$W$53,"호텔",$D$56:$W$56) -> 70374.3 | E48: =SUMIF($D$53:$W$53,"호텔",$D$55:$W$55) -> 21288.226
C49: 오피스 | D49: =SUMIF($D$53:$W$53,"오피스",$D$56:$W$56) -> 46433.07 | E49: =SUMIF($D$53:$W$53,"오피스",$D$55:$W$55) -> 14046.004
C50: 부대시설 | D50: =SUMIF($D$53:$W$53,"부대시설",$D$56:$W$56) -> 32889.63 | E50: =SUMIF($D$53:$W$53,"부대시설",$D$55:$W$55) -> 9949.1131
C51: 합계 | D51: =SUM(D46:D50) -> 270450.99 | E51: =SUM(E46:E50) -> 81811.424 | F51: =ABS(D51-$D$44)<1 -> TRUE | G51: =ABS(E51-$C$55)<0.1 -> TRUE
D53: 시니어 레지던스 | E53: 시니어 레지던스 | F53: 부대시설 | G53: 부대시설 | H53: 시니어 레지던스 | J53: 레지던스 | K53: 레지던스 | L53: 호텔 | M53: 호텔 | N53: 호텔 | O53: 호텔 | P53: 호텔 | Q53: 호텔 | R53: 오피스 | S53: 호텔 | U53: 부대시설 | V53: 부대시설 | W53: 부대시설
B54: 구분 | C54: 총계 | D54: 시니어 | E54: 시니어 부대 | F54: 국제학교 | G54: 영어유치원 | H54: SSZ | I54: B동 계 | J54: 가족호텔 | K54: 가족호텔 부대 멤버전용 | L54: 호텔 | M54: 컨벤션 | N54: 호텔부대_피트니스&수영장 | O54: 호텔부대_파인다이닝 | P54: 호텔부대_휴게 | Q54: 호텔 BOH | R54: 오피스 | S54: SSZ | T54: A동 계 | U54: 메디컬 | V54: 스파2.0 | W54: 판매시설 | X54: 부대시설 계 | Y54: MEP | Z54: 주차장
B55: 연면적(평) | C55: =I55+T55+X55 -> 81811.424 | D55: =D56*$F$40 -> 20475.245 | E55: =E56*$F$40 -> 2338.198 | F55: =F56*$F$40 -> 1425.6281 | G55: =G56*$F$40 -> 597.16525 | H55: =H56*$F$40 -> 194.73135 | I55: =SUM(D55:H55) -> 25030.967 | J55: =J56*$F$40 -> 10714.913 | K55: =K56*$F$40 -> 2804.9948 | L55: =L56*$F$40 -> 11246.593 | M55: =M56*$F$40 -> 2165.776 | N55: =N56*$F$40 -> 1829.3446 | O55: =O56*$F$40 -> 1274.2329 | P55: =P56*$F$40 -> 1063.9651 | Q55: =Q56*$F$40 -> 3250.7679 | ... S55: =S56*$F$40 -> 457.54638 | T55: =SUM(J55:S55) -> 48854.137 | U55: =U56*$F$40 -> 1673.7446 | V55: =V56*$F$40 -> 2443.3318 | W55: =W56*$F$40 -> 3809.2434 | X55: =SUM(U55:W55) -> 7926.3198
B56: 연면적(㎡) | C56: =I56+T56+X56 -> 270450.99 | D56: 67686.76 | E56: 7729.58 | F56: 4712.82 | G56: 1974.1 | H56: 643.74 | I56: =SUM(D56:H56) -> 82747 | J56: 35421.2 | K56: 9272.71 | L56: 37178.82 | M56: 7159.59 | N56: 6047.42 | O56: 4212.34 | P56: 3517.24 | Q56: 10746.34 | R56: 46433.07 | S56: 1512.55 | T56: =SUM(J56:S56) -> 161501.28 | U56: 5533.04 | V56: 8077.13 | W56: 12592.54 | X56: =SUM(U56:W56) -> 26202.71
B57: 구성비 | C57: =C55/$C$55 -> 1 | D57: =D55/$C$55 -> 0.25027366 | E57: =E55/$C$55 -> 0.028580335 | F57: =F55/$C$55 -> 0.017425782 | G57: =G55/$C$55 -> 0.0072992892 | H57: =H55/$C$55 -> 0.0023802464 | I57: =I55/$C$55 -> 0.30595932 | J57: =J55/$C$55 -> 0.13097086 | ... X57: =X55/$C$55 -> 0.096885243
B58: 전용면적 | C58: =I58+T58+X58 -> 40534.76 | D58: 10848.89 | E58: 1218.17 | F58: 591.99 | G58: 213.87 | H58: 0 | I58: =SUM(D58:H58) -> 12872.92 | J58: 5174.57 | K58: 1462.29 | L58: 5186.06 | M58: 847 | N58: 910.53 | O58: 535.43 | P58: 514.25 | Q58: 1870.66 | R58: 7377.98 | S58: 0 | T58: =SUM(J58:S58) -> 23878.77 | U58: 948.64 | V58: 1270.5 | W58: 1563.93 | X58: =SUM(U58:W58) -> 3783.07
B59: 공용면적 | C59: =I59+T59+X59 -> 18313.26 | D59: 3879.26 | E59: 463.73 | F59: 433.48 | G59: 215.68 | H59: 140.07 | I59: =SUM(D59:H59) -> 5132.22 | J59: 2532.63 | K59: 555.39 | L59: 2903.78 | M59: 710.88 | N59: 405.35 | O59: 381.15 | P59: 251.08 | Q59: 467.67 | R59: 2725.53 | S59: 329.12 | T59: =SUM(J59:S59) -> 11262.58 | U59: 255.31 | V59: 487.03 | W59: 1176.12 | X59: =SUM(U59:W59) -> 1918.46
B60: 시설면적 | C60: =I60+T60+X60+Y60+Z60 -> 81811.424 | D60: =D58+D59 -> 14728.15 | E60: =E58+E59 -> 1681.9 | F60: =F58+F59 -> 1025.47 | G60: =G58+G59 -> 429.55 | H60: =H58+H59 -> 140.07 | I60: =SUM(D60:H60) -> 18005.14 | J60: =J58+J59 -> 7707.2 | K60: =K58+K59 -> 2017.68 | L60: =L58+L59 -> 8089.84 | M60: =M58+M59 -> 1557.88 | N60: =N58+N59 -> 1315.88 | O60: =O58+O59 -> 916.58 | P60: =P58+P59 -> 765.33 | Q60: =Q58+Q59 -> 2338.33 | ... S60: =S58+S59 -> 329.12 | T60: =SUM(J60:S60) -> 35141.35 | U60: =U58+U59 -> 1203.95 | V60: =V58+V59 -> 1757.53 | W60: =W58+W59 -> 2740.05 | X60: =SUM(U60:W60) -> 5701.53 | Y60: 1585.81 | Z60: =$C$55-($I$60+$T$60+$X$60)-$Y$60 -> 21377.594
B61: 구성비 | C61: =C60/$C$60 -> 1 | D61: =D60/$C$60 -> 0.18002559 | E61: =E60/$C$60 -> 0.020558253 | F61: =F60/$C$60 -> 0.012534557 | G61: =G60/$C$60 -> 0.0052504892 | H61: =H60/$C$60 -> 0.0017121081 | I61: =I60/$C$60 -> 0.220081 | J61: =J60/$C$60 -> 0.094206892 | ... Z61: =Z60/$C$60 -> 0.26130329
B62: 주차장 배분 | C62: =I62+T62+X62 -> 21377.594 | D62: =$Z$60*D60/($I$60+$T$60+$X$60) -> 5350.2636 | E62: =$Z$60*E60/($I$60+$T$60+$X$60) -> 610.98022 | F62: =$Z$60*F60/($I$60+$T$60+$X$60) -> 372.5203 | G62: =$Z$60*G60/($I$60+$T$60+$X$60) -> 156.04171 | H62: =$Z$60*H60/($I$60+$T$60+$X$60) -> 50.88293 | I62: =SUM(D62:H62) -> 6540.6887 | J62: =$Z$60*J60/($I$60+$T$60+$X$60) -> 2799.7781 | K62: =$Z$60*K60/($I$60+$T$60+$X$60) -> 732.9583 | L62: =$Z$60*L60/($I$60+$T$60+$X$60) -> 2938.7789 | M62: =$Z$60*M60/($I$60+$T$60+$X$60) -> 565.92774 | N62: =$Z$60*N60/($I$60+$T$60+$X$60) -> 478.01692 | O62: =$Z$60*O60/($I$60+$T$60+$X$60) -> 332.96406 | P62: =$Z$60*P60/($I$60+$T$60+$X$60) -> 278.01979 | Q62: =$Z$60*Q60/($I$60+$T$60+$X$60) -> 849.44014 | ... S62: =$Z$60*S60/($I$60+$T$60+$X$60) -> 119.55872 | T62: =SUM(J62:S62) -> 12765.723 | U62: =$Z$60*U60/($I$60+$T$60+$X$60) -> 437.35634 | V62: =$Z$60*V60/($I$60+$T$60+$X$60) -> 638.45417 | W62: =$Z$60*W60/($I$60+$T$60+$X$60) -> 995.37211 | X62: =SUM(U62:W62) -> 2071.1826
B63: 기계실 배분 | C63: =I63+T63+X63 -> 1585.81 | D63: =$Y$60*D60/($I$60+$T$60+$X$60) -> 396.88757 | E63: =$Y$60*E60/($I$60+$T$60+$X$60) -> 45.323085 | F63: =$Y$60*F60/($I$60+$T$60+$X$60) -> 27.633905 | G63: =$Y$60*G60/($I$60+$T$60+$X$60) -> 11.57532 | H63: =$Y$60*H60/($I$60+$T$60+$X$60) -> 3.7745434 | I63: =SUM(D63:H63) -> 485.19442 | J63: =$Y$60*J60/($I$60+$T$60+$X$60) -> 207.69016 | K63: =$Y$60*K60/($I$60+$T$60+$X$60) -> 54.371534 | L63: =$Y$60*L60/($I$60+$T$60+$X$60) -> 218.00137 | M63: =$Y$60*M60/($I$60+$T$60+$X$60) -> 41.98105 | N63: =$Y$60*N60/($I$60+$T$60+$X$60) -> 35.459743 | O63: =$Y$60*O60/($I$60+$T$60+$X$60) -> 24.699586 | P63: =$Y$60*P60/($I$60+$T$60+$X$60) -> 20.623769 | Q63: =$Y$60*Q60/($I$60+$T$60+$X$60) -> 63.012266 | ... S63: =$Y$60*S60/($I$60+$T$60+$X$60) -> 8.8689779 | T63: =SUM(J63:S63) -> 946.97331 | U63: =$Y$60*U60/($I$60+$T$60+$X$60) -> 32.443504 | V63: =$Y$60*V60/($I$60+$T$60+$X$60) -> 47.361129 | W63: =$Y$60*W60/($I$60+$T$60+$X$60) -> 73.837636 | X63: =SUM(U63:W63) -> 153.64227
B64: 전체 공용면적 | C64: =I64+T64+X64 -> 41276.664 | D64: =D59+D62+D63 -> 9626.4111 | E64: =E59+E62+E63 -> 1120.0333 | F64: =F59+F62+F63 -> 833.6342 | G64: =G59+G62+G63 -> 383.29703 | H64: =H59+H62+H63 -> 194.72747 | I64: =SUM(D64:H64) -> 12158.103 | J64: =J59+J62+J63 -> 5540.0982 | K64: =K59+K62+K63 -> 1342.7198 | L64: =L59+L62+L63 -> 6060.5603 | M64: =M59+M62+M63 -> 1318.7888 | N64: =N59+N62+N63 -> 918.82666 | O64: =O59+O62+O63 -> 738.81364 | P64: =P59+P62+P63 -> 549.72356 | Q64: =Q59+Q62+Q63 -> 1380.1224 | ... S64: =S59+S62+S63 -> 457.5477 | T64: =SUM(J64:S64) -> 24975.276 | U64: =U59+U62+U63 -> 725.10985 | V64: =V59+V62+V63 -> 1172.8453 | W64: =W59+W62+W63 -> 2245.3297 | X64: =SUM(U64:W64) -> 4143.2849
B65: 전용률 | C65: =C58/C55 -> 0.49546576 | D65: =IF(D55=0,0,D58/D55) -> 0.52985398 | E65: =IF(E55=0,0,E58/E55) -> 0.52098669 | F65: =IF(F55=0,0,F58/F55) -> 0.41524856 | G65: =IF(G55=0,0,G58/G55) -> 0.35814207 | H65: =IF(H55=0,0,H58/H55) -> 0 | I65: =IF(I55=0,0,I58/I55) -> 0.51427976 | J65: =IF(J55=0,0,J58/J55) -> 0.48293159 | K65: =IF(K55=0,0,K58/K55) -> 0.52131648 | ... X65: =IF(X55=0,0,X58/X55) -> 0.47727951
B66: 비고 | D66: 270세대 | J66: 92세대 | L66: 257실
B68: (6) 대지면적 | D68: 16515 | E68: =$D$68*$F$40 -> 4995.7875
B70: 구분 | C70: Ratio | D70: 토지면적(㎡) | E70: 토지면적(평)
B71: 시니어 레지던스 | C71: =$E$46/$C$55 -> 0.28123425 | D71: =C71*$D$68 -> 4644.5836 | E71: =C71*$E$68 -> 1404.9865
B72: 서비스드 레지던스 | C72: =$E$47/$C$55 -> 0.16525697 | D72: =C72*$D$68 -> 2729.2188 | E72: =C72*$E$68 -> 825.58868
B73: 호텔 | C73: =$E$48/$C$55 -> 0.26021092 | D73: =C73*$D$68 -> 4297.3833 | E73: =C73*$E$68 -> 1299.9584
B74: 오피스 | C74: =$E$49/$C$55 -> 0.17168756 | D74: =C74*$D$68 -> 2835.42 | E74: =C74*$E$68 -> 857.71456
B75: 부대시설 | C75: =$E$50/$C$55 -> 0.12161031 | D75: =C75*$D$68 -> 2008.3943 | E75: =C75*$E$68 -> 607.53929
B76: 합계 | C76: =SUM(C71:C75) -> 1 | D76: =SUM(D71:D75) -> 16515 | E76: =SUM(E71:E75) -> 4995.7875
A78: Operation
B79: ※ 운영기간 시계열(Index: 운영기간 누적, 입주모집률, OCC, 공실률, 리징비용, 상승률 등)은 CF 시트에서 월별로 계산
A81: 시니어 레지던스
B82: 운영수입 | C82: 세대수 | D82: 세대 | E82: 270 | G82: 보증금 | H82: 일자 | I82: 비중 | J82: 월Key
C83: 보증금 | D83: 백만원/세대 | E83: 2000 | G83: 계약금 | H83: 46477 | I83: 0.1 | J83: =EOMONTH(H83,0) -> 46477
C84: 보증금(100% 기준) | D84: 백만원 | E84: =$E$82*$E$83 -> 540000 | G84: 중도금(1차) | H84: 46842 | I84: 0.2 | J84: =EOMONTH(H84,0) -> 46843
C85: 월임대료 | D85: 천원/세대,월 | E85: 0 | G85: 중도금(2차) | H85: 47208 | I85: 0.2 | J85: =EOMONTH(H85,0) -> 47208
C86: 이용료수익 | D86: 천원/세대,월 | E86: 6000 | G86: 중도금(3차) | H86: 47573 | I86: 0.2 | J86: =EOMONTH(H86,0) -> 47573
C87: 보증금 및 임대료상승률 | D87: % | E87: 0.02 | G87: 잔금 | H87: 47938 | I87: 0.3 | J87: =EOMONTH(H87,0) -> 47938
C88: 보증금 및 임대료상승주기 | D88: 개월 | E88: 12 | G88: 합계 | I88: =SUM(I83:I87) -> 1
C89: 물가상승률 | D89: % | E89: 0.02
C90: 입주모집률 | D90: Y+1 | E90: 0.8
D91: Y+2 | E91: 1
D92: Y+3 이후 | E92: 1
C93: 추가수입(세대관리비등) | D93: 매출액 대비 | E93: 0.15
B94: 운영비용 | C94: ADR | D94: 천원/일 | E94: 200
C95: OCC | D95: % | E95: 0.9
C96: 일반운영비 | D96: 매출대비 % | E96: 0.75
C97: 소모품비 | D97: 매출대비 % | E97: 0.04
A99: 시니어 부대시설
B100: 운영수입 | C100: 보증금 | D100: 백만원 | E100: 1500
C101: 월임대료(전용면적당) | D101: 천원/평,월 | E101: 120
C102: 전용면적 | D102: 평 | E102: =$E$58 -> 1218.17
C103: 월임대료(총) | D103: 백만원/월 | E103: =$E$101*$E$102/1000 -> 146.1804
C104: 보증금 및 임대료상승률 | D104: % | E104: 0.02
C105: 보증금 및 임대료상승주기 | D105: 개월 | E105: 12
C106: 물가상승률 | D106: % | E106: 0.02
A108: 레지던스(휴양콘도미니엄)
B109: 타입 | C109: 전용면적(평) | D109: 세대수(세대) | E109: 보증금(백만원) | F109: ADR(원) | G109: ADR×세대(원/일) | I109: 보증금 | J109: 일자 | K109: 비중 | L109: 월Key
B110: F.H-Suite-1 | C110: 39 | D110: 24 | E110: 2364 | F110: 530888 | G110: =D110*F110 -> 12741312 | I110: 계약금 | J110: 46477 | K110: 0.1 | L110: =EOMONTH(J110,0) -> 46477
B111: F.H-Suite-2 | C111: 43 | D111: 24 | E111: 2592 | F111: 583976 | G111: =D111*F111 -> 14015424 | I111: 중도금(1차) | J111: 46842 | K111: 0.2 | L111: =EOMONTH(J111,0) -> 46843
B112: F.H-E.Suite | C112: 61 | D112: 40 | E112: 3636 | F112: 816750 | G112: =D112*F112 -> 32670000 | I112: 중도금(2차) | J112: 47208 | K112: 0.2 | L112: =EOMONTH(J112,0) -> 47208
B113: PENT-1 | C113: 157 | D113: 3 | E113: 9444 | F113: 2123550 | G113: =D113*F113 -> 6370650 | I113: 중도금(3차) | J113: 47573 | K113: 0.2 | L113: =EOMONTH(J113,0) -> 47573
B114: PENT2 | C114: 301 | D114: 1 | E114: 18036 | F114: 4059248 | G114: =D114*F114 -> 4059248 | I114: 잔금 | J114: 47938 | K114: 0.3 | L114: =EOMONTH(J114,0) -> 47938
B115: 합계 | C115: =SUMPRODUCT(C110:C114,D110:D114) -> 5180 | D115: =SUM(D110:D114) -> 92 | E115: =SUMPRODUCT(D110:D114,E110:E114) -> 310752 | F115: =G115/D115 -> 759311.24 | G115: =SUM(G110:G114) -> 69856634 | I115: 합계 | K115: =SUM(K110:K114) -> 1
...

Sheet CF
A1: 월별 현금흐름 (CF) — 단위: 백만원
A3: ※ 월말 기준. 모든 입력은 Assumption 시트 연결. C열 = 기간 합계(잔액행은 최대값/최종값, IRR행은 연환산 IRR)
A5: 구분 | B5: 단위 | C5: 합계
A6: 월말일자 | E6: =EOMONTH(Assumption!$E$8,0) -> 46112 | F6: =EOMONTH(E6,1) -> 46142 | G6: =EOMONTH(F6,1) -> 46173 | H6: =EOMONTH(G6,1) -> 46203 | I6: =EOMONTH(H6,1) -> 46234 | J6: =EOMONTH(I6,1) -> 46265 | K6: =EOMONTH(J6,1) -> 46295 | L6: =EOMONTH(K6,1) -> 46326 | M6: =EOMONTH(L6,1) -> 46356 | ... EF6: =EOMONTH(EE6,1) -> 50099
A7: 연도 | E7: =YEAR(E6) -> 2026 | F7: =YEAR(F6) -> 2026 | G7: =YEAR(G6) -> 2026 | H7: =YEAR(H6) -> 2026 | I7: =YEAR(I6) -> 2026 | J7: =YEAR(J6) -> 2026 | K7: =YEAR(K6) -> 2026 | L7: =YEAR(L6) -> 2026 | ... EF7: =YEAR(EF6) -> 2037
A8: 월차 | E8: =1 -> 1 | F8: =E8+1 -> 2 | G8: =F8+1 -> 3 | H8: =G8+1 -> 4 | I8: =H8+1 -> 5 | J8: =I8+1 -> 6 | K8: =J8+1 -> 7 | L8: =K8+1 -> 8 | M8: =L8+1 -> 9 | ... EF8: =EE8+1 -> 132
A9: 모델기간 Flag | E9: =IF(E6<=Assumption!$E$24,1,0) -> 1 | F9: =IF(F6<=Assumption!$E$24,1,0) -> 1 | G9: =IF(G6<=Assumption!$E$24,1,0) -> 1 | H9: =IF(H6<=Assumption!$E$24,1,0) -> 1 | I9: =IF(I6<=Assumption!$E$24,1,0) -> 1 | J9: =IF(J6<=Assumption!$E$24,1,0) -> 1 | K9: =IF(K6<=Assumption!$E$24,1,0) -> 1 | L9: =IF(L6<=Assumption!$E$24,1,0) -> 1 | ... EF9: =IF(EF6<=Assumption!$E$24,1,0) -> 0
A10: 개발기간 Flag(설립~준공) | E10: =IF(E6<=Assumption!$E$16,1,0) -> 1 | F10: =IF(F6<=Assumption!$E$16,1,0) -> 1 | G10: =IF(G6<=Assumption!$E$16,1,0) -> 1 | H10: =IF(H6<=Assumption!$E$16,1,0) -> 1 | I10: =IF(I6<=Assumption!$E$16,1,0) -> 1 | J10: =IF(J6<=Assumption!$E$16,1,0) -> 1 | K10: =IF(K6<=Assumption!$E$16,1,0) -> 1 | L10: =IF(L6<=Assumption!$E$16,1,0) -> 1 | ... EF10: =IF(EF6<=Assumption!$E$16,1,0) -> 0
A11: 공사기간 Flag | E11: =IF(AND(E6>=Assumption!$E$14,E6<=Assumption!$E$16),1,0) -> 0 | F11: =IF(AND(F6>=Assumption!$E$14,F6<=Assumption!$E$16),1,0) -> 0 | G11: =IF(AND(G6>=Assumption!$E$14,G6<=Assumption!$E$16),1,0) -> 0 | H11: =IF(AND(H6>=Assumption!$E$14,H6<=Assumption!$E$16),1,0) -> 0 | I11: =IF(AND(I6>=Assumption!$E$14,I6<=Assumption!$E$16),1,0) -> 0 | J11: =IF(AND(J6>=Assumption!$E$14,J6<=Assumption!$E$16),1,0) -> 0 | K11: =IF(AND(K6>=Assumption!$E$14,K6<=Assumption!$E$16),1,0) -> 0 | L11: =IF(AND(L6>=Assumption!$E$14,L6<=Assumption!$E$16),1,0) -> 0 | ... EF11: =IF(AND(EF6>=Assumption!$E$14,EF6<=Assumption!$E$16),1,0) -> 0
A12: 공사 월차 | E12: =IF(E11=1,(YEAR(E6)-YEAR(Assumption!$E$14))*12+MONTH(E6)-MONTH(Assumption!$E$14)+1,0) -> 0 | F12: =IF(F11=1,(YEAR(F6)-YEAR(Assumption!$E$14))*12+MONTH(F6)-MONTH(Assumption!$E$14)+1,0) -> 0 | G12: =IF(G11=1,(YEAR(G6)-YEAR(Assumption!$E$14))*12+MONTH(G6)-MONTH(Assumption!$E$14)+1,0) -> 0 | H12: =IF(H11=1,(YEAR(H6)-YEAR(Assumption!$E$14))*12+MONTH(H6)-MONTH(Assumption!$E$14)+1,0) -> 0 | I12: =IF(I11=1,(YEAR(I6)-YEAR(Assumption!$E$14))*12+MONTH(I6)-MONTH(Assumption!$E$14)+1,0) -> 0 | J12: =IF(J11=1,(YEAR(J6)-YEAR(Assumption!$E$14))*12+MONTH(J6)-MONTH(Assumption!$E$14)+1,0) -> 0 | K12: =IF(K11=1,(YEAR(K6)-YEAR(Assumption!$E$14))*12+MONTH(K6)-MONTH(Assumption!$E$14)+1,0) -> 0 | L12: =IF(L11=1,(YEAR(L6)-YEAR(Assumption!$E$14))*12+MONTH(L6)-MONTH(Assumption!$E$14)+1,0) -> 0 | ... EF12: =IF(EF11=1,(YEAR(EF6)-YEAR(Assumption!$E$14))*12+MONTH(EF6)-MONTH(Assumption!$E$14)+1,0) -> 0
A13: S-curve 집행률 | B13: % | C13: =SUM(E13:EF13) -> 1 | E13: =IF(E12>0,(COS(PI()*(E12-1)/Assumption!$E$15)-COS(PI()*E12/Assumption!$E$15))/2,0) -> 0 | F13: =IF(F12>0,(COS(PI()*(F12-1)/Assumption!$E$15)-COS(PI()*F12/Assumption!$E$15))/2,0) -> 0 | G13: =IF(G12>0,(COS(PI()*(G12-1)/Assumption!$E$15)-COS(PI()*G12/Assumption!$E$15))/2,0) -> 0 | H13: =IF(H12>0,(COS(PI()*(H12-1)/Assumption!$E$15)-COS(PI()*H12/Assumption!$E$15))/2,0) -> 0 | I13: =IF(I12>0,(COS(PI()*(I12-1)/Assumption!$E$15)-COS(PI()*I12/Assumption!$E$15))/2,0) -> 0 | J13: =IF(J12>0,(COS(PI()*(J12-1)/Assumption!$E$15)-COS(PI()*J12/Assumption!$E$15))/2,0) -> 0 | K13: =IF(K12>0,(COS(PI()*(K12-1)/Assumption!$E$15)-COS(PI()*K12/Assumption!$E$15))/2,0) -> 0 | L13: =IF(L12>0,(COS(PI()*(L12-1)/Assumption!$E$15)-COS(PI()*L12/Assumption!$E$15))/2,0) -> 0 | ... EF13: =IF(EF12>0,(COS(PI()*(EF12-1)/Assumption!$E$15)-COS(PI()*EF12/Assumption!$E$15))/2,0) -> 0
A14: 운영기간 Flag | E14: =IF(AND(E6>=Assumption!$E$18,E6<=Assumption!$E$20),1,0) -> 0 | F14: =IF(AND(F6>=Assumption!$E$18,F6<=Assumption!$E$20),1,0) -> 0 | G14: =IF(AND(G6>=Assumption!$E$18,G6<=Assumption!$E$20),1,0) -> 0 | H14: =IF(AND(H6>=Assumption!$E$18,H6<=Assumption!$E$20),1,0) -> 0 | I14: =IF(AND(I6>=Assumption!$E$18,I6<=Assumption!$E$20),1,0) -> 0 | J14: =IF(AND(J6>=Assumption!$E$18,J6<=Assumption!$E$20),1,0) -> 0 | K14: =IF(AND(K6>=Assumption!$E$18,K6<=Assumption!$E$20),1,0) -> 0 | L14: =IF(AND(L6>=Assumption!$E$18,L6<=Assumption!$E$20),1,0) -> 0 | ... EF14: =IF(AND(EF6>=Assumption!$E$18,EF6<=Assumption!$E$20),1,0) -> 0
A15: 운영 월차 | E15: =IF(E14=1,(YEAR(E6)-YEAR(Assumption!$E$18))*12+MONTH(E6)-MONTH(Assumption!$E$18)+1,0) -> 0 | F15: =IF(F14=1,(YEAR(F6)-YEAR(Assumption!$E$18))*12+MONTH(F6)-MONTH(Assumption!$E$18)+1,0) -> 0 | G15: =IF(G14=1,(YEAR(G6)-YEAR(Assumption!$E$18))*12+MONTH(G6)-MONTH(Assumption!$E$18)+1,0) -> 0 | H15: =IF(H14=1,(YEAR(H6)-YEAR(Assumption!$E$18))*12+MONTH(H6)-MONTH(Assumption!$E$18)+1,0) -> 0 | I15: =IF(I14=1,(YEAR(I6)-YEAR(Assumption!$E$18))*12+MONTH(I6)-MONTH(Assumption!$E$18)+1,0) -> 0 | J15: =IF(J14=1,(YEAR(J6)-YEAR(Assumption!$E$18))*12+MONTH(J6)-MONTH(Assumption!$E$18)+1,0) -> 0 | K15: =IF(K14=1,(YEAR(K6)-YEAR(Assumption!$E$18))*12+MONTH(K6)-MONTH(Assumption!$E$18)+1,0) -> 0 | L15: =IF(L14=1,(YEAR(L6)-YEAR(Assumption!$E$18))*12+MONTH(L6)-MONTH(Assumption!$E$18)+1,0) -> 0 | ... EF15: =IF(EF14=1,(YEAR(EF6)-YEAR(Assumption!$E$18))*12+MONTH(EF6)-MONTH(Assumption!$E$18)+1,0) -> 0
A16: 운영 연차 | E16: =IF(E15>0,INT((E15-1)/12)+1,0) -> 0 | F16: =IF(F15>0,INT((F15-1)/12)+1,0) -> 0 | G16: =IF(G15>0,INT((G15-1)/12)+1,0) -> 0 | H16: =IF(H15>0,INT((H15-1)/12)+1,0) -> 0 | I16: =IF(I15>0,INT((I15-1)/12)+1,0) -> 0 | J16: =IF(J15>0,INT((J15-1)/12)+1,0) -> 0 | K16: =IF(K15>0,INT((K15-1)/12)+1,0) -> 0 | L16: =IF(L15>0,INT((L15-1)/12)+1,0) -> 0 | ... EF16: =IF(EF15>0,INT((EF15-1)/12)+1,0) -> 0
A17: 리츠운용기간 Flag(운영개시~청산) | E17: =IF(AND(E6>=Assumption!$E$18,E6<=Assumption!$E$24),1,0) -> 0 | F17: =IF(AND(F6>=Assumption!$E$18,F6<=Assumption!$E$24),1,0) -> 0 | G17: =IF(AND(G6>=Assumption!$E$18,G6<=Assumption!$E$24),1,0) -> 0 | H17: =IF(AND(H6>=Assumption!$E$18,H6<=Assumption!$E$24),1,0) -> 0 | I17: =IF(AND(I6>=Assumption!$E$18,I6<=Assumption!$E$24),1,0) -> 0 | J17: =IF(AND(J6>=Assumption!$E$18,J6<=Assumption!$E$24),1,0) -> 0 | K17: =IF(AND(K6>=Assumption!$E$18,K6<=Assumption!$E$24),1,0) -> 0 | L17: =IF(AND(L6>=Assumption!$E$18,L6<=Assumption!$E$24),1,0) -> 0 | ... EF17: =IF(AND(EF6>=Assumption!$E$18,EF6<=Assumption!$E$24),1,0) -> 0
A18: 일수 | B18: 일 | E18: =DAY(E6) -> 31 | F18: =DAY(F6) -> 30 | G18: =DAY(G6) -> 31 | H18: =DAY(H6) -> 30 | I18: =DAY(I6) -> 31 | J18: =DAY(J6) -> 31 | K18: =DAY(K6) -> 30 | L18: =DAY(L6) -> 31 | ... EF18: =DAY(EF6) -> 28
A20: 운영수입
A21: 시니어 레지던스 이용료·임대료 | B21: 백만원 | C21: =SUM(E21:EF21) -> 97278.541 | E21: =(E14=1)*Assumption!$E$82*CHOOSE(MIN(MAX(E16,1),3),Assumption!$E$90,Assumption!$E$91,Assumption!$E$92)*(Assumption!$E$86+Assumption!$E$85)/1000*(1+Assumption!$E$87)^INT((E15-1)/Assumption!$E$88) -> 0 | F21: =(F14=1)*Assumption!$E$82*CHOOSE(MIN(MAX(F16,1),3),Assumption!$E$90,Assumption!$E$91,Assumption!$E$92)*(Assumption!$E$86+Assumption!$E$85)/1000*(1+Assumption!$E$87)^INT((F15-1)/Assumption!$E$88) -> 0 | G21: =(G14=1)*Assumption!$E$82*CHOOSE(MIN(MAX(G16,1),3),Assumption!$E$90,Assumption!$E$91,Assumption!$E$92)*(Assumption!$E$86+Assumption!$E$85)/1000*(1+Assumption!$E$87)^INT((G15-1)/Assumption!$E$88) -> 0 | H21: =(H14=1)*Assumption!$E$82*CHOOSE(MIN(MAX(H16,1),3),Assumption!$E$90,Assumption!$E$91,Assumption!$E$92)*(Assumption!$E$86+Assumption!$E$85)/1000*(1+Assumption!$E$87)^INT((H15-1)/Assumption!$E$88) -> 0 | I21: =(I14=1)*Assumption!$E$82*CHOOSE(MIN(MAX(I16,1),3),Assumption!$E$90,Assumption!$E$91,Assumption!$E$92)*(Assumption!$E$86+Assumption!$E$85)/1000*(1+Assumption!$E$87)^INT((I15-1)/Assumption!$E$88) -> 0 | J21: =(J14=1)*Assumption!$E$82*CHOOSE(MIN(MAX(J16,1),3),Assumption!$E$90,Assumption!$E$91,Assumption!$E$92)*(Assumption!$E$86+Assumption!$E$85)/1000*(1+Assumption!$E$87)^INT((J15-1)/Assumption!$E$88) -> 0 | K21: =(K14=1)*Assumption!$E$82*CHOOSE(MIN(MAX(K16,1),3),Assumption!$E$90,Assumption!$E$91,Assumption!$E$92)*(Assumption!$E$86+Assumption!$E$85)/1000*(1+Assumption!$E$87)^INT((K15-1)/Assumption!$E$88) -> 0 | L21: =(L14=1)*Assumption!$E$82*CHOOSE(MIN(MAX(L16,1),3),Assumption!$E$90,Assumption!$E$91,Assumption!$E$92)*(Assumption!$E$86+Assumption!$E$85)/1000*(1+Assumption!$E$87)^INT((L15-1)/Assumption!$E$88) -> 0 | ... EF21: =(EF14=1)*Assumption!$E$82*CHOOSE(MIN(MAX(EF16,1),3),Assumption!$E$90,Assumption!$E$91,Assumption!$E$92)*(Assumption!$E$86+Assumption!$E$85)/1000*(1+Assumption!$E$87)^INT((EF15-1)/Assumption!$E$88) -> 0
A22: 시니어 추가수입(세대관리비 등) | B22: 백만원 | C22: =SUM(E22:EF22) -> 14591.781 | E22: =E21*Assumption!$E$93 -> 0 | F22: =F21*Assumption!$E$93 -> 0 | G22: =G21*Assumption!$E$93 -> 0 | H22: =H21*Assumption!$E$93 -> 0 | I22: =I21*Assumption!$E$93 -> 0 | J22: =J21*Assumption!$E$93 -> 0 | K22: =K21*Assumption!$E$93 -> 0 | L22: =L21*Assumption!$E$93 -> 0 | ... EF22: =EF21*Assumption!$E$93 -> 0
A23: 시니어 부대시설 임대료 | B23: 백만원 | C23: =SUM(E23:EF23) -> 9128.7441 | E23: =(E14=1)*Assumption!$E$101*Assumption!$E$102/1000*(1+Assumption!$E$104)^INT((E15-1)/Assumption!$E$105) -> 0 | F23: =(F14=1)*Assumption!$E$101*Assumption!$E$102/1000*(1+Assumption!$E$104)^INT((F15-1)/Assumption!$E$105) -> 0 | G23: =(G14=1)*Assumption!$E$101*Assumption!$E$102/1000*(1+Assumption!$E$104)^INT((G15-1)/Assumption!$E$105) -> 0 | H23: =(H14=1)*Assumption!$E$101*Assumption!$E$102/1000*(1+Assumption!$E$104)^INT((H15-1)/Assumption!$E$105) -> 0 | I23: =(I14=1)*Assumption!$E$101*Assumption!$E$102/1000*(1+Assumption!$E$104)^INT((I15-1)/Assumption!$E$105) -> 0 | J23: =(J14=1)*Assumption!$E$101*Assumption!$E$102/1000*(1+Assumption!$E$104)^INT((J15-1)/Assumption!$E$105) -> 0 | K23: =(K14=1)*Assumption!$E$101*Assumption!$E$102/1000*(1+Assumption!$E$104)^INT((K15-1)/Assumption!$E$105) -> 0 | L23: =(L14=1)*Assumption!$E$101*Assumption!$E$102/1000*(1+Assumption!$E$104)^INT((L15-1)/Assumption!$E$105) -> 0 | ... EF23: =(EF14=1)*Assumption!$E$101*Assumption!$E$102/1000*(1+Assumption!$E$104)^INT((EF15-1)/Assumption!$E$105) -> 0
A24: 레지던스 객실매출 | B24: 백만원 | C24: =SUM(E24:EF24) -> 97070.53 | E24: =(E14=1)*Assumption!$G$115*CHOOSE(MIN(MAX(E16,1),3),Assumption!$E$122,Assumption!$E$123,Assumption!$E$124)*E18/1000000*(1+Assumption!$E$118)^(MAX(E16,1)-1) -> 0 | F24: =(F14=1)*Assumption!$G$115*CHOOSE(MIN(MAX(F16,1),3),Assumption!$E$122,Assumption!$E$123,Assumption!$E$124)*F18/1000000*(1+Assumption!$E$118)^(MAX(F16,1)-1) -> 0 | G24: =(G14=1)*Assumption!$G$115*CHOOSE(MIN(MAX(G16,1),3),Assumption!$E$122,Assumption!$E$123,Assumption!$E$124)*G18/1000000*(1+Assumption!$E$118)^(MAX(G16,1)-1) -> 0 | H24: =(H14=1)*Assumption!$G$115*CHOOSE(MIN(MAX(H16,1),3),Assumption!$E$122,Assumption!$E$123,Assumption!$E$124)*H18/1000000*(1+Assumption!$E$118)^(MAX(H16,1)-1) -> 0 | I24: =(I14=1)*Assumption!$G$115*CHOOSE(MIN(MAX(I16,1),3),Assumption!$E$122,Assumption!$E$123,Assumption!$E$124)*I18/1000000*(1+Assumption!$E$118)^(MAX(I16,1)-1) -> 0 | J24: =(J14=1)*Assumption!$G$115*CHOOSE(MIN(MAX(J16,1),3),Assumption!$E$122,Assumption!$E$123,Assumption!$E$124)*J18/1000000*(1+Assumption!$E$118)^(MAX(J16,1)-1) -> 0 | K24: =(K14=1)*Assumption!$G$115*CHOOSE(MIN(MAX(K16,1),3),Assumption!$E$122,Assumption!$E$123,Assumption!$E$124)*K18/1000000*(1+Assumption!$E$118)^(MAX(K16,1)-1) -> 0 | L24: =(L14=1)*Assumption!$G$115*CHOOSE(MIN(MAX(L16,1),3),Assumption!$E$122,Assumption!$E$123,Assumption!$E$124)*L18/1000000*(1+Assumption!$E$118)^(MAX(L16,1)-1) -> 0 | ... EF24: =(EF14=1)*Assumption!$G$115*CHOOSE(MIN(MAX(EF16,1),3),Assumption!$E$122,Assumption!$E$123,Assumption!$E$124)*EF18/1000000*(1+Assumption!$E$118)^(MAX(EF16,1)-1) -> 0
A25: 레지던스 객실외매출 | B25: 백만원 | C25: =SUM(E25:EF25) -> 64746.044 | E25: =E24*Assumption!$E$125 -> 0 | F25: =F24*Assumption!$E$125 -> 0 | G25: =G24*Assumption!$E$125 -> 0 | H25: =H24*Assumption!$E$125 -> 0 | I25: =I24*Assumption!$E$125 -> 0 | J25: =J24*Assumption!$E$125 -> 0 | K25: =K24*Assumption!$E$125 -> 0 | L25: =L24*Assumption!$E$125 -> 0 | ... EF25: =EF24*Assumption!$E$125 -> 0
A26: 레지던스 멤버전용 매출 | B26: 백만원 | C26: =SUM(E26:EF26) -> 35430.744 | E26: =E24*Assumption!$E$130 -> 0 | F26: =F24*Assumption!$E$130 -> 0 | G26: =G24*Assumption!$E$130 -> 0 | H26: =H24*Assumption!$E$130 -> 0 | I26: =I24*Assumption!$E$130 -> 0 | J26: =J24*Assumption!$E$130 -> 0 | K26: =K24*Assumption!$E$130 -> 0 | L26: =L24*Assumption!$E$130 -> 0 | ... EF26: =EF24*Assumption!$E$130 -> 0
A27: 호텔 객실매출 | B27: 백만원 | C27: =SUM(E27:EF27) -> 214271.36 | E27: =(E14=1)*Assumption!$E$134*Assumption!$E$145*CHOOSE(MIN(MAX(E16,1),3),Assumption!$E$146,Assumption!$E$147,Assumption!$E$148)*E18/1000000*(1+Assumption!$E$141)^(MAX(E16,1)-1) -> 0 | F27: =(F14=1)*Assumption!$E$134*Assumption!$E$145*CHOOSE(MIN(MAX(F16,1),3),Assumption!$E$146,Assumption!$E$147,Assumption!$E$148)*F18/1000000*(1+Assumption!$E$141)^(MAX(F16,1)-1) -> 0 | G27: =(G14=1)*Assumption!$E$134*Assumption!$E$145*CHOOSE(MIN(MAX(G16,1),3),Assumption!$E$146,Assumption!$E$147,Assumption!$E$148)*G18/1000000*(1+Assumption!$E$141)^(MAX(G16,1)-1) -> 0 | H27: =(H14=1)*Assumption!$E$134*Assumption!$E$145*CHOOSE(MIN(MAX(H16,1),3),Assumption!$E$146,Assumption!$E$147,Assumption!$E$148)*H18/1000000*(1+Assumption!$E$141)^(MAX(H16,1)-1) -> 0 | I27: =(I14=1)*Assumption!$E$134*Assumption!$E$145*CHOOSE(MIN(MAX(I16,1),3),Assumption!$E$146,Assumption!$E$147,Assumption!$E$148)*I18/1000000*(1+Assumption!$E$141)^(MAX(I16,1)-1) -> 0 | J27: =(J14=1)*Assumption!$E$134*Assumption!$E$145*CHOOSE(MIN(MAX(J16,1),3),Assumption!$E$146,Assumption!$E$147,Assumption!$E$148)*J18/1000000*(1+Assumption!$E$141)^(MAX(J16,1)-1) -> 0 | K27: =(K14=1)*Assumption!$E$134*Assumption!$E$145*CHOOSE(MIN(MAX(K16,1),3),Assumption!$E$146,Assumption!$E$147,Assumption!$E$148)*K18/1000000*(1+Assumption!$E$141)^(MAX(K16,1)-1) -> 0 | L27: =(L14=1)*Assumption!$E$134*Assumption!$E$145*CHOOSE(MIN(MAX(L16,1),3),Assumption!$E$146,Assumption!$E$147,Assumption!$E$148)*L18/1000000*(1+Assumption!$E$141)^(MAX(L16,1)-1) -> 0 | ... EF27: =(EF14=1)*Assumption!$E$134*Assumption!$E$145*CHOOSE(MIN(MAX(EF16,1),3),Assumption!$E$146,Assumption!$E$147,Assumption!$E$148)*EF18/1000000*(1+Assumption!$E$141)^(MAX(EF16,1)-1) -> 0
A28: 호텔 객실외매출(식음) | B28: 백만원 | C28: =SUM(E28:EF28) -> 96422.111 | E28: =E27*Assumption!$E$149 -> 0 | F28: =F27*Assumption!$E$149 -> 0 | G28: =G27*Assumption!$E$149 -> 0 | H28: =H27*Assumption!$E$149 -> 0 | I28: =I27*Assumption!$E$149 -> 0 | J28: =J27*Assumption!$E$149 -> 0 | K28: =K27*Assumption!$E$149 -> 0 | L28: =L27*Assumption!$E$149 -> 0 | ... EF28: =EF27*Assumption!$E$149 -> 0
A29: 호텔 객실외매출(기타) | B29: 백만원 | C29: =SUM(E29:EF29) -> 12856.281 | E29: =E27*Assumption!$E$150 -> 0 | F29: =F27*Assumption!$E$150 -> 0 | G29: =G27*Assumption!$E$150 -> 0 | H29: =H27*Assumption!$E$150 -> 0 | I29: =I27*Assumption!$E$150 -> 0 | J29: =J27*Assumption!$E$150 -> 0 | K29: =K27*Assumption!$E$150 -> 0 | L29: =L27*Assumption!$E$150 -> 0 | ... EF29: =EF27*Assumption!$E$150 -> 0
A30: 컨벤션(연회장) | B30: 백만원 | C30: =SUM(E30:EF30) -> 77137.689 | E30: =E27*Assumption!$E$155 -> 0 | F30: =F27*Assumption!$E$155 -> 0 | G30: =G27*Assumption!$E$155 -> 0 | H30: =H27*Assumption!$E$155 -> 0 | I30: =I27*Assumption!$E$155 -> 0 | J30: =J27*Assumption!$E$155 -> 0 | K30: =K27*Assumption!$E$155 -> 0 | L30: =L27*Assumption!$E$155 -> 0 | ... EF30: =EF27*Assumption!$E$155 -> 0
A31: 스파&수영장&피트니스 | B31: 백만원 | C31: =SUM(E31:EF31) -> 29997.99 | E31: =E27*Assumption!$E$156 -> 0 | F31: =F27*Assumption!$E$156 -> 0 | G31: =G27*Assumption!$E$156 -> 0 | H31: =H27*Assumption!$E$156 -> 0 | I31: =I27*Assumption!$E$156 -> 0 | J31: =J27*Assumption!$E$156 -> 0 | K31: =K27*Assumption!$E$156 -> 0 | L31: =L27*Assumption!$E$156 -> 0 | ... EF31: =EF27*Assumption!$E$156 -> 0
A32: 파인다이닝/ADD | B32: 백만원 | C32: =SUM(E32:EF32) -> 96422.111 | E32: =E27*Assumption!$E$157 -> 0 | F32: =F27*Assumption!$E$157 -> 0 | G32: =G27*Assumption!$E$157 -> 0 | H32: =H27*Assumption!$E$157 -> 0 | I32: =I27*Assumption!$E$157 -> 0 | J32: =J27*Assumption!$E$157 -> 0 | K32: =K27*Assumption!$E$157 -> 0 | L32: =L27*Assumption!$E$157 -> 0 | ... EF32: =EF27*Assumption!$E$157 -> 0
A33: 휴게시설 | B33: 백만원 | C33: =SUM(E33:EF33) -> 42854.272 | E33: =E27*Assumption!$E$158 -> 0 | F33: =F27*Assumption!$E$158 -> 0 | G33: =G27*Assumption!$E$158 -> 0 | H33: =H27*Assumption!$E$158 -> 0 | I33: =I27*Assumption!$E$158 -> 0 | J33: =J27*Assumption!$E$158 -> 0 | K33: =K27*Assumption!$E$158 -> 0 | L33: =L27*Assumption!$E$158 -> 0 | ... EF33: =EF27*Assumption!$E$158 -> 0
A34: BOH | B34: 백만원 | C34: =SUM(E34:EF34) -> 8570.8543 | E34: =E33*Assumption!$E$159 -> 0 | F34: =F33*Assumption!$E$159 -> 0 | G34: =G33*Assumption!$E$159 -> 0 | H34: =H33*Assumption!$E$159 -> 0 | I34: =I33*Assumption!$E$159 -> 0 | J34: =J33*Assumption!$E$159 -> 0 | K34: =K33*Assumption!$E$159 -> 0 | L34: =L33*Assumption!$E$159 -> 0 | ... EF34: =EF33*Assumption!$E$159 -> 0
A35: 오피스 임대료 | B35: 백만원 | C35: =SUM(E35:EF35) -> 84940.506 | E35: =(E14=1)*Assumption!$E$169*Assumption!$E$170/1000*(1+Assumption!$E$172)^INT((E15-1)/Assumption!$E$173)*(1-CHOOSE(MIN(MAX(E16,1),3),Assumption!$E$175,Assumption!$E$176,Assumption!$E$177)) -> 0 | F35: =(F14=1)*Assumption!$E$169*Assumption!$E$170/1000*(1+Assumption!$E$172)^INT((F15-1)/Assumption!$E$173)*(1-CHOOSE(MIN(MAX(F16,1),3),Assumption!$E$175,Assumption!$E$176,Assumption!$E$177)) -> 0 | G35: =(G14=1)*Assumption!$E$169*Assumption!$E$170/1000*(1+Assumption!$E$172)^INT((G15-1)/Assumption!$E$173)*(1-CHOOSE(MIN(MAX(G16,1),3),Assumption!$E$175,Assumption!$E$176,Assumption!$E$177)) -> 0 | H35: =(H14=1)*Assumption!$E$169*Assumption!$E$170/1000*(1+Assumption!$E$172)^INT((H15-1)/Assumption!$E$173)*(1-CHOOSE(MIN(MAX(H16,1),3),Assumption!$E$175,Assumption!$E$176,Assumption!$E$177)) -> 0 | I35: =(I14=1)*Assumption!$E$169*Assumption!$E$170/1000*(1+Assumption!$E$172)^INT((I15-1)/Assumption!$E$173)*(1-CHOOSE(MIN(MAX(I16,1),3),Assumption!$E$175,Assumption!$E$176,Assumption!$E$177)) -> 0 | J35: =(J14=1)*Assumption!$E$169*Assumption!$E$170/1000*(1+Assumption!$E$172)^INT((J15-1)/Assumption!$E$173)*(1-CHOOSE(MIN(MAX(J16,1),3),Assumption!$E$175,Assumption!$E$176,Assumption!$E$177)) -> 0 | K35: =(K14=1)*Assumption!$E$169*Assumption!$E$170/1000*(1+Assumption!$E$172)^INT((K15-1)/Assumption!$E$173)*(1-CHOOSE(MIN(MAX(K16,1),3),Assumption!$E$175,Assumption!$E$176,Assumption!$E$177)) -> 0 | L35: =(L14=1)*Assumption!$E$169*Assumption!$E$170/1000*(1+Assumption!$E$172)^INT((L15-1)/Assumption!$E$173)*(1-CHOOSE(MIN(MAX(L16,1),3),Assumption!$E$175,Assumption!$E$176,Assumption!$E$177)) -> 0 | ... EF35: =(EF14=1)*Assumption!$E$169*Assumption!$E$170/1000*(1+Assumption!$E$172)^INT((EF15-1)/Assumption!$E$173)*(1-CHOOSE(MIN(MAX(EF16,1),3),Assumption!$E$175,Assumption!$E$176,Assumption!$E$177)) -> 0
A36: 메디컬 임대료 | B36: 백만원 | C36: =SUM(E36:EF36) -> 8886.1692 | E36: =(E14=1)*Assumption!$E$187*Assumption!$E$188/1000*(1+Assumption!$E$190)^INT((E15-1)/Assumption!$E$191)*(1-CHOOSE(MIN(MAX(E16,1),3),Assumption!$E$193,Assumption!$E$194,Assumption!$E$195)) -> 0 | F36: =(F14=1)*Assumption!$E$187*Assumption!$E$188/1000*(1+Assumption!$E$190)^INT((F15-1)/Assumption!$E$191)*(1-CHOOSE(MIN(MAX(F16,1),3),Assumption!$E$193,Assumption!$E$194,Assumption!$E$195)) -> 0 | G36: =(G14=1)*Assumption!$E$187*Assumption!$E$188/1000*(1+Assumption!$E$190)^INT((G15-1)/Assumption!$E$191)*(1-CHOOSE(MIN(MAX(G16,1),3),Assumption!$E$193,Assumption!$E$194,Assumption!$E$195)) -> 0 | H36: =(H14=1)*Assumption!$E$187*Assumption!$E$188/1000*(1+Assumption!$E$190)^INT((H15-1)/Assumption!$E$191)*(1-CHOOSE(MIN(MAX(H16,1),3),Assumption!$E$193,Assumption!$E$194,Assumption!$E$195)) -> 0 | I36: =(I14=1)*Assumption!$E$187*Assumption!$E$188/1000*(1+Assumption!$E$190)^INT((I15-1)/Assumption!$E$191)*(1-CHOOSE(MIN(MAX(I16,1),3),Assumption!$E$193,Assumption!$E$194,Assumption!$E$195)) -> 0 | J36: =(J14=1)*Assumption!$E$187*Assumption!$E$188/1000*(1+Assumption!$E$190)^INT((J15-1)/Assumption!$E$191)*(1-CHOOSE(MIN(MAX(J16,1),3),Assumption!$E$193,Assumption!$E$194,Assumption!$E$195)) -> 0 | K36: =(K14=1)*Assumption!$E$187*Assumption!$E$188/1000*(1+Assumption!$E$190)^INT((K15-1)/Assumption!$E$191)*(1-CHOOSE(MIN(MAX(K16,1),3),Assumption!$E$193,Assumption!$E$194,Assumption!$E$195)) -> 0 | L36: =(L14=1)*Assumption!$E$187*Assumption!$E$188/1000*(1+Assumption!$E$190)^INT((L15-1)/Assumption!$E$191)*(1-CHOOSE(MIN(MAX(L16,1),3),Assumption!$E$193,Assumption!$E$194,Assumption!$E$195)) -> 0 | ... EF36: =(EF14=1)*Assumption!$E$187*Assumption!$E$188/1000*(1+Assumption!$E$190)^INT((EF15-1)/Assumption!$E$191)*(1-CHOOSE(MIN(MAX(EF16,1),3),Assumption!$E$193,Assumption!$E$194,Assumption!$E$195)) -> 0
A37: 스파2.0 임대료 | B37: 백만원 | C37: =SUM(E37:EF37) -> 9520.8956 | E37: =(E14=1)*Assumption!$E$200*Assumption!$E$201/1000*(1+Assumption!$E$203)^INT((E15-1)/Assumption!$E$204)*(1-CHOOSE(MIN(MAX(E16,1),3),Assumption!$E$206,Assumption!$E$207,Assumption!$E$208)) -> 0 | F37: =(F14=1)*Assumption!$E$200*Assumption!$E$201/1000*(1+Assumption!$E$203)^INT((F15-1)/Assumption!$E$204)*(1-CHOOSE(MIN(MAX(F16,1),3),Assumption!$E$206,Assumption!$E$207,Assumption!$E$208)) -> 0 | G37: =(G14=1)*Assumption!$E$200*Assumption!$E$201/1000*(1+Assumption!$E$203)^INT((G15-1)/Assumption!$E$204)*(1-CHOOSE(MIN(MAX(G16,1),3),Assumption!$E$206,Assumption!$E$207,Assumption!$E$208)) -> 0 | H37: =(H14=1)*Assumption!$E$200*Assumption!$E$201/1000*(1+Assumption!$E$203)^INT((H15-1)/Assumption!$E$204)*(1-CHOOSE(MIN(MAX(H16,1),3),Assumption!$E$206,Assumption!$E$207,Assumption!$E$208)) -> 0 | I37: =(I14=1)*Assumption!$E$200*Assumption!$E$201/1000*(1+Assumption!$E$203)^INT((I15-1)/Assumption!$E$204)*(1-CHOOSE(MIN(MAX(I16,1),3),Assumption!$E$206,Assumption!$E$207,Assumption!$E$208)) -> 0 | J37: =(J14=1)*Assumption!$E$200*Assumption!$E$201/1000*(1+Assumption!$E$203)^INT((J15-1)/Assumption!$E$204)*(1-CHOOSE(MIN(MAX(J16,1),3),Assumption!$E$206,Assumption!$E$207,Assumption!$E$208)) -> 0 | K37: =(K14=1)*Assumption!$E$200*Assumption!$E$201/1000*(1+Assumption!$E$203)^INT((K15-1)/Assumption!$E$204)*(1-CHOOSE(MIN(MAX(K16,1),3),Assumption!$E$206,Assumption!$E$207,Assumption!$E$208)) -> 0 | L37: =(L14=1)*Assumption!$E$200*Assumption!$E$201/1000*(1+Assumption!$E$203)^INT((L15-1)/Assumption!$E$204)*(1-CHOOSE(MIN(MAX(L16,1),3),Assumption!$E$206,Assumption!$E$207,Assumption!$E$208)) -> 0 | ... EF37: =(EF14=1)*Assumption!$E$200*Assumption!$E$201/1000*(1+Assumption!$E$203)^INT((EF15-1)/Assumption!$E$204)*(1-CHOOSE(MIN(MAX(EF16,1),3),Assumption!$E$206,Assumption!$E$207,Assumption!$E$208)) -> 0
A38: 판매시설 임대료 | B38: 백만원 | C38: =SUM(E38:EF38) -> 16700.724 | E38: =(E14=1)*Assumption!$E$213*Assumption!$E$214/1000*(1+Assumption!$E$216)^INT((E15-1)/Assumption!$E$217)*(1-CHOOSE(MIN(MAX(E16,1),3),Assumption!$E$219,Assumption!$E$220,Assumption!$E$221)) -> 0 | F38: =(F14=1)*Assumption!$E$213*Assumption!$E$214/1000*(1+Assumption!$E$216)^INT((F15-1)/Assumption!$E$217)*(1-CHOOSE(MIN(MAX(F16,1),3),Assumption!$E$219,Assumption!$E$220,Assumption!$E$221)) -> 0 | G38: =(G14=1)*Assumption!$E$213*Assumption!$E$214/1000*(1+Assumption!$E$216)^INT((G15-1)/Assumption!$E$217)*(1-CHOOSE(MIN(MAX(G16,1),3),Assumption!$E$219,Assumption!$E$220,Assumption!$E$221)) -> 0 | H38: =(H14=1)*Assumption!$E$213*Assumption!$E$214/1000*(1+Assumption!$E$216)^INT((H15-1)/Assumption!$E$217)*(1-CHOOSE(MIN(MAX(H16,1),3),Assumption!$E$219,Assumption!$E$220,Assumption!$E$221)) -> 0 | I38: =(I14=1)*Assumption!$E$213*Assumption!$E$214/1000*(1+Assumption!$E$216)^INT((I15-1)/Assumption!$E$217)*(1-CHOOSE(MIN(MAX(I16,1),3),Assumption!$E$219,Assumption!$E$220,Assumption!$E$221)) -> 0 | J38: =(J14=1)*Assumption!$E$213*Assumption!$E$214/1000*(1+Assumption!$E$216)^INT((J15-1)/Assumption!$E$217)*(1-CHOOSE(MIN(MAX(J16,1),3),Assumption!$E$219,Assumption!$E$220,Assumption!$E$221)) -> 0 | K38: =(K14=1)*Assumption!$E$213*Assumption!$E$214/1000*(1+Assumption!$E$216)^INT((K15-1)/Assumption!$E$217)*(1-CHOOSE(MIN(MAX(K16,1),3),Assumption!$E$219,Assumption!$E$220,Assumption!$E$221)) -> 0 | L38: =(L14=1)*Assumption!$E$213*Assumption!$E$214/1000*(1+Assumption!$E$216)^INT((L15-1)/Assumption!$E$217)*(1-CHOOSE(MIN(MAX(L16,1),3),Assumption!$E$219,Assumption!$E$220,Assumption!$E$221)) -> 0 | ... EF38: =(EF14=1)*Assumption!$E$213*Assumption!$E$214/1000*(1+Assumption!$E$216)^INT((EF15-1)/Assumption!$E$217)*(1-CHOOSE(MIN(MAX(EF16,1),3),Assumption!$E$219,Assumption!$E$220,Assumption!$E$221)) -> 0
A39: 국제학교 임대료 | B39: 백만원 | C39: =SUM(E39:EF39) -> 4436.2652 | E39: =(E14=1)*Assumption!$E$226*Assumption!$E$227/1000*(1+Assumption!$E$229)^INT((E15-1)/Assumption!$E$230)*(1-CHOOSE(MIN(MAX(E16,1),3),Assumption!$E$232,Assumption!$E$233,Assumption!$E$234)) -> 0 | F39: =(F14=1)*Assumption!$E$226*Assumption!$E$227/1000*(1+Assumption!$E$229)^INT((F15-1)/Assumption!$E$230)*(1-CHOOSE(MIN(MAX(F16,1),3),Assumption!$E$232,Assumption!$E$233,Assumption!$E$234)) -> 0 | G39: =(G14=1)*Assumption!$E$226*Assumption!$E$227/1000*(1+Assumption!$E$229)^INT((G15-1)/Assumption!$E$230)*(1-CHOOSE(MIN(MAX(G16,1),3),Assumption!$E$232,Assumption!$E$233,Assumption!$E$234)) -> 0 | H39: =(H14=1)*Assumption!$E$226*Assumption!$E$227/1000*(1+Assumption!$E$229)^INT((H15-1)/Assumption!$E$230)*(1-CHOOSE(MIN(MAX(H16,1),3),Assumption!$E$232,Assumption!$E$233,Assumption!$E$234)) -> 0 | I39: =(I14=1)*Assumption!$E$226*Assumption!$E$227/1000*(1+Assumption!$E$229)^INT((I15-1)/Assumption!$E$230)*(1-CHOOSE(MIN(MAX(I16,1),3),Assumption!$E$232,Assumption!$E$233,Assumption!$E$234)) -> 0 | J39: =(J14=1)*Assumption!$E$226*Assumption!$E$227/1000*(1+Assumption!$E$229)^INT((J15-1)/Assumption!$E$230)*(1-CHOOSE(MIN(MAX(J16,1),3),Assumption!$E$232,Assumption!$E$233,Assumption!$E$234)) -> 0 | K39: =(K14=1)*Assumption!$E$226*Assumption!$E$227/1000*(1+Assumption!$E$229)^INT((K15-1)/Assumption!$E$230)*(1-CHOOSE(MIN(MAX(K16,1),3),Assumption!$E$232,Assumption!$E$233,Assumption!$E$234)) -> 0 | L39: =(L14=1)*Assumption!$E$226*Assumption!$E$227/1000*(1+Assumption!$E$229)^INT((L15-1)/Assumption!$E$230)*(1-CHOOSE(MIN(MAX(L16,1),3),Assumption!$E$232,Assumption!$E$233,Assumption!$E$234)) -> 0 | ... EF39: =(EF14=1)*Assumption!$E$226*Assumption!$E$227/1000*(1+Assumption!$E$229)^INT((EF15-1)/Assumption!$E$230)*(1-CHOOSE(MIN(MAX(EF16,1),3),Assumption!$E$232,Assumption!$E$233,Assumption!$E$234)) -> 0
A40: 영어유치원 임대료 | B40: 백만원 | C40: =SUM(E40:EF40) -> 1602.7028 | E40: =(E14=1)*Assumption!$E$239*Assumption!$E$240/1000*(1+Assumption!$E$242)^INT((E15-1)/Assumption!$E$243)*(1-CHOOSE(MIN(MAX(E16,1),3),Assumption!$E$245,Assumption!$E$246,Assumption!$E$247)) -> 0 | F40: =(F14=1)*Assumption!$E$239*Assumption!$E$240/1000*(1+Assumption!$E$242)^INT((F15-1)/Assumption!$E$243)*(1-CHOOSE(MIN(MAX(F16,1),3),Assumption!$E$245,Assumption!$E$246,Assumption!$E$247)) -> 0 | G40: =(G14=1)*Assumption!$E$239*Assumption!$E$240/1000*(1+Assumption!$E$242)^INT((G15-1)/Assumption!$E$243)*(1-CHOOSE(MIN(MAX(G16,1),3),Assumption!$E$245,Assumption!$E$246,Assumption!$E$247)) -> 0 | H40: =(H14=1)*Assumption!$E$239*Assumption!$E$240/1000*(1+Assumption!$E$242)^INT((H15-1)/Assumption!$E$243)*(1-CHOOSE(MIN(MAX(H16,1),3),Assumption!$E$245,Assumption!$E$246,Assumption!$E$247)) -> 0 | I40: =(I14=1)*Assumption!$E$239*Assumption!$E$240/1000*(1+Assumption!$E$242)^INT((I15-1)/Assumption!$E$243)*(1-CHOOSE(MIN(MAX(I16,1),3),Assumption!$E$245,Assumption!$E$246,Assumption!$E$247)) -> 0 | J40: =(J14=1)*Assumption!$E$239*Assumption!$E$240/1000*(1+Assumption!$E$242)^INT((J15-1)/Assumption!$E$243)*(1-CHOOSE(MIN(MAX(J16,1),3),Assumption!$E$245,Assumption!$E$246,Assumption!$E$247)) -> 0 | K40: =(K14=1)*Assumption!$E$239*Assumption!$E$240/1000*(1+Assumption!$E$242)^INT((K15-1)/Assumption!$E$243)*(1-CHOOSE(MIN(MAX(K16,1),3),Assumption!$E$245,Assumption!$E$246,Assumption!$E$247)) -> 0 | L40: =(L14=1)*Assumption!$E$239*Assumption!$E$240/1000*(1+Assumption!$E$242)^INT((L15-1)/Assumption!$E$243)*(1-CHOOSE(MIN(MAX(L16,1),3),Assumption!$E$245,Assumption!$E$246,Assumption!$E$247)) -> 0 | ... EF40: =(EF14=1)*Assumption!$E$239*Assumption!$E$240/1000*(1+Assumption!$E$242)^INT((EF15-1)/Assumption!$E$243)*(1-CHOOSE(MIN(MAX(EF16,1),3),Assumption!$E$245,Assumption!$E$246,Assumption!$E$247)) -> 0
A41: 운영수입 합계 | B41: 백만원 | C41: =SUM(E41:EF41) -> 1022866.3 | E41: =SUM(E21:E40) -> 0 | F41: =SUM(F21:F40) -> 0 | G41: =SUM(G21:G40) -> 0 | H41: =SUM(H21:H40) -> 0 | I41: =SUM(I21:I40) -> 0 | J41: =SUM(J21:J40) -> 0 | K41: =SUM(K21:K40) -> 0 | L41: =SUM(L21:L40) -> 0 | ... EF41: =SUM(EF21:EF40) -> 0
A43: 직접운영비용
A44: 시니어 운영비(일반+소모품) | B44: 백만원 | C44: =SUM(E44:EF44) -> 88377.554 | E44: =(E21+E22)*(Assumption!$E$96+Assumption!$E$97) -> 0 | F44: =(F21+F22)*(Assumption!$E$96+Assumption!$E$97) -> 0 | G44: =(G21+G22)*(Assumption!$E$96+Assumption!$E$97) -> 0 | H44: =(H21+H22)*(Assumption!$E$96+Assumption!$E$97) -> 0 | I44: =(I21+I22)*(Assumption!$E$96+Assumption!$E$97) -> 0 | J44: =(J21+J22)*(Assumption!$E$96+Assumption!$E$97) -> 0 | K44: =(K21+K22)*(Assumption!$E$96+Assumption!$E$97) -> 0 | L44: =(L21+L22)*(Assumption!$E$96+Assumption!$E$97) -> 0 | ... EF44: =(EF21+EF22)*(Assumption!$E$96+Assumption!$E$97) -> 0
A45: 레지던스 운영비(일반+소모품) | B45: 백만원 | C45: =SUM(E45:EF45) -> 127835.09 | E45: =(E24+E25)*(Assumption!$E$126+Assumption!$E$127) -> 0 | F45: =(F24+F25)*(Assumption!$E$126+Assumption!$E$127) -> 0 | G45: =(G24+G25)*(Assumption!$E$126+Assumption!$E$127) -> 0 | H45: =(H24+H25)*(Assumption!$E$126+Assumption!$E$127) -> 0 | I45: =(I24+I25)*(Assumption!$E$126+Assumption!$E$127) -> 0 | J45: =(J24+J25)*(Assumption!$E$126+Assumption!$E$127) -> 0 | K45: =(K24+K25)*(Assumption!$E$126+Assumption!$E$127) -> 0 | L45: =(L24+L25)*(Assumption!$E$126+Assumption!$E$127) -> 0 | ... EF45: =(EF24+EF25)*(Assumption!$E$126+Assumption!$E$127) -> 0
A46: 레지던스 멤버전용 운영비 | B46: 백만원 | C46: =SUM(E46:EF46) -> 26573.058 | E46: =E26*Assumption!$E$131 -> 0 | F46: =F26*Assumption!$E$131 -> 0 | G46: =G26*Assumption!$E$131 -> 0 | H46: =H26*Assumption!$E$131 -> 0 | I46: =I26*Assumption!$E$131 -> 0 | J46: =J26*Assumption!$E$131 -> 0 | K46: =K26*Assumption!$E$131 -> 0 | L46: =L26*Assumption!$E$131 -> 0 | ... EF46: =EF26*Assumption!$E$131 -> 0
A47: 호텔 운영비(일반+소모품) | B47: 백만원 | C47: =SUM(E47:EF47) -> 255604.3 | E47: =(E27+E28+E29)*(Assumption!$E$151+Assumption!$E$152) -> 0 | F47: =(F27+F28+F29)*(Assumption!$E$151+Assumption!$E$152) -> 0 | G47: =(G27+G28+G29)*(Assumption!$E$151+Assumption!$E$152) -> 0 | H47: =(H27+H28+H29)*(Assumption!$E$151+Assumption!$E$152) -> 0 | I47: =(I27+I28+I29)*(Assumption!$E$151+Assumption!$E$152) -> 0 | J47: =(J27+J28+J29)*(Assumption!$E$151+Assumption!$E$152) -> 0 | K47: =(K27+K28+K29)*(Assumption!$E$151+Assumption!$E$152) -> 0 | L47: =(L27+L28+L29)*(Assumption!$E$151+Assumption!$E$152) -> 0 | ... EF47: =(EF27+EF28+EF29)*(Assumption!$E$151+Assumption!$E$152) -> 0
A48: 컨벤션 운영비 | B48: 백만원 | C48: =SUM(E48:EF48) -> 57853.267 | E48: =E30*Assumption!$E$161 -> 0 | F48: =F30*Assumption!$E$161 -> 0 | G48: =G30*Assumption!$E$161 -> 0 | H48: =H30*Assumption!$E$161 -> 0 | I48: =I30*Assumption!$E$161 -> 0 | J48: =J30*Assumption!$E$161 -> 0 | K48: =K30*Assumption!$E$161 -> 0 | L48: =L30*Assumption!$E$161 -> 0 | ... EF48: =EF30*Assumption!$E$161 -> 0
A49: 스파&수영장&피트니스 운영비 | B49: 백만원 | C49: =SUM(E49:EF49) -> 22498.493 | E49: =E31*Assumption!$E$162 -> 0 | F49: =F31*Assumption!$E$162 -> 0 | G49: =G31*Assumption!$E$162 -> 0 | H49: =H31*Assumption!$E$162 -> 0 | I49: =I31*Assumption!$E$162 -> 0 | J49: =J31*Assumption!$E$162 -> 0 | K49: =K31*Assumption!$E$162 -> 0 | L49: =L31*Assumption!$E$162 -> 0 | ... EF49: =EF31*Assumption!$E$162 -> 0
A50: 파인다이닝/ADD 운영비 | B50: 백만원 | C50: =SUM(E50:EF50) -> 72316.583 | E50: =E32*Assumption!$E$163 -> 0 | F50: =F32*Assumption!$E$163 -> 0 | G50: =G32*Assumption!$E$163 -> 0 | H50: =H32*Assumption!$E$163 -> 0 | I50: =I32*Assumption!$E$163 -> 0 | J50: =J32*Assumption!$E$163 -> 0 | K50: =K32*Assumption!$E$163 -> 0 | L50: =L32*Assumption!$E$163 -> 0 | ... EF50: =EF32*Assumption!$E$163 -> 0
A51: 휴게시설 운영비 | B51: 백만원 | C51: =SUM(E51:EF51) -> 29997.99 | E51: =E33*Assumption!$E$164 -> 0 | F51: =F33*Assumption!$E$164 -> 0 | G51: =G33*Assumption!$E$164 -> 0 | H51: =H33*Assumption!$E$164 -> 0 | I51: =I33*Assumption!$E$164 -> 0 | J51: =J33*Assumption!$E$164 -> 0 | K51: =K33*Assumption!$E$164 -> 0 | L51: =L33*Assumption!$E$164 -> 0 | ... EF51: =EF33*Assumption!$E$164 -> 0
A52: BOH 운영비 | B52: 백만원 | C52: =SUM(E52:EF52) -> 7285.2262 | E52: =E34*Assumption!$E$165 -> 0 | F52: =F34*Assumption!$E$165 -> 0 | G52: =G34*Assumption!$E$165 -> 0 | H52: =H34*Assumption!$E$165 -> 0 | I52: =I34*Assumption!$E$165 -> 0 | J52: =J34*Assumption!$E$165 -> 0 | K52: =K34*Assumption!$E$165 -> 0 | L52: =L34*Assumption!$E$165 -> 0 | ... EF52: =EF34*Assumption!$E$165 -> 0
A53: 오피스 리징비용 | B53: 백만원 | C53: =SUM(E53:EF53) -> 9356.5957 | E53: =E35*CHOOSE(MIN(MAX(E16,1),3),Assumption!$E$178,Assumption!$E$179,Assumption!$E$180) -> 0 | F53: =F35*CHOOSE(MIN(MAX(F16,1),3),Assumption!$E$178,Assumption!$E$179,Assumption!$E$180) -> 0 | G53: =G35*CHOOSE(MIN(MAX(G16,1),3),Assumption!$E$178,Assumption!$E$179,Assumption!$E$180) -> 0 | H53: =H35*CHOOSE(MIN(MAX(H16,1),3),Assumption!$E$178,Assumption!$E$179,Assumption!$E$180) -> 0 | I53: =I35*CHOOSE(MIN(MAX(I16,1),3),Assumption!$E$178,Assumption!$E$179,Assumption!$E$180) -> 0 | J53: =J35*CHOOSE(MIN(MAX(J16,1),3),Assumption!$E$178,Assumption!$E$179,Assumption!$E$180) -> 0 | K53: =K35*CHOOSE(MIN(MAX(K16,1),3),Assumption!$E$178,Assumption!$E$179,Assumption!$E$180) -> 0 | L53: =L35*CHOOSE(MIN(MAX(L16,1),3),Assumption!$E$178,Assumption!$E$179,Assumption!$E$180) -> 0 | ... EF53: =EF35*CHOOSE(MIN(MAX(EF16,1),3),Assumption!$E$178,Assumption!$E$179,Assumption!$E$180) -> 0
A54: 오피스 관리비용 | B54: 백만원 | C54: =SUM(E54:EF54) -> 9214.873 | E54: =(E14=1)*Assumption!$E$181*Assumption!$E$170/1000*(1+Assumption!$E$174)^(MAX(E16,1)-1) -> 0 | F54: =(F14=1)*Assumption!$E$181*Assumption!$E$170/1000*(1+Assumption!$E$174)^(MAX(F16,1)-1) -> 0 | G54: =(G14=1)*Assumption!$E$181*Assumption!$E$170/1000*(1+Assumption!$E$174)^(MAX(G16,1)-1) -> 0 | H54: =(H14=1)*Assumption!$E$181*Assumption!$E$170/1000*(1+Assumption!$E$174)^(MAX(H16,1)-1) -> 0 | I54: =(I14=1)*Assumption!$E$181*Assumption!$E$170/1000*(1+Assumption!$E$174)^(MAX(I16,1)-1) -> 0 | J54: =(J14=1)*Assumption!$E$181*Assumption!$E$170/1000*(1+Assumption!$E$174)^(MAX(J16,1)-1) -> 0 | K54: =(K14=1)*Assumption!$E$181*Assumption!$E$170/1000*(1+Assumption!$E$174)^(MAX(K16,1)-1) -> 0 | L54: =(L14=1)*Assumption!$E$181*Assumption!$E$170/1000*(1+Assumption!$E$174)^(MAX(L16,1)-1) -> 0 | ... EF54: =(EF14=1)*Assumption!$E$181*Assumption!$E$170/1000*(1+Assumption!$E$174)^(MAX(EF16,1)-1) -> 0
A55: 부대시설 운영비 | B55: 백만원 | C55: =SUM(E55:EF55) -> 0 | E55: =E36*Assumption!$E$196+E37*Assumption!$E$209+E38*Assumption!$E$222+E39*Assumption!$E$235+E40*Assumption!$E$248 -> 0 | F55: =F36*Assumption!$E$196+F37*Assumption!$E$209+F38*Assumption!$E$222+F39*Assumption!$E$235+F40*Assumption!$E$248 -> 0 | G55: =G36*Assumption!$E$196+G37*Assumption!$E$209+G38*Assumption!$E$222+G39*Assumption!$E$235+G40*Assumption!$E$248 -> 0 | H55: =H36*Assumption!$E$196+H37*Assumption!$E$209+H38*Assumption!$E$222+H39*Assumption!$E$235+H40*Assumption!$E$248 -> 0 | I55: =I36*Assumption!$E$196+I37*Assumption!$E$209+I38*Assumption!$E$222+I39*Assumption!$E$235+I40*Assumption!$E$248 -> 0 | J55: =J36*Assumption!$E$196+J37*Assumption!$E$209+J38*Assumption!$E$222+J39*Assumption!$E$235+J40*Assumption!$E$248 -> 0 | K55: =K36*Assumption!$E$196+K37*Assumption!$E$209+K38*Assumption!$E$222+K39*Assumption!$E$235+K40*Assumption!$E$248 -> 0 | L55: =L36*Assumption!$E$196+L37*Assumption!$E$209+L38*Assumption!$E$222+L39*Assumption!$E$235+L40*Assumption!$E$248 -> 0 | ... EF55: =EF36*Assumption!$E$196+EF37*Assumption!$E$209+EF38*Assumption!$E$222+EF39*Assumption!$E$235+EF40*Assumption!$E$248 -> 0
A56: 직접운영비용 합계 | B56: 백만원 | C56: =SUM(E56:EF56) -> 706913.04 | E56: =SUM(E44:E55) -> 0 | F56: =SUM(F44:F55) -> 0 | G56: =SUM(G44:G55) -> 0 | H56: =SUM(H44:H55) -> 0 | I56: =SUM(I44:I55) -> 0 | J56: =SUM(J44:J55) -> 0 | K56: =SUM(K44:K55) -> 0 | L56: =SUM(L44:L55) -> 0 | ... EF56: =SUM(EF44:EF55) -> 0
A58: 용도별 NOI
A59: NOI - 시니어 레지던스 | B59: 백만원 | C59: =SUM(E59:EF59) -> 32621.512 | E59: =E21+E22+E23-E44 -> 0 | F59: =F21+F22+F23-F44 -> 0 | G59: =G21+G22+G23-G44 -> 0 | H59: =H21+H22+H23-H44 -> 0 | I59: =I21+I22+I23-I44 -> 0 | J59: =J21+J22+J23-J44 -> 0 | K59: =K21+K22+K23-K44 -> 0 | L59: =L21+L22+L23-L44 -> 0 | ... EF59: =EF21+EF22+EF23-EF44 -> 0
A60: NOI - 레지던스 | B60: 백만원 | C60: =SUM(E60:EF60) -> 42839.167 | E60: =E24+E25+E26-E45-E46 -> 0 | F60: =F24+F25+F26-F45-F46 -> 0 | G60: =G24+G25+G26-G45-G46 -> 0 | H60: =H24+H25+H26-H45-H46 -> 0 | I60: =I24+I25+I26-I45-I46 -> 0 | J60: =J24+J25+J26-J45-J46 -> 0 | K60: =K24+K25+K26-K45-K46 -> 0 | L60: =L24+L25+L26-L45-L46 -> 0 | ... EF60: =EF24+EF25+EF26-EF45-EF46 -> 0
A61: NOI - 호텔 | B61: 백만원 | C61: =SUM(E61:EF61) -> 132976.8 | E61: =SUM(E27:E34)-SUM(E47:E52) -> 0 | F61: =SUM(F27:F34)-SUM(F47:F52) -> 0 | G61: =SUM(G27:G34)-SUM(G47:G52) -> 0 | H61: =SUM(H27:H34)-SUM(H47:H52) -> 0 | I61: =SUM(I27:I34)-SUM(I47:I52) -> 0 | J61: =SUM(J27:J34)-SUM(J47:J52) -> 0 | K61: =SUM(K27:K34)-SUM(K47:K52) -> 0 | L61: =SUM(L27:L34)-SUM(L47:L52) -> 0 | ... EF61: =SUM(EF27:EF34)-SUM(EF47:EF52) -> 0
A62: NOI - 오피스 | B62: 백만원 | C62: =SUM(E62:EF62) -> 66369.038 | E62: =E35-E53-E54 -> 0 | F62: =F35-F53-F54 -> 0 | G62: =G35-G53-G54 -> 0 | H62: =H35-H53-H54 -> 0 | I62: =I35-I53-I54 -> 0 | J62: =J35-J53-J54 -> 0 | K62: =K35-K53-K54 -> 0 | L62: =L35-L53-L54 -> 0 | ... EF62: =EF35-EF53-EF54 -> 0
A63: NOI - 부대시설 | B63: 백만원 | C63: =SUM(E63:EF63) -> 41146.757 | E63: =SUM(E36:E40)-E55 -> 0 | F63: =SUM(F36:F40)-F55 -> 0 | G63: =SUM(G36:G40)-G55 -> 0 | H63: =SUM(H36:H40)-H55 -> 0 | I63: =SUM(I36:I40)-I55 -> 0 | J63: =SUM(J36:J40)-J55 -> 0 | K63: =SUM(K36:K40)-K55 -> 0 | L63: =SUM(L36:L40)-L55 -> 0 | ... EF63: =SUM(EF36:EF40)-EF55 -> 0
A64: NOI 합계 | B64: 백만원 | C64: =SUM(E64:EF64) -> 315953.28 | E64: =SUM(E59:E63) -> 0 | F64: =SUM(F59:F63) -> 0 | G64: =SUM(G59:G63) -> 0 | H64: =SUM(H59:H63) -> 0 | I64: =SUM(I59:I63) -> 0 | J64: =SUM(J59:J63) -> 0 | K64: =SUM(K59:K63) -> 0 | L64: =SUM(L59:L63) -> 0 | ... EF64: =SUM(EF59:EF63) -> 0
A66: 기타공통비용 및 리츠운용비(운영)
A67: 수선비 | B67: 백만원 | C67: =SUM(E67:EF67) -> 7663.4989 | E67: =(E14=1)*Assumption!$E$251*Assumption!$C$55/1000000*(1+Assumption!$E$256)^(MAX(E16,1)-1) -> 0 | F67: =(F14=1)*Assumption!$E$251*Assumption!$C$55/1000000*(1+Assumption!$E$256)^(MAX(F16,1)-1) -> 0 | G67: =(G14=1)*Assumption!$E$251*Assumption!$C$55/1000000*(1+Assumption!$E$256)^(MAX(G16,1)-1) -> 0 | H67: =(H14=1)*Assumption!$E$251*Assumption!$C$55/1000000*(1+Assumption!$E$256)^(MAX(H16,1)-1) -> 0 | I67: =(I14=1)*Assumption!$E$251*Assumption!$C$55/1000000*(1+Assumption!$E$256)^(MAX(I16,1)-1) -> 0 | J67: =(J14=1)*Assumption!$E$251*Assumption!$C$55/1000000*(1+Assumption!$E$256)^(MAX(J16,1)-1) -> 0 | K67: =(K14=1)*Assumption!$E$251*Assumption!$C$55/1000000*(1+Assumption!$E$256)^(MAX(K16,1)-1) -> 0 | L67: =(L14=1)*Assumption!$E$251*Assumption!$C$55/1000000*(1+Assumption!$E$256)^(MAX(L16,1)-1) -> 0 | ... EF67: =(EF14=1)*Assumption!$E$251*Assumption!$C$55/1000000*(1+Assumption!$E$256)^(MAX(EF16,1)-1) -> 0
A68: 보험료 | B68: 백만원 | C68: =SUM(E68:EF68) -> 7663.4989 | E68: =(E14=1)*Assumption!$E$252*Assumption!$C$55/1000000*(1+Assumption!$E$256)^(MAX(E16,1)-1) -> 0 | F68: =(F14=1)*Assumption!$E$252*Assumption!$C$55/1000000*(1+Assumption!$E$256)^(MAX(F16,1)-1) -> 0 | G68: =(G14=1)*Assumption!$E$252*Assumption!$C$55/1000000*(1+Assumption!$E$256)^(MAX(G16,1)-1) -> 0 | H68: =(H14=1)*Assumption!$E$252*Assumption!$C$55/1000000*(1+Assumption!$E$256)^(MAX(H16,1)-1) -> 0 | I68: =(I14=1)*Assumption!$E$252*Assumption!$C$55/1000000*(1+Assumption!$E$256)^(MAX(I16,1)-1) -> 0 | J68: =(J14=1)*Assumption!$E$252*Assumption!$C$55/1000000*(1+Assumption!$E$256)^(MAX(J16,1)-1) -> 0 | K68: =(K14=1)*Assumption!$E$252*Assumption!$C$55/1000000*(1+Assumption!$E$256)^(MAX(K16,1)-1) -> 0 | L68: =(L14=1)*Assumption!$E$252*Assumption!$C$55/1000000*(1+Assumption!$E$256)^(MAX(L16,1)-1) -> 0 | ... EF68: =(EF14=1)*Assumption!$E$252*Assumption!$C$55/1000000*(1+Assumption!$E$256)^(MAX(EF16,1)-1) -> 0
A69: PM 수수료 | B69: 백만원 | C69: =SUM(E69:EF69) -> 7663.4989 | E69: =(E14=1)*Assumption!$E$253*Assumption!$C$55/1000000*(1+Assumption!$E$256)^(MAX(E16,1)-1) -> 0 | F69: =(F14=1)*Assumption!$E$253*Assumption!$C$55/1000000*(1+Assumption!$E$256)^(MAX(F16,1)-1) -> 0 | G69: =(G14=1)*Assumption!$E$253*Assumption!$C$55/1000000*(1+Assumption!$E$256)^(MAX(G16,1)-1) -> 0 | H69: =(H14=1)*Assumption!$E$253*Assumption!$C$55/1000000*(1+Assumption!$E$256)^(MAX(H16,1)-1) -> 0 | I69: =(I14=1)*Assumption!$E$253*Assumption!$C$55/1000000*(1+Assumption!$E$256)^(MAX(I16,1)-1) -> 0 | J69: =(J14=1)*Assumption!$E$253*Assumption!$C$55/1000000*(1+Assumption!$E$256)^(MAX(J16,1)-1) -> 0 | K69: =(K14=1)*Assumption!$E$253*Assumption!$C$55/1000000*(1+Assumption!$E$256)^(MAX(K16,1)-1) -> 0 | L69: =(L14=1)*Assumption!$E$253*Assumption!$C$55/1000000*(1+Assumption!$E$256)^(MAX(L16,1)-1) -> 0 | ... EF69: =(EF14=1)*Assumption!$E$253*Assumption!$C$55/1000000*(1+Assumption!$E$256)^(MAX(EF16,1)-1) -> 0
A70: 교통유발부담금 | B70: 백만원 | C70: =SUM(E70:EF70) -> 8196.3633 | E70: =(E14=1)*Assumption!$E$254/12*(1+Assumption!$E$256)^(MAX(E16,1)-1) -> 0 | F70: =(F14=1)*Assumption!$E$254/12*(1+Assumption!$E$256)^(MAX(F16,1)-1) -> 0 | G70: =(G14=1)*Assumption!$E$254/12*(1+Assumption!$E$256)^(MAX(G16,1)-1) -> 0 | H70: =(H14=1)*Assumption!$E$254/12*(1+Assumption!$E$256)^(MAX(H16,1)-1) -> 0 | I70: =(I14=1)*Assumption!$E$254/12*(1+Assumption!$E$256)^(MAX(I16,1)-1) -> 0 | J70: =(J14=1)*Assumption!$E$254/12*(1+Assumption!$E$256)^(MAX(J16,1)-1) -> 0 | K70: =(K14=1)*Assumption!$E$254/12*(1+Assumption!$E$256)^(MAX(K16,1)-1) -> 0 | L70: =(L14=1)*Assumption!$E$254/12*(1+Assumption!$E$256)^(MAX(L16,1)-1) -> 0 | ... EF70: =(EF14=1)*Assumption!$E$254/12*(1+Assumption!$E$256)^(MAX(EF16,1)-1) -> 0
A71: 간주임대료 부가세 | B71: 백만원 | C71: =SUM(E71:EF71) -> 15614.254 | E71: =(E14=1)*0*Assumption!$E$255/12*Assumption!$D$539 -> 0 | F71: =(F14=1)*E86*Assumption!$E$255/12*Assumption!$D$539 -> 0 | G71: =(G14=1)*F86*Assumption!$E$255/12*Assumption!$D$539 -> 0 | H71: =(H14=1)*G86*Assumption!$E$255/12*Assumption!$D$539 -> 0 | I71: =(I14=1)*H86*Assumption!$E$255/12*Assumption!$D$539 -> 0 | J71: =(J14=1)*I86*Assumption!$E$255/12*Assumption!$D$539 -> 0 | K71: =(K14=1)*J86*Assumption!$E$255/12*Assumption!$D$539 -> 0 | L71: =(L14=1)*K86*Assumption!$E$255/12*Assumption!$D$539 -> 0 | M71: =(M14=1)*L86*Assumption!$E$255/12*Assumption!$D$539 -> 0 | ... EF71: =(EF14=1)*EE86*Assumption!$E$255/12*Assumption!$D$539 -> 0
A72: 리츠운용비(운영) | B72: 백만원 | C72: =SUM(E72:EF72) -> 6935.9777 | E72: =E17*Assumption!$E$410 -> 0 | F72: =F17*Assumption!$E$410 -> 0 | G72: =G17*Assumption!$E$410 -> 0 | H72: =H17*Assumption!$E$410 -> 0 | I72: =I17*Assumption!$E$410 -> 0 | J72: =J17*Assumption!$E$410 -> 0 | K72: =K17*Assumption!$E$410 -> 0 | L72: =L17*Assumption!$E$410 -> 0 | ... EF72: =EF17*Assumption!$E$410 -> 0
A73: 자산관리 수수료(매각보수) | B73: 백만원 | C73: =SUM(E73:EF73) -> 9377.6982 | E73: =IF(E6=Assumption!$E$22,Assumption!$R$404,0) -> 0 | F73: =IF(F6=Assumption!$E$22,Assumption!$R$404,0) -> 0 | G73: =IF(G6=Assumption!$E$22,Assumption!$R$404,0) -> 0 | H73: =IF(H6=Assumption!$E$22,Assumption!$R$404,0) -> 0 | I73: =IF(I6=Assumption!$E$22,Assumption!$R$404,0) -> 0 | J73: =IF(J6=Assumption!$E$22,Assumption!$R$404,0) -> 0 | K73: =IF(K6=Assumption!$E$22,Assumption!$R$404,0) -> 0 | L73: =IF(L6=Assumption!$E$22,Assumption!$R$404,0) -> 0 | ... EF73: =IF(EF6=Assumption!$E$22,Assumption!$R$404,0) -> 0
A74: 공통비용 합계 | B74: 백만원 | C74: =SUM(E74:EF74) -> 63114.79 | E74: =SUM(E67:E73) -> 0 | F74: =SUM(F67:F73) -> 0 | G74: =SUM(G67:G73) -> 0 | H74: =SUM(H67:H73) -> 0 | I74: =SUM(I67:I73) -> 0 | J74: =SUM(J67:J73) -> 0 | K74: =SUM(K67:K73) -> 0 | L74: =SUM(L67:L73) -> 0 | ... EF74: =SUM(EF67:EF73) -> 0
A75: 운영현금흐름(NOI-공통비용) | B75: 백만원 | C75: =SUM(E75:EF75) -> 252838.49 | E75: =E64-E74 -> 0 | F75: =F64-F74 -> 0 | G75: =G64-G74 -> 0 | H75: =H64-H74 -> 0 | I75: =I64-I74 -> 0 | J75: =J64-J74 -> 0 | K75: =K64-K74 -> 0 | L75: =L64-L74 -> 0 | ... EF75: =EF64-EF74 -> 0
A77: 임대·입주 보증금
A78: 시니어 레지던스 보증금 유입 | B78: 백만원 | C78: =SUM(E78:EF78) -> 540000 | E78: =Assumption!$E$84*(Assumption!$E$90*SUMIF(Assumption!$J$83:$J$87,E6,Assumption!$I$83:$I$87)+IF(E15=13,Assumption!$E$91-Assumption!$E$90,0)+IF(E15=25,Assumption!$E$92-Assumption!$E$91,0)) -> 0 | F78: =Assumption!$E$84*(Assumption!$E$90*SUMIF(Assumption!$J$83:$J$87,F6,Assumption!$I$83:$I$87)+IF(F15=13,Assumption!$E$91-Assumption!$E$90,0)+IF(F15=25,Assumption!$E$92-Assumption!$E$91,0)) -> 0 | G78: =Assumption!$E$84*(Assumption!$E$90*SUMIF(Assumption!$J$83:$J$87,G6,Assumption!$I$83:$I$87)+IF(G15=13,Assumption!$E$91-Assumption!$E$90,0)+IF(G15=25,Assumption!$E$92-Assumption!$E$91,0)) -> 0 | H78: =Assumption!$E$84*(Assumption!$E$90*SUMIF(Assumption!$J$83:$J$87,H6,Assumption!$I$83:$I$87)+IF(H15=13,Assumption!$E$91-Assumption!$E$90,0)+IF(H15=25,Assumption!$E$92-Assumption!$E$91,0)) -> 0 | I78: =Assumption!$E$84*(Assumption!$E$90*SUMIF(Assumption!$J$83:$J$87,I6,Assumption!$I$83:$I$87)+IF(I15=13,Assumption!$E$91-Assumption!$E$90,0)+IF(I15=25,Assumption!$E$92-Assumption!$E$91,0)) -> 0 | J78: =Assumption!$E$84*(Assumption!$E$90*SUMIF(Assumption!$J$83:$J$87,J6,Assumption!$I$83:$I$87)+IF(J15=13,Assumption!$E$91-Assumption!$E$90,0)+IF(J15=25,Assumption!$E$92-Assumption!$E$91,0)) -> 0 | K78: =Assumption!$E$84*(Assumption!$E$90*SUMIF(Assumption!$J$83:$J$87,K6,Assumption!$I$83:$I$87)+IF(K15=13,Assumption!$E$91-Assumption!$E$90,0)+IF(K15=25,Assumption!$E$92-Assumption!$E$91,0)) -> 0 | L78: =Assumption!$E$84*(Assumption!$E$90*SUMIF(Assumption!$J$83:$J$87,L6,Assumption!$I$83:$I$87)+IF(L15=13,Assumption!$E$91-Assumption!$E$90,0)+IF(L15=25,Assumption!$E$92-Assumption!$E$91,0)) -> 0 | ... EF78: =Assumption!$E$84*(Assumption!$E$90*SUMIF(Assumption!$J$83:$J$87,EF6,Assumption!$I$83:$I$87)+IF(EF15=13,Assumption!$E$91-Assumption!$E$90,0)+IF(EF15=25,Assumption!$E$92-Assumption!$E$91,0)) -> 0
A79: 레지던스 보증금 유입 | B79: 백만원 | C79: =SUM(E79:EF79) -> 310752 | E79: =Assumption!$E$115*(Assumption!$E$119*SUMIF(Assumption!$L$110:$L$114,E6,Assumption!$K$110:$K$114)+IF(E15=13,Assumption!$E$120-Assumption!$E$119,0)+IF(E15=25,Assumption!$E$121-Assumption!$E$120,0)) -> 0 | F79: =Assumption!$E$115*(Assumption!$E$119*SUMIF(Assumption!$L$110:$L$114,F6,Assumption!$K$110:$K$114)+IF(F15=13,Assumption!$E$120-Assumption!$E$119,0)+IF(F15=25,Assumption!$E$121-Assumption!$E$120,0)) -> 0 | G79: =Assumption!$E$115*(Assumption!$E$119*SUMIF(Assumption!$L$110:$L$114,G6,Assumption!$K$110:$K$114)+IF(G15=13,Assumption!$E$120-Assumption!$E$119,0)+IF(G15=25,Assumption!$E$121-Assumption!$E$120,0)) -> 0 | H79: =Assumption!$E$115*(Assumption!$E$119*SUMIF(Assumption!$L$110:$L$114,H6,Assumption!$K$110:$K$114)+IF(H15=13,Assumption!$E$120-Assumption!$E$119,0)+IF(H15=25,Assumption!$E$121-Assumption!$E$120,0)) -> 0 | I79: =Assumption!$E$115*(Assumption!$E$119*SUMIF(Assumption!$L$110:$L$114,I6,Assumption!$K$110:$K$114)+IF(I15=13,Assumption!$E$120-Assumption!$E$119,0)+IF(I15=25,Assumption!$E$121-Assumption!$E$120,0)) -> 0 | J79: =Assumption!$E$115*(Assumption!$E$119*SUMIF(Assumption!$L$110:$L$114,J6,Assumption!$K$110:$K$114)+IF(J15=13,Assumption!$E$120-Assumption!$E$119,0)+IF(J15=25,Assumption!$E$121-Assumption!$E$120,0)) -> 0 | K79: =Assumption!$E$115*(Assumption!$E$119*SUMIF(Assumption!$L$110:$L$114,K6,Assumption!$K$110:$K$114)+IF(K15=13,Assumption!$E$120-Assumption!$E$119,0)+IF(K15=25,Assumption!$E$121-Assumption!$E$120,0)) -> 0 | L79: =Assumption!$E$115*(Assumption!$E$119*SUMIF(Assumption!$L$110:$L$114,L6,Assumption!$K$110:$K$114)+IF(L15=13,Assumption!$E$120-Assumption!$E$119,0)+IF(L15=25,Assumption!$E$121-Assumption!$E$120,0)) -> 0 | ... EF79: =Assumption!$E$115*(Assumption!$E$119*SUMIF(Assumption!$L$110:$L$114,EF6,Assumption!$K$110:$K$114)+IF(EF15=13,Assumption!$E$120-Assumption!$E$119,0)+IF(EF15=25,Assumption!$E$121-Assumption!$E$120,0)) -> 0
A80: 호텔 회원보증금 유입 | B80: 백만원 | C80: =SUM(E80:EF80) -> 66000 | E80: =Assumption!$E$137*(IF(E15=1,Assumption!$E$142,0)+IF(E15=13,Assumption!$E$143-Assumption!$E$142,0)+IF(E15=25,Assumption!$E$144-Assumption!$E$143,0)) -> 0 | F80: =Assumption!$E$137*(IF(F15=1,Assumption!$E$142,0)+IF(F15=13,Assumption!$E$143-Assumption!$E$142,0)+IF(F15=25,Assumption!$E$144-Assumption!$E$143,0)) -> 0 | G80: =Assumption!$E$137*(IF(G15=1,Assumption!$E$142,0)+IF(G15=13,Assumption!$E$143-Assumption!$E$142,0)+IF(G15=25,Assumption!$E$144-Assumption!$E$143,0)) -> 0 | H80: =Assumption!$E$137*(IF(H15=1,Assumption!$E$142,0)+IF(H15=13,Assumption!$E$143-Assumption!$E$142,0)+IF(H15=25,Assumption!$E$144-Assumption!$E$143,0)) -> 0 | I80: =Assumption!$E$137*(IF(I15=1,Assumption!$E$142,0)+IF(I15=13,Assumption!$E$143-Assumption!$E$142,0)+IF(I15=25,Assumption!$E$144-Assumption!$E$143,0)) -> 0 | J80: =Assumption!$E$137*(IF(J15=1,Assumption!$E$142,0)+IF(J15=13,Assumption!$E$143-Assumption!$E$142,0)+IF(J15=25,Assumption!$E$144-Assumption!$E$143,0)) -> 0 | K80: =Assumption!$E$137*(IF(K15=1,Assumption!$E$142,0)+IF(K15=13,Assumption!$E$143-Assumption!$E$142,0)+IF(K15=25,Assumption!$E$144-Assumption!$E$143,0)) -> 0 | L80: =Assumption!$E$137*(IF(L15=1,Assumption!$E$142,0)+IF(L15=13,Assumption!$E$143-Assumption!$E$142,0)+IF(L15=25,Assumption!$E$144-Assumption!$E$143,0)) -> 0 | ... EF80: =Assumption!$E$137*(IF(EF15=1,Assumption!$E$142,0)+IF(EF15=13,Assumption!$E$143-Assumption!$E$142,0)+IF(EF15=25,Assumption!$E$144-Assumption!$E$143,0)) -> 0
A81: 시니어 부대 임대보증금 | B81: 백만원 | C81: =SUM(E81:EF81) -> 1500 | E81: =IF(E15=1,Assumption!$E$100,0) -> 0 | F81: =IF(F15=1,Assumption!$E$100,0) -> 0 | G81: =IF(G15=1,Assumption!$E$100,0) -> 0 | H81: =IF(H15=1,Assumption!$E$100,0) -> 0 | I81: =IF(I15=1,Assumption!$E$100,0) -> 0 | J81: =IF(J15=1,Assumption!$E$100,0) -> 0 | K81: =IF(K15=1,Assumption!$E$100,0) -> 0 | L81: =IF(L15=1,Assumption!$E$100,0) -> 0 | ... EF81: =IF(EF15=1,Assumption!$E$100,0) -> 0
A82: 오피스 임대보증금 | B82: 백만원 | C82: =SUM(E82:EF82) -> 14400 | E82: =IF(E15=1,Assumption!$E$168,0) -> 0 | F82: =IF(F15=1,Assumption!$E$168,0) -> 0 | G82: =IF(G15=1,Assumption!$E$168,0) -> 0 | H82: =IF(H15=1,Assumption!$E$168,0) -> 0 | I82: =IF(I15=1,Assumption!$E$168,0) -> 0 | J82: =IF(J15=1,Assumption!$E$168,0) -> 0 | K82: =IF(K15=1,Assumption!$E$168,0) -> 0 | L82: =IF(L15=1,Assumption!$E$168,0) -> 0 | ... EF82: =IF(EF15=1,Assumption!$E$168,0) -> 0
A83: 부대시설 임대보증금 | B83: 백만원 | C83: =SUM(E83:EF83) -> 9300 | E83: =IF(E15=1,Assumption!$E$186+Assumption!$E$199+Assumption!$E$212+Assumption!$E$225+Assumption!$E$238,0) -> 0 | F83: =IF(F15=1,Assumption!$E$186+Assumption!$E$199+Assumption!$E$212+Assumption!$E$225+Assumption!$E$238,0) -> 0 | G83: =IF(G15=1,Assumption!$E$186+Assumption!$E$199+Assumption!$E$212+Assumption!$E$225+Assumption!$E$238,0) -> 0 | H83: =IF(H15=1,Assumption!$E$186+Assumption!$E$199+Assumption!$E$212+Assumption!$E$225+Assumption!$E$238,0) -> 0 | I83: =IF(I15=1,Assumption!$E$186+Assumption!$E$199+Assumption!$E$212+Assumption!$E$225+Assumption!$E$238,0) -> 0 | J83: =IF(J15=1,Assumption!$E$186+Assumption!$E$199+Assumption!$E$212+Assumption!$E$225+Assumption!$E$238,0) -> 0 | K83: =IF(K15=1,Assumption!$E$186+Assumption!$E$199+Assumption!$E$212+Assumption!$E$225+Assumption!$E$238,0) -> 0 | L83: =IF(L15=1,Assumption!$E$186+Assumption!$E$199+Assumption!$E$212+Assumption!$E$225+Assumption!$E$238,0) -> 0 | ... EF83: =IF(EF15=1,Assumption!$E$186+Assumption!$E$199+Assumption!$E$212+Assumption!$E$225+Assumption!$E$238,0) -> 0
A84: 보증금 유입 합계 | B84: 백만원 | C84: =SUM(E84:EF84) -> 941952 | E84: =SUM(E78:E83) -> 0 | F84: =SUM(F78:F83) -> 0 | G84: =SUM(G78:G83) -> 0 | H84: =SUM(H78:H83) -> 0 | I84: =SUM(I78:I83) -> 0 | J84: =SUM(J78:J83) -> 0 | K84: =SUM(K78:K83) -> 0 | L84: =SUM(L78:L83) -> 0 | ... EF84: =SUM(EF78:EF83) -> 0
A85: 보증금 승계(처분시 매수인 인계) | B85: 백만원 | C85: =SUM(E85:EF85) -> 941952 | E85: =IF(E6=Assumption!$E$22,0+E84,0) -> 0 | F85: =IF(F6=Assumption!$E$22,E86+F84,0) -> 0 | G85: =IF(G6=Assumption!$E$22,F86+G84,0) -> 0 | H85: =IF(H6=Assumption!$E$22,G86+H84,0) -> 0 | I85: =IF(I6=Assumption!$E$22,H86+I84,0) -> 0 | J85: =IF(J6=Assumption!$E$22,I86+J84,0) -> 0 | K85: =IF(K6=Assumption!$E$22,J86+K84,0) -> 0 | L85: =IF(L6=Assumption!$E$22,K86+L84,0) -> 0 | M85: =IF(M6=Assumption!$E$22,L86+M84,0) -> 0 | ... EF85: =IF(EF6=Assumption!$E$22,EE86+EF84,0) -> 0
A86: 보증금 잔액 | B86: 백만원 | C86: =MAX(E86:EF86) -> 941952 | E86: =0+E84-E85 -> 0 | F86: =E86+F84-F85 -> 0 | G86: =F86+G84-G85 -> 0 | H86: =G86+H84-H85 -> 0 | I86: =H86+I84-I85 -> 0 | J86: =I86+J84-J85 -> 0 | K86: =J86+K84-K85 -> 0 | L86: =K86+L84-L85 -> 0 | M86: =L86+M84-M85 -> 0 | ... EF86: =EE86+EF84-EF85 -> 0
A88: 개발사업비 집행 (공제후 순액)
A89: 토지 계약금 | B89: 백만원 | C89: =SUM(E89:EF89) -> 11000 | E89: =IF(E6=Assumption!$E$10,Assumption!$R$342*Assumption!$D$538,0) -> 0 | F89: =IF(F6=Assumption!$E$10,Assumption!$R$342*Assumption!$D$538,0) -> 0 | G89: =IF(G6=Assumption!$E$10,Assumption!$R$342*Assumption!$D$538,0) -> 0 | H89: =IF(H6=Assumption!$E$10,Assumption!$R$342*Assumption!$D$538,0) -> 11000 | I89: =IF(I6=Assumption!$E$10,Assumption!$R$342*Assumption!$D$538,0) -> 0 | J89: =IF(J6=Assumption!$E$10,Assumption!$R$342*Assumption!$D$538,0) -> 0 | K89: =IF(K6=Assumption!$E$10,Assumption!$R$342*Assumption!$D$538,0) -> 0 | L89: =IF(L6=Assumption!$E$10,Assumption!$R$342*Assumption!$D$538,0) -> 0 | ... EF89: =IF(EF6=Assumption!$E$10,Assumption!$R$342*Assumption!$D$538,0) -> 0
A90: 토지 잔금·취득세·임차료·등기 | B90: 백만원 | C90: =SUM(E90:EF90) -> 221320 | E90: =IF(E6=Assumption!$E$14,Assumption!$R$342*(1-Assumption!$D$538)+Assumption!$R$343+Assumption!$R$344+Assumption!$R$345,0) -> 0 | F90: =IF(F6=Assumption!$E$14,Assumption!$R$342*(1-Assumption!$D$538)+Assumption!$R$343+Assumption!$R$344+Assumption!$R$345,0) -> 0 | G90: =IF(G6=Assumption!$E$14,Assumption!$R$342*(1-Assumption!$D$538)+Assumption!$R$343+Assumption!$R$344+Assumption!$R$345,0) -> 0 | H90: =IF(H6=Assumption!$E$14,Assumption!$R$342*(1-Assumption!$D$538)+Assumption!$R$343+Assumption!$R$344+Assumption!$R$345,0) -> 0 | I90: =IF(I6=Assumption!$E$14,Assumption!$R$342*(1-Assumption!$D$538)+Assumption!$R$343+Assumption!$R$344+Assumption!$R$345,0) -> 0 | J90: =IF(J6=Assumption!$E$14,Assumption!$R$342*(1-Assumption!$D$538)+Assumption!$R$343+Assumption!$R$344+Assumption!$R$345,0) -> 0 | K90: =IF(K6=Assumption!$E$14,Assumption!$R$342*(1-Assumption!$D$538)+Assumption!$R$343+Assumption!$R$344+Assumption!$R$345,0) -> 0 | L90: =IF(L6=Assumption!$E$14,Assumption!$R$342*(1-Assumption!$D$538)+Assumption!$R$343+Assumption!$R$344+Assumption!$R$345,0) -> 0 | ... EF90: =IF(EF6=Assumption!$E$14,Assumption!$R$342*(1-Assumption!$D$538)+Assumption!$R$343+Assumption!$R$344+Assumption!$R$345,0) -> 0
A91: 토지보유세(건설기간) | B91: 백만원 | C91: =SUM(E91:EF91) -> 5324 | E91: =E11*Assumption!$R$346/Assumption!$E$15 -> 0 | F91: =F11*Assumption!$R$346/Assumption!$E$15 -> 0 | G91: =G11*Assumption!$R$346/Assumption!$E$15 -> 0 | H91: =H11*Assumption!$R$346/Assumption!$E$15 -> 0 | I91: =I11*Assumption!$R$346/Assumption!$E$15 -> 0 | J91: =J11*Assumption!$R$346/Assumption!$E$15 -> 0 | K91: =K11*Assumption!$R$346/Assumption!$E$15 -> 0 | L91: =L11*Assumption!$R$346/Assumption!$E$15 -> 0 | ... EF91: =EF11*Assumption!$R$346/Assumption!$E$15 -> 0
A92: 직접공사비(유보금 제외, S-curve) | B92: 백만원 | C92: =SUM(E92:EF92) -> 554609.17 | E92: =E13*(Assumption!$R$351-Assumption!$E$417) -> 0 | F92: =F13*(Assumption!$R$351-Assumption!$E$417) -> 0 | G92: =G13*(Assumption!$R$351-Assumption!$E$417) -> 0 | H92: =H13*(Assumption!$R$351-Assumption!$E$417) -> 0 | I92: =I13*(Assumption!$R$351-Assumption!$E$417) -> 0 | J92: =J13*(Assumption!$R$351-Assumption!$E$417) -> 0 | K92: =K13*(Assumption!$R$351-Assumption!$E$417) -> 0 | L92: =L13*(Assumption!$R$351-Assumption!$E$417) -> 0 | ... EF92: =EF13*(Assumption!$R$351-Assumption!$E$417) -> 0
A93: 공사비 유보금 지급 | B93: 백만원 | C93: =SUM(E93:EF93) -> 59683.967 | E93: =IF(E6=Assumption!$E$18,Assumption!$E$417,0) -> 0 | F93: =IF(F6=Assumption!$E$18,Assumption!$E$417,0) -> 0 | G93: =IF(G6=Assumption!$E$18,Assumption!$E$417,0) -> 0 | H93: =IF(H6=Assumption!$E$18,Assumption!$E$417,0) -> 0 | I93: =IF(I6=Assumption!$E$18,Assumption!$E$417,0) -> 0 | J93: =IF(J6=Assumption!$E$18,Assumption!$E$417,0) -> 0 | K93: =IF(K6=Assumption!$E$18,Assumption!$E$417,0) -> 0 | L93: =IF(L6=Assumption!$E$18,Assumption!$E$417,0) -> 0 | ... EF93: =IF(EF6=Assumption!$E$18,Assumption!$E$417,0) -> 0
A94: 간접공사비(S-curve) | B94: 백만원 | C94: =SUM(E94:EF94) -> 476391.09 | E94: =E13*Assumption!$R$365 -> 0 | F94: =F13*Assumption!$R$365 -> 0 | G94: =G13*Assumption!$R$365 -> 0 | H94: =H13*Assumption!$R$365 -> 0 | I94: =I13*Assumption!$R$365 -> 0 | J94: =J13*Assumption!$R$365 -> 0 | K94: =K13*Assumption!$R$365 -> 0 | L94: =L13*Assumption!$R$365 -> 0 | ... EF94: =EF13*Assumption!$R$365 -> 0
A95: 판매비 | B95: 백만원 | C95: =SUM(E95:EF95) -> 30843.703 | E95: =E11*Assumption!$R$370/Assumption!$E$15 -> 0 | F95: =F11*Assumption!$R$370/Assumption!$E$15 -> 0 | G95: =G11*Assumption!$R$370/Assumption!$E$15 -> 0 | H95: =H11*Assumption!$R$370/Assumption!$E$15 -> 0 | I95: =I11*Assumption!$R$370/Assumption!$E$15 -> 0 | J95: =J11*Assumption!$R$370/Assumption!$E$15 -> 0 | K95: =K11*Assumption!$R$370/Assumption!$E$15 -> 0 | L95: =L11*Assumption!$R$370/Assumption!$E$15 -> 0 | ... EF95: =EF11*Assumption!$R$370/Assumption!$E$15 -> 0
A96: 부대비용(보존등기비 등) | B96: 백만원 | C96: =SUM(E96:EF96) -> 29598.314 | E96: =IF(E6=Assumption!$E$16,Assumption!$R$373,0) -> 0 | F96: =IF(F6=Assumption!$E$16,Assumption!$R$373,0) -> 0 | G96: =IF(G6=Assumption!$E$16,Assumption!$R$373,0) -> 0 | H96: =IF(H6=Assumption!$E$16,Assumption!$R$373,0) -> 0 | I96: =IF(I6=Assumption!$E$16,Assumption!$R$373,0) -> 0 | J96: =IF(J6=Assumption!$E$16,Assumption!$R$373,0) -> 0 | K96: =IF(K6=Assumption!$E$16,Assumption!$R$373,0) -> 0 | L96: =IF(L6=Assumption!$E$16,Assumption!$R$373,0) -> 0 | ... EF96: =IF(EF6=Assumption!$E$16,Assumption!$R$373,0) -> 0
A97: 리츠운용비(일시: 등록면허세·실사·예비비) | B97: 백만원 | C97: =SUM(E97:EF97) -> 1945.329 | E97: =IF(E6=Assumption!$E$8,Assumption!$R$393+Assumption!$R$394+Assumption!$R$395,0) -> 1945.329 | F97: =IF(F6=Assumption!$E$8,Assumption!$R$393+Assumption!$R$394+Assumption!$R$395,0) -> 0 | G97: =IF(G6=Assumption!$E$8,Assumption!$R$393+Assumption!$R$394+Assumption!$R$395,0) -> 0 | H97: =IF(H6=Assumption!$E$8,Assumption!$R$393+Assumption!$R$394+Assumption!$R$395,0) -> 0 | I97: =IF(I6=Assumption!$E$8,Assumption!$R$393+Assumption!$R$394+Assumption!$R$395,0) -> 0 | J97: =IF(J6=Assumption!$E$8,Assumption!$R$393+Assumption!$R$394+Assumption!$R$395,0) -> 0 | K97: =IF(K6=Assumption!$E$8,Assumption!$R$393+Assumption!$R$394+Assumption!$R$395,0) -> 0 | L97: =IF(L6=Assumption!$E$8,Assumption!$R$393+Assumption!$R$394+Assumption!$R$395,0) -> 0 | ... EF97: =IF(EF6=Assumption!$E$8,Assumption!$R$393+Assumption!$R$394+Assumption!$R$395,0) -> 0
A98: 리츠운용비(매입보수) | B98: 백만원 | C98: =SUM(E98:EF98) -> 4777.0727 | E98: =IF(E6=Assumption!$E$14,Assumption!$R$388,0) -> 0 | F98: =IF(F6=Assumption!$E$14,Assumption!$R$388,0) -> 0 | G98: =IF(G6=Assumption!$E$14,Assumption!$R$388,0) -> 0 | H98: =IF(H6=Assumption!$E$14,Assumption!$R$388,0) -> 0 | I98: =IF(I6=Assumption!$E$14,Assumption!$R$388,0) -> 0 | J98: =IF(J6=Assumption!$E$14,Assumption!$R$388,0) -> 0 | K98: =IF(K6=Assumption!$E$14,Assumption!$R$388,0) -> 0 | L98: =IF(L6=Assumption!$E$14,Assumption!$R$388,0) -> 0 | ... EF98: =IF(EF6=Assumption!$E$14,Assumption!$R$388,0) -> 0
A99: 리츠운용비(개발기간 정기) | B99: 백만원 | C99: =SUM(E99:EF99) -> 5577.5696 | E99: =E10*(Assumption!$R$387+Assumption!$R$389+Assumption!$R$390+Assumption!$R$391+Assumption!$R$392)/(Assumption!$E$25*12) -> 92.959493 | F99: =F10*(Assumption!$R$387+Assumption!$R$389+Assumption!$R$390+Assumption!$R$391+Assumption!$R$392)/(Assumption!$E$25*12) -> 92.959493 | G99: =G10*(Assumption!$R$387+Assumption!$R$389+Assumption!$R$390+Assumption!$R$391+Assumption!$R$392)/(Assumption!$E$25*12) -> 92.959493 | H99: =H10*(Assumption!$R$387+Assumption!$R$389+Assumption!$R$390+Assumption!$R$391+Assumption!$R$392)/(Assumption!$E$25*12) -> 92.959493 | I99: =I10*(Assumption!$R$387+Assumption!$R$389+Assumption!$R$390+Assumption!$R$391+Assumption!$R$392)/(Assumption!$E$25*12) -> 92.959493 | J99: =J10*(Assumption!$R$387+Assumption!$R$389+Assumption!$R$390+Assumption!$R$391+Assumption!$R$392)/(Assumption!$E$25*12) -> 92.959493 | K99: =K10*(Assumption!$R$387+Assumption!$R$389+Assumption!$R$390+Assumption!$R$391+Assumption!$R$392)/(Assumption!$E$25*12) -> 92.959493 | L99: =L10*(Assumption!$R$387+Assumption!$R$389+Assumption!$R$390+Assumption!$R$391+Assumption!$R$392)/(Assumption!$E$25*12) -> 92.959493 | ... EF99: =EF10*(Assumption!$R$387+Assumption!$R$389+Assumption!$R$390+Assumption!$R$391+Assumption!$R$392)/(Assumption!$E$25*12) -> 0
A100: 개발사업비 집행 합계 | B100: 백만원 | C100: =SUM(E100:EF100) -> 1401070.2 | E100: =SUM(E89:E99) -> 2038.2885 | F100: =SUM(F89:F99) -> 92.959493 | G100: =SUM(G89:G99) -> 92.959493 | H100: =SUM(H89:H99) -> 11092.959 | I100: =SUM(I89:I99) -> 92.959493 | J100: =SUM(J89:J99) -> 92.959493 | K100: =SUM(K89:K99) -> 92.959493 | L100: =SUM(L89:L99) -> 92.959493 | ... EF100: =SUM(EF89:EF99) -> 0
A102: PF (개발기간)
A103: Tr.A 취급수수료 | B103: 백만원 | C103: =SUM(E103:EF103) -> 8210.9752 | E103: =IF(E6=Assumption!$E$14,Assumption!$E$436*Assumption!$J$467,0) -> 0 | F103: =IF(F6=Assumption!$E$14,Assumption!$E$436*Assumption!$J$467,0) -> 0 | G103: =IF(G6=Assumption!$E$14,Assumption!$E$436*Assumption!$J$467,0) -> 0 | H103: =IF(H6=Assumption!$E$14,Assumption!$E$436*Assumption!$J$467,0) -> 0 | I103: =IF(I6=Assumption!$E$14,Assumption!$E$436*Assumption!$J$467,0) -> 0 | J103: =IF(J6=Assumption!$E$14,Assumption!$E$436*Assumption!$J$467,0) -> 0 | K103: =IF(K6=Assumption!$E$14,Assumption!$E$436*Assumption!$J$467,0) -> 0 | L103: =IF(L6=Assumption!$E$14,Assumption!$E$436*Assumption!$J$467,0) -> 0 | ... EF103: =IF(EF6=Assumption!$E$14,Assumption!$E$436*Assumption!$J$467,0) -> 0
A104: Tr.B 취급수수료 | B104: 백만원 | C104: =SUM(E104:EF104) -> 1642.6549 | E104: =IF(E6=Assumption!$E$14,Assumption!$E$437*Assumption!$J$468,0) -> 0 | F104: =IF(F6=Assumption!$E$14,Assumption!$E$437*Assumption!$J$468,0) -> 0 | G104: =IF(G6=Assumption!$E$14,Assumption!$E$437*Assumption!$J$468,0) -> 0 | H104: =IF(H6=Assumption!$E$14,Assumption!$E$437*Assumption!$J$468,0) -> 0 | I104: =IF(I6=Assumption!$E$14,Assumption!$E$437*Assumption!$J$468,0) -> 0 | J104: =IF(J6=Assumption!$E$14,Assumption!$E$437*Assumption!$J$468,0) -> 0 | K104: =IF(K6=Assumption!$E$14,Assumption!$E$437*Assumption!$J$468,0) -> 0 | L104: =IF(L6=Assumption!$E$14,Assumption!$E$437*Assumption!$J$468,0) -> 0 | ... EF104: =IF(EF6=Assumption!$E$14,Assumption!$E$437*Assumption!$J$468,0) -> 0
A105: Tr.C 취급수수료 | B105: 백만원 | C105: =SUM(E105:EF105) -> 1641.5053 | E105: =IF(E6=Assumption!$E$14,Assumption!$E$438*Assumption!$J$469,0) -> 0 | F105: =IF(F6=Assumption!$E$14,Assumption!$E$438*Assumption!$J$469,0) -> 0 | G105: =IF(G6=Assumption!$E$14,Assumption!$E$438*Assumption!$J$469,0) -> 0 | H105: =IF(H6=Assumption!$E$14,Assumption!$E$438*Assumption!$J$469,0) -> 0 | I105: =IF(I6=Assumption!$E$14,Assumption!$E$438*Assumption!$J$469,0) -> 0 | J105: =IF(J6=Assumption!$E$14,Assumption!$E$438*Assumption!$J$469,0) -> 0 | K105: =IF(K6=Assumption!$E$14,Assumption!$E$438*Assumption!$J$469,0) -> 0 | L105: =IF(L6=Assumption!$E$14,Assumption!$E$438*Assumption!$J$469,0) -> 0 | ... EF105: =IF(EF6=Assumption!$E$14,Assumption!$E$438*Assumption!$J$469,0) -> 0
A106: Tr.A 이자비용 | B106: 백만원 | C106: =SUM(E106:EF106) -> 17629.919 | E106: =0*Assumption!$K$467/12 -> 0 | F106: =E121*Assumption!$K$467/12 -> 0 | G106: =F121*Assumption!$K$467/12 -> 0 | H106: =G121*Assumption!$K$467/12 -> 0 | I106: =H121*Assumption!$K$467/12 -> 0 | J106: =I121*Assumption!$K$467/12 -> 0 | K106: =J121*Assumption!$K$467/12 -> 0 | L106: =K121*Assumption!$K$467/12 -> 0 | M106: =L121*Assumption!$K$467/12 -> 0 | ... EF106: =EE121*Assumption!$K$467/12 -> 0
A107: Tr.B 이자비용 | B107: 백만원 | C107: =SUM(E107:EF107) -> 19183.889 | E107: =0*Assumption!$K$468/12 -> 0 | F107: =E122*Assumption!$K$468/12 -> 0 | G107: =F122*Assumption!$K$468/12 -> 0 | H107: =G122*Assumption!$K$468/12 -> 0 | I107: =H122*Assumption!$K$468/12 -> 0 | J107: =I122*Assumption!$K$468/12 -> 0 | K107: =J122*Assumption!$K$468/12 -> 0 | L107: =K122*Assumption!$K$468/12 -> 0 | M107: =L122*Assumption!$K$468/12 -> 0 | ... EF107: =EE122*Assumption!$K$468/12 -> 0
A108: Tr.C 이자비용 | B108: 백만원 | C108: =SUM(E108:EF108) -> 31542.554 | E108: =0*Assumption!$K$469/12 -> 0 | F108: =E123*Assumption!$K$469/12 -> 0 | G108: =F123*Assumption!$K$469/12 -> 0 | H108: =G123*Assumption!$K$469/12 -> 0 | I108: =H123*Assumption!$K$469/12 -> 0 | J108: =I123*Assumption!$K$469/12 -> 0 | K108: =J123*Assumption!$K$469/12 -> 0 | L108: =K123*Assumption!$K$469/12 -> 0 | M108: =L123*Assumption!$K$469/12 -> 0 | ... EF108: =EE123*Assumption!$K$469/12 -> 0
A109: Tr.A 미인출수수료 | B109: 백만원 | C109: =SUM(E109:EF109) -> 13013.059 | E109: =E11*MAX(0,Assumption!$E$436-0)*Assumption!$O$467/12 -> 0 | F109: =F11*MAX(0,Assumption!$E$436-E121)*Assumption!$O$467/12 -> 0 | G109: =G11*MAX(0,Assumption!$E$436-F121)*Assumption!$O$467/12 -> 0 | H109: =H11*MAX(0,Assumption!$E$436-G121)*Assumption!$O$467/12 -> 0 | I109: =I11*MAX(0,Assumption!$E$436-H121)*Assumption!$O$467/12 -> 0 | J109: =J11*MAX(0,Assumption!$E$436-I121)*Assumption!$O$467/12 -> 0 | K109: =K11*MAX(0,Assumption!$E$436-J121)*Assumption!$O$467/12 -> 0 | L109: =L11*MAX(0,Assumption!$E$436-K121)*Assumption!$O$467/12 -> 0 | M109: =M11*MAX(0,Assumption!$E$436-L121)*Assumption!$O$467/12 -> 0 | ... EF109: =EF11*MAX(0,Assumption!$E$436-EE121)*Assumption!$O$467/12 -> 0
...

Sheet Annual
A1: 연도별 요약 (CF 시트 집계) — 단위: 백만원
A3: 구분 | B3: 합계 | C3: =YEAR(Assumption!$E$8) -> 2026 | D3: =C3+1 -> 2027 | E3: =D3+1 -> 2028 | F3: =E3+1 -> 2029 | G3: =F3+1 -> 2030 | H3: =G3+1 -> 2031 | I3: =H3+1 -> 2032 | J3: =I3+1 -> 2033 | K3: =J3+1 -> 2034 | ... M3: =L3+1 -> 2036
A4: 운영
A5: 운영수입 합계 | B5: =SUM(C5:M5) -> 1022866.3 | C5: =SUMIF(CF!$E$7:$EF$7,C$3,CF!$E$41:$EF$41) -> 0 | D5: =SUMIF(CF!$E$7:$EF$7,D$3,CF!$E$41:$EF$41) -> 0 | E5: =SUMIF(CF!$E$7:$EF$7,E$3,CF!$E$41:$EF$41) -> 0 | F5: =SUMIF(CF!$E$7:$EF$7,F$3,CF!$E$41:$EF$41) -> 0 | G5: =SUMIF(CF!$E$7:$EF$7,G$3,CF!$E$41:$EF$41) -> 0 | H5: =SUMIF(CF!$E$7:$EF$7,H$3,CF!$E$41:$EF$41) -> 145507.98 | I5: =SUMIF(CF!$E$7:$EF$7,I$3,CF!$E$41:$EF$41) -> 200951.57 | J5: =SUMIF(CF!$E$7:$EF$7,J$3,CF!$E$41:$EF$41) -> 209248.63 | ... M5: =SUMIF(CF!$E$7:$EF$7,M$3,CF!$E$41:$EF$41) -> 36022.258
A6: 직접운영비용 | B6: =SUM(C6:M6) -> 706913.04 | C6: =SUMIF(CF!$E$7:$EF$7,C$3,CF!$E$56:$EF$56) -> 0 | D6: =SUMIF(CF!$E$7:$EF$7,D$3,CF!$E$56:$EF$56) -> 0 | E6: =SUMIF(CF!$E$7:$EF$7,E$3,CF!$E$56:$EF$56) -> 0 | F6: =SUMIF(CF!$E$7:$EF$7,F$3,CF!$E$56:$EF$56) -> 0 | G6: =SUMIF(CF!$E$7:$EF$7,G$3,CF!$E$56:$EF$56) -> 0 | H6: =SUMIF(CF!$E$7:$EF$7,H$3,CF!$E$56:$EF$56) -> 102004.83 | I6: =SUMIF(CF!$E$7:$EF$7,I$3,CF!$E$56:$EF$56) -> 138846.41 | J6: =SUMIF(CF!$E$7:$EF$7,J$3,CF!$E$56:$EF$56) -> 144187.65 | ... M6: =SUMIF(CF!$E$7:$EF$7,M$3,CF!$E$56:$EF$56) -> 24789.909
A7: NOI - 시니어 레지던스 | B7: =SUM(C7:M7) -> 32621.512 | C7: =SUMIF(CF!$E$7:$EF$7,C$3,CF!$E$59:$EF$59) -> 0 | D7: =SUMIF(CF!$E$7:$EF$7,D$3,CF!$E$59:$EF$59) -> 0 | E7: =SUMIF(CF!$E$7:$EF$7,E$3,CF!$E$59:$EF$59) -> 0 | F7: =SUMIF(CF!$E$7:$EF$7,F$3,CF!$E$59:$EF$59) -> 0 | G7: =SUMIF(CF!$E$7:$EF$7,G$3,CF!$E$59:$EF$59) -> 0 | H7: =SUMIF(CF!$E$7:$EF$7,H$3,CF!$E$59:$EF$59) -> 4591.644 | I7: =SUMIF(CF!$E$7:$EF$7,I$3,CF!$E$59:$EF$59) -> 6399.9149 | J7: =SUMIF(CF!$E$7:$EF$7,J$3,CF!$E$59:$EF$59) -> 6687.535 | ... M7: =SUMIF(CF!$E$7:$EF$7,M$3,CF!$E$59:$EF$59) -> 1163.4206
A8: NOI - 레지던스 | B8: =SUM(C8:M8) -> 42839.167 | C8: =SUMIF(CF!$E$7:$EF$7,C$3,CF!$E$60:$EF$60) -> 0 | D8: =SUMIF(CF!$E$7:$EF$7,D$3,CF!$E$60:$EF$60) -> 0 | E8: =SUMIF(CF!$E$7:$EF$7,E$3,CF!$E$60:$EF$60) -> 0 | F8: =SUMIF(CF!$E$7:$EF$7,F$3,CF!$E$60:$EF$60) -> 0 | G8: =SUMIF(CF!$E$7:$EF$7,G$3,CF!$E$60:$EF$60) -> 0 | H8: =SUMIF(CF!$E$7:$EF$7,H$3,CF!$E$60:$EF$60) -> 6131.9139 | I8: =SUMIF(CF!$E$7:$EF$7,I$3,CF!$E$60:$EF$60) -> 8419.127 | J8: =SUMIF(CF!$E$7:$EF$7,J$3,CF!$E$60:$EF$60) -> 8752.5996 | ... M8: =SUMIF(CF!$E$7:$EF$7,M$3,CF!$E$60:$EF$60) -> 1501.6699
A9: NOI - 호텔 | B9: =SUM(C9:M9) -> 132976.8 | C9: =SUMIF(CF!$E$7:$EF$7,C$3,CF!$E$61:$EF$61) -> 0 | D9: =SUMIF(CF!$E$7:$EF$7,D$3,CF!$E$61:$EF$61) -> 0 | E9: =SUMIF(CF!$E$7:$EF$7,E$3,CF!$E$61:$EF$61) -> 0 | F9: =SUMIF(CF!$E$7:$EF$7,F$3,CF!$E$61:$EF$61) -> 0 | G9: =SUMIF(CF!$E$7:$EF$7,G$3,CF!$E$61:$EF$61) -> 0 | H9: =SUMIF(CF!$E$7:$EF$7,H$3,CF!$E$61:$EF$61) -> 19034.038 | I9: =SUMIF(CF!$E$7:$EF$7,I$3,CF!$E$61:$EF$61) -> 26133.763 | J9: =SUMIF(CF!$E$7:$EF$7,J$3,CF!$E$61:$EF$61) -> 27168.893 | ... M9: =SUMIF(CF!$E$7:$EF$7,M$3,CF!$E$61:$EF$61) -> 4661.3246
A10: NOI - 오피스 | B10: =SUM(C10:M10) -> 66369.038 | C10: =SUMIF(CF!$E$7:$EF$7,C$3,CF!$E$62:$EF$62) -> 0 | D10: =SUMIF(CF!$E$7:$EF$7,D$3,CF!$E$62:$EF$62) -> 0 | E10: =SUMIF(CF!$E$7:$EF$7,E$3,CF!$E$62:$EF$62) -> 0 | F10: =SUMIF(CF!$E$7:$EF$7,F$3,CF!$E$62:$EF$62) -> 0 | G10: =SUMIF(CF!$E$7:$EF$7,G$3,CF!$E$62:$EF$62) -> 0 | H10: =SUMIF(CF!$E$7:$EF$7,H$3,CF!$E$62:$EF$62) -> 7156.6406 | I10: =SUMIF(CF!$E$7:$EF$7,I$3,CF!$E$62:$EF$62) -> 13113.878 | J10: =SUMIF(CF!$E$7:$EF$7,J$3,CF!$E$62:$EF$62) -> 14252.711 | ... M10: =SUMIF(CF!$E$7:$EF$7,M$3,CF!$E$62:$EF$62) -> 2479.5231
A11: NOI - 부대시설 | B11: =SUM(C11:M11) -> 41146.757 | C11: =SUMIF(CF!$E$7:$EF$7,C$3,CF!$E$63:$EF$63) -> 0 | D11: =SUMIF(CF!$E$7:$EF$7,D$3,CF!$E$63:$EF$63) -> 0 | E11: =SUMIF(CF!$E$7:$EF$7,E$3,CF!$E$63:$EF$63) -> 0 | F11: =SUMIF(CF!$E$7:$EF$7,F$3,CF!$E$63:$EF$63) -> 0 | G11: =SUMIF(CF!$E$7:$EF$7,G$3,CF!$E$63:$EF$63) -> 0 | H11: =SUMIF(CF!$E$7:$EF$7,H$3,CF!$E$63:$EF$63) -> 6588.9123 | I11: =SUMIF(CF!$E$7:$EF$7,I$3,CF!$E$63:$EF$63) -> 8038.473 | J11: =SUMIF(CF!$E$7:$EF$7,J$3,CF!$E$63:$EF$63) -> 8199.2425 | ... M11: =SUMIF(CF!$E$7:$EF$7,M$3,CF!$E$63:$EF$63) -> 1426.4101
A12: NOI 합계 | B12: =SUM(C12:M12) -> 315953.28 | C12: =SUMIF(CF!$E$7:$EF$7,C$3,CF!$E$64:$EF$64) -> 0 | D12: =SUMIF(CF!$E$7:$EF$7,D$3,CF!$E$64:$EF$64) -> 0 | E12: =SUMIF(CF!$E$7:$EF$7,E$3,CF!$E$64:$EF$64) -> 0 | F12: =SUMIF(CF!$E$7:$EF$7,F$3,CF!$E$64:$EF$64) -> 0 | G12: =SUMIF(CF!$E$7:$EF$7,G$3,CF!$E$64:$EF$64) -> 0 | H12: =SUMIF(CF!$E$7:$EF$7,H$3,CF!$E$64:$EF$64) -> 43503.149 | I12: =SUMIF(CF!$E$7:$EF$7,I$3,CF!$E$64:$EF$64) -> 62105.156 | J12: =SUMIF(CF!$E$7:$EF$7,J$3,CF!$E$64:$EF$64) -> 65060.981 | ... M12: =SUMIF(CF!$E$7:$EF$7,M$3,CF!$E$64:$EF$64) -> 11232.348
A13: 공통비용·리츠운용비 | B13: =SUM(C13:M13) -> 63114.79 | C13: =SUMIF(CF!$E$7:$EF$7,C$3,CF!$E$74:$EF$74) -> 0 | D13: =SUMIF(CF!$E$7:$EF$7,D$3,CF!$E$74:$EF$74) -> 0 | E13: =SUMIF(CF!$E$7:$EF$7,E$3,CF!$E$74:$EF$74) -> 0 | F13: =SUMIF(CF!$E$7:$EF$7,F$3,CF!$E$74:$EF$74) -> 0 | G13: =SUMIF(CF!$E$7:$EF$7,G$3,CF!$E$74:$EF$74) -> 0 | H13: =SUMIF(CF!$E$7:$EF$7,H$3,CF!$E$74:$EF$74) -> 8190.5983 | I13: =SUMIF(CF!$E$7:$EF$7,I$3,CF!$E$74:$EF$74) -> 10504.036 | J13: =SUMIF(CF!$E$7:$EF$7,J$3,CF!$E$74:$EF$74) -> 10820.972 | ... M13: =SUMIF(CF!$E$7:$EF$7,M$3,CF!$E$74:$EF$74) -> 11558.781
A14: 운영현금흐름 | B14: =SUM(C14:M14) -> 252838.49 | C14: =SUMIF(CF!$E$7:$EF$7,C$3,CF!$E$75:$EF$75) -> 0 | D14: =SUMIF(CF!$E$7:$EF$7,D$3,CF!$E$75:$EF$75) -> 0 | E14: =SUMIF(CF!$E$7:$EF$7,E$3,CF!$E$75:$EF$75) -> 0 | F14: =SUMIF(CF!$E$7:$EF$7,F$3,CF!$E$75:$EF$75) -> 0 | G14: =SUMIF(CF!$E$7:$EF$7,G$3,CF!$E$75:$EF$75) -> 0 | H14: =SUMIF(CF!$E$7:$EF$7,H$3,CF!$E$75:$EF$75) -> 35312.55 | I14: =SUMIF(CF!$E$7:$EF$7,I$3,CF!$E$75:$EF$75) -> 51601.119 | J14: =SUMIF(CF!$E$7:$EF$7,J$3,CF!$E$75:$EF$75) -> 54240.009 | ... M14: =SUMIF(CF!$E$7:$EF$7,M$3,CF!$E$75:$EF$75) -> -326.43265
A15: 개발 및 금융
A16: 개발사업비 집행 | B16: =SUM(C16:M16) -> 1401070.2 | C16: =SUMIF(CF!$E$7:$EF$7,C$3,CF!$E$100:$EF$100) -> 13874.924 | D16: =SUMIF(CF!$E$7:$EF$7,D$3,CF!$E$100:$EF$100) -> 253559.35 | E16: =SUMIF(CF!$E$7:$EF$7,E$3,CF!$E$100:$EF$100) -> 315713.7 | F16: =SUMIF(CF!$E$7:$EF$7,F$3,CF!$E$100:$EF$100) -> 457532.55 | G16: =SUMIF(CF!$E$7:$EF$7,G$3,CF!$E$100:$EF$100) -> 263441.5 | H16: =SUMIF(CF!$E$7:$EF$7,H$3,CF!$E$100:$EF$100) -> 96948.181 | I16: =SUMIF(CF!$E$7:$EF$7,I$3,CF!$E$100:$EF$100) -> 0 | J16: =SUMIF(CF!$E$7:$EF$7,J$3,CF!$E$100:$EF$100) -> 0 | ... M16: =SUMIF(CF!$E$7:$EF$7,M$3,CF!$E$100:$EF$100) -> 0
A17: PF 금융비용 | B17: =SUM(C17:M17) -> 95505.682 | C17: =SUMIF(CF!$E$7:$EF$7,C$3,CF!$E$112:$EF$112) -> 0 | D17: =SUMIF(CF!$E$7:$EF$7,D$3,CF!$E$112:$EF$112) -> 13410.991 | E17: =SUMIF(CF!$E$7:$EF$7,E$3,CF!$E$112:$EF$112) -> 6486.9755 | F17: =SUMIF(CF!$E$7:$EF$7,F$3,CF!$E$112:$EF$112) -> 24417.029 | G17: =SUMIF(CF!$E$7:$EF$7,G$3,CF!$E$112:$EF$112) -> 43104.746 | H17: =SUMIF(CF!$E$7:$EF$7,H$3,CF!$E$112:$EF$112) -> 8085.9409 | I17: =SUMIF(CF!$E$7:$EF$7,I$3,CF!$E$112:$EF$112) -> 0 | J17: =SUMIF(CF!$E$7:$EF$7,J$3,CF!$E$112:$EF$112) -> 0 | ... M17: =SUMIF(CF!$E$7:$EF$7,M$3,CF!$E$112:$EF$112) -> 0
A18: 담보대출 이자 | B18: =SUM(C18:M18) -> 198878.57 | C18: =SUMIF(CF!$E$7:$EF$7,C$3,CF!$E$129:$EF$129) -> 0 | D18: =SUMIF(CF!$E$7:$EF$7,D$3,CF!$E$129:$EF$129) -> 0 | E18: =SUMIF(CF!$E$7:$EF$7,E$3,CF!$E$129:$EF$129) -> 0 | F18: =SUMIF(CF!$E$7:$EF$7,F$3,CF!$E$129:$EF$129) -> 0 | G18: =SUMIF(CF!$E$7:$EF$7,G$3,CF!$E$129:$EF$129) -> 0 | H18: =SUMIF(CF!$E$7:$EF$7,H$3,CF!$E$129:$EF$129) -> 33146.428 | I18: =SUMIF(CF!$E$7:$EF$7,I$3,CF!$E$129:$EF$129) -> 39775.714 | J18: =SUMIF(CF!$E$7:$EF$7,J$3,CF!$E$129:$EF$129) -> 39775.714 | ... M18: =SUMIF(CF!$E$7:$EF$7,M$3,CF!$E$129:$EF$129) -> 6629.2857
A19: 담보대출 취급수수료 | B19: =SUM(C19:M19) -> 7596.6828 | C19: =SUMIF(CF!$E$7:$EF$7,C$3,CF!$E$128:$EF$128) -> 0 | D19: =SUMIF(CF!$E$7:$EF$7,D$3,CF!$E$128:$EF$128) -> 0 | E19: =SUMIF(CF!$E$7:$EF$7,E$3,CF!$E$128:$EF$128) -> 0 | F19: =SUMIF(CF!$E$7:$EF$7,F$3,CF!$E$128:$EF$128) -> 0 | G19: =SUMIF(CF!$E$7:$EF$7,G$3,CF!$E$128:$EF$128) -> 0 | H19: =SUMIF(CF!$E$7:$EF$7,H$3,CF!$E$128:$EF$128) -> 7596.6828 | I19: =SUMIF(CF!$E$7:$EF$7,I$3,CF!$E$128:$EF$128) -> 0 | J19: =SUMIF(CF!$E$7:$EF$7,J$3,CF!$E$128:$EF$128) -> 0 | ... M19: =SUMIF(CF!$E$7:$EF$7,M$3,CF!$E$128:$EF$128) -> 0
A20: 자금 유출입
A21: Equity 납입 | B21: =SUM(C21:M21) -> 287378.39 | C21: =SUMIF(CF!$E$7:$EF$7,C$3,CF!$E$142:$EF$142) -> 15820.18 | D21: =SUMIF(CF!$E$7:$EF$7,D$3,CF!$E$142:$EF$142) -> 271558.21 | E21: =SUMIF(CF!$E$7:$EF$7,E$3,CF!$E$142:$EF$142) -> 0 | F21: =SUMIF(CF!$E$7:$EF$7,F$3,CF!$E$142:$EF$142) -> 0 | G21: =SUMIF(CF!$E$7:$EF$7,G$3,CF!$E$142:$EF$142) -> 0 | H21: =SUMIF(CF!$E$7:$EF$7,H$3,CF!$E$142:$EF$142) -> 0 | I21: =SUMIF(CF!$E$7:$EF$7,I$3,CF!$E$142:$EF$142) -> 0 | J21: =SUMIF(CF!$E$7:$EF$7,J$3,CF!$E$142:$EF$142) -> 0 | ... M21: =SUMIF(CF!$E$7:$EF$7,M$3,CF!$E$142:$EF$142) -> 0
A22: 보증금 유입 | B22: =SUM(C22:M22) -> 941952 | C22: =SUMIF(CF!$E$7:$EF$7,C$3,CF!$E$84:$EF$84) -> 0 | D22: =SUMIF(CF!$E$7:$EF$7,D$3,CF!$E$84:$EF$84) -> 68060.16 | E22: =SUMIF(CF!$E$7:$EF$7,E$3,CF!$E$84:$EF$84) -> 136120.32 | F22: =SUMIF(CF!$E$7:$EF$7,F$3,CF!$E$84:$EF$84) -> 136120.32 | G22: =SUMIF(CF!$E$7:$EF$7,G$3,CF!$E$84:$EF$84) -> 136120.32 | H22: =SUMIF(CF!$E$7:$EF$7,H$3,CF!$E$84:$EF$84) -> 268980.48 | I22: =SUMIF(CF!$E$7:$EF$7,I$3,CF!$E$84:$EF$84) -> 183350.4 | J22: =SUMIF(CF!$E$7:$EF$7,J$3,CF!$E$84:$EF$84) -> 13200 | ... M22: =SUMIF(CF!$E$7:$EF$7,M$3,CF!$E$84:$EF$84) -> 0
A23: 보증금 승계(처분) | B23: =SUM(C23:M23) -> 941952 | C23: =SUMIF(CF!$E$7:$EF$7,C$3,CF!$E$85:$EF$85) -> 0 | D23: =SUMIF(CF!$E$7:$EF$7,D$3,CF!$E$85:$EF$85) -> 0 | E23: =SUMIF(CF!$E$7:$EF$7,E$3,CF!$E$85:$EF$85) -> 0 | F23: =SUMIF(CF!$E$7:$EF$7,F$3,CF!$E$85:$EF$85) -> 0 | G23: =SUMIF(CF!$E$7:$EF$7,G$3,CF!$E$85:$EF$85) -> 0 | H23: =SUMIF(CF!$E$7:$EF$7,H$3,CF!$E$85:$EF$85) -> 0 | I23: =SUMIF(CF!$E$7:$EF$7,I$3,CF!$E$85:$EF$85) -> 0 | J23: =SUMIF(CF!$E$7:$EF$7,J$3,CF!$E$85:$EF$85) -> 0 | ... M23: =SUMIF(CF!$E$7:$EF$7,M$3,CF!$E$85:$EF$85) -> 941952
A24: PF 인출 | B24: =SUM(C24:M24) -> 632619.29 | C24: =SUMIF(CF!$E$7:$EF$7,C$3,CF!$E$116:$EF$116) -> 0 | D24: =SUMIF(CF!$E$7:$EF$7,D$3,CF!$E$116:$EF$116) -> 0 | E24: =SUMIF(CF!$E$7:$EF$7,E$3,CF!$E$116:$EF$116) -> 108087.92 | F24: =SUMIF(CF!$E$7:$EF$7,F$3,CF!$E$116:$EF$116) -> 345404.15 | G24: =SUMIF(CF!$E$7:$EF$7,G$3,CF!$E$116:$EF$116) -> 169838.35 | H24: =SUMIF(CF!$E$7:$EF$7,H$3,CF!$E$116:$EF$116) -> 9288.8612 | I24: =SUMIF(CF!$E$7:$EF$7,I$3,CF!$E$116:$EF$116) -> 0 | J24: =SUMIF(CF!$E$7:$EF$7,J$3,CF!$E$116:$EF$116) -> 0 | ... M24: =SUMIF(CF!$E$7:$EF$7,M$3,CF!$E$116:$EF$116) -> 0
A25: PF 상환 | B25: =SUM(C25:M25) -> 632619.29 | C25: =SUMIF(CF!$E$7:$EF$7,C$3,CF!$E$120:$EF$120) -> 0 | D25: =SUMIF(CF!$E$7:$EF$7,D$3,CF!$E$120:$EF$120) -> 0 | E25: =SUMIF(CF!$E$7:$EF$7,E$3,CF!$E$120:$EF$120) -> 0 | F25: =SUMIF(CF!$E$7:$EF$7,F$3,CF!$E$120:$EF$120) -> 0 | G25: =SUMIF(CF!$E$7:$EF$7,G$3,CF!$E$120:$EF$120) -> 0 | H25: =SUMIF(CF!$E$7:$EF$7,H$3,CF!$E$120:$EF$120) -> 632619.29 | I25: =SUMIF(CF!$E$7:$EF$7,I$3,CF!$E$120:$EF$120) -> 0 | J25: =SUMIF(CF!$E$7:$EF$7,J$3,CF!$E$120:$EF$120) -> 0 | ... M25: =SUMIF(CF!$E$7:$EF$7,M$3,CF!$E$120:$EF$120) -> 0
A26: 담보대출 인출 | B26: =SUM(C26:M26) -> 759668.28 | C26: =SUMIF(CF!$E$7:$EF$7,C$3,CF!$E$127:$EF$127) -> 0 | D26: =SUMIF(CF!$E$7:$EF$7,D$3,CF!$E$127:$EF$127) -> 0 | E26: =SUMIF(CF!$E$7:$EF$7,E$3,CF!$E$127:$EF$127) -> 0 | F26: =SUMIF(CF!$E$7:$EF$7,F$3,CF!$E$127:$EF$127) -> 0 | G26: =SUMIF(CF!$E$7:$EF$7,G$3,CF!$E$127:$EF$127) -> 0 | H26: =SUMIF(CF!$E$7:$EF$7,H$3,CF!$E$127:$EF$127) -> 759668.28 | I26: =SUMIF(CF!$E$7:$EF$7,I$3,CF!$E$127:$EF$127) -> 0 | J26: =SUMIF(CF!$E$7:$EF$7,J$3,CF!$E$127:$EF$127) -> 0 | ... M26: =SUMIF(CF!$E$7:$EF$7,M$3,CF!$E$127:$EF$127) -> 0
A27: 담보대출 상환 | B27: =SUM(C27:M27) -> 759668.28 | C27: =SUMIF(CF!$E$7:$EF$7,C$3,CF!$E$130:$EF$130) -> 0 | D27: =SUMIF(CF!$E$7:$EF$7,D$3,CF!$E$130:$EF$130) -> 0 | E27: =SUMIF(CF!$E$7:$EF$7,E$3,CF!$E$130:$EF$130) -> 0 | F27: =SUMIF(CF!$E$7:$EF$7,F$3,CF!$E$130:$EF$130) -> 0 | G27: =SUMIF(CF!$E$7:$EF$7,G$3,CF!$E$130:$EF$130) -> 0 | H27: =SUMIF(CF!$E$7:$EF$7,H$3,CF!$E$130:$EF$130) -> 0 | I27: =SUMIF(CF!$E$7:$EF$7,I$3,CF!$E$130:$EF$130) -> 0 | J27: =SUMIF(CF!$E$7:$EF$7,J$3,CF!$E$130:$EF$130) -> 0 | ... M27: =SUMIF(CF!$E$7:$EF$7,M$3,CF!$E$130:$EF$130) -> 759668.28
A28: 매각대금 | B28: =SUM(C28:M28) -> 1824235.9 | C28: =SUMIF(CF!$E$7:$EF$7,C$3,CF!$E$145:$EF$145) -> 0 | D28: =SUMIF(CF!$E$7:$EF$7,D$3,CF!$E$145:$EF$145) -> 0 | E28: =SUMIF(CF!$E$7:$EF$7,E$3,CF!$E$145:$EF$145) -> 0 | F28: =SUMIF(CF!$E$7:$EF$7,F$3,CF!$E$145:$EF$145) -> 0 | G28: =SUMIF(CF!$E$7:$EF$7,G$3,CF!$E$145:$EF$145) -> 0 | H28: =SUMIF(CF!$E$7:$EF$7,H$3,CF!$E$145:$EF$145) -> 0 | I28: =SUMIF(CF!$E$7:$EF$7,I$3,CF!$E$145:$EF$145) -> 0 | J28: =SUMIF(CF!$E$7:$EF$7,J$3,CF!$E$145:$EF$145) -> 0 | ... M28: =SUMIF(CF!$E$7:$EF$7,M$3,CF!$E$145:$EF$145) -> 1824235.9
A29: 분배
A30: 우선주 배당 | B30: =SUM(C30:M30) -> 91331.559 | C30: =SUMIF(CF!$E$7:$EF$7,C$3,CF!$E$165:$EF$165) -> 0 | D30: =SUMIF(CF!$E$7:$EF$7,D$3,CF!$E$165:$EF$165) -> 0 | E30: =SUMIF(CF!$E$7:$EF$7,E$3,CF!$E$165:$EF$165) -> 0 | F30: =SUMIF(CF!$E$7:$EF$7,F$3,CF!$E$165:$EF$165) -> 0 | G30: =SUMIF(CF!$E$7:$EF$7,G$3,CF!$E$165:$EF$165) -> 0 | H30: =SUMIF(CF!$E$7:$EF$7,H$3,CF!$E$165:$EF$165) -> 13776.401 | I30: =SUMIF(CF!$E$7:$EF$7,I$3,CF!$E$165:$EF$165) -> 24599.06 | J30: =SUMIF(CF!$E$7:$EF$7,J$3,CF!$E$165:$EF$165) -> 28910.077 | ... M30: =SUMIF(CF!$E$7:$EF$7,M$3,CF!$E$165:$EF$165) -> 4117.9416
A31: 우선주 원금상환 | B31: =SUM(C31:M31) -> 201164.87 | C31: =SUMIF(CF!$E$7:$EF$7,C$3,CF!$E$166:$EF$166) -> 0 | D31: =SUMIF(CF!$E$7:$EF$7,D$3,CF!$E$166:$EF$166) -> 0 | E31: =SUMIF(CF!$E$7:$EF$7,E$3,CF!$E$166:$EF$166) -> 0 | F31: =SUMIF(CF!$E$7:$EF$7,F$3,CF!$E$166:$EF$166) -> 0 | G31: =SUMIF(CF!$E$7:$EF$7,G$3,CF!$E$166:$EF$166) -> 0 | H31: =SUMIF(CF!$E$7:$EF$7,H$3,CF!$E$166:$EF$166) -> 0 | I31: =SUMIF(CF!$E$7:$EF$7,I$3,CF!$E$166:$EF$166) -> 0 | J31: =SUMIF(CF!$E$7:$EF$7,J$3,CF!$E$166:$EF$166) -> 0 | ... M31: =SUMIF(CF!$E$7:$EF$7,M$3,CF!$E$166:$EF$166) -> 201164.87
A32: 보통주 분배 | B32: =SUM(C32:M32) -> 443763.15 | C32: =SUMIF(CF!$E$7:$EF$7,C$3,CF!$E$168:$EF$168) -> 0 | D32: =SUMIF(CF!$E$7:$EF$7,D$3,CF!$E$168:$EF$168) -> 0 | E32: =SUMIF(CF!$E$7:$EF$7,E$3,CF!$E$168:$EF$168) -> 0 | F32: =SUMIF(CF!$E$7:$EF$7,F$3,CF!$E$168:$EF$168) -> 0 | G32: =SUMIF(CF!$E$7:$EF$7,G$3,CF!$E$168:$EF$168) -> 0 | H32: =SUMIF(CF!$E$7:$EF$7,H$3,CF!$E$168:$EF$168) -> 0 | I32: =SUMIF(CF!$E$7:$EF$7,I$3,CF!$E$168:$EF$168) -> 0 | J32: =SUMIF(CF!$E$7:$EF$7,J$3,CF!$E$168:$EF$168) -> 0 | ... M32: =SUMIF(CF!$E$7:$EF$7,M$3,CF!$E$168:$EF$168) -> 402141.85
A33: 보통주 CF | B33: =SUM(C33:M33) -> 357549.63 | C33: =SUMIF(CF!$E$7:$EF$7,C$3,CF!$E$171:$EF$171) -> -15820.18 | D33: =SUMIF(CF!$E$7:$EF$7,D$3,CF!$E$171:$EF$171) -> -70393.336 | E33: =SUMIF(CF!$E$7:$EF$7,E$3,CF!$E$171:$EF$171) -> 0 | F33: =SUMIF(CF!$E$7:$EF$7,F$3,CF!$E$171:$EF$171) -> 0 | G33: =SUMIF(CF!$E$7:$EF$7,G$3,CF!$E$171:$EF$171) -> 0 | H33: =SUMIF(CF!$E$7:$EF$7,H$3,CF!$E$171:$EF$171) -> 0 | I33: =SUMIF(CF!$E$7:$EF$7,I$3,CF!$E$171:$EF$171) -> 0 | J33: =SUMIF(CF!$E$7:$EF$7,J$3,CF!$E$171:$EF$171) -> 0 | ... M33: =SUMIF(CF!$E$7:$EF$7,M$3,CF!$E$171:$EF$171) -> 402141.85
A34: 우선주 CF | B34: =SUM(C34:M34) -> 91331.559 | C34: =SUMIF(CF!$E$7:$EF$7,C$3,CF!$E$172:$EF$172) -> 0 | D34: =SUMIF(CF!$E$7:$EF$7,D$3,CF!$E$172:$EF$172) -> -201164.87 | E34: =SUMIF(CF!$E$7:$EF$7,E$3,CF!$E$172:$EF$172) -> 0 | F34: =SUMIF(CF!$E$7:$EF$7,F$3,CF!$E$172:$EF$172) -> 0 | G34: =SUMIF(CF!$E$7:$EF$7,G$3,CF!$E$172:$EF$172) -> 0 | H34: =SUMIF(CF!$E$7:$EF$7,H$3,CF!$E$172:$EF$172) -> 13776.401 | I34: =SUMIF(CF!$E$7:$EF$7,I$3,CF!$E$172:$EF$172) -> 24599.06 | J34: =SUMIF(CF!$E$7:$EF$7,J$3,CF!$E$172:$EF$172) -> 28910.077 | ... M34: =SUMIF(CF!$E$7:$EF$7,M$3,CF!$E$172:$EF$172) -> 205282.81
A35: 전체 Equity CF | B35: =SUM(C35:M35) -> 448881.19 | C35: =SUMIF(CF!$E$7:$EF$7,C$3,CF!$E$173:$EF$173) -> -15820.18 | D35: =SUMIF(CF!$E$7:$EF$7,D$3,CF!$E$173:$EF$173) -> -271558.21 | E35: =SUMIF(CF!$E$7:$EF$7,E$3,CF!$E$173:$EF$173) -> 0 | F35: =SUMIF(CF!$E$7:$EF$7,F$3,CF!$E$173:$EF$173) -> 0 | G35: =SUMIF(CF!$E$7:$EF$7,G$3,CF!$E$173:$EF$173) -> 0 | H35: =SUMIF(CF!$E$7:$EF$7,H$3,CF!$E$173:$EF$173) -> 13776.401 | I35: =SUMIF(CF!$E$7:$EF$7,I$3,CF!$E$173:$EF$173) -> 24599.06 | J35: =SUMIF(CF!$E$7:$EF$7,J$3,CF!$E$173:$EF$173) -> 28910.077 | ... M35: =SUMIF(CF!$E$7:$EF$7,M$3,CF!$E$173:$EF$173) -> 607424.66
A36: 기말현금 | C36: =SUMIF(CF!$E$6:$EF$6,MIN(DATE(C$3,12,31),Assumption!$E$24),CF!$E$159:$EF$159)*(C$3<=YEAR(Assumption!$E$24)) -> 2084.0179 | D36: =SUMIF(CF!$E$6:$EF$6,MIN(DATE(D$3,12,31),Assumption!$E$24),CF!$E$159:$EF$159)*(D$3<=YEAR(Assumption!$E$24)) -> 76511.599 | E36: =SUMIF(CF!$E$6:$EF$6,MIN(DATE(E$3,12,31),Assumption!$E$24),CF!$E$159:$EF$159)*(E$3<=YEAR(Assumption!$E$24)) -> 500 | F36: =SUMIF(CF!$E$6:$EF$6,MIN(DATE(F$3,12,31),Assumption!$E$24),CF!$E$159:$EF$159)*(F$3<=YEAR(Assumption!$E$24)) -> 500 | G36: =SUMIF(CF!$E$6:$EF$6,MIN(DATE(G$3,12,31),Assumption!$E$24),CF!$E$159:$EF$159)*(G$3<=YEAR(Assumption!$E$24)) -> 500 | H36: =SUMIF(CF!$E$6:$EF$6,MIN(DATE(H$3,12,31),Assumption!$E$24),CF!$E$159:$EF$159)*(H$3<=YEAR(Assumption!$E$24)) -> 288275.69 | I36: =SUMIF(CF!$E$6:$EF$6,MIN(DATE(I$3,12,31),Assumption!$E$24),CF!$E$159:$EF$159)*(I$3<=YEAR(Assumption!$E$24)) -> 471626.09 | J36: =SUMIF(CF!$E$6:$EF$6,MIN(DATE(J$3,12,31),Assumption!$E$24),CF!$E$159:$EF$159)*(J$3<=YEAR(Assumption!$E$24)) -> 484826.09 | ... M36: =SUMIF(CF!$E$6:$EF$6,MIN(DATE(M$3,12,31),Assumption!$E$24),CF!$E$159:$EF$159)*(M$3<=YEAR(Assumption!$E$24)) -> 0
A38: IRR (보통주) | B38: =CF!$C$171 -> 0.20392787
A39: IRR (우선주) | B39: =CF!$C$172 -> 0.05
A40: IRR (전체) | B40: =CF!$C$173 -> 0.12111635

Sheet Macro_VBA
A1: Run all Macro — 순환참조(금융비용·자본금) 수렴용 VBA
A3: 사용법: 1) 파일을 .xlsm으로 다른 이름 저장 2) Alt+F11 → 삽입 → 모듈 3) 아래 코드 붙여넣기 4) Alt+F8 → RunAllMacro 실행
A4: (Assumption 시트의 Macro 표: Copy 열 값을 Paste 열로 반복 복사하여 Difference가 0이 될 때까지 수렴)
A5: 가정을 바꾼 뒤 Assumption 상단 Macro Check가 "Run Macro"로 바뀌면 실행하세요.
A7: Sub RunAllMacro()
A8: Dim i As Integer
A9: Application.ScreenUpdating = False
A10: For i = 1 To 50
A11: Application.Calculate
A12: Range("Paste_Range").Value = Range("Copy_Range").Value
A13: Application.Calculate
A14: If Application.WorksheetFunction.SumProduct(Application.Evaluate("ABS(Diff_Range)")) < 0.001 Then Exit For
... A18: End Sub
