Workbook

Sheet 비교요약
B1: 센텀C부지 복합개발사업 — Vehicle 분리 비교
B2: ① 통합(시니어+기타 단일 리츠) vs ② 시니어 레지던스 리츠 + ③ 기타 용도 리츠 (단위: 백만원)
B4: 항목 | C4: 단위 | D4: ① 통합 | E4: ② 시니어 Vehicle | F4: ③ 기타 Vehicle | G4: ②+③ 합계 | H4: 차이 (②+③ − ①) | I4: 비고
B5: 검증
B6: Balance / Macro / Shortage / Cash Check | D6: =①통합_가정!C3&" / "&①통합_가정!D3&" / "&①통합_가정!E3&" / "&①통합_가정!F3 -> OK / OK / OK / OK | E6: =②시니어_가정!C3&" / "&②시니어_가정!D3&" / "&②시니어_가정!E3&" / "&②시니어_가정!F3 -> Error / OK / Shortage / OK | F6: =③기타_가정!C3&" / "&③기타_가정!D3&" / "&③기타_가정!E3&" / "&③기타_가정!F3 -> OK / OK / OK / OK
B7: 개요
B8: Vehicle 연면적 | C8: 평 | D8: =①통합_가정!$I$39 -> 81811.424 | E8: =②시니어_가정!$I$39 -> 23008.174 | F8: =③기타_가정!$I$39 -> 58803.25 | G8: =E8+F8 -> 81811.424 | H8: =G8-D8 -> 0
B9: 토지 지분 | C9: % | D9: =①통합_가정!$I$42 -> 1 | E9: =②시니어_가정!$I$42 -> 0.28123425 | F9: =③기타_가정!$I$42 -> 0.71876575 | G9: =E9+F9 -> 1 | H9: =G9-D9 -> 0
B10: VAT 공통 공제비율 | C10: % | D10: =①통합_가정!$N$355 -> 0.71876575 | E10: =②시니어_가정!$N$355 -> 0 | F10: =③기타_가정!$N$355 -> 1 | I10: 면세(시니어)·과세 혼재 시 안분 → 분리하면 ②는 0%, ③은 100% 공제
B11: 개발사업비 (공제후 순액)
B12: 토지비 | C12: 백만원 | D12: =①통합_가정!$R$363 -> 237644 | E12: =②시니어_가정!$R$363 -> 66833.631 | F12: =③기타_가정!$R$363 -> 170810.37 | G12: =E12+F12 -> 237644 | H12: =G12-D12 -> 0
B13: 직접공사비 | C13: 백만원 | D13: =①통합_가정!$R$367 -> 614293.14 | E13: =②시니어_가정!$R$367 -> 191988.19 | F13: =③기타_가정!$R$367 -> 422304.95 | G13: =E13+F13 -> 614293.14 | H13: =G13-D13 -> 0 | I13: VAT 공제율 변화 영향
B14: 간접공사비 | C14: 백만원 | D14: =①통합_가정!$R$381 -> 476391.09 | E14: =②시니어_가정!$R$381 -> 118414.72 | F14: =③기타_가정!$R$381 -> 357976.37 | G14: =E14+F14 -> 476391.09 | H14: =G14-D14 -> 0 | I14: VAT 공제율 변화 영향
B15: 판매비 | C15: 백만원 | D15: =①통합_가정!$R$386 -> 30843.703 | E15: =②시니어_가정!$R$386 -> 11000 | F15: =③기타_가정!$R$386 -> 20000 | G15: =E15+F15 -> 31000 | H15: =G15-D15 -> 156.29726
B16: 부대비용 | C16: 백만원 | D16: =①통합_가정!$R$389 -> 29598.314 | E16: =②시니어_가정!$R$389 -> 6542.0982 | F16: =③기타_가정!$R$389 -> 23056.215 | G16: =E16+F16 -> 29598.314 | H16: =G16-D16 -> 0
B17: 금융비용(PF) | C17: 백만원 | D17: =①통합_가정!$R$401 -> 95505.682 | E17: =②시니어_가정!$R$401 -> 11165.567 | F17: =③기타_가정!$R$401 -> 88773.504 | G17: =E17+F17 -> 99939.071 | H17: =G17-D17 -> 4433.389 | I17: 보증금 교차보조 소멸 → ③ PF 인출·이자 증가
B18: 리츠운용비(개발) | C18: 백만원 | D18: =①통합_가정!$R$412 -> 12299.971 | E18: =②시니어_가정!$R$412 -> 8331.7219 | F18: =③기타_가정!$R$412 -> 10315.68 | G18: =E18+F18 -> 18647.402 | H18: =G18-D18 -> 6347.4305 | I18: 리츠 고정비 비히클별 중복
B19: 총사업비 | C19: 백만원 | D19: =①통합_가정!$R$413 -> 1496575.9 | E19: =②시니어_가정!$R$413 -> 414275.93 | F19: =③기타_가정!$R$413 -> 1093237.1 | G19: =E19+F19 -> 1507513 | H19: =G19-D19 -> 10937.117
B20: 재원조달
B21: 재원조달요구액 | C21: 백만원 | D21: =①통합_가정!$E$434 -> 1436891.9 | E21: =②시니어_가정!$E$434 -> 396822.46 | F21: =③기타_가정!$E$434 -> 1051006.6 | G21: =E21+F21 -> 1447829 | H21: =G21-D21 -> 10937.117
B22: 자기자본(Equity) | C22: 백만원 | D22: =①통합_가정!$E$438 -> 287378.39 | E22: =②시니어_가정!$E$438 -> 79364.491 | F22: =③기타_가정!$E$438 -> 210201.32 | G22: =E22+F22 -> 289565.81 | H22: =G22-D22 -> 2187.4234
B23: 우선주 | C23: 백만원 | D23: =①통합_가정!$E$444 -> 201164.87 | E23: =②시니어_가정!$E$444 -> 55555.144 | F23: =③기타_가정!$E$444 -> 147140.92 | G23: =E23+F23 -> 202696.07 | H23: =G23-D23 -> 1531.1964
B24: 보통주 | C24: 백만원 | D24: =①통합_가정!$E$450 -> 86213.516 | E24: =②시니어_가정!$E$450 -> 23809.347 | F24: =③기타_가정!$E$450 -> 63060.395 | G24: =E24+F24 -> 86869.743 | H24: =G24-D24 -> 656.22701
B25: PF 한도 | C25: 백만원 | D25: =①통합_가정!$E$451 -> 1149513.5 | E25: =②시니어_가정!$E$451 -> 317457.96 | F25: =③기타_가정!$E$451 -> 840805.27 | G25: =E25+F25 -> 1158263.2 | H25: =G25-D25 -> 8749.6935
B26: PF 최대 인출액 | C26: 백만원 | D26: =①통합_가정!$E$486 -> 632619.29 | E26: =②시니어_가정!$E$486 -> 27207.3 | F26: =③기타_가정!$E$486 -> 637282.27 | G26: =E26+F26 -> 664489.57 | H26: =G26-D26 -> 31870.288
B27: 준공시점 보증금(시니어+레지던스) | C27: 백만원 | D27: =①통합_가정!$F$490+①통합_가정!$F$491 -> 476421.12 | E27: =②시니어_가정!$F$490+②시니어_가정!$F$491 -> 302400 | F27: =③기타_가정!$F$490+③기타_가정!$F$491 -> 174021.12 | G27: =E27+F27 -> 476421.12 | H27: =G27-D27 -> 0
B28: 준공후 담보대출 | C28: 백만원 | D28: =①통합_가정!$E$536 -> 759668.28 | E28: =②시니어_가정!$E$536 -> 47455.1 | F28: =③기타_가정!$E$536 -> 712213.18 | G28: =E28+F28 -> 759668.28 | H28: =G28-D28 -> 0
B29: 증자 필요액(현금부족) | C29: 백만원 | D29: =①통합_가정!$C$497 -> 0 | E29: =②시니어_가정!$C$497 -> 161611.76 | F29: =③기타_가정!$C$497 -> 0 | G29: =E29+F29 -> 161611.76 | H29: =G29-D29 -> 161611.76 | I29: 0이 아니면 해당 Vehicle 현금부족 발생
B30: 운영 및 매각
B31: 운영수입 합계 | C31: 백만원 | D31: =①통합_CF!$C$41 -> 1022866.3 | E31: =②시니어_CF!$C$41 -> 120999.07 | F31: =③기타_CF!$C$41 -> 901867.25 | G31: =E31+F31 -> 1022866.3 | H31: =G31-D31 -> 0
B32: NOI 합계 | C32: 백만원 | D32: =①통합_CF!$C$64 -> 315953.28 | E32: =②시니어_CF!$C$64 -> 32621.512 | F32: =③기타_CF!$C$64 -> 283331.77 | G32: =E32+F32 -> 315953.28 | H32: =G32-D32 -> 0
B33: 공통비용·리츠운용비(운영) | C33: 백만원 | D33: =①통합_CF!$C$74 -> 63114.79 | E33: =②시니어_CF!$C$74 -> 26180.023 | F33: =③기타_CF!$C$74 -> 43996.652 | G33: =E33+F33 -> 70176.675 | H33: =G33-D33 -> 7061.8851 | I33: 리츠 고정비 중복
B34: 담보대출 이자 | C34: 백만원 | D34: =①통합_CF!$C$129 -> 198878.57 | E34: =②시니어_CF!$C$129 -> 12812.877 | F34: =③기타_CF!$C$129 -> 186065.69 | G34: =E34+F34 -> 198878.57 | H34: =G34-D34 -> 0
B35: 보유현금 이자수익 | C35: 백만원 | D35: =①통합_CF!$C$149 -> 74857.976 | E35: =②시니어_CF!$C$149 -> 39980.44 | F35: =③기타_CF!$C$149 -> 36938.462 | G35: =E35+F35 -> 76918.902 | H35: =G35-D35 -> 2060.926
B36: 최대 유휴현금(기말현금 최대) | C36: 백만원 | D36: =MAX(①통합_CF!$E$159:$EF$159) -> 603335.5 | E36: =MAX(②시니어_CF!$E$159:$EF$159) -> 253569.11 | F36: =MAX(③기타_CF!$E$159:$EF$159) -> 756646.5 | I36: 보증금 잉여가 비히클 안에 묶임
B37: 매각가치 | C37: 백만원 | D37: =①통합_가정!$G$283 -> 1824235.9 | E37: =②시니어_가정!$G$283 -> 174513.09 | F37: =③기타_가정!$G$283 -> 1649722.8 | G37: =E37+F37 -> 1824235.9 | H37: =G37-D37 -> 0
B38: 처분시 보증금 승계액 | C38: 백만원 | D38: =①통합_CF!$C$85 -> 941952 | E38: =②시니어_CF!$C$85 -> 541500 | F38: =③기타_CF!$C$85 -> 400452 | G38: =E38+F38 -> 941952 | H38: =G38-D38 -> 0 | I38: 매각대금에서 차감(매수인 인계)
B39: 분배 및 수익률
B40: Equity 투입 | C40: 백만원 | D40: =①통합_CF!$C$142 -> 287378.39 | E40: =②시니어_CF!$C$142 -> 79364.491 | F40: =③기타_CF!$C$142 -> 210201.32 | G40: =E40+F40 -> 289565.81 | H40: =G40-D40 -> 2187.4234
B41: 우선주 배당 | C41: 백만원 | D41: =①통합_CF!$C$165 -> 91331.559 | E41: =②시니어_CF!$C$165 -> 23865.04 | F41: =③기타_CF!$C$165 -> 67367.234 | G41: =E41+F41 -> 91232.274 | H41: =G41-D41 -> -99.285701
B42: 우선주 원금상환 | C42: 백만원 | D42: =①통합_CF!$C$166 -> 201164.87 | E42: =②시니어_CF!$C$166 -> 0 | F42: =③기타_CF!$C$166 -> 147140.92 | G42: =E42+F42 -> 147140.92 | H42: =G42-D42 -> -54023.947
B43: 보통주 분배 | C43: 백만원 | D43: =①통합_CF!$C$168 -> 443763.15 | E43: =②시니어_CF!$C$168 -> 10482.88 | F43: =③기타_CF!$C$168 -> 635264.61 | G43: =E43+F43 -> 645747.49 | H43: =G43-D43 -> 201984.35
B44: Equity 순수익 | C44: 백만원 | D44: =D41+D42+D43-D40 -> 448881.19 | E44: =E41+E42+E43-E40 -> -45016.571 | F44: =F41+F42+F43-F40 -> 639571.45 | G44: =E44+F44 -> 594554.88 | H44: =G44-D44 -> 145673.69 | I44: 분배 합계 − Equity 투입
B45: Equity Multiple | C45: x | D45: =IFERROR((D41+D42+D43)/D40,0) -> 2.5619866 | E45: =IFERROR((E41+E42+E43)/E40,0) -> 0.432787 | F45: =IFERROR((F41+F42+F43)/F40,0) -> 4.0426615 | G45: =IFERROR((G41+G42+G43)/G40,0) -> 3.0532634 | H45: =G45-D45 -> 0.49127679
B46: IRR (보통주) | C46: % | D46: =①통합_CF!$C$171 -> 0.20392787 | E46: =②시니어_CF!$C$171 -> -0.1050309 | F46: =③기타_CF!$C$171 -> 0.29508635 | G46: =IFERROR((1+IRR(E58:EF58,0.01))^12-1,IFERROR((1+IRR(E58:EF58,-0.05))^12-1,-1)) -> 0.25288888 | H46: =G46-D46 -> 0.048961009
B47: IRR (우선주) | C47: % | D47: =①통합_CF!$C$172 -> 0.05 | E47: =②시니어_CF!$C$172 -> -0.14547119 | F47: =③기타_CF!$C$172 -> 0.05 | G47: =IFERROR((1+IRR(E59:EF59,0.01))^12-1,IFERROR((1+IRR(E59:EF59,-0.05))^12-1,-1)) -> 0.021872915 | H47: =G47-D47 -> -0.028127085
B48: IRR (전체 Equity) | C48: % | D48: =①통합_CF!$C$173 -> 0.12111635 | E48: =②시니어_CF!$C$173 -> -0.12979711 | F48: =③기타_CF!$C$173 -> 0.18026527 | G48: =IFERROR((1+IRR(E60:EF60,0.01))^12-1,IFERROR((1+IRR(E60:EF60,-0.05))^12-1,-1)) -> 0.1436646 | H48: =G48-D48 -> 0.022548251 | I48: ②+③은 두 비히클 월별 CF를 합산해 IRR 재계산
B50: 분리 시 값이 달라지는 이유
B51: 1) 보증금 교차보조 소멸: 통합 시 시니어 입주보증금이 호텔·오피스 공사비까지 충당 → 분리 시 ③은 PF 인출·이자↑, ②는 현금이 남아 유휴화
B52: 2) 리츠 고정비 중복: AMC 운영보수·자산보관·사무수탁·회계감사·실사비 등이 비히클마다 발생 (각 가정시트의 "리츠 고정비 적용비율"로 조정 가능)
B53: 3) VAT: 통합 시 공통비용은 과세면적 비율(약 71.9%)만 공제 → 분리 시 ③은 과세사업 100% 공제, ②는 면세로 0% 공제
B54: 4) 자본구조: 각 비히클이 자기 사업비 기준으로 Equity 20% / PF 80% 한도를 따로 잡음, 최소보유현금도 비히클별 적용
B55: 5) 시니어 단독 리츠는 매각가치(NOI/Cap)보다 승계할 입주보증금이 커서 처분시 현금부족 발생 가능 → 가정시트 매각가정의 "보증금 운용수익률"로 평가방식 민감도 확인
B56: ②+③ 합산 투자자 월별 현금흐름 (IRR 계산용)
B57: 월말일자 | E57: =①통합_CF!E6 -> 46112 | F57: =①통합_CF!F6 -> 46142 | G57: =①통합_CF!G6 -> 46173 | H57: =①통합_CF!H6 -> 46203 | I57: =①통합_CF!I6 -> 46234 | J57: =①통합_CF!J6 -> 46265 | K57: =①통합_CF!K6 -> 46295 | L57: =①통합_CF!L6 -> 46326 | ... EF57: =①통합_CF!EF6 -> 50099
B58: 보통주 CF (②+③) | E58: =②시니어_CF!E171+③기타_CF!E171 -> -15940.598 | F58: =②시니어_CF!F171+③기타_CF!F171 -> 0 | G58: =②시니어_CF!G171+③기타_CF!G171 -> 0 | H58: =②시니어_CF!H171+③기타_CF!H171 -> 0 | I58: =②시니어_CF!I171+③기타_CF!I171 -> 0 | J58: =②시니어_CF!J171+③기타_CF!J171 -> 0 | K58: =②시니어_CF!K171+③기타_CF!K171 -> 0 | L58: =②시니어_CF!L171+③기타_CF!L171 -> 0 | ... EF58: =②시니어_CF!EF171+③기타_CF!EF171 -> 0
B59: 우선주 CF (②+③) | E59: =②시니어_CF!E172+③기타_CF!E172 -> 0 | F59: =②시니어_CF!F172+③기타_CF!F172 -> 0 | G59: =②시니어_CF!G172+③기타_CF!G172 -> 0 | H59: =②시니어_CF!H172+③기타_CF!H172 -> 0 | I59: =②시니어_CF!I172+③기타_CF!I172 -> 0 | J59: =②시니어_CF!J172+③기타_CF!J172 -> 0 | K59: =②시니어_CF!K172+③기타_CF!K172 -> 0 | L59: =②시니어_CF!L172+③기타_CF!L172 -> 0 | ... EF59: =②시니어_CF!EF172+③기타_CF!EF172 -> 0
B60: 전체 Equity CF (②+③) | E60: =②시니어_CF!E173+③기타_CF!E173 -> -15940.598 | F60: =②시니어_CF!F173+③기타_CF!F173 -> 0 | G60: =②시니어_CF!G173+③기타_CF!G173 -> 0 | H60: =②시니어_CF!H173+③기타_CF!H173 -> 0 | I60: =②시니어_CF!I173+③기타_CF!I173 -> 0 | J60: =②시니어_CF!J173+③기타_CF!J173 -> 0 | K60: =②시니어_CF!K173+③기타_CF!K173 -> 0 | L60: =②시니어_CF!L173+③기타_CF!L173 -> 0 | ... EF60: =②시니어_CF!EF173+③기타_CF!EF173 -> 0

Sheet ①통합_가정
B1: 센텀C부지 복합개발사업 재무모델 | I1: 입력값 | J1: 파란 글씨 = 입력(하드코딩)
B2: ① 통합 (단일 Vehicle) — Assumption (단위: 백만원) | I2: 수식 | J2: 검정 = 계산 수식
C3: =IF(ABS(①통합_CF!$C$159)<1,"OK","Error") -> OK | D3: =IF(SUMPRODUCT(ABS($F$560:$F$569))<1,"OK","Run Macro") -> OK | E3: =IF(MIN(①통합_CF!$E$159:$EF$159)>-0.5,"OK","Shortage") -> OK | F3: =IF(SUM(①통합_CF!$E$153:$EF$153)-SUM(①통합_CF!$E$116:$EF$116)<1,"OK","PF한도부족") -> OK | I3: 연결 | J3: 초록 = CF 시트 연결
C4: Balance Check | D4: Macro Check | E4: Shortage Check | F4: Cash Check | I4: Macro | J4: 노랑 = Macro Paste 값(순환참조 차단)
A6: 프로젝트 일정 (계획)
B8: 리츠설립일 | D8: Date | E8: 46112
B9: 매매계약체결 준비기간 | D9: Months | E9: 3
B10: 토지매매계약체결일 | D10: Date | E10: =EOMONTH($E$8,$E$9) -> 46203
B11: 인허가 준비기간 | D11: Months | E11: 14
B12: 인허가 완료일 | D12: Date | E12: =EOMONTH($E$10,$E$11) -> 46630
B13: 공사준비기간 | D13: Months | E13: 1
B14: 착공일 | D14: Date | E14: =EOMONTH($E$12,$E$13) -> 46660
B15: 공사기간 | D15: Months | E15: 42
B16: 준공일 | D16: Date | E16: =EOMONTH($E$14,$E$15-1) -> 47907
B17: 운영준비기간 | D17: Months | E17: 1
B18: 운영개시일 | D18: Date | E18: =EOMONTH($E$16,$E$17) -> 47938
B19: 운영기간 | D19: Months | E19: 60
B20: 운영종료일 | D20: Date | E20: =EOMONTH($E$18,$E$19-1) -> 49734
B21: 처분준비기간 | D21: Months | E21: 0
B22: 처분일 | D22: Date | E22: =EOMONTH($E$20,$E$21) -> 49734
B23: 청산준비기간 | D23: Months | E23: 3
B24: 리츠청산일 | D24: Date | E24: =EOMONTH($E$22,$E$23) -> 49826
B25: 개발기간(설립~준공) | D25: Years | E25: =((YEAR($E$16)-YEAR($E$8))*12+MONTH($E$16)-MONTH($E$8)+1)/12 -> 5
B26: 리츠운용기간(운영개시~청산) | D26: Years | E26: =((YEAR($E$24)-YEAR($E$18))*12+MONTH($E$24)-MONTH($E$18)+1)/12 -> 5.25
A28: Results
B30: IRR On Equity (보통주) | E30: =①통합_CF!$C$171 -> 0.20392787
B31: IRR On Equity (우선주) | E31: =①통합_CF!$C$172 -> 0.05
B32: IRR On Equity (전체) | E32: =①통합_CF!$C$173 -> 0.12111635
A34: Vehicle 설정 (용도별 포함여부: 1=포함, 0=제외)
B36: 구분 | C36: 항목 | D36: 시니어 레지던스 | E36: 레지던스 | F36: 호텔 | G36: 오피스 | H36: 부대시설 | I36: Vehicle 합계/비율
B37: Vehicle명 | C37: ① 통합 (단일 Vehicle)
B38: 포함여부 | C38: 1 / 0 | D38: 1 | E38: 1 | F38: 1 | G38: 1 | H38: 1
B39: 연면적 | C39: 평 | D39: =$E$60 -> 23008.174 | E39: =$E$61 -> 13519.908 | F39: =$E$62 -> 21288.226 | G39: =$E$63 -> 14046.004 | H39: =$E$64 -> 9949.1131 | I39: =SUMPRODUCT(D38:H38,D39:H39) -> 81811.424
C40: 시니어 포함 연면적 | I40: =$D$38*$E$60 -> 23008.174
C41: 연면적 비중(전체 대비) | I41: =$I$39/$C$69 -> 1
B42: 토지 지분 | C42: Ratio | D42: =$C$85 -> 0.28123425 | E42: =$C$86 -> 0.16525697 | F42: =$C$87 -> 0.26021092 | G42: =$C$88 -> 0.17168756 | H42: =$C$89 -> 0.12161031 | I42: =SUMPRODUCT(D38:H38,D42:H42) -> 1
C43: 분양홍보비 지분 | I43: =IFERROR(SUMPRODUCT($D$38:$H$38,$P$325:$T$325)/SUM($P$325:$T$325),0) -> 1
C44: 보존등기비 지분(건물분 취득세 기준) | I44: =IFERROR(SUMPRODUCT($D$38:$H$38,$P$323:$T$323)/SUM($P$323:$T$323),0) -> 1
C45: 리츠 고정비 적용비율 | I45: 1
B46: ※ 토지비·공사비·보증금·운영수입·담보대출은 포함 용도만 반영, 리츠 고정비는 Vehicle별로 별도 발생, VAT 공통공제비율은 Vehicle 내 과세면적 비중으로 재계산
A48: 사업개요
B50: (1) 사 업 명 | D50: 센텀C부지 복합개발사업
B51: (2) 대 지 위 치 | D51: 부산광역시 해운대 우동 1492
B52: (3) 지 역 지 구 | D52: 중심상업지역/지구단위계획구역
B53: (4) 용 도 | D53: 관광숙박시설(호텔, 콘도), 노유자시설(시니어레지던스), 문화집회시설(공연장 등), 판매시설
B54: (5) 건축연면적 | E54: 평 환산계수 | F54: 0.3025
B56: 연면적 | C56: 지상연면적 | D56: 178919.43 | E56: =$D$56*$F$54 -> 54123.128
C57: 지하연면적 | D57: 91531.54 | E57: =$D$57*$F$54 -> 27688.291
C58: 전체연면적 | D58: =$D$56+$D$57 -> 270450.97 | E58: =$D$58*$F$54 -> 81811.418 | F58: =ABS($D$58-$C$70)<1 -> TRUE | G58: =ABS($D$58*$F$54-$C$69)<1 -> TRUE
B60: 용도별 연면적 | C60: 시니어 레지던스 | D60: =SUMIF($D$67:$W$67,"시니어 레지던스",$D$70:$W$70) -> 76060.08 | E60: =SUMIF($D$67:$W$67,"시니어 레지던스",$D$69:$W$69) -> 23008.174
C61: 레지던스 | D61: =SUMIF($D$67:$W$67,"레지던스",$D$70:$W$70) -> 44693.91 | E61: =SUMIF($D$67:$W$67,"레지던스",$D$69:$W$69) -> 13519.908
C62: 호텔 | D62: =SUMIF($D$67:$W$67,"호텔",$D$70:$W$70) -> 70374.3 | E62: =SUMIF($D$67:$W$67,"호텔",$D$69:$W$69) -> 21288.226
C63: 오피스 | D63: =SUMIF($D$67:$W$67,"오피스",$D$70:$W$70) -> 46433.07 | E63: =SUMIF($D$67:$W$67,"오피스",$D$69:$W$69) -> 14046.004
C64: 부대시설 | D64: =SUMIF($D$67:$W$67,"부대시설",$D$70:$W$70) -> 32889.63 | E64: =SUMIF($D$67:$W$67,"부대시설",$D$69:$W$69) -> 9949.1131
C65: 합계 | D65: =SUM(D60:D64) -> 270450.99 | E65: =SUM(E60:E64) -> 81811.424 | F65: =ABS(D65-$D$58)<1 -> TRUE | G65: =ABS(E65-$C$69)<0.1 -> TRUE
D67: 시니어 레지던스 | E67: 시니어 레지던스 | F67: 부대시설 | G67: 부대시설 | H67: 시니어 레지던스 | J67: 레지던스 | K67: 레지던스 | L67: 호텔 | M67: 호텔 | N67: 호텔 | O67: 호텔 | P67: 호텔 | Q67: 호텔 | R67: 오피스 | S67: 호텔 | U67: 부대시설 | V67: 부대시설 | W67: 부대시설
B68: 구분 | C68: 총계 | D68: 시니어 | E68: 시니어 부대 | F68: 국제학교 | G68: 영어유치원 | H68: SSZ | I68: B동 계 | J68: 가족호텔 | K68: 가족호텔 부대 멤버전용 | L68: 호텔 | M68: 컨벤션 | N68: 호텔부대_피트니스&수영장 | O68: 호텔부대_파인다이닝 | P68: 호텔부대_휴게 | Q68: 호텔 BOH | R68: 오피스 | S68: SSZ | T68: A동 계 | U68: 메디컬 | V68: 스파2.0 | W68: 판매시설 | X68: 부대시설 계 | Y68: MEP | Z68: 주차장
B69: 연면적(평) | C69: =I69+T69+X69 -> 81811.424 | D69: =D70*$F$54 -> 20475.245 | E69: =E70*$F$54 -> 2338.198 | F69: =F70*$F$54 -> 1425.6281 | G69: =G70*$F$54 -> 597.16525 | H69: =H70*$F$54 -> 194.73135 | I69: =SUM(D69:H69) -> 25030.967 | J69: =J70*$F$54 -> 10714.913 | K69: =K70*$F$54 -> 2804.9948 | L69: =L70*$F$54 -> 11246.593 | M69: =M70*$F$54 -> 2165.776 | N69: =N70*$F$54 -> 1829.3446 | O69: =O70*$F$54 -> 1274.2329 | P69: =P70*$F$54 -> 1063.9651 | Q69: =Q70*$F$54 -> 3250.7679 | ... S69: =S70*$F$54 -> 457.54638 | T69: =SUM(J69:S69) -> 48854.137 | U69: =U70*$F$54 -> 1673.7446 | V69: =V70*$F$54 -> 2443.3318 | W69: =W70*$F$54 -> 3809.2434 | X69: =SUM(U69:W69) -> 7926.3198
B70: 연면적(㎡) | C70: =I70+T70+X70 -> 270450.99 | D70: 67686.76 | E70: 7729.58 | F70: 4712.82 | G70: 1974.1 | H70: 643.74 | I70: =SUM(D70:H70) -> 82747 | J70: 35421.2 | K70: 9272.71 | L70: 37178.82 | M70: 7159.59 | N70: 6047.42 | O70: 4212.34 | P70: 3517.24 | Q70: 10746.34 | R70: 46433.07 | S70: 1512.55 | T70: =SUM(J70:S70) -> 161501.28 | U70: 5533.04 | V70: 8077.13 | W70: 12592.54 | X70: =SUM(U70:W70) -> 26202.71
B71: 구성비 | C71: =C69/$C$69 -> 1 | D71: =D69/$C$69 -> 0.25027366 | E71: =E69/$C$69 -> 0.028580335 | F71: =F69/$C$69 -> 0.017425782 | G71: =G69/$C$69 -> 0.0072992892 | H71: =H69/$C$69 -> 0.0023802464 | I71: =I69/$C$69 -> 0.30595932 | J71: =J69/$C$69 -> 0.13097086 | ... X71: =X69/$C$69 -> 0.096885243
B72: 전용면적 | C72: =I72+T72+X72 -> 40534.76 | D72: 10848.89 | E72: 1218.17 | F72: 591.99 | G72: 213.87 | H72: 0 | I72: =SUM(D72:H72) -> 12872.92 | J72: 5174.57 | K72: 1462.29 | L72: 5186.06 | M72: 847 | N72: 910.53 | O72: 535.43 | P72: 514.25 | Q72: 1870.66 | R72: 7377.98 | S72: 0 | T72: =SUM(J72:S72) -> 23878.77 | U72: 948.64 | V72: 1270.5 | W72: 1563.93 | X72: =SUM(U72:W72) -> 3783.07
B73: 공용면적 | C73: =I73+T73+X73 -> 18313.26 | D73: 3879.26 | E73: 463.73 | F73: 433.48 | G73: 215.68 | H73: 140.07 | I73: =SUM(D73:H73) -> 5132.22 | J73: 2532.63 | K73: 555.39 | L73: 2903.78 | M73: 710.88 | N73: 405.35 | O73: 381.15 | P73: 251.08 | Q73: 467.67 | R73: 2725.53 | S73: 329.12 | T73: =SUM(J73:S73) -> 11262.58 | U73: 255.31 | V73: 487.03 | W73: 1176.12 | X73: =SUM(U73:W73) -> 1918.46
B74: 시설면적 | C74: =I74+T74+X74+Y74+Z74 -> 81811.424 | D74: =D72+D73 -> 14728.15 | E74: =E72+E73 -> 1681.9 | F74: =F72+F73 -> 1025.47 | G74: =G72+G73 -> 429.55 | H74: =H72+H73 -> 140.07 | I74: =SUM(D74:H74) -> 18005.14 | J74: =J72+J73 -> 7707.2 | K74: =K72+K73 -> 2017.68 | L74: =L72+L73 -> 8089.84 | M74: =M72+M73 -> 1557.88 | N74: =N72+N73 -> 1315.88 | O74: =O72+O73 -> 916.58 | P74: =P72+P73 -> 765.33 | Q74: =Q72+Q73 -> 2338.33 | ... S74: =S72+S73 -> 329.12 | T74: =SUM(J74:S74) -> 35141.35 | U74: =U72+U73 -> 1203.95 | V74: =V72+V73 -> 1757.53 | W74: =W72+W73 -> 2740.05 | X74: =SUM(U74:W74) -> 5701.53 | Y74: 1585.81 | Z74: =$C$69-($I$74+$T$74+$X$74)-$Y$74 -> 21377.594
B75: 구성비 | C75: =C74/$C$74 -> 1 | D75: =D74/$C$74 -> 0.18002559 | E75: =E74/$C$74 -> 0.020558253 | F75: =F74/$C$74 -> 0.012534557 | G75: =G74/$C$74 -> 0.0052504892 | H75: =H74/$C$74 -> 0.0017121081 | I75: =I74/$C$74 -> 0.220081 | J75: =J74/$C$74 -> 0.094206892 | ... Z75: =Z74/$C$74 -> 0.26130329
B76: 주차장 배분 | C76: =I76+T76+X76 -> 21377.594 | D76: =$Z$74*D74/($I$74+$T$74+$X$74) -> 5350.2636 | E76: =$Z$74*E74/($I$74+$T$74+$X$74) -> 610.98022 | F76: =$Z$74*F74/($I$74+$T$74+$X$74) -> 372.5203 | G76: =$Z$74*G74/($I$74+$T$74+$X$74) -> 156.04171 | H76: =$Z$74*H74/($I$74+$T$74+$X$74) -> 50.88293 | I76: =SUM(D76:H76) -> 6540.6887 | J76: =$Z$74*J74/($I$74+$T$74+$X$74) -> 2799.7781 | K76: =$Z$74*K74/($I$74+$T$74+$X$74) -> 732.9583 | L76: =$Z$74*L74/($I$74+$T$74+$X$74) -> 2938.7789 | M76: =$Z$74*M74/($I$74+$T$74+$X$74) -> 565.92774 | N76: =$Z$74*N74/($I$74+$T$74+$X$74) -> 478.01692 | O76: =$Z$74*O74/($I$74+$T$74+$X$74) -> 332.96406 | P76: =$Z$74*P74/($I$74+$T$74+$X$74) -> 278.01979 | Q76: =$Z$74*Q74/($I$74+$T$74+$X$74) -> 849.44014 | ... S76: =$Z$74*S74/($I$74+$T$74+$X$74) -> 119.55872 | T76: =SUM(J76:S76) -> 12765.723 | U76: =$Z$74*U74/($I$74+$T$74+$X$74) -> 437.35634 | V76: =$Z$74*V74/($I$74+$T$74+$X$74) -> 638.45417 | W76: =$Z$74*W74/($I$74+$T$74+$X$74) -> 995.37211 | X76: =SUM(U76:W76) -> 2071.1826
B77: 기계실 배분 | C77: =I77+T77+X77 -> 1585.81 | D77: =$Y$74*D74/($I$74+$T$74+$X$74) -> 396.88757 | E77: =$Y$74*E74/($I$74+$T$74+$X$74) -> 45.323085 | F77: =$Y$74*F74/($I$74+$T$74+$X$74) -> 27.633905 | G77: =$Y$74*G74/($I$74+$T$74+$X$74) -> 11.57532 | H77: =$Y$74*H74/($I$74+$T$74+$X$74) -> 3.7745434 | I77: =SUM(D77:H77) -> 485.19442 | J77: =$Y$74*J74/($I$74+$T$74+$X$74) -> 207.69016 | K77: =$Y$74*K74/($I$74+$T$74+$X$74) -> 54.371534 | L77: =$Y$74*L74/($I$74+$T$74+$X$74) -> 218.00137 | M77: =$Y$74*M74/($I$74+$T$74+$X$74) -> 41.98105 | N77: =$Y$74*N74/($I$74+$T$74+$X$74) -> 35.459743 | O77: =$Y$74*O74/($I$74+$T$74+$X$74) -> 24.699586 | P77: =$Y$74*P74/($I$74+$T$74+$X$74) -> 20.623769 | Q77: =$Y$74*Q74/($I$74+$T$74+$X$74) -> 63.012266 | ... S77: =$Y$74*S74/($I$74+$T$74+$X$74) -> 8.8689779 | T77: =SUM(J77:S77) -> 946.97331 | U77: =$Y$74*U74/($I$74+$T$74+$X$74) -> 32.443504 | V77: =$Y$74*V74/($I$74+$T$74+$X$74) -> 47.361129 | W77: =$Y$74*W74/($I$74+$T$74+$X$74) -> 73.837636 | X77: =SUM(U77:W77) -> 153.64227
B78: 전체 공용면적 | C78: =I78+T78+X78 -> 41276.664 | D78: =D73+D76+D77 -> 9626.4111 | E78: =E73+E76+E77 -> 1120.0333 | F78: =F73+F76+F77 -> 833.6342 | G78: =G73+G76+G77 -> 383.29703 | H78: =H73+H76+H77 -> 194.72747 | I78: =SUM(D78:H78) -> 12158.103 | J78: =J73+J76+J77 -> 5540.0982 | K78: =K73+K76+K77 -> 1342.7198 | L78: =L73+L76+L77 -> 6060.5603 | M78: =M73+M76+M77 -> 1318.7888 | N78: =N73+N76+N77 -> 918.82666 | O78: =O73+O76+O77 -> 738.81364 | P78: =P73+P76+P77 -> 549.72356 | Q78: =Q73+Q76+Q77 -> 1380.1224 | ... S78: =S73+S76+S77 -> 457.5477 | T78: =SUM(J78:S78) -> 24975.276 | U78: =U73+U76+U77 -> 725.10985 | V78: =V73+V76+V77 -> 1172.8453 | W78: =W73+W76+W77 -> 2245.3297 | X78: =SUM(U78:W78) -> 4143.2849
B79: 전용률 | C79: =C72/C69 -> 0.49546576 | D79: =IF(D69=0,0,D72/D69) -> 0.52985398 | E79: =IF(E69=0,0,E72/E69) -> 0.52098669 | F79: =IF(F69=0,0,F72/F69) -> 0.41524856 | G79: =IF(G69=0,0,G72/G69) -> 0.35814207 | H79: =IF(H69=0,0,H72/H69) -> 0 | I79: =IF(I69=0,0,I72/I69) -> 0.51427976 | J79: =IF(J69=0,0,J72/J69) -> 0.48293159 | K79: =IF(K69=0,0,K72/K69) -> 0.52131648 | ... X79: =IF(X69=0,0,X72/X69) -> 0.47727951
B80: 비고 | D80: 270세대 | J80: 92세대 | L80: 257실
B82: (6) 대지면적 | D82: 16515 | E82: =$D$82*$F$54 -> 4995.7875
B84: 구분 | C84: Ratio | D84: 토지면적(㎡) | E84: 토지면적(평)
B85: 시니어 레지던스 | C85: =$E$60/$C$69 -> 0.28123425 | D85: =C85*$D$82 -> 4644.5836 | E85: =C85*$E$82 -> 1404.9865
B86: 서비스드 레지던스 | C86: =$E$61/$C$69 -> 0.16525697 | D86: =C86*$D$82 -> 2729.2188 | E86: =C86*$E$82 -> 825.58868
B87: 호텔 | C87: =$E$62/$C$69 -> 0.26021092 | D87: =C87*$D$82 -> 4297.3833 | E87: =C87*$E$82 -> 1299.9584
B88: 오피스 | C88: =$E$63/$C$69 -> 0.17168756 | D88: =C88*$D$82 -> 2835.42 | E88: =C88*$E$82 -> 857.71456
B89: 부대시설 | C89: =$E$64/$C$69 -> 0.12161031 | D89: =C89*$D$82 -> 2008.3943 | E89: =C89*$E$82 -> 607.53929
B90: 합계 | C90: =SUM(C85:C89) -> 1 | D90: =SUM(D85:D89) -> 16515 | E90: =SUM(E85:E89) -> 4995.7875
A92: Operation
B93: ※ 운영기간 시계열(Index: 운영기간 누적, 입주모집률, OCC, 공실률, 리징비용, 상승률 등)은 CF 시트에서 월별로 계산
A95: 시니어 레지던스
B96: 운영수입 | C96: 세대수 | D96: 세대 | E96: 270 | G96: 보증금 | H96: 일자 | I96: 비중 | J96: 월Key
C97: 보증금 | D97: 백만원/세대 | E97: 2000 | G97: 계약금 | H97: 46477 | I97: 0.1 | J97: =EOMONTH(H97,0) -> 46477
C98: 보증금(100% 기준) | D98: 백만원 | E98: =$E$96*$E$97 -> 540000 | G98: 중도금(1차) | H98: 46842 | I98: 0.2 | J98: =EOMONTH(H98,0) -> 46843
C99: 월임대료 | D99: 천원/세대,월 | E99: 0 | G99: 중도금(2차) | H99: 47208 | I99: 0.2 | J99: =EOMONTH(H99,0) -> 47208
C100: 이용료수익 | D100: 천원/세대,월 | E100: 6000 | G100: 중도금(3차) | H100: 47573 | I100: 0.2 | J100: =EOMONTH(H100,0) -> 47573
C101: 보증금 및 임대료상승률 | D101: % | E101: 0.02 | G101: 잔금 | H101: 47938 | I101: 0.3 | J101: =EOMONTH(H101,0) -> 47938
C102: 보증금 및 임대료상승주기 | D102: 개월 | E102: 12 | G102: 합계 | I102: =SUM(I97:I101) -> 1
C103: 물가상승률 | D103: % | E103: 0.02
C104: 입주모집률 | D104: Y+1 | E104: 0.8
D105: Y+2 | E105: 1
D106: Y+3 이후 | E106: 1
C107: 추가수입(세대관리비등) | D107: 매출액 대비 | E107: 0.15
B108: 운영비용 | C108: ADR | D108: 천원/일 | E108: 200
C109: OCC | D109: % | E109: 0.9
C110: 일반운영비 | D110: 매출대비 % | E110: 0.75
C111: 소모품비 | D111: 매출대비 % | E111: 0.04
A113: 시니어 부대시설
B114: 운영수입 | C114: 보증금 | D114: 백만원 | E114: 1500
C115: 월임대료(전용면적당) | D115: 천원/평,월 | E115: 120
C116: 전용면적 | D116: 평 | E116: =$E$72 -> 1218.17
...

Sheet ①통합_CF
A1: 월별 현금흐름 (CF) — 단위: 백만원
A3: ※ 월말 기준. 모든 입력은 Assumption 시트 연결. C열 = 기간 합계(잔액행은 최대값/최종값, IRR행은 연환산 IRR)
A5: 구분 | B5: 단위 | C5: 합계
A6: 월말일자 | E6: =EOMONTH(①통합_가정!$E$8,0) -> 46112 | F6: =EOMONTH(E6,1) -> 46142 | G6: =EOMONTH(F6,1) -> 46173 | H6: =EOMONTH(G6,1) -> 46203 | I6: =EOMONTH(H6,1) -> 46234 | J6: =EOMONTH(I6,1) -> 46265 | K6: =EOMONTH(J6,1) -> 46295 | L6: =EOMONTH(K6,1) -> 46326 | M6: =EOMONTH(L6,1) -> 46356 | ... EF6: =EOMONTH(EE6,1) -> 50099
A7: 연도 | E7: =YEAR(E6) -> 2026 | F7: =YEAR(F6) -> 2026 | G7: =YEAR(G6) -> 2026 | H7: =YEAR(H6) -> 2026 | I7: =YEAR(I6) -> 2026 | J7: =YEAR(J6) -> 2026 | K7: =YEAR(K6) -> 2026 | L7: =YEAR(L6) -> 2026 | ... EF7: =YEAR(EF6) -> 2037
A8: 월차 | E8: =1 -> 1 | F8: =E8+1 -> 2 | G8: =F8+1 -> 3 | H8: =G8+1 -> 4 | I8: =H8+1 -> 5 | J8: =I8+1 -> 6 | K8: =J8+1 -> 7 | L8: =K8+1 -> 8 | M8: =L8+1 -> 9 | ... EF8: =EE8+1 -> 132
A9: 모델기간 Flag | E9: =IF(E6<=①통합_가정!$E$24,1,0) -> 1 | F9: =IF(F6<=①통합_가정!$E$24,1,0) -> 1 | G9: =IF(G6<=①통합_가정!$E$24,1,0) -> 1 | H9: =IF(H6<=①통합_가정!$E$24,1,0) -> 1 | I9: =IF(I6<=①통합_가정!$E$24,1,0) -> 1 | J9: =IF(J6<=①통합_가정!$E$24,1,0) -> 1 | K9: =IF(K6<=①통합_가정!$E$24,1,0) -> 1 | L9: =IF(L6<=①통합_가정!$E$24,1,0) -> 1 | ... EF9: =IF(EF6<=①통합_가정!$E$24,1,0) -> 0
A10: 개발기간 Flag(설립~준공) | E10: =IF(E6<=①통합_가정!$E$16,1,0) -> 1 | F10: =IF(F6<=①통합_가정!$E$16,1,0) -> 1 | G10: =IF(G6<=①통합_가정!$E$16,1,0) -> 1 | H10: =IF(H6<=①통합_가정!$E$16,1,0) -> 1 | I10: =IF(I6<=①통합_가정!$E$16,1,0) -> 1 | J10: =IF(J6<=①통합_가정!$E$16,1,0) -> 1 | K10: =IF(K6<=①통합_가정!$E$16,1,0) -> 1 | L10: =IF(L6<=①통합_가정!$E$16,1,0) -> 1 | ... EF10: =IF(EF6<=①통합_가정!$E$16,1,0) -> 0
A11: 공사기간 Flag | E11: =IF(AND(E6>=①통합_가정!$E$14,E6<=①통합_가정!$E$16),1,0) -> 0 | F11: =IF(AND(F6>=①통합_가정!$E$14,F6<=①통합_가정!$E$16),1,0) -> 0 | G11: =IF(AND(G6>=①통합_가정!$E$14,G6<=①통합_가정!$E$16),1,0) -> 0 | H11: =IF(AND(H6>=①통합_가정!$E$14,H6<=①통합_가정!$E$16),1,0) -> 0 | I11: =IF(AND(I6>=①통합_가정!$E$14,I6<=①통합_가정!$E$16),1,0) -> 0 | J11: =IF(AND(J6>=①통합_가정!$E$14,J6<=①통합_가정!$E$16),1,0) -> 0 | K11: =IF(AND(K6>=①통합_가정!$E$14,K6<=①통합_가정!$E$16),1,0) -> 0 | L11: =IF(AND(L6>=①통합_가정!$E$14,L6<=①통합_가정!$E$16),1,0) -> 0 | ... EF11: =IF(AND(EF6>=①통합_가정!$E$14,EF6<=①통합_가정!$E$16),1,0) -> 0
A12: 공사 월차 | E12: =IF(E11=1,(YEAR(E6)-YEAR(①통합_가정!$E$14))*12+MONTH(E6)-MONTH(①통합_가정!$E$14)+1,0) -> 0 | F12: =IF(F11=1,(YEAR(F6)-YEAR(①통합_가정!$E$14))*12+MONTH(F6)-MONTH(①통합_가정!$E$14)+1,0) -> 0 | G12: =IF(G11=1,(YEAR(G6)-YEAR(①통합_가정!$E$14))*12+MONTH(G6)-MONTH(①통합_가정!$E$14)+1,0) -> 0 | H12: =IF(H11=1,(YEAR(H6)-YEAR(①통합_가정!$E$14))*12+MONTH(H6)-MONTH(①통합_가정!$E$14)+1,0) -> 0 | I12: =IF(I11=1,(YEAR(I6)-YEAR(①통합_가정!$E$14))*12+MONTH(I6)-MONTH(①통합_가정!$E$14)+1,0) -> 0 | J12: =IF(J11=1,(YEAR(J6)-YEAR(①통합_가정!$E$14))*12+MONTH(J6)-MONTH(①통합_가정!$E$14)+1,0) -> 0 | K12: =IF(K11=1,(YEAR(K6)-YEAR(①통합_가정!$E$14))*12+MONTH(K6)-MONTH(①통합_가정!$E$14)+1,0) -> 0 | L12: =IF(L11=1,(YEAR(L6)-YEAR(①통합_가정!$E$14))*12+MONTH(L6)-MONTH(①통합_가정!$E$14)+1,0) -> 0 | ... EF12: =IF(EF11=1,(YEAR(EF6)-YEAR(①통합_가정!$E$14))*12+MONTH(EF6)-MONTH(①통합_가정!$E$14)+1,0) -> 0
A13: S-curve 집행률 | B13: % | C13: =SUM(E13:EF13) -> 1 | E13: =IF(E12>0,(COS(PI()*(E12-1)/①통합_가정!$E$15)-COS(PI()*E12/①통합_가정!$E$15))/2,0) -> 0 | F13: =IF(F12>0,(COS(PI()*(F12-1)/①통합_가정!$E$15)-COS(PI()*F12/①통합_가정!$E$15))/2,0) -> 0 | G13: =IF(G12>0,(COS(PI()*(G12-1)/①통합_가정!$E$15)-COS(PI()*G12/①통합_가정!$E$15))/2,0) -> 0 | H13: =IF(H12>0,(COS(PI()*(H12-1)/①통합_가정!$E$15)-COS(PI()*H12/①통합_가정!$E$15))/2,0) -> 0 | I13: =IF(I12>0,(COS(PI()*(I12-1)/①통합_가정!$E$15)-COS(PI()*I12/①통합_가정!$E$15))/2,0) -> 0 | J13: =IF(J12>0,(COS(PI()*(J12-1)/①통합_가정!$E$15)-COS(PI()*J12/①통합_가정!$E$15))/2,0) -> 0 | K13: =IF(K12>0,(COS(PI()*(K12-1)/①통합_가정!$E$15)-COS(PI()*K12/①통합_가정!$E$15))/2,0) -> 0 | L13: =IF(L12>0,(COS(PI()*(L12-1)/①통합_가정!$E$15)-COS(PI()*L12/①통합_가정!$E$15))/2,0) -> 0 | ... EF13: =IF(EF12>0,(COS(PI()*(EF12-1)/①통합_가정!$E$15)-COS(PI()*EF12/①통합_가정!$E$15))/2,0) -> 0
A14: 운영기간 Flag | E14: =IF(AND(E6>=①통합_가정!$E$18,E6<=①통합_가정!$E$20),1,0) -> 0 | F14: =IF(AND(F6>=①통합_가정!$E$18,F6<=①통합_가정!$E$20),1,0) -> 0 | G14: =IF(AND(G6>=①통합_가정!$E$18,G6<=①통합_가정!$E$20),1,0) -> 0 | H14: =IF(AND(H6>=①통합_가정!$E$18,H6<=①통합_가정!$E$20),1,0) -> 0 | I14: =IF(AND(I6>=①통합_가정!$E$18,I6<=①통합_가정!$E$20),1,0) -> 0 | J14: =IF(AND(J6>=①통합_가정!$E$18,J6<=①통합_가정!$E$20),1,0) -> 0 | K14: =IF(AND(K6>=①통합_가정!$E$18,K6<=①통합_가정!$E$20),1,0) -> 0 | L14: =IF(AND(L6>=①통합_가정!$E$18,L6<=①통합_가정!$E$20),1,0) -> 0 | ... EF14: =IF(AND(EF6>=①통합_가정!$E$18,EF6<=①통합_가정!$E$20),1,0) -> 0
A15: 운영 월차 | E15: =IF(E14=1,(YEAR(E6)-YEAR(①통합_가정!$E$18))*12+MONTH(E6)-MONTH(①통합_가정!$E$18)+1,0) -> 0 | F15: =IF(F14=1,(YEAR(F6)-YEAR(①통합_가정!$E$18))*12+MONTH(F6)-MONTH(①통합_가정!$E$18)+1,0) -> 0 | G15: =IF(G14=1,(YEAR(G6)-YEAR(①통합_가정!$E$18))*12+MONTH(G6)-MONTH(①통합_가정!$E$18)+1,0) -> 0 | H15: =IF(H14=1,(YEAR(H6)-YEAR(①통합_가정!$E$18))*12+MONTH(H6)-MONTH(①통합_가정!$E$18)+1,0) -> 0 | I15: =IF(I14=1,(YEAR(I6)-YEAR(①통합_가정!$E$18))*12+MONTH(I6)-MONTH(①통합_가정!$E$18)+1,0) -> 0 | J15: =IF(J14=1,(YEAR(J6)-YEAR(①통합_가정!$E$18))*12+MONTH(J6)-MONTH(①통합_가정!$E$18)+1,0) -> 0 | K15: =IF(K14=1,(YEAR(K6)-YEAR(①통합_가정!$E$18))*12+MONTH(K6)-MONTH(①통합_가정!$E$18)+1,0) -> 0 | L15: =IF(L14=1,(YEAR(L6)-YEAR(①통합_가정!$E$18))*12+MONTH(L6)-MONTH(①통합_가정!$E$18)+1,0) -> 0 | ... EF15: =IF(EF14=1,(YEAR(EF6)-YEAR(①통합_가정!$E$18))*12+MONTH(EF6)-MONTH(①통합_가정!$E$18)+1,0) -> 0
A16: 운영 연차 | E16: =IF(E15>0,INT((E15-1)/12)+1,0) -> 0 | F16: =IF(F15>0,INT((F15-1)/12)+1,0) -> 0 | G16: =IF(G15>0,INT((G15-1)/12)+1,0) -> 0 | H16: =IF(H15>0,INT((H15-1)/12)+1,0) -> 0 | I16: =IF(I15>0,INT((I15-1)/12)+1,0) -> 0 | J16: =IF(J15>0,INT((J15-1)/12)+1,0) -> 0 | K16: =IF(K15>0,INT((K15-1)/12)+1,0) -> 0 | L16: =IF(L15>0,INT((L15-1)/12)+1,0) -> 0 | ... EF16: =IF(EF15>0,INT((EF15-1)/12)+1,0) -> 0
A17: 리츠운용기간 Flag(운영개시~청산) | E17: =IF(AND(E6>=①통합_가정!$E$18,E6<=①통합_가정!$E$24),1,0) -> 0 | F17: =IF(AND(F6>=①통합_가정!$E$18,F6<=①통합_가정!$E$24),1,0) -> 0 | G17: =IF(AND(G6>=①통합_가정!$E$18,G6<=①통합_가정!$E$24),1,0) -> 0 | H17: =IF(AND(H6>=①통합_가정!$E$18,H6<=①통합_가정!$E$24),1,0) -> 0 | I17: =IF(AND(I6>=①통합_가정!$E$18,I6<=①통합_가정!$E$24),1,0) -> 0 | J17: =IF(AND(J6>=①통합_가정!$E$18,J6<=①통합_가정!$E$24),1,0) -> 0 | K17: =IF(AND(K6>=①통합_가정!$E$18,K6<=①통합_가정!$E$24),1,0) -> 0 | L17: =IF(AND(L6>=①통합_가정!$E$18,L6<=①통합_가정!$E$24),1,0) -> 0 | ... EF17: =IF(AND(EF6>=①통합_가정!$E$18,EF6<=①통합_가정!$E$24),1,0) -> 0
A18: 일수 | B18: 일 | E18: =DAY(E6) -> 31 | F18: =DAY(F6) -> 30 | G18: =DAY(G6) -> 31 | H18: =DAY(H6) -> 30 | I18: =DAY(I6) -> 31 | J18: =DAY(J6) -> 31 | K18: =DAY(K6) -> 30 | L18: =DAY(L6) -> 31 | ... EF18: =DAY(EF6) -> 28
A20: 운영수입
A21: 시니어 레지던스 이용료·임대료 | B21: 백만원 | C21: =SUM(E21:EF21) -> 97278.541 | E21: =(E14=1)*①통합_가정!$D$38*①통합_가정!$E$96*CHOOSE(MIN(MAX(E16,1),3),①통합_가정!$E$104,①통합_가정!$E$105,①통합_가정!$E$106)*(①통합_가정!$E$100+①통합_가정!$E$99)/1000*(1+①통합_가정!$E$101)^INT((E15-1)/①통합_가정!$E$102) -> 0 | F21: =(F14=1)*①통합_가정!$D$38*①통합_가정!$E$96*CHOOSE(MIN(MAX(F16,1),3),①통합_가정!$E$104,①통합_가정!$E$105,①통합_가정!$E$106)*(①통합_가정!$E$100+①통합_가정!$E$99)/1000*(1+①통합_가정!$E$101)^INT((F15-1)/①통합_가정!$E$102) -> 0 | G21: =(G14=1)*①통합_가정!$D$38*①통합_가정!$E$96*CHOOSE(MIN(MAX(G16,1),3),①통합_가정!$E$104,①통합_가정!$E$105,①통합_가정!$E$106)*(①통합_가정!$E$100+①통합_가정!$E$99)/1000*(1+①통합_가정!$E$101)^INT((G15-1)/①통합_가정!$E$102) -> 0 | H21: =(H14=1)*①통합_가정!$D$38*①통합_가정!$E$96*CHOOSE(MIN(MAX(H16,1),3),①통합_가정!$E$104,①통합_가정!$E$105,①통합_가정!$E$106)*(①통합_가정!$E$100+①통합_가정!$E$99)/1000*(1+①통합_가정!$E$101)^INT((H15-1)/①통합_가정!$E$102) -> 0 | I21: =(I14=1)*①통합_가정!$D$38*①통합_가정!$E$96*CHOOSE(MIN(MAX(I16,1),3),①통합_가정!$E$104,①통합_가정!$E$105,①통합_가정!$E$106)*(①통합_가정!$E$100+①통합_가정!$E$99)/1000*(1+①통합_가정!$E$101)^INT((I15-1)/①통합_가정!$E$102) -> 0 | J21: =(J14=1)*①통합_가정!$D$38*①통합_가정!$E$96*CHOOSE(MIN(MAX(J16,1),3),①통합_가정!$E$104,①통합_가정!$E$105,①통합_가정!$E$106)*(①통합_가정!$E$100+①통합_가정!$E$99)/1000*(1+①통합_가정!$E$101)^INT((J15-1)/①통합_가정!$E$102) -> 0 | K21: =(K14=1)*①통합_가정!$D$38*①통합_가정!$E$96*CHOOSE(MIN(MAX(K16,1),3),①통합_가정!$E$104,①통합_가정!$E$105,①통합_가정!$E$106)*(①통합_가정!$E$100+①통합_가정!$E$99)/1000*(1+①통합_가정!$E$101)^INT((K15-1)/①통합_가정!$E$102) -> 0 | L21: =(L14=1)*①통합_가정!$D$38*①통합_가정!$E$96*CHOOSE(MIN(MAX(L16,1),3),①통합_가정!$E$104,①통합_가정!$E$105,①통합_가정!$E$106)*(①통합_가정!$E$100+①통합_가정!$E$99)/1000*(1+①통합_가정!$E$101)^INT((L15-1)/①통합_가정!$E$102) -> 0 | ... EF21: =(EF14=1)*①통합_가정!$D$38*①통합_가정!$E$96*CHOOSE(MIN(MAX(EF16,1),3),①통합_가정!$E$104,①통합_가정!$E$105,①통합_가정!$E$106)*(①통합_가정!$E$100+①통합_가정!$E$99)/1000*(1+①통합_가정!$E$101)^INT((EF15-1)/①통합_가정!$E$102) -> 0
A22: 시니어 추가수입(세대관리비 등) | B22: 백만원 | C22: =SUM(E22:EF22) -> 14591.781 | E22: =E21*①통합_가정!$E$107 -> 0 | F22: =F21*①통합_가정!$E$107 -> 0 | G22: =G21*①통합_가정!$E$107 -> 0 | H22: =H21*①통합_가정!$E$107 -> 0 | I22: =I21*①통합_가정!$E$107 -> 0 | J22: =J21*①통합_가정!$E$107 -> 0 | K22: =K21*①통합_가정!$E$107 -> 0 | L22: =L21*①통합_가정!$E$107 -> 0 | ... EF22: =EF21*①통합_가정!$E$107 -> 0
A23: 시니어 부대시설 임대료 | B23: 백만원 | C23: =SUM(E23:EF23) -> 9128.7441 | E23: =(E14=1)*①통합_가정!$D$38*①통합_가정!$E$115*①통합_가정!$E$116/1000*(1+①통합_가정!$E$118)^INT((E15-1)/①통합_가정!$E$119) -> 0 | F23: =(F14=1)*①통합_가정!$D$38*①통합_가정!$E$115*①통합_가정!$E$116/1000*(1+①통합_가정!$E$118)^INT((F15-1)/①통합_가정!$E$119) -> 0 | G23: =(G14=1)*①통합_가정!$D$38*①통합_가정!$E$115*①통합_가정!$E$116/1000*(1+①통합_가정!$E$118)^INT((G15-1)/①통합_가정!$E$119) -> 0 | H23: =(H14=1)*①통합_가정!$D$38*①통합_가정!$E$115*①통합_가정!$E$116/1000*(1+①통합_가정!$E$118)^INT((H15-1)/①통합_가정!$E$119) -> 0 | I23: =(I14=1)*①통합_가정!$D$38*①통합_가정!$E$115*①통합_가정!$E$116/1000*(1+①통합_가정!$E$118)^INT((I15-1)/①통합_가정!$E$119) -> 0 | J23: =(J14=1)*①통합_가정!$D$38*①통합_가정!$E$115*①통합_가정!$E$116/1000*(1+①통합_가정!$E$118)^INT((J15-1)/①통합_가정!$E$119) -> 0 | K23: =(K14=1)*①통합_가정!$D$38*①통합_가정!$E$115*①통합_가정!$E$116/1000*(1+①통합_가정!$E$118)^INT((K15-1)/①통합_가정!$E$119) -> 0 | L23: =(L14=1)*①통합_가정!$D$38*①통합_가정!$E$115*①통합_가정!$E$116/1000*(1+①통합_가정!$E$118)^INT((L15-1)/①통합_가정!$E$119) -> 0 | ... EF23: =(EF14=1)*①통합_가정!$D$38*①통합_가정!$E$115*①통합_가정!$E$116/1000*(1+①통합_가정!$E$118)^INT((EF15-1)/①통합_가정!$E$119) -> 0
A24: 레지던스 객실매출 | B24: 백만원 | C24: =SUM(E24:EF24) -> 97070.53 | E24: =(E14=1)*①통합_가정!$E$38*①통합_가정!$G$129*CHOOSE(MIN(MAX(E16,1),3),①통합_가정!$E$136,①통합_가정!$E$137,①통합_가정!$E$138)*E18/1000000*(1+①통합_가정!$E$132)^(MAX(E16,1)-1) -> 0 | F24: =(F14=1)*①통합_가정!$E$38*①통합_가정!$G$129*CHOOSE(MIN(MAX(F16,1),3),①통합_가정!$E$136,①통합_가정!$E$137,①통합_가정!$E$138)*F18/1000000*(1+①통합_가정!$E$132)^(MAX(F16,1)-1) -> 0 | G24: =(G14=1)*①통합_가정!$E$38*①통합_가정!$G$129*CHOOSE(MIN(MAX(G16,1),3),①통합_가정!$E$136,①통합_가정!$E$137,①통합_가정!$E$138)*G18/1000000*(1+①통합_가정!$E$132)^(MAX(G16,1)-1) -> 0 | H24: =(H14=1)*①통합_가정!$E$38*①통합_가정!$G$129*CHOOSE(MIN(MAX(H16,1),3),①통합_가정!$E$136,①통합_가정!$E$137,①통합_가정!$E$138)*H18/1000000*(1+①통합_가정!$E$132)^(MAX(H16,1)-1) -> 0 | I24: =(I14=1)*①통합_가정!$E$38*①통합_가정!$G$129*CHOOSE(MIN(MAX(I16,1),3),①통합_가정!$E$136,①통합_가정!$E$137,①통합_가정!$E$138)*I18/1000000*(1+①통합_가정!$E$132)^(MAX(I16,1)-1) -> 0 | J24: =(J14=1)*①통합_가정!$E$38*①통합_가정!$G$129*CHOOSE(MIN(MAX(J16,1),3),①통합_가정!$E$136,①통합_가정!$E$137,①통합_가정!$E$138)*J18/1000000*(1+①통합_가정!$E$132)^(MAX(J16,1)-1) -> 0 | K24: =(K14=1)*①통합_가정!$E$38*①통합_가정!$G$129*CHOOSE(MIN(MAX(K16,1),3),①통합_가정!$E$136,①통합_가정!$E$137,①통합_가정!$E$138)*K18/1000000*(1+①통합_가정!$E$132)^(MAX(K16,1)-1) -> 0 | L24: =(L14=1)*①통합_가정!$E$38*①통합_가정!$G$129*CHOOSE(MIN(MAX(L16,1),3),①통합_가정!$E$136,①통합_가정!$E$137,①통합_가정!$E$138)*L18/1000000*(1+①통합_가정!$E$132)^(MAX(L16,1)-1) -> 0 | ... EF24: =(EF14=1)*①통합_가정!$E$38*①통합_가정!$G$129*CHOOSE(MIN(MAX(EF16,1),3),①통합_가정!$E$136,①통합_가정!$E$137,①통합_가정!$E$138)*EF18/1000000*(1+①통합_가정!$E$132)^(MAX(EF16,1)-1) -> 0
A25: 레지던스 객실외매출 | B25: 백만원 | C25: =SUM(E25:EF25) -> 64746.044 | E25: =E24*①통합_가정!$E$139 -> 0 | F25: =F24*①통합_가정!$E$139 -> 0 | G25: =G24*①통합_가정!$E$139 -> 0 | H25: =H24*①통합_가정!$E$139 -> 0 | I25: =I24*①통합_가정!$E$139 -> 0 | J25: =J24*①통합_가정!$E$139 -> 0 | K25: =K24*①통합_가정!$E$139 -> 0 | L25: =L24*①통합_가정!$E$139 -> 0 | ... EF25: =EF24*①통합_가정!$E$139 -> 0
A26: 레지던스 멤버전용 매출 | B26: 백만원 | C26: =SUM(E26:EF26) -> 35430.744 | E26: =E24*①통합_가정!$E$144 -> 0 | F26: =F24*①통합_가정!$E$144 -> 0 | G26: =G24*①통합_가정!$E$144 -> 0 | H26: =H24*①통합_가정!$E$144 -> 0 | I26: =I24*①통합_가정!$E$144 -> 0 | J26: =J24*①통합_가정!$E$144 -> 0 | K26: =K24*①통합_가정!$E$144 -> 0 | L26: =L24*①통합_가정!$E$144 -> 0 | ... EF26: =EF24*①통합_가정!$E$144 -> 0
A27: 호텔 객실매출 | B27: 백만원 | C27: =SUM(E27:EF27) -> 214271.36 | E27: =(E14=1)*①통합_가정!$F$38*①통합_가정!$E$148*①통합_가정!$E$159*CHOOSE(MIN(MAX(E16,1),3),①통합_가정!$E$160,①통합_가정!$E$161,①통합_가정!$E$162)*E18/1000000*(1+①통합_가정!$E$155)^(MAX(E16,1)-1) -> 0 | F27: =(F14=1)*①통합_가정!$F$38*①통합_가정!$E$148*①통합_가정!$E$159*CHOOSE(MIN(MAX(F16,1),3),①통합_가정!$E$160,①통합_가정!$E$161,①통합_가정!$E$162)*F18/1000000*(1+①통합_가정!$E$155)^(MAX(F16,1)-1) -> 0 | G27: =(G14=1)*①통합_가정!$F$38*①통합_가정!$E$148*①통합_가정!$E$159*CHOOSE(MIN(MAX(G16,1),3),①통합_가정!$E$160,①통합_가정!$E$161,①통합_가정!$E$162)*G18/1000000*(1+①통합_가정!$E$155)^(MAX(G16,1)-1) -> 0 | H27: =(H14=1)*①통합_가정!$F$38*①통합_가정!$E$148*①통합_가정!$E$159*CHOOSE(MIN(MAX(H16,1),3),①통합_가정!$E$160,①통합_가정!$E$161,①통합_가정!$E$162)*H18/1000000*(1+①통합_가정!$E$155)^(MAX(H16,1)-1) -> 0 | I27: =(I14=1)*①통합_가정!$F$38*①통합_가정!$E$148*①통합_가정!$E$159*CHOOSE(MIN(MAX(I16,1),3),①통합_가정!$E$160,①통합_가정!$E$161,①통합_가정!$E$162)*I18/1000000*(1+①통합_가정!$E$155)^(MAX(I16,1)-1) -> 0 | J27: =(J14=1)*①통합_가정!$F$38*①통합_가정!$E$148*①통합_가정!$E$159*CHOOSE(MIN(MAX(J16,1),3),①통합_가정!$E$160,①통합_가정!$E$161,①통합_가정!$E$162)*J18/1000000*(1+①통합_가정!$E$155)^(MAX(J16,1)-1) -> 0 | K27: =(K14=1)*①통합_가정!$F$38*①통합_가정!$E$148*①통합_가정!$E$159*CHOOSE(MIN(MAX(K16,1),3),①통합_가정!$E$160,①통합_가정!$E$161,①통합_가정!$E$162)*K18/1000000*(1+①통합_가정!$E$155)^(MAX(K16,1)-1) -> 0 | L27: =(L14=1)*①통합_가정!$F$38*①통합_가정!$E$148*①통합_가정!$E$159*CHOOSE(MIN(MAX(L16,1),3),①통합_가정!$E$160,①통합_가정!$E$161,①통합_가정!$E$162)*L18/1000000*(1+①통합_가정!$E$155)^(MAX(L16,1)-1) -> 0 | ... EF27: =(EF14=1)*①통합_가정!$F$38*①통합_가정!$E$148*①통합_가정!$E$159*CHOOSE(MIN(MAX(EF16,1),3),①통합_가정!$E$160,①통합_가정!$E$161,①통합_가정!$E$162)*EF18/1000000*(1+①통합_가정!$E$155)^(MAX(EF16,1)-1) -> 0
A28: 호텔 객실외매출(식음) | B28: 백만원 | C28: =SUM(E28:EF28) -> 96422.111 | E28: =E27*①통합_가정!$E$163 -> 0 | F28: =F27*①통합_가정!$E$163 -> 0 | G28: =G27*①통합_가정!$E$163 -> 0 | H28: =H27*①통합_가정!$E$163 -> 0 | I28: =I27*①통합_가정!$E$163 -> 0 | J28: =J27*①통합_가정!$E$163 -> 0 | K28: =K27*①통합_가정!$E$163 -> 0 | L28: =L27*①통합_가정!$E$163 -> 0 | ... EF28: =EF27*①통합_가정!$E$163 -> 0
A29: 호텔 객실외매출(기타) | B29: 백만원 | C29: =SUM(E29:EF29) -> 12856.281 | E29: =E27*①통합_가정!$E$164 -> 0 | F29: =F27*①통합_가정!$E$164 -> 0 | G29: =G27*①통합_가정!$E$164 -> 0 | H29: =H27*①통합_가정!$E$164 -> 0 | I29: =I27*①통합_가정!$E$164 -> 0 | J29: =J27*①통합_가정!$E$164 -> 0 | K29: =K27*①통합_가정!$E$164 -> 0 | L29: =L27*①통합_가정!$E$164 -> 0 | ... EF29: =EF27*①통합_가정!$E$164 -> 0
A30: 컨벤션(연회장) | B30: 백만원 | C30: =SUM(E30:EF30) -> 77137.689 | E30: =E27*①통합_가정!$E$169 -> 0 | F30: =F27*①통합_가정!$E$169 -> 0 | G30: =G27*①통합_가정!$E$169 -> 0 | H30: =H27*①통합_가정!$E$169 -> 0 | I30: =I27*①통합_가정!$E$169 -> 0 | J30: =J27*①통합_가정!$E$169 -> 0 | K30: =K27*①통합_가정!$E$169 -> 0 | L30: =L27*①통합_가정!$E$169 -> 0 | ... EF30: =EF27*①통합_가정!$E$169 -> 0
A31: 스파&수영장&피트니스 | B31: 백만원 | C31: =SUM(E31:EF31) -> 29997.99 | E31: =E27*①통합_가정!$E$170 -> 0 | F31: =F27*①통합_가정!$E$170 -> 0 | G31: =G27*①통합_가정!$E$170 -> 0 | H31: =H27*①통합_가정!$E$170 -> 0 | I31: =I27*①통합_가정!$E$170 -> 0 | J31: =J27*①통합_가정!$E$170 -> 0 | K31: =K27*①통합_가정!$E$170 -> 0 | L31: =L27*①통합_가정!$E$170 -> 0 | ... EF31: =EF27*①통합_가정!$E$170 -> 0
A32: 파인다이닝/ADD | B32: 백만원 | C32: =SUM(E32:EF32) -> 96422.111 | E32: =E27*①통합_가정!$E$171 -> 0 | F32: =F27*①통합_가정!$E$171 -> 0 | G32: =G27*①통합_가정!$E$171 -> 0 | H32: =H27*①통합_가정!$E$171 -> 0 | I32: =I27*①통합_가정!$E$171 -> 0 | J32: =J27*①통합_가정!$E$171 -> 0 | K32: =K27*①통합_가정!$E$171 -> 0 | L32: =L27*①통합_가정!$E$171 -> 0 | ... EF32: =EF27*①통합_가정!$E$171 -> 0
A33: 휴게시설 | B33: 백만원 | C33: =SUM(E33:EF33) -> 42854.272 | E33: =E27*①통합_가정!$E$172 -> 0 | F33: =F27*①통합_가정!$E$172 -> 0 | G33: =G27*①통합_가정!$E$172 -> 0 | H33: =H27*①통합_가정!$E$172 -> 0 | I33: =I27*①통합_가정!$E$172 -> 0 | J33: =J27*①통합_가정!$E$172 -> 0 | K33: =K27*①통합_가정!$E$172 -> 0 | L33: =L27*①통합_가정!$E$172 -> 0 | ... EF33: =EF27*①통합_가정!$E$172 -> 0
A34: BOH | B34: 백만원 | C34: =SUM(E34:EF34) -> 8570.8543 | E34: =E33*①통합_가정!$E$173 -> 0 | F34: =F33*①통합_가정!$E$173 -> 0 | G34: =G33*①통합_가정!$E$173 -> 0 | H34: =H33*①통합_가정!$E$173 -> 0 | I34: =I33*①통합_가정!$E$173 -> 0 | J34: =J33*①통합_가정!$E$173 -> 0 | K34: =K33*①통합_가정!$E$173 -> 0 | L34: =L33*①통합_가정!$E$173 -> 0 | ... EF34: =EF33*①통합_가정!$E$173 -> 0
A35: 오피스 임대료 | B35: 백만원 | C35: =SUM(E35:EF35) -> 84940.506 | E35: =(E14=1)*①통합_가정!$G$38*①통합_가정!$E$183*①통합_가정!$E$184/1000*(1+①통합_가정!$E$186)^INT((E15-1)/①통합_가정!$E$187)*(1-CHOOSE(MIN(MAX(E16,1),3),①통합_가정!$E$189,①통합_가정!$E$190,①통합_가정!$E$191)) -> 0 | F35: =(F14=1)*①통합_가정!$G$38*①통합_가정!$E$183*①통합_가정!$E$184/1000*(1+①통합_가정!$E$186)^INT((F15-1)/①통합_가정!$E$187)*(1-CHOOSE(MIN(MAX(F16,1),3),①통합_가정!$E$189,①통합_가정!$E$190,①통합_가정!$E$191)) -> 0 | G35: =(G14=1)*①통합_가정!$G$38*①통합_가정!$E$183*①통합_가정!$E$184/1000*(1+①통합_가정!$E$186)^INT((G15-1)/①통합_가정!$E$187)*(1-CHOOSE(MIN(MAX(G16,1),3),①통합_가정!$E$189,①통합_가정!$E$190,①통합_가정!$E$191)) -> 0 | H35: =(H14=1)*①통합_가정!$G$38*①통합_가정!$E$183*①통합_가정!$E$184/1000*(1+①통합_가정!$E$186)^INT((H15-1)/①통합_가정!$E$187)*(1-CHOOSE(MIN(MAX(H16,1),3),①통합_가정!$E$189,①통합_가정!$E$190,①통합_가정!$E$191)) -> 0 | I35: =(I14=1)*①통합_가정!$G$38*①통합_가정!$E$183*①통합_가정!$E$184/1000*(1+①통합_가정!$E$186)^INT((I15-1)/①통합_가정!$E$187)*(1-CHOOSE(MIN(MAX(I16,1),3),①통합_가정!$E$189,①통합_가정!$E$190,①통합_가정!$E$191)) -> 0 | J35: =(J14=1)*①통합_가정!$G$38*①통합_가정!$E$183*①통합_가정!$E$184/1000*(1+①통합_가정!$E$186)^INT((J15-1)/①통합_가정!$E$187)*(1-CHOOSE(MIN(MAX(J16,1),3),①통합_가정!$E$189,①통합_가정!$E$190,①통합_가정!$E$191)) -> 0 | K35: =(K14=1)*①통합_가정!$G$38*①통합_가정!$E$183*①통합_가정!$E$184/1000*(1+①통합_가정!$E$186)^INT((K15-1)/①통합_가정!$E$187)*(1-CHOOSE(MIN(MAX(K16,1),3),①통합_가정!$E$189,①통합_가정!$E$190,①통합_가정!$E$191)) -> 0 | L35: =(L14=1)*①통합_가정!$G$38*①통합_가정!$E$183*①통합_가정!$E$184/1000*(1+①통합_가정!$E$186)^INT((L15-1)/①통합_가정!$E$187)*(1-CHOOSE(MIN(MAX(L16,1),3),①통합_가정!$E$189,①통합_가정!$E$190,①통합_가정!$E$191)) -> 0 | ... EF35: =(EF14=1)*①통합_가정!$G$38*①통합_가정!$E$183*①통합_가정!$E$184/1000*(1+①통합_가정!$E$186)^INT((EF15-1)/①통합_가정!$E$187)*(1-CHOOSE(MIN(MAX(EF16,1),3),①통합_가정!$E$189,①통합_가정!$E$190,①통합_가정!$E$191)) -> 0
A36: 메디컬 임대료 | B36: 백만원 | C36: =SUM(E36:EF36) -> 8886.1692 | E36: =(E14=1)*①통합_가정!$H$38*①통합_가정!$E$201*①통합_가정!$E$202/1000*(1+①통합_가정!$E$204)^INT((E15-1)/①통합_가정!$E$205)*(1-CHOOSE(MIN(MAX(E16,1),3),①통합_가정!$E$207,①통합_가정!$E$208,①통합_가정!$E$209)) -> 0 | F36: =(F14=1)*①통합_가정!$H$38*①통합_가정!$E$201*①통합_가정!$E$202/1000*(1+①통합_가정!$E$204)^INT((F15-1)/①통합_가정!$E$205)*(1-CHOOSE(MIN(MAX(F16,1),3),①통합_가정!$E$207,①통합_가정!$E$208,①통합_가정!$E$209)) -> 0 | G36: =(G14=1)*①통합_가정!$H$38*①통합_가정!$E$201*①통합_가정!$E$202/1000*(1+①통합_가정!$E$204)^INT((G15-1)/①통합_가정!$E$205)*(1-CHOOSE(MIN(MAX(G16,1),3),①통합_가정!$E$207,①통합_가정!$E$208,①통합_가정!$E$209)) -> 0 | H36: =(H14=1)*①통합_가정!$H$38*①통합_가정!$E$201*①통합_가정!$E$202/1000*(1+①통합_가정!$E$204)^INT((H15-1)/①통합_가정!$E$205)*(1-CHOOSE(MIN(MAX(H16,1),3),①통합_가정!$E$207,①통합_가정!$E$208,①통합_가정!$E$209)) -> 0 | I36: =(I14=1)*①통합_가정!$H$38*①통합_가정!$E$201*①통합_가정!$E$202/1000*(1+①통합_가정!$E$204)^INT((I15-1)/①통합_가정!$E$205)*(1-CHOOSE(MIN(MAX(I16,1),3),①통합_가정!$E$207,①통합_가정!$E$208,①통합_가정!$E$209)) -> 0 | J36: =(J14=1)*①통합_가정!$H$38*①통합_가정!$E$201*①통합_가정!$E$202/1000*(1+①통합_가정!$E$204)^INT((J15-1)/①통합_가정!$E$205)*(1-CHOOSE(MIN(MAX(J16,1),3),①통합_가정!$E$207,①통합_가정!$E$208,①통합_가정!$E$209)) -> 0 | K36: =(K14=1)*①통합_가정!$H$38*①통합_가정!$E$201*①통합_가정!$E$202/1000*(1+①통합_가정!$E$204)^INT((K15-1)/①통합_가정!$E$205)*(1-CHOOSE(MIN(MAX(K16,1),3),①통합_가정!$E$207,①통합_가정!$E$208,①통합_가정!$E$209)) -> 0 | L36: =(L14=1)*①통합_가정!$H$38*①통합_가정!$E$201*①통합_가정!$E$202/1000*(1+①통합_가정!$E$204)^INT((L15-1)/①통합_가정!$E$205)*(1-CHOOSE(MIN(MAX(L16,1),3),①통합_가정!$E$207,①통합_가정!$E$208,①통합_가정!$E$209)) -> 0 | ... EF36: =(EF14=1)*①통합_가정!$H$38*①통합_가정!$E$201*①통합_가정!$E$202/1000*(1+①통합_가정!$E$204)^INT((EF15-1)/①통합_가정!$E$205)*(1-CHOOSE(MIN(MAX(EF16,1),3),①통합_가정!$E$207,①통합_가정!$E$208,①통합_가정!$E$209)) -> 0
A37: 스파2.0 임대료 | B37: 백만원 | C37: =SUM(E37:EF37) -> 9520.8956 | E37: =(E14=1)*①통합_가정!$H$38*①통합_가정!$E$214*①통합_가정!$E$215/1000*(1+①통합_가정!$E$217)^INT((E15-1)/①통합_가정!$E$218)*(1-CHOOSE(MIN(MAX(E16,1),3),①통합_가정!$E$220,①통합_가정!$E$221,①통합_가정!$E$222)) -> 0 | F37: =(F14=1)*①통합_가정!$H$38*①통합_가정!$E$214*①통합_가정!$E$215/1000*(1+①통합_가정!$E$217)^INT((F15-1)/①통합_가정!$E$218)*(1-CHOOSE(MIN(MAX(F16,1),3),①통합_가정!$E$220,①통합_가정!$E$221,①통합_가정!$E$222)) -> 0 | G37: =(G14=1)*①통합_가정!$H$38*①통합_가정!$E$214*①통합_가정!$E$215/1000*(1+①통합_가정!$E$217)^INT((G15-1)/①통합_가정!$E$218)*(1-CHOOSE(MIN(MAX(G16,1),3),①통합_가정!$E$220,①통합_가정!$E$221,①통합_가정!$E$222)) -> 0 | H37: =(H14=1)*①통합_가정!$H$38*①통합_가정!$E$214*①통합_가정!$E$215/1000*(1+①통합_가정!$E$217)^INT((H15-1)/①통합_가정!$E$218)*(1-CHOOSE(MIN(MAX(H16,1),3),①통합_가정!$E$220,①통합_가정!$E$221,①통합_가정!$E$222)) -> 0 | I37: =(I14=1)*①통합_가정!$H$38*①통합_가정!$E$214*①통합_가정!$E$215/1000*(1+①통합_가정!$E$217)^INT((I15-1)/①통합_가정!$E$218)*(1-CHOOSE(MIN(MAX(I16,1),3),①통합_가정!$E$220,①통합_가정!$E$221,①통합_가정!$E$222)) -> 0 | J37: =(J14=1)*①통합_가정!$H$38*①통합_가정!$E$214*①통합_가정!$E$215/1000*(1+①통합_가정!$E$217)^INT((J15-1)/①통합_가정!$E$218)*(1-CHOOSE(MIN(MAX(J16,1),3),①통합_가정!$E$220,①통합_가정!$E$221,①통합_가정!$E$222)) -> 0 | K37: =(K14=1)*①통합_가정!$H$38*①통합_가정!$E$214*①통합_가정!$E$215/1000*(1+①통합_가정!$E$217)^INT((K15-1)/①통합_가정!$E$218)*(1-CHOOSE(MIN(MAX(K16,1),3),①통합_가정!$E$220,①통합_가정!$E$221,①통합_가정!$E$222)) -> 0 | L37: =(L14=1)*①통합_가정!$H$38*①통합_가정!$E$214*①통합_가정!$E$215/1000*(1+①통합_가정!$E$217)^INT((L15-1)/①통합_가정!$E$218)*(1-CHOOSE(MIN(MAX(L16,1),3),①통합_가정!$E$220,①통합_가정!$E$221,①통합_가정!$E$222)) -> 0 | ... EF37: =(EF14=1)*①통합_가정!$H$38*①통합_가정!$E$214*①통합_가정!$E$215/1000*(1+①통합_가정!$E$217)^INT((EF15-1)/①통합_가정!$E$218)*(1-CHOOSE(MIN(MAX(EF16,1),3),①통합_가정!$E$220,①통합_가정!$E$221,①통합_가정!$E$222)) -> 0
A38: 판매시설 임대료 | B38: 백만원 | C38: =SUM(E38:EF38) -> 16700.724 | E38: =(E14=1)*①통합_가정!$H$38*①통합_가정!$E$227*①통합_가정!$E$228/1000*(1+①통합_가정!$E$230)^INT((E15-1)/①통합_가정!$E$231)*(1-CHOOSE(MIN(MAX(E16,1),3),①통합_가정!$E$233,①통합_가정!$E$234,①통합_가정!$E$235)) -> 0 | F38: =(F14=1)*①통합_가정!$H$38*①통합_가정!$E$227*①통합_가정!$E$228/1000*(1+①통합_가정!$E$230)^INT((F15-1)/①통합_가정!$E$231)*(1-CHOOSE(MIN(MAX(F16,1),3),①통합_가정!$E$233,①통합_가정!$E$234,①통합_가정!$E$235)) -> 0 | G38: =(G14=1)*①통합_가정!$H$38*①통합_가정!$E$227*①통합_가정!$E$228/1000*(1+①통합_가정!$E$230)^INT((G15-1)/①통합_가정!$E$231)*(1-CHOOSE(MIN(MAX(G16,1),3),①통합_가정!$E$233,①통합_가정!$E$234,①통합_가정!$E$235)) -> 0 | H38: =(H14=1)*①통합_가정!$H$38*①통합_가정!$E$227*①통합_가정!$E$228/1000*(1+①통합_가정!$E$230)^INT((H15-1)/①통합_가정!$E$231)*(1-CHOOSE(MIN(MAX(H16,1),3),①통합_가정!$E$233,①통합_가정!$E$234,①통합_가정!$E$235)) -> 0 | I38: =(I14=1)*①통합_가정!$H$38*①통합_가정!$E$227*①통합_가정!$E$228/1000*(1+①통합_가정!$E$230)^INT((I15-1)/①통합_가정!$E$231)*(1-CHOOSE(MIN(MAX(I16,1),3),①통합_가정!$E$233,①통합_가정!$E$234,①통합_가정!$E$235)) -> 0 | J38: =(J14=1)*①통합_가정!$H$38*①통합_가정!$E$227*①통합_가정!$E$228/1000*(1+①통합_가정!$E$230)^INT((J15-1)/①통합_가정!$E$231)*(1-CHOOSE(MIN(MAX(J16,1),3),①통합_가정!$E$233,①통합_가정!$E$234,①통합_가정!$E$235)) -> 0 | K38: =(K14=1)*①통합_가정!$H$38*①통합_가정!$E$227*①통합_가정!$E$228/1000*(1+①통합_가정!$E$230)^INT((K15-1)/①통합_가정!$E$231)*(1-CHOOSE(MIN(MAX(K16,1),3),①통합_가정!$E$233,①통합_가정!$E$234,①통합_가정!$E$235)) -> 0 | L38: =(L14=1)*①통합_가정!$H$38*①통합_가정!$E$227*①통합_가정!$E$228/1000*(1+①통합_가정!$E$230)^INT((L15-1)/①통합_가정!$E$231)*(1-CHOOSE(MIN(MAX(L16,1),3),①통합_가정!$E$233,①통합_가정!$E$234,①통합_가정!$E$235)) -> 0 | ... EF38: =(EF14=1)*①통합_가정!$H$38*①통합_가정!$E$227*①통합_가정!$E$228/1000*(1+①통합_가정!$E$230)^INT((EF15-1)/①통합_가정!$E$231)*(1-CHOOSE(MIN(MAX(EF16,1),3),①통합_가정!$E$233,①통합_가정!$E$234,①통합_가정!$E$235)) -> 0
A39: 국제학교 임대료 | B39: 백만원 | C39: =SUM(E39:EF39) -> 4436.2652 | E39: =(E14=1)*①통합_가정!$H$38*①통합_가정!$E$240*①통합_가정!$E$241/1000*(1+①통합_가정!$E$243)^INT((E15-1)/①통합_가정!$E$244)*(1-CHOOSE(MIN(MAX(E16,1),3),①통합_가정!$E$246,①통합_가정!$E$247,①통합_가정!$E$248)) -> 0 | F39: =(F14=1)*①통합_가정!$H$38*①통합_가정!$E$240*①통합_가정!$E$241/1000*(1+①통합_가정!$E$243)^INT((F15-1)/①통합_가정!$E$244)*(1-CHOOSE(MIN(MAX(F16,1),3),①통합_가정!$E$246,①통합_가정!$E$247,①통합_가정!$E$248)) -> 0 | G39: =(G14=1)*①통합_가정!$H$38*①통합_가정!$E$240*①통합_가정!$E$241/1000*(1+①통합_가정!$E$243)^INT((G15-1)/①통합_가정!$E$244)*(1-CHOOSE(MIN(MAX(G16,1),3),①통합_가정!$E$246,①통합_가정!$E$247,①통합_가정!$E$248)) -> 0 | H39: =(H14=1)*①통합_가정!$H$38*①통합_가정!$E$240*①통합_가정!$E$241/1000*(1+①통합_가정!$E$243)^INT((H15-1)/①통합_가정!$E$244)*(1-CHOOSE(MIN(MAX(H16,1),3),①통합_가정!$E$246,①통합_가정!$E$247,①통합_가정!$E$248)) -> 0 | I39: =(I14=1)*①통합_가정!$H$38*①통합_가정!$E$240*①통합_가정!$E$241/1000*(1+①통합_가정!$E$243)^INT((I15-1)/①통합_가정!$E$244)*(1-CHOOSE(MIN(MAX(I16,1),3),①통합_가정!$E$246,①통합_가정!$E$247,①통합_가정!$E$248)) -> 0 | J39: =(J14=1)*①통합_가정!$H$38*①통합_가정!$E$240*①통합_가정!$E$241/1000*(1+①통합_가정!$E$243)^INT((J15-1)/①통합_가정!$E$244)*(1-CHOOSE(MIN(MAX(J16,1),3),①통합_가정!$E$246,①통합_가정!$E$247,①통합_가정!$E$248)) -> 0 | K39: =(K14=1)*①통합_가정!$H$38*①통합_가정!$E$240*①통합_가정!$E$241/1000*(1+①통합_가정!$E$243)^INT((K15-1)/①통합_가정!$E$244)*(1-CHOOSE(MIN(MAX(K16,1),3),①통합_가정!$E$246,①통합_가정!$E$247,①통합_가정!$E$248)) -> 0 | L39: =(L14=1)*①통합_가정!$H$38*①통합_가정!$E$240*①통합_가정!$E$241/1000*(1+①통합_가정!$E$243)^INT((L15-1)/①통합_가정!$E$244)*(1-CHOOSE(MIN(MAX(L16,1),3),①통합_가정!$E$246,①통합_가정!$E$247,①통합_가정!$E$248)) -> 0 | ... EF39: =(EF14=1)*①통합_가정!$H$38*①통합_가정!$E$240*①통합_가정!$E$241/1000*(1+①통합_가정!$E$243)^INT((EF15-1)/①통합_가정!$E$244)*(1-CHOOSE(MIN(MAX(EF16,1),3),①통합_가정!$E$246,①통합_가정!$E$247,①통합_가정!$E$248)) -> 0
A40: 영어유치원 임대료 | B40: 백만원 | C40: =SUM(E40:EF40) -> 1602.7028 | E40: =(E14=1)*①통합_가정!$H$38*①통합_가정!$E$253*①통합_가정!$E$254/1000*(1+①통합_가정!$E$256)^INT((E15-1)/①통합_가정!$E$257)*(1-CHOOSE(MIN(MAX(E16,1),3),①통합_가정!$E$259,①통합_가정!$E$260,①통합_가정!$E$261)) -> 0 | F40: =(F14=1)*①통합_가정!$H$38*①통합_가정!$E$253*①통합_가정!$E$254/1000*(1+①통합_가정!$E$256)^INT((F15-1)/①통합_가정!$E$257)*(1-CHOOSE(MIN(MAX(F16,1),3),①통합_가정!$E$259,①통합_가정!$E$260,①통합_가정!$E$261)) -> 0 | G40: =(G14=1)*①통합_가정!$H$38*①통합_가정!$E$253*①통합_가정!$E$254/1000*(1+①통합_가정!$E$256)^INT((G15-1)/①통합_가정!$E$257)*(1-CHOOSE(MIN(MAX(G16,1),3),①통합_가정!$E$259,①통합_가정!$E$260,①통합_가정!$E$261)) -> 0 | H40: =(H14=1)*①통합_가정!$H$38*①통합_가정!$E$253*①통합_가정!$E$254/1000*(1+①통합_가정!$E$256)^INT((H15-1)/①통합_가정!$E$257)*(1-CHOOSE(MIN(MAX(H16,1),3),①통합_가정!$E$259,①통합_가정!$E$260,①통합_가정!$E$261)) -> 0 | I40: =(I14=1)*①통합_가정!$H$38*①통합_가정!$E$253*①통합_가정!$E$254/1000*(1+①통합_가정!$E$256)^INT((I15-1)/①통합_가정!$E$257)*(1-CHOOSE(MIN(MAX(I16,1),3),①통합_가정!$E$259,①통합_가정!$E$260,①통합_가정!$E$261)) -> 0 | J40: =(J14=1)*①통합_가정!$H$38*①통합_가정!$E$253*①통합_가정!$E$254/1000*(1+①통합_가정!$E$256)^INT((J15-1)/①통합_가정!$E$257)*(1-CHOOSE(MIN(MAX(J16,1),3),①통합_가정!$E$259,①통합_가정!$E$260,①통합_가정!$E$261)) -> 0 | K40: =(K14=1)*①통합_가정!$H$38*①통합_가정!$E$253*①통합_가정!$E$254/1000*(1+①통합_가정!$E$256)^INT((K15-1)/①통합_가정!$E$257)*(1-CHOOSE(MIN(MAX(K16,1),3),①통합_가정!$E$259,①통합_가정!$E$260,①통합_가정!$E$261)) -> 0 | L40: =(L14=1)*①통합_가정!$H$38*①통합_가정!$E$253*①통합_가정!$E$254/1000*(1+①통합_가정!$E$256)^INT((L15-1)/①통합_가정!$E$257)*(1-CHOOSE(MIN(MAX(L16,1),3),①통합_가정!$E$259,①통합_가정!$E$260,①통합_가정!$E$261)) -> 0 | ... EF40: =(EF14=1)*①통합_가정!$H$38*①통합_가정!$E$253*①통합_가정!$E$254/1000*(1+①통합_가정!$E$256)^INT((EF15-1)/①통합_가정!$E$257)*(1-CHOOSE(MIN(MAX(EF16,1),3),①통합_가정!$E$259,①통합_가정!$E$260,①통합_가정!$E$261)) -> 0
A41: 운영수입 합계 | B41: 백만원 | C41: =SUM(E41:EF41) -> 1022866.3 | E41: =SUM(E21:E40) -> 0 | F41: =SUM(F21:F40) -> 0 | G41: =SUM(G21:G40) -> 0 | H41: =SUM(H21:H40) -> 0 | I41: =SUM(I21:I40) -> 0 | J41: =SUM(J21:J40) -> 0 | K41: =SUM(K21:K40) -> 0 | L41: =SUM(L21:L40) -> 0 | ... EF41: =SUM(EF21:EF40) -> 0
A43: 직접운영비용
A44: 시니어 운영비(일반+소모품) | B44: 백만원 | C44: =SUM(E44:EF44) -> 88377.554 | E44: =(E21+E22)*(①통합_가정!$E$110+①통합_가정!$E$111) -> 0 | F44: =(F21+F22)*(①통합_가정!$E$110+①통합_가정!$E$111) -> 0 | G44: =(G21+G22)*(①통합_가정!$E$110+①통합_가정!$E$111) -> 0 | H44: =(H21+H22)*(①통합_가정!$E$110+①통합_가정!$E$111) -> 0 | I44: =(I21+I22)*(①통합_가정!$E$110+①통합_가정!$E$111) -> 0 | J44: =(J21+J22)*(①통합_가정!$E$110+①통합_가정!$E$111) -> 0 | K44: =(K21+K22)*(①통합_가정!$E$110+①통합_가정!$E$111) -> 0 | L44: =(L21+L22)*(①통합_가정!$E$110+①통합_가정!$E$111) -> 0 | ... EF44: =(EF21+EF22)*(①통합_가정!$E$110+①통합_가정!$E$111) -> 0
A45: 레지던스 운영비(일반+소모품) | B45: 백만원 | C45: =SUM(E45:EF45) -> 127835.09 | E45: =(E24+E25)*(①통합_가정!$E$140+①통합_가정!$E$141) -> 0 | F45: =(F24+F25)*(①통합_가정!$E$140+①통합_가정!$E$141) -> 0 | G45: =(G24+G25)*(①통합_가정!$E$140+①통합_가정!$E$141) -> 0 | H45: =(H24+H25)*(①통합_가정!$E$140+①통합_가정!$E$141) -> 0 | I45: =(I24+I25)*(①통합_가정!$E$140+①통합_가정!$E$141) -> 0 | J45: =(J24+J25)*(①통합_가정!$E$140+①통합_가정!$E$141) -> 0 | K45: =(K24+K25)*(①통합_가정!$E$140+①통합_가정!$E$141) -> 0 | L45: =(L24+L25)*(①통합_가정!$E$140+①통합_가정!$E$141) -> 0 | ... EF45: =(EF24+EF25)*(①통합_가정!$E$140+①통합_가정!$E$141) -> 0
A46: 레지던스 멤버전용 운영비 | B46: 백만원 | C46: =SUM(E46:EF46) -> 26573.058 | E46: =E26*①통합_가정!$E$145 -> 0 | F46: =F26*①통합_가정!$E$145 -> 0 | G46: =G26*①통합_가정!$E$145 -> 0 | H46: =H26*①통합_가정!$E$145 -> 0 | I46: =I26*①통합_가정!$E$145 -> 0 | J46: =J26*①통합_가정!$E$145 -> 0 | K46: =K26*①통합_가정!$E$145 -> 0 | L46: =L26*①통합_가정!$E$145 -> 0 | ... EF46: =EF26*①통합_가정!$E$145 -> 0
A47: 호텔 운영비(일반+소모품) | B47: 백만원 | C47: =SUM(E47:EF47) -> 255604.3 | E47: =(E27+E28+E29)*(①통합_가정!$E$165+①통합_가정!$E$166) -> 0 | F47: =(F27+F28+F29)*(①통합_가정!$E$165+①통합_가정!$E$166) -> 0 | G47: =(G27+G28+G29)*(①통합_가정!$E$165+①통합_가정!$E$166) -> 0 | H47: =(H27+H28+H29)*(①통합_가정!$E$165+①통합_가정!$E$166) -> 0 | I47: =(I27+I28+I29)*(①통합_가정!$E$165+①통합_가정!$E$166) -> 0 | J47: =(J27+J28+J29)*(①통합_가정!$E$165+①통합_가정!$E$166) -> 0 | K47: =(K27+K28+K29)*(①통합_가정!$E$165+①통합_가정!$E$166) -> 0 | L47: =(L27+L28+L29)*(①통합_가정!$E$165+①통합_가정!$E$166) -> 0 | ... EF47: =(EF27+EF28+EF29)*(①통합_가정!$E$165+①통합_가정!$E$166) -> 0
A48: 컨벤션 운영비 | B48: 백만원 | C48: =SUM(E48:EF48) -> 57853.267 | E48: =E30*①통합_가정!$E$175 -> 0 | F48: =F30*①통합_가정!$E$175 -> 0 | G48: =G30*①통합_가정!$E$175 -> 0 | H48: =H30*①통합_가정!$E$175 -> 0 | I48: =I30*①통합_가정!$E$175 -> 0 | J48: =J30*①통합_가정!$E$175 -> 0 | K48: =K30*①통합_가정!$E$175 -> 0 | L48: =L30*①통합_가정!$E$175 -> 0 | ... EF48: =EF30*①통합_가정!$E$175 -> 0
A49: 스파&수영장&피트니스 운영비 | B49: 백만원 | C49: =SUM(E49:EF49) -> 22498.493 | E49: =E31*①통합_가정!$E$176 -> 0 | F49: =F31*①통합_가정!$E$176 -> 0 | G49: =G31*①통합_가정!$E$176 -> 0 | H49: =H31*①통합_가정!$E$176 -> 0 | I49: =I31*①통합_가정!$E$176 -> 0 | J49: =J31*①통합_가정!$E$176 -> 0 | K49: =K31*①통합_가정!$E$176 -> 0 | L49: =L31*①통합_가정!$E$176 -> 0 | ... EF49: =EF31*①통합_가정!$E$176 -> 0
A50: 파인다이닝/ADD 운영비 | B50: 백만원 | C50: =SUM(E50:EF50) -> 72316.583 | E50: =E32*①통합_가정!$E$177 -> 0 | F50: =F32*①통합_가정!$E$177 -> 0 | G50: =G32*①통합_가정!$E$177 -> 0 | H50: =H32*①통합_가정!$E$177 -> 0 | I50: =I32*①통합_가정!$E$177 -> 0 | J50: =J32*①통합_가정!$E$177 -> 0 | K50: =K32*①통합_가정!$E$177 -> 0 | L50: =L32*①통합_가정!$E$177 -> 0 | ... EF50: =EF32*①통합_가정!$E$177 -> 0
A51: 휴게시설 운영비 | B51: 백만원 | C51: =SUM(E51:EF51) -> 29997.99 | E51: =E33*①통합_가정!$E$178 -> 0 | F51: =F33*①통합_가정!$E$178 -> 0 | G51: =G33*①통합_가정!$E$178 -> 0 | H51: =H33*①통합_가정!$E$178 -> 0 | I51: =I33*①통합_가정!$E$178 -> 0 | J51: =J33*①통합_가정!$E$178 -> 0 | K51: =K33*①통합_가정!$E$178 -> 0 | L51: =L33*①통합_가정!$E$178 -> 0 | ... EF51: =EF33*①통합_가정!$E$178 -> 0
A52: BOH 운영비 | B52: 백만원 | C52: =SUM(E52:EF52) -> 7285.2262 | E52: =E34*①통합_가정!$E$179 -> 0 | F52: =F34*①통합_가정!$E$179 -> 0 | G52: =G34*①통합_가정!$E$179 -> 0 | H52: =H34*①통합_가정!$E$179 -> 0 | I52: =I34*①통합_가정!$E$179 -> 0 | J52: =J34*①통합_가정!$E$179 -> 0 | K52: =K34*①통합_가정!$E$179 -> 0 | L52: =L34*①통합_가정!$E$179 -> 0 | ... EF52: =EF34*①통합_가정!$E$179 -> 0
A53: 오피스 리징비용 | B53: 백만원 | C53: =SUM(E53:EF53) -> 9356.5957 | E53: =E35*CHOOSE(MIN(MAX(E16,1),3),①통합_가정!$E$192,①통합_가정!$E$193,①통합_가정!$E$194) -> 0 | F53: =F35*CHOOSE(MIN(MAX(F16,1),3),①통합_가정!$E$192,①통합_가정!$E$193,①통합_가정!$E$194) -> 0 | G53: =G35*CHOOSE(MIN(MAX(G16,1),3),①통합_가정!$E$192,①통합_가정!$E$193,①통합_가정!$E$194) -> 0 | H53: =H35*CHOOSE(MIN(MAX(H16,1),3),①통합_가정!$E$192,①통합_가정!$E$193,①통합_가정!$E$194) -> 0 | I53: =I35*CHOOSE(MIN(MAX(I16,1),3),①통합_가정!$E$192,①통합_가정!$E$193,①통합_가정!$E$194) -> 0 | J53: =J35*CHOOSE(MIN(MAX(J16,1),3),①통합_가정!$E$192,①통합_가정!$E$193,①통합_가정!$E$194) -> 0 | K53: =K35*CHOOSE(MIN(MAX(K16,1),3),①통합_가정!$E$192,①통합_가정!$E$193,①통합_가정!$E$194) -> 0 | L53: =L35*CHOOSE(MIN(MAX(L16,1),3),①통합_가정!$E$192,①통합_가정!$E$193,①통합_가정!$E$194) -> 0 | ... EF53: =EF35*CHOOSE(MIN(MAX(EF16,1),3),①통합_가정!$E$192,①통합_가정!$E$193,①통합_가정!$E$194) -> 0
A54: 오피스 관리비용 | B54: 백만원 | C54: =SUM(E54:EF54) -> 9214.873 | E54: =(E14=1)*①통합_가정!$G$38*①통합_가정!$E$195*①통합_가정!$E$184/1000*(1+①통합_가정!$E$188)^(MAX(E16,1)-1) -> 0 | F54: =(F14=1)*①통합_가정!$G$38*①통합_가정!$E$195*①통합_가정!$E$184/1000*(1+①통합_가정!$E$188)^(MAX(F16,1)-1) -> 0 | G54: =(G14=1)*①통합_가정!$G$38*①통합_가정!$E$195*①통합_가정!$E$184/1000*(1+①통합_가정!$E$188)^(MAX(G16,1)-1) -> 0 | H54: =(H14=1)*①통합_가정!$G$38*①통합_가정!$E$195*①통합_가정!$E$184/1000*(1+①통합_가정!$E$188)^(MAX(H16,1)-1) -> 0 | I54: =(I14=1)*①통합_가정!$G$38*①통합_가정!$E$195*①통합_가정!$E$184/1000*(1+①통합_가정!$E$188)^(MAX(I16,1)-1) -> 0 | J54: =(J14=1)*①통합_가정!$G$38*①통합_가정!$E$195*①통합_가정!$E$184/1000*(1+①통합_가정!$E$188)^(MAX(J16,1)-1) -> 0 | K54: =(K14=1)*①통합_가정!$G$38*①통합_가정!$E$195*①통합_가정!$E$184/1000*(1+①통합_가정!$E$188)^(MAX(K16,1)-1) -> 0 | L54: =(L14=1)*①통합_가정!$G$38*①통합_가정!$E$195*①통합_가정!$E$184/1000*(1+①통합_가정!$E$188)^(MAX(L16,1)-1) -> 0 | ... EF54: =(EF14=1)*①통합_가정!$G$38*①통합_가정!$E$195*①통합_가정!$E$184/1000*(1+①통합_가정!$E$188)^(MAX(EF16,1)-1) -> 0
A55: 부대시설 운영비 | B55: 백만원 | C55: =SUM(E55:EF55) -> 0 | E55: =E36*①통합_가정!$E$210+E37*①통합_가정!$E$223+E38*①통합_가정!$E$236+E39*①통합_가정!$E$249+E40*①통합_가정!$E$262 -> 0 | F55: =F36*①통합_가정!$E$210+F37*①통합_가정!$E$223+F38*①통합_가정!$E$236+F39*①통합_가정!$E$249+F40*①통합_가정!$E$262 -> 0 | G55: =G36*①통합_가정!$E$210+G37*①통합_가정!$E$223+G38*①통합_가정!$E$236+G39*①통합_가정!$E$249+G40*①통합_가정!$E$262 -> 0 | H55: =H36*①통합_가정!$E$210+H37*①통합_가정!$E$223+H38*①통합_가정!$E$236+H39*①통합_가정!$E$249+H40*①통합_가정!$E$262 -> 0 | I55: =I36*①통합_가정!$E$210+I37*①통합_가정!$E$223+I38*①통합_가정!$E$236+I39*①통합_가정!$E$249+I40*①통합_가정!$E$262 -> 0 | J55: =J36*①통합_가정!$E$210+J37*①통합_가정!$E$223+J38*①통합_가정!$E$236+J39*①통합_가정!$E$249+J40*①통합_가정!$E$262 -> 0 | K55: =K36*①통합_가정!$E$210+K37*①통합_가정!$E$223+K38*①통합_가정!$E$236+K39*①통합_가정!$E$249+K40*①통합_가정!$E$262 -> 0 | L55: =L36*①통합_가정!$E$210+L37*①통합_가정!$E$223+L38*①통합_가정!$E$236+L39*①통합_가정!$E$249+L40*①통합_가정!$E$262 -> 0 | ... EF55: =EF36*①통합_가정!$E$210+EF37*①통합_가정!$E$223+EF38*①통합_가정!$E$236+EF39*①통합_가정!$E$249+EF40*①통합_가정!$E$262 -> 0
A56: 직접운영비용 합계 | B56: 백만원 | C56: =SUM(E56:EF56) -> 706913.04 | E56: =SUM(E44:E55) -> 0 | F56: =SUM(F44:F55) -> 0 | G56: =SUM(G44:G55) -> 0 | H56: =SUM(H44:H55) -> 0 | I56: =SUM(I44:I55) -> 0 | J56: =SUM(J44:J55) -> 0 | K56: =SUM(K44:K55) -> 0 | L56: =SUM(L44:L55) -> 0 | ... EF56: =SUM(EF44:EF55) -> 0
A58: 용도별 NOI
A59: NOI - 시니어 레지던스 | B59: 백만원 | C59: =SUM(E59:EF59) -> 32621.512 | E59: =E21+E22+E23-E44 -> 0 | F59: =F21+F22+F23-F44 -> 0 | G59: =G21+G22+G23-G44 -> 0 | H59: =H21+H22+H23-H44 -> 0 | I59: =I21+I22+I23-I44 -> 0 | J59: =J21+J22+J23-J44 -> 0 | K59: =K21+K22+K23-K44 -> 0 | L59: =L21+L22+L23-L44 -> 0 | ... EF59: =EF21+EF22+EF23-EF44 -> 0
A60: NOI - 레지던스 | B60: 백만원 | C60: =SUM(E60:EF60) -> 42839.167 | E60: =E24+E25+E26-E45-E46 -> 0 | F60: =F24+F25+F26-F45-F46 -> 0 | G60: =G24+G25+G26-G45-G46 -> 0 | H60: =H24+H25+H26-H45-H46 -> 0 | I60: =I24+I25+I26-I45-I46 -> 0 | J60: =J24+J25+J26-J45-J46 -> 0 | K60: =K24+K25+K26-K45-K46 -> 0 | L60: =L24+L25+L26-L45-L46 -> 0 | ... EF60: =EF24+EF25+EF26-EF45-EF46 -> 0
A61: NOI - 호텔 | B61: 백만원 | C61: =SUM(E61:EF61) -> 132976.8 | E61: =SUM(E27:E34)-SUM(E47:E52) -> 0 | F61: =SUM(F27:F34)-SUM(F47:F52) -> 0 | G61: =SUM(G27:G34)-SUM(G47:G52) -> 0 | H61: =SUM(H27:H34)-SUM(H47:H52) -> 0 | I61: =SUM(I27:I34)-SUM(I47:I52) -> 0 | J61: =SUM(J27:J34)-SUM(J47:J52) -> 0 | K61: =SUM(K27:K34)-SUM(K47:K52) -> 0 | L61: =SUM(L27:L34)-SUM(L47:L52) -> 0 | ... EF61: =SUM(EF27:EF34)-SUM(EF47:EF52) -> 0
A62: NOI - 오피스 | B62: 백만원 | C62: =SUM(E62:EF62) -> 66369.038 | E62: =E35-E53-E54 -> 0 | F62: =F35-F53-F54 -> 0 | G62: =G35-G53-G54 -> 0 | H62: =H35-H53-H54 -> 0 | I62: =I35-I53-I54 -> 0 | J62: =J35-J53-J54 -> 0 | K62: =K35-K53-K54 -> 0 | L62: =L35-L53-L54 -> 0 | ... EF62: =EF35-EF53-EF54 -> 0
A63: NOI - 부대시설 | B63: 백만원 | C63: =SUM(E63:EF63) -> 41146.757 | E63: =SUM(E36:E40)-E55 -> 0 | F63: =SUM(F36:F40)-F55 -> 0 | G63: =SUM(G36:G40)-G55 -> 0 | H63: =SUM(H36:H40)-H55 -> 0 | I63: =SUM(I36:I40)-I55 -> 0 | J63: =SUM(J36:J40)-J55 -> 0 | K63: =SUM(K36:K40)-K55 -> 0 | L63: =SUM(L36:L40)-L55 -> 0 | ... EF63: =SUM(EF36:EF40)-EF55 -> 0
A64: NOI 합계 | B64: 백만원 | C64: =SUM(E64:EF64) -> 315953.28 | E64: =SUM(E59:E63) -> 0 | F64: =SUM(F59:F63) -> 0 | G64: =SUM(G59:G63) -> 0 | H64: =SUM(H59:H63) -> 0 | I64: =SUM(I59:I63) -> 0 | J64: =SUM(J59:J63) -> 0 | K64: =SUM(K59:K63) -> 0 | L64: =SUM(L59:L63) -> 0 | ... EF64: =SUM(EF59:EF63) -> 0
A66: 기타공통비용 및 리츠운용비(운영)
A67: 수선비 | B67: 백만원 | C67: =SUM(E67:EF67) -> 7663.4989 | E67: =(E14=1)*①통합_가정!$E$265*①통합_가정!$I$39/1000000*(1+①통합_가정!$E$270)^(MAX(E16,1)-1) -> 0 | F67: =(F14=1)*①통합_가정!$E$265*①통합_가정!$I$39/1000000*(1+①통합_가정!$E$270)^(MAX(F16,1)-1) -> 0 | G67: =(G14=1)*①통합_가정!$E$265*①통합_가정!$I$39/1000000*(1+①통합_가정!$E$270)^(MAX(G16,1)-1) -> 0 | H67: =(H14=1)*①통합_가정!$E$265*①통합_가정!$I$39/1000000*(1+①통합_가정!$E$270)^(MAX(H16,1)-1) -> 0 | I67: =(I14=1)*①통합_가정!$E$265*①통합_가정!$I$39/1000000*(1+①통합_가정!$E$270)^(MAX(I16,1)-1) -> 0 | J67: =(J14=1)*①통합_가정!$E$265*①통합_가정!$I$39/1000000*(1+①통합_가정!$E$270)^(MAX(J16,1)-1) -> 0 | K67: =(K14=1)*①통합_가정!$E$265*①통합_가정!$I$39/1000000*(1+①통합_가정!$E$270)^(MAX(K16,1)-1) -> 0 | L67: =(L14=1)*①통합_가정!$E$265*①통합_가정!$I$39/1000000*(1+①통합_가정!$E$270)^(MAX(L16,1)-1) -> 0 | ... EF67: =(EF14=1)*①통합_가정!$E$265*①통합_가정!$I$39/1000000*(1+①통합_가정!$E$270)^(MAX(EF16,1)-1) -> 0
A68: 보험료 | B68: 백만원 | C68: =SUM(E68:EF68) -> 7663.4989 | E68: =(E14=1)*①통합_가정!$E$266*①통합_가정!$I$39/1000000*(1+①통합_가정!$E$270)^(MAX(E16,1)-1) -> 0 | F68: =(F14=1)*①통합_가정!$E$266*①통합_가정!$I$39/1000000*(1+①통합_가정!$E$270)^(MAX(F16,1)-1) -> 0 | G68: =(G14=1)*①통합_가정!$E$266*①통합_가정!$I$39/1000000*(1+①통합_가정!$E$270)^(MAX(G16,1)-1) -> 0 | H68: =(H14=1)*①통합_가정!$E$266*①통합_가정!$I$39/1000000*(1+①통합_가정!$E$270)^(MAX(H16,1)-1) -> 0 | I68: =(I14=1)*①통합_가정!$E$266*①통합_가정!$I$39/1000000*(1+①통합_가정!$E$270)^(MAX(I16,1)-1) -> 0 | J68: =(J14=1)*①통합_가정!$E$266*①통합_가정!$I$39/1000000*(1+①통합_가정!$E$270)^(MAX(J16,1)-1) -> 0 | K68: =(K14=1)*①통합_가정!$E$266*①통합_가정!$I$39/1000000*(1+①통합_가정!$E$270)^(MAX(K16,1)-1) -> 0 | L68: =(L14=1)*①통합_가정!$E$266*①통합_가정!$I$39/1000000*(1+①통합_가정!$E$270)^(MAX(L16,1)-1) -> 0 | ... EF68: =(EF14=1)*①통합_가정!$E$266*①통합_가정!$I$39/1000000*(1+①통합_가정!$E$270)^(MAX(EF16,1)-1) -> 0
A69: PM 수수료 | B69: 백만원 | C69: =SUM(E69:EF69) -> 7663.4989 | E69: =(E14=1)*①통합_가정!$E$267*①통합_가정!$I$39/1000000*(1+①통합_가정!$E$270)^(MAX(E16,1)-1) -> 0 | F69: =(F14=1)*①통합_가정!$E$267*①통합_가정!$I$39/1000000*(1+①통합_가정!$E$270)^(MAX(F16,1)-1) -> 0 | G69: =(G14=1)*①통합_가정!$E$267*①통합_가정!$I$39/1000000*(1+①통합_가정!$E$270)^(MAX(G16,1)-1) -> 0 | H69: =(H14=1)*①통합_가정!$E$267*①통합_가정!$I$39/1000000*(1+①통합_가정!$E$270)^(MAX(H16,1)-1) -> 0 | I69: =(I14=1)*①통합_가정!$E$267*①통합_가정!$I$39/1000000*(1+①통합_가정!$E$270)^(MAX(I16,1)-1) -> 0 | J69: =(J14=1)*①통합_가정!$E$267*①통합_가정!$I$39/1000000*(1+①통합_가정!$E$270)^(MAX(J16,1)-1) -> 0 | K69: =(K14=1)*①통합_가정!$E$267*①통합_가정!$I$39/1000000*(1+①통합_가정!$E$270)^(MAX(K16,1)-1) -> 0 | L69: =(L14=1)*①통합_가정!$E$267*①통합_가정!$I$39/1000000*(1+①통합_가정!$E$270)^(MAX(L16,1)-1) -> 0 | ... EF69: =(EF14=1)*①통합_가정!$E$267*①통합_가정!$I$39/1000000*(1+①통합_가정!$E$270)^(MAX(EF16,1)-1) -> 0
A70: 교통유발부담금 | B70: 백만원 | C70: =SUM(E70:EF70) -> 8196.3633 | E70: =(E14=1)*①통합_가정!$E$268*①통합_가정!$I$41/12*(1+①통합_가정!$E$270)^(MAX(E16,1)-1) -> 0 | F70: =(F14=1)*①통합_가정!$E$268*①통합_가정!$I$41/12*(1+①통합_가정!$E$270)^(MAX(F16,1)-1) -> 0 | G70: =(G14=1)*①통합_가정!$E$268*①통합_가정!$I$41/12*(1+①통합_가정!$E$270)^(MAX(G16,1)-1) -> 0 | H70: =(H14=1)*①통합_가정!$E$268*①통합_가정!$I$41/12*(1+①통합_가정!$E$270)^(MAX(H16,1)-1) -> 0 | I70: =(I14=1)*①통합_가정!$E$268*①통합_가정!$I$41/12*(1+①통합_가정!$E$270)^(MAX(I16,1)-1) -> 0 | J70: =(J14=1)*①통합_가정!$E$268*①통합_가정!$I$41/12*(1+①통합_가정!$E$270)^(MAX(J16,1)-1) -> 0 | K70: =(K14=1)*①통합_가정!$E$268*①통합_가정!$I$41/12*(1+①통합_가정!$E$270)^(MAX(K16,1)-1) -> 0 | L70: =(L14=1)*①통합_가정!$E$268*①통합_가정!$I$41/12*(1+①통합_가정!$E$270)^(MAX(L16,1)-1) -> 0 | ... EF70: =(EF14=1)*①통합_가정!$E$268*①통합_가정!$I$41/12*(1+①통합_가정!$E$270)^(MAX(EF16,1)-1) -> 0
A71: 간주임대료 부가세 | B71: 백만원 | C71: =SUM(E71:EF71) -> 15614.254 | E71: =(E14=1)*0*①통합_가정!$E$269/12*①통합_가정!$D$555 -> 0 | F71: =(F14=1)*E86*①통합_가정!$E$269/12*①통합_가정!$D$555 -> 0 | G71: =(G14=1)*F86*①통합_가정!$E$269/12*①통합_가정!$D$555 -> 0 | H71: =(H14=1)*G86*①통합_가정!$E$269/12*①통합_가정!$D$555 -> 0 | I71: =(I14=1)*H86*①통합_가정!$E$269/12*①통합_가정!$D$555 -> 0 | J71: =(J14=1)*I86*①통합_가정!$E$269/12*①통합_가정!$D$555 -> 0 | K71: =(K14=1)*J86*①통합_가정!$E$269/12*①통합_가정!$D$555 -> 0 | L71: =(L14=1)*K86*①통합_가정!$E$269/12*①통합_가정!$D$555 -> 0 | M71: =(M14=1)*L86*①통합_가정!$E$269/12*①통합_가정!$D$555 -> 0 | ... EF71: =(EF14=1)*EE86*①통합_가정!$E$269/12*①통합_가정!$D$555 -> 0
A72: 리츠운용비(운영) | B72: 백만원 | C72: =SUM(E72:EF72) -> 6935.9777 | E72: =E17*①통합_가정!$E$426 -> 0 | F72: =F17*①통합_가정!$E$426 -> 0 | G72: =G17*①통합_가정!$E$426 -> 0 | H72: =H17*①통합_가정!$E$426 -> 0 | I72: =I17*①통합_가정!$E$426 -> 0 | J72: =J17*①통합_가정!$E$426 -> 0 | K72: =K17*①통합_가정!$E$426 -> 0 | L72: =L17*①통합_가정!$E$426 -> 0 | ... EF72: =EF17*①통합_가정!$E$426 -> 0
A73: 자산관리 수수료(매각보수) | B73: 백만원 | C73: =SUM(E73:EF73) -> 9377.6982 | E73: =IF(E6=①통합_가정!$E$22,①통합_가정!$R$420,0) -> 0 | F73: =IF(F6=①통합_가정!$E$22,①통합_가정!$R$420,0) -> 0 | G73: =IF(G6=①통합_가정!$E$22,①통합_가정!$R$420,0) -> 0 | H73: =IF(H6=①통합_가정!$E$22,①통합_가정!$R$420,0) -> 0 | I73: =IF(I6=①통합_가정!$E$22,①통합_가정!$R$420,0) -> 0 | J73: =IF(J6=①통합_가정!$E$22,①통합_가정!$R$420,0) -> 0 | K73: =IF(K6=①통합_가정!$E$22,①통합_가정!$R$420,0) -> 0 | L73: =IF(L6=①통합_가정!$E$22,①통합_가정!$R$420,0) -> 0 | ... EF73: =IF(EF6=①통합_가정!$E$22,①통합_가정!$R$420,0) -> 0
A74: 공통비용 합계 | B74: 백만원 | C74: =SUM(E74:EF74) -> 63114.79 | E74: =SUM(E67:E73) -> 0 | F74: =SUM(F67:F73) -> 0 | G74: =SUM(G67:G73) -> 0 | H74: =SUM(H67:H73) -> 0 | I74: =SUM(I67:I73) -> 0 | J74: =SUM(J67:J73) -> 0 | K74: =SUM(K67:K73) -> 0 | L74: =SUM(L67:L73) -> 0 | ... EF74: =SUM(EF67:EF73) -> 0
A75: 운영현금흐름(NOI-공통비용) | B75: 백만원 | C75: =SUM(E75:EF75) -> 252838.49 | E75: =E64-E74 -> 0 | F75: =F64-F74 -> 0 | G75: =G64-G74 -> 0 | H75: =H64-H74 -> 0 | I75: =I64-I74 -> 0 | J75: =J64-J74 -> 0 | K75: =K64-K74 -> 0 | L75: =L64-L74 -> 0 | ... EF75: =EF64-EF74 -> 0
A77: 임대·입주 보증금
A78: 시니어 레지던스 보증금 유입 | B78: 백만원 | C78: =SUM(E78:EF78) -> 540000 | E78: =①통합_가정!$D$38*①통합_가정!$E$98*(①통합_가정!$E$104*SUMIF(①통합_가정!$J$97:$J$101,E6,①통합_가정!$I$97:$I$101)+IF(E15=13,①통합_가정!$E$105-①통합_가정!$E$104,0)+IF(E15=25,①통합_가정!$E$106-①통합_가정!$E$105,0)) -> 0 | F78: =①통합_가정!$D$38*①통합_가정!$E$98*(①통합_가정!$E$104*SUMIF(①통합_가정!$J$97:$J$101,F6,①통합_가정!$I$97:$I$101)+IF(F15=13,①통합_가정!$E$105-①통합_가정!$E$104,0)+IF(F15=25,①통합_가정!$E$106-①통합_가정!$E$105,0)) -> 0 | G78: =①통합_가정!$D$38*①통합_가정!$E$98*(①통합_가정!$E$104*SUMIF(①통합_가정!$J$97:$J$101,G6,①통합_가정!$I$97:$I$101)+IF(G15=13,①통합_가정!$E$105-①통합_가정!$E$104,0)+IF(G15=25,①통합_가정!$E$106-①통합_가정!$E$105,0)) -> 0 | H78: =①통합_가정!$D$38*①통합_가정!$E$98*(①통합_가정!$E$104*SUMIF(①통합_가정!$J$97:$J$101,H6,①통합_가정!$I$97:$I$101)+IF(H15=13,①통합_가정!$E$105-①통합_가정!$E$104,0)+IF(H15=25,①통합_가정!$E$106-①통합_가정!$E$105,0)) -> 0 | I78: =①통합_가정!$D$38*①통합_가정!$E$98*(①통합_가정!$E$104*SUMIF(①통합_가정!$J$97:$J$101,I6,①통합_가정!$I$97:$I$101)+IF(I15=13,①통합_가정!$E$105-①통합_가정!$E$104,0)+IF(I15=25,①통합_가정!$E$106-①통합_가정!$E$105,0)) -> 0 | J78: =①통합_가정!$D$38*①통합_가정!$E$98*(①통합_가정!$E$104*SUMIF(①통합_가정!$J$97:$J$101,J6,①통합_가정!$I$97:$I$101)+IF(J15=13,①통합_가정!$E$105-①통합_가정!$E$104,0)+IF(J15=25,①통합_가정!$E$106-①통합_가정!$E$105,0)) -> 0 | K78: =①통합_가정!$D$38*①통합_가정!$E$98*(①통합_가정!$E$104*SUMIF(①통합_가정!$J$97:$J$101,K6,①통합_가정!$I$97:$I$101)+IF(K15=13,①통합_가정!$E$105-①통합_가정!$E$104,0)+IF(K15=25,①통합_가정!$E$106-①통합_가정!$E$105,0)) -> 0 | L78: =①통합_가정!$D$38*①통합_가정!$E$98*(①통합_가정!$E$104*SUMIF(①통합_가정!$J$97:$J$101,L6,①통합_가정!$I$97:$I$101)+IF(L15=13,①통합_가정!$E$105-①통합_가정!$E$104,0)+IF(L15=25,①통합_가정!$E$106-①통합_가정!$E$105,0)) -> 0 | ... EF78: =①통합_가정!$D$38*①통합_가정!$E$98*(①통합_가정!$E$104*SUMIF(①통합_가정!$J$97:$J$101,EF6,①통합_가정!$I$97:$I$101)+IF(EF15=13,①통합_가정!$E$105-①통합_가정!$E$104,0)+IF(EF15=25,①통합_가정!$E$106-①통합_가정!$E$105,0)) -> 0
A79: 레지던스 보증금 유입 | B79: 백만원 | C79: =SUM(E79:EF79) -> 310752 | E79: =①통합_가정!$E$38*①통합_가정!$E$129*(①통합_가정!$E$133*SUMIF(①통합_가정!$L$124:$L$128,E6,①통합_가정!$K$124:$K$128)+IF(E15=13,①통합_가정!$E$134-①통합_가정!$E$133,0)+IF(E15=25,①통합_가정!$E$135-①통합_가정!$E$134,0)) -> 0 | F79: =①통합_가정!$E$38*①통합_가정!$E$129*(①통합_가정!$E$133*SUMIF(①통합_가정!$L$124:$L$128,F6,①통합_가정!$K$124:$K$128)+IF(F15=13,①통합_가정!$E$134-①통합_가정!$E$133,0)+IF(F15=25,①통합_가정!$E$135-①통합_가정!$E$134,0)) -> 0 | G79: =①통합_가정!$E$38*①통합_가정!$E$129*(①통합_가정!$E$133*SUMIF(①통합_가정!$L$124:$L$128,G6,①통합_가정!$K$124:$K$128)+IF(G15=13,①통합_가정!$E$134-①통합_가정!$E$133,0)+IF(G15=25,①통합_가정!$E$135-①통합_가정!$E$134,0)) -> 0 | H79: =①통합_가정!$E$38*①통합_가정!$E$129*(①통합_가정!$E$133*SUMIF(①통합_가정!$L$124:$L$128,H6,①통합_가정!$K$124:$K$128)+IF(H15=13,①통합_가정!$E$134-①통합_가정!$E$133,0)+IF(H15=25,①통합_가정!$E$135-①통합_가정!$E$134,0)) -> 0 | I79: =①통합_가정!$E$38*①통합_가정!$E$129*(①통합_가정!$E$133*SUMIF(①통합_가정!$L$124:$L$128,I6,①통합_가정!$K$124:$K$128)+IF(I15=13,①통합_가정!$E$134-①통합_가정!$E$133,0)+IF(I15=25,①통합_가정!$E$135-①통합_가정!$E$134,0)) -> 0 | J79: =①통합_가정!$E$38*①통합_가정!$E$129*(①통합_가정!$E$133*SUMIF(①통합_가정!$L$124:$L$128,J6,①통합_가정!$K$124:$K$128)+IF(J15=13,①통합_가정!$E$134-①통합_가정!$E$133,0)+IF(J15=25,①통합_가정!$E$135-①통합_가정!$E$134,0)) -> 0 | K79: =①통합_가정!$E$38*①통합_가정!$E$129*(①통합_가정!$E$133*SUMIF(①통합_가정!$L$124:$L$128,K6,①통합_가정!$K$124:$K$128)+IF(K15=13,①통합_가정!$E$134-①통합_가정!$E$133,0)+IF(K15=25,①통합_가정!$E$135-①통합_가정!$E$134,0)) -> 0 | L79: =①통합_가정!$E$38*①통합_가정!$E$129*(①통합_가정!$E$133*SUMIF(①통합_가정!$L$124:$L$128,L6,①통합_가정!$K$124:$K$128)+IF(L15=13,①통합_가정!$E$134-①통합_가정!$E$133,0)+IF(L15=25,①통합_가정!$E$135-①통합_가정!$E$134,0)) -> 0 | ... EF79: =①통합_가정!$E$38*①통합_가정!$E$129*(①통합_가정!$E$133*SUMIF(①통합_가정!$L$124:$L$128,EF6,①통합_가정!$K$124:$K$128)+IF(EF15=13,①통합_가정!$E$134-①통합_가정!$E$133,0)+IF(EF15=25,①통합_가정!$E$135-①통합_가정!$E$134,0)) -> 0
A80: 호텔 회원보증금 유입 | B80: 백만원 | C80: =SUM(E80:EF80) -> 66000 | E80: =①통합_가정!$F$38*①통합_가정!$E$151*(IF(E15=1,①통합_가정!$E$156,0)+IF(E15=13,①통합_가정!$E$157-①통합_가정!$E$156,0)+IF(E15=25,①통합_가정!$E$158-①통합_가정!$E$157,0)) -> 0 | F80: =①통합_가정!$F$38*①통합_가정!$E$151*(IF(F15=1,①통합_가정!$E$156,0)+IF(F15=13,①통합_가정!$E$157-①통합_가정!$E$156,0)+IF(F15=25,①통합_가정!$E$158-①통합_가정!$E$157,0)) -> 0 | G80: =①통합_가정!$F$38*①통합_가정!$E$151*(IF(G15=1,①통합_가정!$E$156,0)+IF(G15=13,①통합_가정!$E$157-①통합_가정!$E$156,0)+IF(G15=25,①통합_가정!$E$158-①통합_가정!$E$157,0)) -> 0 | H80: =①통합_가정!$F$38*①통합_가정!$E$151*(IF(H15=1,①통합_가정!$E$156,0)+IF(H15=13,①통합_가정!$E$157-①통합_가정!$E$156,0)+IF(H15=25,①통합_가정!$E$158-①통합_가정!$E$157,0)) -> 0 | I80: =①통합_가정!$F$38*①통합_가정!$E$151*(IF(I15=1,①통합_가정!$E$156,0)+IF(I15=13,①통합_가정!$E$157-①통합_가정!$E$156,0)+IF(I15=25,①통합_가정!$E$158-①통합_가정!$E$157,0)) -> 0 | J80: =①통합_가정!$F$38*①통합_가정!$E$151*(IF(J15=1,①통합_가정!$E$156,0)+IF(J15=13,①통합_가정!$E$157-①통합_가정!$E$156,0)+IF(J15=25,①통합_가정!$E$158-①통합_가정!$E$157,0)) -> 0 | K80: =①통합_가정!$F$38*①통합_가정!$E$151*(IF(K15=1,①통합_가정!$E$156,0)+IF(K15=13,①통합_가정!$E$157-①통합_가정!$E$156,0)+IF(K15=25,①통합_가정!$E$158-①통합_가정!$E$157,0)) -> 0 | L80: =①통합_가정!$F$38*①통합_가정!$E$151*(IF(L15=1,①통합_가정!$E$156,0)+IF(L15=13,①통합_가정!$E$157-①통합_가정!$E$156,0)+IF(L15=25,①통합_가정!$E$158-①통합_가정!$E$157,0)) -> 0 | ... EF80: =①통합_가정!$F$38*①통합_가정!$E$151*(IF(EF15=1,①통합_가정!$E$156,0)+IF(EF15=13,①통합_가정!$E$157-①통합_가정!$E$156,0)+IF(EF15=25,①통합_가정!$E$158-①통합_가정!$E$157,0)) -> 0
A81: 시니어 부대 임대보증금 | B81: 백만원 | C81: =SUM(E81:EF81) -> 1500 | E81: =IF(E15=1,①통합_가정!$D$38*①통합_가정!$E$114,0) -> 0 | F81: =IF(F15=1,①통합_가정!$D$38*①통합_가정!$E$114,0) -> 0 | G81: =IF(G15=1,①통합_가정!$D$38*①통합_가정!$E$114,0) -> 0 | H81: =IF(H15=1,①통합_가정!$D$38*①통합_가정!$E$114,0) -> 0 | I81: =IF(I15=1,①통합_가정!$D$38*①통합_가정!$E$114,0) -> 0 | J81: =IF(J15=1,①통합_가정!$D$38*①통합_가정!$E$114,0) -> 0 | K81: =IF(K15=1,①통합_가정!$D$38*①통합_가정!$E$114,0) -> 0 | L81: =IF(L15=1,①통합_가정!$D$38*①통합_가정!$E$114,0) -> 0 | ... EF81: =IF(EF15=1,①통합_가정!$D$38*①통합_가정!$E$114,0) -> 0
A82: 오피스 임대보증금 | B82: 백만원 | C82: =SUM(E82:EF82) -> 14400 | E82: =IF(E15=1,①통합_가정!$G$38*①통합_가정!$E$182,0) -> 0 | F82: =IF(F15=1,①통합_가정!$G$38*①통합_가정!$E$182,0) -> 0 | G82: =IF(G15=1,①통합_가정!$G$38*①통합_가정!$E$182,0) -> 0 | H82: =IF(H15=1,①통합_가정!$G$38*①통합_가정!$E$182,0) -> 0 | I82: =IF(I15=1,①통합_가정!$G$38*①통합_가정!$E$182,0) -> 0 | J82: =IF(J15=1,①통합_가정!$G$38*①통합_가정!$E$182,0) -> 0 | K82: =IF(K15=1,①통합_가정!$G$38*①통합_가정!$E$182,0) -> 0 | L82: =IF(L15=1,①통합_가정!$G$38*①통합_가정!$E$182,0) -> 0 | ... EF82: =IF(EF15=1,①통합_가정!$G$38*①통합_가정!$E$182,0) -> 0
A83: 부대시설 임대보증금 | B83: 백만원 | C83: =SUM(E83:EF83) -> 9300 | E83: =IF(E15=1,①통합_가정!$H$38*(①통합_가정!$E$200+①통합_가정!$E$213+①통합_가정!$E$226+①통합_가정!$E$239+①통합_가정!$E$252),0) -> 0 | F83: =IF(F15=1,①통합_가정!$H$38*(①통합_가정!$E$200+①통합_가정!$E$213+①통합_가정!$E$226+①통합_가정!$E$239+①통합_가정!$E$252),0) -> 0 | G83: =IF(G15=1,①통합_가정!$H$38*(①통합_가정!$E$200+①통합_가정!$E$213+①통합_가정!$E$226+①통합_가정!$E$239+①통합_가정!$E$252),0) -> 0 | H83: =IF(H15=1,①통합_가정!$H$38*(①통합_가정!$E$200+①통합_가정!$E$213+①통합_가정!$E$226+①통합_가정!$E$239+①통합_가정!$E$252),0) -> 0 | I83: =IF(I15=1,①통합_가정!$H$38*(①통합_가정!$E$200+①통합_가정!$E$213+①통합_가정!$E$226+①통합_가정!$E$239+①통합_가정!$E$252),0) -> 0 | J83: =IF(J15=1,①통합_가정!$H$38*(①통합_가정!$E$200+①통합_가정!$E$213+①통합_가정!$E$226+①통합_가정!$E$239+①통합_가정!$E$252),0) -> 0 | K83: =IF(K15=1,①통합_가정!$H$38*(①통합_가정!$E$200+①통합_가정!$E$213+①통합_가정!$E$226+①통합_가정!$E$239+①통합_가정!$E$252),0) -> 0 | L83: =IF(L15=1,①통합_가정!$H$38*(①통합_가정!$E$200+①통합_가정!$E$213+①통합_가정!$E$226+①통합_가정!$E$239+①통합_가정!$E$252),0) -> 0 | ... EF83: =IF(EF15=1,①통합_가정!$H$38*(①통합_가정!$E$200+①통합_가정!$E$213+①통합_가정!$E$226+①통합_가정!$E$239+①통합_가정!$E$252),0) -> 0
A84: 보증금 유입 합계 | B84: 백만원 | C84: =SUM(E84:EF84) -> 941952 | E84: =SUM(E78:E83) -> 0 | F84: =SUM(F78:F83) -> 0 | G84: =SUM(G78:G83) -> 0 | H84: =SUM(H78:H83) -> 0 | I84: =SUM(I78:I83) -> 0 | J84: =SUM(J78:J83) -> 0 | K84: =SUM(K78:K83) -> 0 | L84: =SUM(L78:L83) -> 0 | ... EF84: =SUM(EF78:EF83) -> 0
A85: 보증금 승계(처분시 매수인 인계) | B85: 백만원 | C85: =SUM(E85:EF85) -> 941952 | E85: =IF(E6=①통합_가정!$E$22,0+E84,0) -> 0 | F85: =IF(F6=①통합_가정!$E$22,E86+F84,0) -> 0 | G85: =IF(G6=①통합_가정!$E$22,F86+G84,0) -> 0 | H85: =IF(H6=①통합_가정!$E$22,G86+H84,0) -> 0 | I85: =IF(I6=①통합_가정!$E$22,H86+I84,0) -> 0 | J85: =IF(J6=①통합_가정!$E$22,I86+J84,0) -> 0 | K85: =IF(K6=①통합_가정!$E$22,J86+K84,0) -> 0 | L85: =IF(L6=①통합_가정!$E$22,K86+L84,0) -> 0 | M85: =IF(M6=①통합_가정!$E$22,L86+M84,0) -> 0 | ... EF85: =IF(EF6=①통합_가정!$E$22,EE86+EF84,0) -> 0
A86: 보증금 잔액 | B86: 백만원 | C86: =MAX(E86:EF86) -> 941952 | E86: =0+E84-E85 -> 0 | F86: =E86+F84-F85 -> 0 | G86: =F86+G84-G85 -> 0 | H86: =G86+H84-H85 -> 0 | I86: =H86+I84-I85 -> 0 | J86: =I86+J84-J85 -> 0 | K86: =J86+K84-K85 -> 0 | L86: =K86+L84-L85 -> 0 | M86: =L86+M84-M85 -> 0 | ... EF86: =EE86+EF84-EF85 -> 0
A88: 개발사업비 집행 (공제후 순액)
A89: 토지 계약금 | B89: 백만원 | C89: =SUM(E89:EF89) -> 11000 | E89: =IF(E6=①통합_가정!$E$10,①통합_가정!$R$358*①통합_가정!$D$554,0) -> 0 | F89: =IF(F6=①통합_가정!$E$10,①통합_가정!$R$358*①통합_가정!$D$554,0) -> 0 | G89: =IF(G6=①통합_가정!$E$10,①통합_가정!$R$358*①통합_가정!$D$554,0) -> 0 | H89: =IF(H6=①통합_가정!$E$10,①통합_가정!$R$358*①통합_가정!$D$554,0) -> 11000 | I89: =IF(I6=①통합_가정!$E$10,①통합_가정!$R$358*①통합_가정!$D$554,0) -> 0 | J89: =IF(J6=①통합_가정!$E$10,①통합_가정!$R$358*①통합_가정!$D$554,0) -> 0 | K89: =IF(K6=①통합_가정!$E$10,①통합_가정!$R$358*①통합_가정!$D$554,0) -> 0 | L89: =IF(L6=①통합_가정!$E$10,①통합_가정!$R$358*①통합_가정!$D$554,0) -> 0 | ... EF89: =IF(EF6=①통합_가정!$E$10,①통합_가정!$R$358*①통합_가정!$D$554,0) -> 0
A90: 토지 잔금·취득세·임차료·등기 | B90: 백만원 | C90: =SUM(E90:EF90) -> 221320 | E90: =IF(E6=①통합_가정!$E$14,①통합_가정!$R$358*(1-①통합_가정!$D$554)+①통합_가정!$R$359+①통합_가정!$R$360+①통합_가정!$R$361,0) -> 0 | F90: =IF(F6=①통합_가정!$E$14,①통합_가정!$R$358*(1-①통합_가정!$D$554)+①통합_가정!$R$359+①통합_가정!$R$360+①통합_가정!$R$361,0) -> 0 | G90: =IF(G6=①통합_가정!$E$14,①통합_가정!$R$358*(1-①통합_가정!$D$554)+①통합_가정!$R$359+①통합_가정!$R$360+①통합_가정!$R$361,0) -> 0 | H90: =IF(H6=①통합_가정!$E$14,①통합_가정!$R$358*(1-①통합_가정!$D$554)+①통합_가정!$R$359+①통합_가정!$R$360+①통합_가정!$R$361,0) -> 0 | I90: =IF(I6=①통합_가정!$E$14,①통합_가정!$R$358*(1-①통합_가정!$D$554)+①통합_가정!$R$359+①통합_가정!$R$360+①통합_가정!$R$361,0) -> 0 | J90: =IF(J6=①통합_가정!$E$14,①통합_가정!$R$358*(1-①통합_가정!$D$554)+①통합_가정!$R$359+①통합_가정!$R$360+①통합_가정!$R$361,0) -> 0 | K90: =IF(K6=①통합_가정!$E$14,①통합_가정!$R$358*(1-①통합_가정!$D$554)+①통합_가정!$R$359+①통합_가정!$R$360+①통합_가정!$R$361,0) -> 0 | L90: =IF(L6=①통합_가정!$E$14,①통합_가정!$R$358*(1-①통합_가정!$D$554)+①통합_가정!$R$359+①통합_가정!$R$360+①통합_가정!$R$361,0) -> 0 | ... EF90: =IF(EF6=①통합_가정!$E$14,①통합_가정!$R$358*(1-①통합_가정!$D$554)+①통합_가정!$R$359+①통합_가정!$R$360+①통합_가정!$R$361,0) -> 0
A91: 토지보유세(건설기간) | B91: 백만원 | C91: =SUM(E91:EF91) -> 5324 | E91: =E11*①통합_가정!$R$362/①통합_가정!$E$15 -> 0 | F91: =F11*①통합_가정!$R$362/①통합_가정!$E$15 -> 0 | G91: =G11*①통합_가정!$R$362/①통합_가정!$E$15 -> 0 | H91: =H11*①통합_가정!$R$362/①통합_가정!$E$15 -> 0 | I91: =I11*①통합_가정!$R$362/①통합_가정!$E$15 -> 0 | J91: =J11*①통합_가정!$R$362/①통합_가정!$E$15 -> 0 | K91: =K11*①통합_가정!$R$362/①통합_가정!$E$15 -> 0 | L91: =L11*①통합_가정!$R$362/①통합_가정!$E$15 -> 0 | ... EF91: =EF11*①통합_가정!$R$362/①통합_가정!$E$15 -> 0
A92: 직접공사비(유보금 제외, S-curve) | B92: 백만원 | C92: =SUM(E92:EF92) -> 554609.17 | E92: =E13*(①통합_가정!$R$367-①통합_가정!$E$433) -> 0 | F92: =F13*(①통합_가정!$R$367-①통합_가정!$E$433) -> 0 | G92: =G13*(①통합_가정!$R$367-①통합_가정!$E$433) -> 0 | H92: =H13*(①통합_가정!$R$367-①통합_가정!$E$433) -> 0 | I92: =I13*(①통합_가정!$R$367-①통합_가정!$E$433) -> 0 | J92: =J13*(①통합_가정!$R$367-①통합_가정!$E$433) -> 0 | K92: =K13*(①통합_가정!$R$367-①통합_가정!$E$433) -> 0 | L92: =L13*(①통합_가정!$R$367-①통합_가정!$E$433) -> 0 | ... EF92: =EF13*(①통합_가정!$R$367-①통합_가정!$E$433) -> 0
A93: 공사비 유보금 지급 | B93: 백만원 | C93: =SUM(E93:EF93) -> 59683.967 | E93: =IF(E6=①통합_가정!$E$18,①통합_가정!$E$433,0) -> 0 | F93: =IF(F6=①통합_가정!$E$18,①통합_가정!$E$433,0) -> 0 | G93: =IF(G6=①통합_가정!$E$18,①통합_가정!$E$433,0) -> 0 | H93: =IF(H6=①통합_가정!$E$18,①통합_가정!$E$433,0) -> 0 | I93: =IF(I6=①통합_가정!$E$18,①통합_가정!$E$433,0) -> 0 | J93: =IF(J6=①통합_가정!$E$18,①통합_가정!$E$433,0) -> 0 | K93: =IF(K6=①통합_가정!$E$18,①통합_가정!$E$433,0) -> 0 | L93: =IF(L6=①통합_가정!$E$18,①통합_가정!$E$433,0) -> 0 | ... EF93: =IF(EF6=①통합_가정!$E$18,①통합_가정!$E$433,0) -> 0
A94: 간접공사비(S-curve) | B94: 백만원 | C94: =SUM(E94:EF94) -> 476391.09 | E94: =E13*①통합_가정!$R$381 -> 0 | F94: =F13*①통합_가정!$R$381 -> 0 | G94: =G13*①통합_가정!$R$381 -> 0 | H94: =H13*①통합_가정!$R$381 -> 0 | I94: =I13*①통합_가정!$R$381 -> 0 | J94: =J13*①통합_가정!$R$381 -> 0 | K94: =K13*①통합_가정!$R$381 -> 0 | L94: =L13*①통합_가정!$R$381 -> 0 | ... EF94: =EF13*①통합_가정!$R$381 -> 0
A95: 판매비 | B95: 백만원 | C95: =SUM(E95:EF95) -> 30843.703 | E95: =E11*①통합_가정!$R$386/①통합_가정!$E$15 -> 0 | F95: =F11*①통합_가정!$R$386/①통합_가정!$E$15 -> 0 | G95: =G11*①통합_가정!$R$386/①통합_가정!$E$15 -> 0 | H95: =H11*①통합_가정!$R$386/①통합_가정!$E$15 -> 0 | I95: =I11*①통합_가정!$R$386/①통합_가정!$E$15 -> 0 | J95: =J11*①통합_가정!$R$386/①통합_가정!$E$15 -> 0 | K95: =K11*①통합_가정!$R$386/①통합_가정!$E$15 -> 0 | L95: =L11*①통합_가정!$R$386/①통합_가정!$E$15 -> 0 | ... EF95: =EF11*①통합_가정!$R$386/①통합_가정!$E$15 -> 0
A96: 부대비용(보존등기비 등) | B96: 백만원 | C96: =SUM(E96:EF96) -> 29598.314 | E96: =IF(E6=①통합_가정!$E$16,①통합_가정!$R$389,0) -> 0 | F96: =IF(F6=①통합_가정!$E$16,①통합_가정!$R$389,0) -> 0 | G96: =IF(G6=①통합_가정!$E$16,①통합_가정!$R$389,0) -> 0 | H96: =IF(H6=①통합_가정!$E$16,①통합_가정!$R$389,0) -> 0 | I96: =IF(I6=①통합_가정!$E$16,①통합_가정!$R$389,0) -> 0 | J96: =IF(J6=①통합_가정!$E$16,①통합_가정!$R$389,0) -> 0 | K96: =IF(K6=①통합_가정!$E$16,①통합_가정!$R$389,0) -> 0 | L96: =IF(L6=①통합_가정!$E$16,①통합_가정!$R$389,0) -> 0 | ... EF96: =IF(EF6=①통합_가정!$E$16,①통합_가정!$R$389,0) -> 0
A97: 리츠운용비(일시: 등록면허세·실사·예비비) | B97: 백만원 | C97: =SUM(E97:EF97) -> 1945.329 | E97: =IF(E6=①통합_가정!$E$8,①통합_가정!$R$409+①통합_가정!$R$410+①통합_가정!$R$411,0) -> 1945.329 | F97: =IF(F6=①통합_가정!$E$8,①통합_가정!$R$409+①통합_가정!$R$410+①통합_가정!$R$411,0) -> 0 | G97: =IF(G6=①통합_가정!$E$8,①통합_가정!$R$409+①통합_가정!$R$410+①통합_가정!$R$411,0) -> 0 | H97: =IF(H6=①통합_가정!$E$8,①통합_가정!$R$409+①통합_가정!$R$410+①통합_가정!$R$411,0) -> 0 | I97: =IF(I6=①통합_가정!$E$8,①통합_가정!$R$409+①통합_가정!$R$410+①통합_가정!$R$411,0) -> 0 | J97: =IF(J6=①통합_가정!$E$8,①통합_가정!$R$409+①통합_가정!$R$410+①통합_가정!$R$411,0) -> 0 | K97: =IF(K6=①통합_가정!$E$8,①통합_가정!$R$409+①통합_가정!$R$410+①통합_가정!$R$411,0) -> 0 | L97: =IF(L6=①통합_가정!$E$8,①통합_가정!$R$409+①통합_가정!$R$410+①통합_가정!$R$411,0) -> 0 | ... EF97: =IF(EF6=①통합_가정!$E$8,①통합_가정!$R$409+①통합_가정!$R$410+①통합_가정!$R$411,0) -> 0
A98: 리츠운용비(매입보수) | B98: 백만원 | C98: =SUM(E98:EF98) -> 4777.0727 | E98: =IF(E6=①통합_가정!$E$14,①통합_가정!$R$404,0) -> 0 | F98: =IF(F6=①통합_가정!$E$14,①통합_가정!$R$404,0) -> 0 | G98: =IF(G6=①통합_가정!$E$14,①통합_가정!$R$404,0) -> 0 | H98: =IF(H6=①통합_가정!$E$14,①통합_가정!$R$404,0) -> 0 | I98: =IF(I6=①통합_가정!$E$14,①통합_가정!$R$404,0) -> 0 | J98: =IF(J6=①통합_가정!$E$14,①통합_가정!$R$404,0) -> 0 | K98: =IF(K6=①통합_가정!$E$14,①통합_가정!$R$404,0) -> 0 | L98: =IF(L6=①통합_가정!$E$14,①통합_가정!$R$404,0) -> 0 | ... EF98: =IF(EF6=①통합_가정!$E$14,①통합_가정!$R$404,0) -> 0
A99: 리츠운용비(개발기간 정기) | B99: 백만원 | C99: =SUM(E99:EF99) -> 5577.5696 | E99: =E10*(①통합_가정!$R$403+①통합_가정!$R$405+①통합_가정!$R$406+①통합_가정!$R$407+①통합_가정!$R$408)/(①통합_가정!$E$25*12) -> 92.959493 | F99: =F10*(①통합_가정!$R$403+①통합_가정!$R$405+①통합_가정!$R$406+①통합_가정!$R$407+①통합_가정!$R$408)/(①통합_가정!$E$25*12) -> 92.959493 | G99: =G10*(①통합_가정!$R$403+①통합_가정!$R$405+①통합_가정!$R$406+①통합_가정!$R$407+①통합_가정!$R$408)/(①통합_가정!$E$25*12) -> 92.959493 | H99: =H10*(①통합_가정!$R$403+①통합_가정!$R$405+①통합_가정!$R$406+①통합_가정!$R$407+①통합_가정!$R$408)/(①통합_가정!$E$25*12) -> 92.959493 | I99: =I10*(①통합_가정!$R$403+①통합_가정!$R$405+①통합_가정!$R$406+①통합_가정!$R$407+①통합_가정!$R$408)/(①통합_가정!$E$25*12) -> 92.959493 | J99: =J10*(①통합_가정!$R$403+①통합_가정!$R$405+①통합_가정!$R$406+①통합_가정!$R$407+①통합_가정!$R$408)/(①통합_가정!$E$25*12) -> 92.959493 | K99: =K10*(①통합_가정!$R$403+①통합_가정!$R$405+①통합_가정!$R$406+①통합_가정!$R$407+①통합_가정!$R$408)/(①통합_가정!$E$25*12) -> 92.959493 | L99: =L10*(①통합_가정!$R$403+①통합_가정!$R$405+①통합_가정!$R$406+①통합_가정!$R$407+①통합_가정!$R$408)/(①통합_가정!$E$25*12) -> 92.959493 | ... EF99: =EF10*(①통합_가정!$R$403+①통합_가정!$R$405+①통합_가정!$R$406+①통합_가정!$R$407+①통합_가정!$R$408)/(①통합_가정!$E$25*12) -> 0
A100: 개발사업비 집행 합계 | B100: 백만원 | C100: =SUM(E100:EF100) -> 1401070.2 | E100: =SUM(E89:E99) -> 2038.2885 | F100: =SUM(F89:F99) -> 92.959493 | G100: =SUM(G89:G99) -> 92.959493 | H100: =SUM(H89:H99) -> 11092.959 | I100: =SUM(I89:I99) -> 92.959493 | J100: =SUM(J89:J99) -> 92.959493 | K100: =SUM(K89:K99) -> 92.959493 | L100: =SUM(L89:L99) -> 92.959493 | ... EF100: =SUM(EF89:EF99) -> 0
A102: PF (개발기간)
A103: Tr.A 취급수수료 | B103: 백만원 | C103: =SUM(E103:EF103) -> 8210.9752 | E103: =IF(E6=①통합_가정!$E$14,①통합_가정!$E$452*①통합_가정!$J$483,0) -> 0 | F103: =IF(F6=①통합_가정!$E$14,①통합_가정!$E$452*①통합_가정!$J$483,0) -> 0 | G103: =IF(G6=①통합_가정!$E$14,①통합_가정!$E$452*①통합_가정!$J$483,0) -> 0 | H103: =IF(H6=①통합_가정!$E$14,①통합_가정!$E$452*①통합_가정!$J$483,0) -> 0 | I103: =IF(I6=①통합_가정!$E$14,①통합_가정!$E$452*①통합_가정!$J$483,0) -> 0 | J103: =IF(J6=①통합_가정!$E$14,①통합_가정!$E$452*①통합_가정!$J$483,0) -> 0 | K103: =IF(K6=①통합_가정!$E$14,①통합_가정!$E$452*①통합_가정!$J$483,0) -> 0 | L103: =IF(L6=①통합_가정!$E$14,①통합_가정!$E$452*①통합_가정!$J$483,0) -> 0 | ... EF103: =IF(EF6=①통합_가정!$E$14,①통합_가정!$E$452*①통합_가정!$J$483,0) -> 0
A104: Tr.B 취급수수료 | B104: 백만원 | C104: =SUM(E104:EF104) -> 1642.6549 | E104: =IF(E6=①통합_가정!$E$14,①통합_가정!$E$453*①통합_가정!$J$484,0) -> 0 | F104: =IF(F6=①통합_가정!$E$14,①통합_가정!$E$453*①통합_가정!$J$484,0) -> 0 | G104: =IF(G6=①통합_가정!$E$14,①통합_가정!$E$453*①통합_가정!$J$484,0) -> 0 | H104: =IF(H6=①통합_가정!$E$14,①통합_가정!$E$453*①통합_가정!$J$484,0) -> 0 | I104: =IF(I6=①통합_가정!$E$14,①통합_가정!$E$453*①통합_가정!$J$484,0) -> 0 | J104: =IF(J6=①통합_가정!$E$14,①통합_가정!$E$453*①통합_가정!$J$484,0) -> 0 | K104: =IF(K6=①통합_가정!$E$14,①통합_가정!$E$453*①통합_가정!$J$484,0) -> 0 | L104: =IF(L6=①통합_가정!$E$14,①통합_가정!$E$453*①통합_가정!$J$484,0) -> 0 | ... EF104: =IF(EF6=①통합_가정!$E$14,①통합_가정!$E$453*①통합_가정!$J$484,0) -> 0
A105: Tr.C 취급수수료 | B105: 백만원 | C105: =SUM(E105:EF105) -> 1641.5053 | E105: =IF(E6=①통합_가정!$E$14,①통합_가정!$E$454*①통합_가정!$J$485,0) -> 0 | F105: =IF(F6=①통합_가정!$E$14,①통합_가정!$E$454*①통합_가정!$J$485,0) -> 0 | G105: =IF(G6=①통합_가정!$E$14,①통합_가정!$E$454*①통합_가정!$J$485,0) -> 0 | H105: =IF(H6=①통합_가정!$E$14,①통합_가정!$E$454*①통합_가정!$J$485,0) -> 0 | I105: =IF(I6=①통합_가정!$E$14,①통합_가정!$E$454*①통합_가정!$J$485,0) -> 0 | J105: =IF(J6=①통합_가정!$E$14,①통합_가정!$E$454*①통합_가정!$J$485,0) -> 0 | K105: =IF(K6=①통합_가정!$E$14,①통합_가정!$E$454*①통합_가정!$J$485,0) -> 0 | L105: =IF(L6=①통합_가정!$E$14,①통합_가정!$E$454*①통합_가정!$J$485,0) -> 0 | ... EF105: =IF(EF6=①통합_가정!$E$14,①통합_가정!$E$454*①통합_가정!$J$485,0) -> 0
A106: Tr.A 이자비용 | B106: 백만원 | C106: =SUM(E106:EF106) -> 17629.919 | E106: =0*①통합_가정!$K$483/12 -> 0 | F106: =E121*①통합_가정!$K$483/12 -> 0 | G106: =F121*①통합_가정!$K$483/12 -> 0 | H106: =G121*①통합_가정!$K$483/12 -> 0 | I106: =H121*①통합_가정!$K$483/12 -> 0 | J106: =I121*①통합_가정!$K$483/12 -> 0 | K106: =J121*①통합_가정!$K$483/12 -> 0 | L106: =K121*①통합_가정!$K$483/12 -> 0 | M106: =L121*①통합_가정!$K$483/12 -> 0 | ... EF106: =EE121*①통합_가정!$K$483/12 -> 0
A107: Tr.B 이자비용 | B107: 백만원 | C107: =SUM(E107:EF107) -> 19183.889 | E107: =0*①통합_가정!$K$484/12 -> 0 | F107: =E122*①통합_가정!$K$484/12 -> 0 | G107: =F122*①통합_가정!$K$484/12 -> 0 | H107: =G122*①통합_가정!$K$484/12 -> 0 | I107: =H122*①통합_가정!$K$484/12 -> 0 | J107: =I122*①통합_가정!$K$484/12 -> 0 | K107: =J122*①통합_가정!$K$484/12 -> 0 | L107: =K122*①통합_가정!$K$484/12 -> 0 | M107: =L122*①통합_가정!$K$484/12 -> 0 | ... EF107: =EE122*①통합_가정!$K$484/12 -> 0
A108: Tr.C 이자비용 | B108: 백만원 | C108: =SUM(E108:EF108) -> 31542.554 | E108: =0*①통합_가정!$K$485/12 -> 0 | F108: =E123*①통합_가정!$K$485/12 -> 0 | G108: =F123*①통합_가정!$K$485/12 -> 0 | H108: =G123*①통합_가정!$K$485/12 -> 0 | I108: =H123*①통합_가정!$K$485/12 -> 0 | J108: =I123*①통합_가정!$K$485/12 -> 0 | K108: =J123*①통합_가정!$K$485/12 -> 0 | L108: =K123*①통합_가정!$K$485/12 -> 0 | M108: =L123*①통합_가정!$K$485/12 -> 0 | ... EF108: =EE123*①통합_가정!$K$485/12 -> 0
A109: Tr.A 미인출수수료 | B109: 백만원 | C109: =SUM(E109:EF109) -> 13013.059 | E109: =E11*MAX(0,①통합_가정!$E$452-0)*①통합_가정!$O$483/12 -> 0 | F109: =F11*MAX(0,①통합_가정!$E$452-E121)*①통합_가정!$O$483/12 -> 0 | G109: =G11*MAX(0,①통합_가정!$E$452-F121)*①통합_가정!$O$483/12 -> 0 | H109: =H11*MAX(0,①통합_가정!$E$452-G121)*①통합_가정!$O$483/12 -> 0 | I109: =I11*MAX(0,①통합_가정!$E$452-H121)*①통합_가정!$O$483/12 -> 0 | J109: =J11*MAX(0,①통합_가정!$E$452-I121)*①통합_가정!$O$483/12 -> 0 | K109: =K11*MAX(0,①통합_가정!$E$452-J121)*①통합_가정!$O$483/12 -> 0 | L109: =L11*MAX(0,①통합_가정!$E$452-K121)*①통합_가정!$O$483/12 -> 0 | M109: =M11*MAX(0,①통합_가정!$E$452-L121)*①통합_가정!$O$483/12 -> 0 | ... EF109: =EF11*MAX(0,①통합_가정!$E$452-EE121)*①통합_가정!$O$483/12 -> 0
...

Sheet ①통합_연도별
A1: 연도별 요약 (CF 시트 집계) — 단위: 백만원
A3: 구분 | B3: 합계 | C3: =YEAR(①통합_가정!$E$8) -> 2026 | D3: =C3+1 -> 2027 | E3: =D3+1 -> 2028 | F3: =E3+1 -> 2029 | G3: =F3+1 -> 2030 | H3: =G3+1 -> 2031 | I3: =H3+1 -> 2032 | J3: =I3+1 -> 2033 | K3: =J3+1 -> 2034 | ... M3: =L3+1 -> 2036
A4: 운영
A5: 운영수입 합계 | B5: =SUM(C5:M5) -> 1022866.3 | C5: =SUMIF(①통합_CF!$E$7:$EF$7,C$3,①통합_CF!$E$41:$EF$41) -> 0 | D5: =SUMIF(①통합_CF!$E$7:$EF$7,D$3,①통합_CF!$E$41:$EF$41) -> 0 | E5: =SUMIF(①통합_CF!$E$7:$EF$7,E$3,①통합_CF!$E$41:$EF$41) -> 0 | F5: =SUMIF(①통합_CF!$E$7:$EF$7,F$3,①통합_CF!$E$41:$EF$41) -> 0 | G5: =SUMIF(①통합_CF!$E$7:$EF$7,G$3,①통합_CF!$E$41:$EF$41) -> 0 | H5: =SUMIF(①통합_CF!$E$7:$EF$7,H$3,①통합_CF!$E$41:$EF$41) -> 145507.98 | I5: =SUMIF(①통합_CF!$E$7:$EF$7,I$3,①통합_CF!$E$41:$EF$41) -> 200951.57 | J5: =SUMIF(①통합_CF!$E$7:$EF$7,J$3,①통합_CF!$E$41:$EF$41) -> 209248.63 | ... M5: =SUMIF(①통합_CF!$E$7:$EF$7,M$3,①통합_CF!$E$41:$EF$41) -> 36022.258
A6: 직접운영비용 | B6: =SUM(C6:M6) -> 706913.04 | C6: =SUMIF(①통합_CF!$E$7:$EF$7,C$3,①통합_CF!$E$56:$EF$56) -> 0 | D6: =SUMIF(①통합_CF!$E$7:$EF$7,D$3,①통합_CF!$E$56:$EF$56) -> 0 | E6: =SUMIF(①통합_CF!$E$7:$EF$7,E$3,①통합_CF!$E$56:$EF$56) -> 0 | F6: =SUMIF(①통합_CF!$E$7:$EF$7,F$3,①통합_CF!$E$56:$EF$56) -> 0 | G6: =SUMIF(①통합_CF!$E$7:$EF$7,G$3,①통합_CF!$E$56:$EF$56) -> 0 | H6: =SUMIF(①통합_CF!$E$7:$EF$7,H$3,①통합_CF!$E$56:$EF$56) -> 102004.83 | I6: =SUMIF(①통합_CF!$E$7:$EF$7,I$3,①통합_CF!$E$56:$EF$56) -> 138846.41 | J6: =SUMIF(①통합_CF!$E$7:$EF$7,J$3,①통합_CF!$E$56:$EF$56) -> 144187.65 | ... M6: =SUMIF(①통합_CF!$E$7:$EF$7,M$3,①통합_CF!$E$56:$EF$56) -> 24789.909
A7: NOI - 시니어 레지던스 | B7: =SUM(C7:M7) -> 32621.512 | C7: =SUMIF(①통합_CF!$E$7:$EF$7,C$3,①통합_CF!$E$59:$EF$59) -> 0 | D7: =SUMIF(①통합_CF!$E$7:$EF$7,D$3,①통합_CF!$E$59:$EF$59) -> 0 | E7: =SUMIF(①통합_CF!$E$7:$EF$7,E$3,①통합_CF!$E$59:$EF$59) -> 0 | F7: =SUMIF(①통합_CF!$E$7:$EF$7,F$3,①통합_CF!$E$59:$EF$59) -> 0 | G7: =SUMIF(①통합_CF!$E$7:$EF$7,G$3,①통합_CF!$E$59:$EF$59) -> 0 | H7: =SUMIF(①통합_CF!$E$7:$EF$7,H$3,①통합_CF!$E$59:$EF$59) -> 4591.644 | I7: =SUMIF(①통합_CF!$E$7:$EF$7,I$3,①통합_CF!$E$59:$EF$59) -> 6399.9149 | J7: =SUMIF(①통합_CF!$E$7:$EF$7,J$3,①통합_CF!$E$59:$EF$59) -> 6687.535 | ... M7: =SUMIF(①통합_CF!$E$7:$EF$7,M$3,①통합_CF!$E$59:$EF$59) -> 1163.4206
A8: NOI - 레지던스 | B8: =SUM(C8:M8) -> 42839.167 | C8: =SUMIF(①통합_CF!$E$7:$EF$7,C$3,①통합_CF!$E$60:$EF$60) -> 0 | D8: =SUMIF(①통합_CF!$E$7:$EF$7,D$3,①통합_CF!$E$60:$EF$60) -> 0 | E8: =SUMIF(①통합_CF!$E$7:$EF$7,E$3,①통합_CF!$E$60:$EF$60) -> 0 | F8: =SUMIF(①통합_CF!$E$7:$EF$7,F$3,①통합_CF!$E$60:$EF$60) -> 0 | G8: =SUMIF(①통합_CF!$E$7:$EF$7,G$3,①통합_CF!$E$60:$EF$60) -> 0 | H8: =SUMIF(①통합_CF!$E$7:$EF$7,H$3,①통합_CF!$E$60:$EF$60) -> 6131.9139 | I8: =SUMIF(①통합_CF!$E$7:$EF$7,I$3,①통합_CF!$E$60:$EF$60) -> 8419.127 | J8: =SUMIF(①통합_CF!$E$7:$EF$7,J$3,①통합_CF!$E$60:$EF$60) -> 8752.5996 | ... M8: =SUMIF(①통합_CF!$E$7:$EF$7,M$3,①통합_CF!$E$60:$EF$60) -> 1501.6699
A9: NOI - 호텔 | B9: =SUM(C9:M9) -> 132976.8 | C9: =SUMIF(①통합_CF!$E$7:$EF$7,C$3,①통합_CF!$E$61:$EF$61) -> 0 | D9: =SUMIF(①통합_CF!$E$7:$EF$7,D$3,①통합_CF!$E$61:$EF$61) -> 0 | E9: =SUMIF(①통합_CF!$E$7:$EF$7,E$3,①통합_CF!$E$61:$EF$61) -> 0 | F9: =SUMIF(①통합_CF!$E$7:$EF$7,F$3,①통합_CF!$E$61:$EF$61) -> 0 | G9: =SUMIF(①통합_CF!$E$7:$EF$7,G$3,①통합_CF!$E$61:$EF$61) -> 0 | H9: =SUMIF(①통합_CF!$E$7:$EF$7,H$3,①통합_CF!$E$61:$EF$61) -> 19034.038 | I9: =SUMIF(①통합_CF!$E$7:$EF$7,I$3,①통합_CF!$E$61:$EF$61) -> 26133.763 | J9: =SUMIF(①통합_CF!$E$7:$EF$7,J$3,①통합_CF!$E$61:$EF$61) -> 27168.893 | ... M9: =SUMIF(①통합_CF!$E$7:$EF$7,M$3,①통합_CF!$E$61:$EF$61) -> 4661.3246
A10: NOI - 오피스 | B10: =SUM(C10:M10) -> 66369.038 | C10: =SUMIF(①통합_CF!$E$7:$EF$7,C$3,①통합_CF!$E$62:$EF$62) -> 0 | D10: =SUMIF(①통합_CF!$E$7:$EF$7,D$3,①통합_CF!$E$62:$EF$62) -> 0 | E10: =SUMIF(①통합_CF!$E$7:$EF$7,E$3,①통합_CF!$E$62:$EF$62) -> 0 | F10: =SUMIF(①통합_CF!$E$7:$EF$7,F$3,①통합_CF!$E$62:$EF$62) -> 0 | G10: =SUMIF(①통합_CF!$E$7:$EF$7,G$3,①통합_CF!$E$62:$EF$62) -> 0 | H10: =SUMIF(①통합_CF!$E$7:$EF$7,H$3,①통합_CF!$E$62:$EF$62) -> 7156.6406 | I10: =SUMIF(①통합_CF!$E$7:$EF$7,I$3,①통합_CF!$E$62:$EF$62) -> 13113.878 | J10: =SUMIF(①통합_CF!$E$7:$EF$7,J$3,①통합_CF!$E$62:$EF$62) -> 14252.711 | ... M10: =SUMIF(①통합_CF!$E$7:$EF$7,M$3,①통합_CF!$E$62:$EF$62) -> 2479.5231
A11: NOI - 부대시설 | B11: =SUM(C11:M11) -> 41146.757 | C11: =SUMIF(①통합_CF!$E$7:$EF$7,C$3,①통합_CF!$E$63:$EF$63) -> 0 | D11: =SUMIF(①통합_CF!$E$7:$EF$7,D$3,①통합_CF!$E$63:$EF$63) -> 0 | E11: =SUMIF(①통합_CF!$E$7:$EF$7,E$3,①통합_CF!$E$63:$EF$63) -> 0 | F11: =SUMIF(①통합_CF!$E$7:$EF$7,F$3,①통합_CF!$E$63:$EF$63) -> 0 | G11: =SUMIF(①통합_CF!$E$7:$EF$7,G$3,①통합_CF!$E$63:$EF$63) -> 0 | H11: =SUMIF(①통합_CF!$E$7:$EF$7,H$3,①통합_CF!$E$63:$EF$63) -> 6588.9123 | I11: =SUMIF(①통합_CF!$E$7:$EF$7,I$3,①통합_CF!$E$63:$EF$63) -> 8038.473 | J11: =SUMIF(①통합_CF!$E$7:$EF$7,J$3,①통합_CF!$E$63:$EF$63) -> 8199.2425 | ... M11: =SUMIF(①통합_CF!$E$7:$EF$7,M$3,①통합_CF!$E$63:$EF$63) -> 1426.4101
A12: NOI 합계 | B12: =SUM(C12:M12) -> 315953.28 | C12: =SUMIF(①통합_CF!$E$7:$EF$7,C$3,①통합_CF!$E$64:$EF$64) -> 0 | D12: =SUMIF(①통합_CF!$E$7:$EF$7,D$3,①통합_CF!$E$64:$EF$64) -> 0 | E12: =SUMIF(①통합_CF!$E$7:$EF$7,E$3,①통합_CF!$E$64:$EF$64) -> 0 | F12: =SUMIF(①통합_CF!$E$7:$EF$7,F$3,①통합_CF!$E$64:$EF$64) -> 0 | G12: =SUMIF(①통합_CF!$E$7:$EF$7,G$3,①통합_CF!$E$64:$EF$64) -> 0 | H12: =SUMIF(①통합_CF!$E$7:$EF$7,H$3,①통합_CF!$E$64:$EF$64) -> 43503.149 | I12: =SUMIF(①통합_CF!$E$7:$EF$7,I$3,①통합_CF!$E$64:$EF$64) -> 62105.156 | J12: =SUMIF(①통합_CF!$E$7:$EF$7,J$3,①통합_CF!$E$64:$EF$64) -> 65060.981 | ... M12: =SUMIF(①통합_CF!$E$7:$EF$7,M$3,①통합_CF!$E$64:$EF$64) -> 11232.348
A13: 공통비용·리츠운용비 | B13: =SUM(C13:M13) -> 63114.79 | C13: =SUMIF(①통합_CF!$E$7:$EF$7,C$3,①통합_CF!$E$74:$EF$74) -> 0 | D13: =SUMIF(①통합_CF!$E$7:$EF$7,D$3,①통합_CF!$E$74:$EF$74) -> 0 | E13: =SUMIF(①통합_CF!$E$7:$EF$7,E$3,①통합_CF!$E$74:$EF$74) -> 0 | F13: =SUMIF(①통합_CF!$E$7:$EF$7,F$3,①통합_CF!$E$74:$EF$74) -> 0 | G13: =SUMIF(①통합_CF!$E$7:$EF$7,G$3,①통합_CF!$E$74:$EF$74) -> 0 | H13: =SUMIF(①통합_CF!$E$7:$EF$7,H$3,①통합_CF!$E$74:$EF$74) -> 8190.5983 | I13: =SUMIF(①통합_CF!$E$7:$EF$7,I$3,①통합_CF!$E$74:$EF$74) -> 10504.036 | J13: =SUMIF(①통합_CF!$E$7:$EF$7,J$3,①통합_CF!$E$74:$EF$74) -> 10820.972 | ... M13: =SUMIF(①통합_CF!$E$7:$EF$7,M$3,①통합_CF!$E$74:$EF$74) -> 11558.781
A14: 운영현금흐름 | B14: =SUM(C14:M14) -> 252838.49 | C14: =SUMIF(①통합_CF!$E$7:$EF$7,C$3,①통합_CF!$E$75:$EF$75) -> 0 | D14: =SUMIF(①통합_CF!$E$7:$EF$7,D$3,①통합_CF!$E$75:$EF$75) -> 0 | E14: =SUMIF(①통합_CF!$E$7:$EF$7,E$3,①통합_CF!$E$75:$EF$75) -> 0 | F14: =SUMIF(①통합_CF!$E$7:$EF$7,F$3,①통합_CF!$E$75:$EF$75) -> 0 | G14: =SUMIF(①통합_CF!$E$7:$EF$7,G$3,①통합_CF!$E$75:$EF$75) -> 0 | H14: =SUMIF(①통합_CF!$E$7:$EF$7,H$3,①통합_CF!$E$75:$EF$75) -> 35312.55 | I14: =SUMIF(①통합_CF!$E$7:$EF$7,I$3,①통합_CF!$E$75:$EF$75) -> 51601.119 | J14: =SUMIF(①통합_CF!$E$7:$EF$7,J$3,①통합_CF!$E$75:$EF$75) -> 54240.009 | ... M14: =SUMIF(①통합_CF!$E$7:$EF$7,M$3,①통합_CF!$E$75:$EF$75) -> -326.43265
A15: 개발 및 금융
A16: 개발사업비 집행 | B16: =SUM(C16:M16) -> 1401070.2 | C16: =SUMIF(①통합_CF!$E$7:$EF$7,C$3,①통합_CF!$E$100:$EF$100) -> 13874.924 | D16: =SUMIF(①통합_CF!$E$7:$EF$7,D$3,①통합_CF!$E$100:$EF$100) -> 253559.35 | E16: =SUMIF(①통합_CF!$E$7:$EF$7,E$3,①통합_CF!$E$100:$EF$100) -> 315713.7 | F16: =SUMIF(①통합_CF!$E$7:$EF$7,F$3,①통합_CF!$E$100:$EF$100) -> 457532.55 | G16: =SUMIF(①통합_CF!$E$7:$EF$7,G$3,①통합_CF!$E$100:$EF$100) -> 263441.5 | H16: =SUMIF(①통합_CF!$E$7:$EF$7,H$3,①통합_CF!$E$100:$EF$100) -> 96948.181 | I16: =SUMIF(①통합_CF!$E$7:$EF$7,I$3,①통합_CF!$E$100:$EF$100) -> 0 | J16: =SUMIF(①통합_CF!$E$7:$EF$7,J$3,①통합_CF!$E$100:$EF$100) -> 0 | ... M16: =SUMIF(①통합_CF!$E$7:$EF$7,M$3,①통합_CF!$E$100:$EF$100) -> 0
A17: PF 금융비용 | B17: =SUM(C17:M17) -> 95505.682 | C17: =SUMIF(①통합_CF!$E$7:$EF$7,C$3,①통합_CF!$E$112:$EF$112) -> 0 | D17: =SUMIF(①통합_CF!$E$7:$EF$7,D$3,①통합_CF!$E$112:$EF$112) -> 13410.991 | E17: =SUMIF(①통합_CF!$E$7:$EF$7,E$3,①통합_CF!$E$112:$EF$112) -> 6486.9755 | F17: =SUMIF(①통합_CF!$E$7:$EF$7,F$3,①통합_CF!$E$112:$EF$112) -> 24417.029 | G17: =SUMIF(①통합_CF!$E$7:$EF$7,G$3,①통합_CF!$E$112:$EF$112) -> 43104.746 | H17: =SUMIF(①통합_CF!$E$7:$EF$7,H$3,①통합_CF!$E$112:$EF$112) -> 8085.9409 | I17: =SUMIF(①통합_CF!$E$7:$EF$7,I$3,①통합_CF!$E$112:$EF$112) -> 0 | J17: =SUMIF(①통합_CF!$E$7:$EF$7,J$3,①통합_CF!$E$112:$EF$112) -> 0 | ... M17: =SUMIF(①통합_CF!$E$7:$EF$7,M$3,①통합_CF!$E$112:$EF$112) -> 0
A18: 담보대출 이자 | B18: =SUM(C18:M18) -> 198878.57 | C18: =SUMIF(①통합_CF!$E$7:$EF$7,C$3,①통합_CF!$E$129:$EF$129) -> 0 | D18: =SUMIF(①통합_CF!$E$7:$EF$7,D$3,①통합_CF!$E$129:$EF$129) -> 0 | E18: =SUMIF(①통합_CF!$E$7:$EF$7,E$3,①통합_CF!$E$129:$EF$129) -> 0 | F18: =SUMIF(①통합_CF!$E$7:$EF$7,F$3,①통합_CF!$E$129:$EF$129) -> 0 | G18: =SUMIF(①통합_CF!$E$7:$EF$7,G$3,①통합_CF!$E$129:$EF$129) -> 0 | H18: =SUMIF(①통합_CF!$E$7:$EF$7,H$3,①통합_CF!$E$129:$EF$129) -> 33146.428 | I18: =SUMIF(①통합_CF!$E$7:$EF$7,I$3,①통합_CF!$E$129:$EF$129) -> 39775.714 | J18: =SUMIF(①통합_CF!$E$7:$EF$7,J$3,①통합_CF!$E$129:$EF$129) -> 39775.714 | ... M18: =SUMIF(①통합_CF!$E$7:$EF$7,M$3,①통합_CF!$E$129:$EF$129) -> 6629.2857
A19: 담보대출 취급수수료 | B19: =SUM(C19:M19) -> 7596.6828 | C19: =SUMIF(①통합_CF!$E$7:$EF$7,C$3,①통합_CF!$E$128:$EF$128) -> 0 | D19: =SUMIF(①통합_CF!$E$7:$EF$7,D$3,①통합_CF!$E$128:$EF$128) -> 0 | E19: =SUMIF(①통합_CF!$E$7:$EF$7,E$3,①통합_CF!$E$128:$EF$128) -> 0 | F19: =SUMIF(①통합_CF!$E$7:$EF$7,F$3,①통합_CF!$E$128:$EF$128) -> 0 | G19: =SUMIF(①통합_CF!$E$7:$EF$7,G$3,①통합_CF!$E$128:$EF$128) -> 0 | H19: =SUMIF(①통합_CF!$E$7:$EF$7,H$3,①통합_CF!$E$128:$EF$128) -> 7596.6828 | I19: =SUMIF(①통합_CF!$E$7:$EF$7,I$3,①통합_CF!$E$128:$EF$128) -> 0 | J19: =SUMIF(①통합_CF!$E$7:$EF$7,J$3,①통합_CF!$E$128:$EF$128) -> 0 | ... M19: =SUMIF(①통합_CF!$E$7:$EF$7,M$3,①통합_CF!$E$128:$EF$128) -> 0
A20: 자금 유출입
A21: Equity 납입 | B21: =SUM(C21:M21) -> 287378.39 | C21: =SUMIF(①통합_CF!$E$7:$EF$7,C$3,①통합_CF!$E$142:$EF$142) -> 15820.18 | D21: =SUMIF(①통합_CF!$E$7:$EF$7,D$3,①통합_CF!$E$142:$EF$142) -> 271558.21 | E21: =SUMIF(①통합_CF!$E$7:$EF$7,E$3,①통합_CF!$E$142:$EF$142) -> 0 | F21: =SUMIF(①통합_CF!$E$7:$EF$7,F$3,①통합_CF!$E$142:$EF$142) -> 0 | G21: =SUMIF(①통합_CF!$E$7:$EF$7,G$3,①통합_CF!$E$142:$EF$142) -> 0 | H21: =SUMIF(①통합_CF!$E$7:$EF$7,H$3,①통합_CF!$E$142:$EF$142) -> 0 | I21: =SUMIF(①통합_CF!$E$7:$EF$7,I$3,①통합_CF!$E$142:$EF$142) -> 0 | J21: =SUMIF(①통합_CF!$E$7:$EF$7,J$3,①통합_CF!$E$142:$EF$142) -> 0 | ... M21: =SUMIF(①통합_CF!$E$7:$EF$7,M$3,①통합_CF!$E$142:$EF$142) -> 0
A22: 보증금 유입 | B22: =SUM(C22:M22) -> 941952 | C22: =SUMIF(①통합_CF!$E$7:$EF$7,C$3,①통합_CF!$E$84:$EF$84) -> 0 | D22: =SUMIF(①통합_CF!$E$7:$EF$7,D$3,①통합_CF!$E$84:$EF$84) -> 68060.16 | E22: =SUMIF(①통합_CF!$E$7:$EF$7,E$3,①통합_CF!$E$84:$EF$84) -> 136120.32 | F22: =SUMIF(①통합_CF!$E$7:$EF$7,F$3,①통합_CF!$E$84:$EF$84) -> 136120.32 | G22: =SUMIF(①통합_CF!$E$7:$EF$7,G$3,①통합_CF!$E$84:$EF$84) -> 136120.32 | H22: =SUMIF(①통합_CF!$E$7:$EF$7,H$3,①통합_CF!$E$84:$EF$84) -> 268980.48 | I22: =SUMIF(①통합_CF!$E$7:$EF$7,I$3,①통합_CF!$E$84:$EF$84) -> 183350.4 | J22: =SUMIF(①통합_CF!$E$7:$EF$7,J$3,①통합_CF!$E$84:$EF$84) -> 13200 | ... M22: =SUMIF(①통합_CF!$E$7:$EF$7,M$3,①통합_CF!$E$84:$EF$84) -> 0
A23: 보증금 승계(처분) | B23: =SUM(C23:M23) -> 941952 | C23: =SUMIF(①통합_CF!$E$7:$EF$7,C$3,①통합_CF!$E$85:$EF$85) -> 0 | D23: =SUMIF(①통합_CF!$E$7:$EF$7,D$3,①통합_CF!$E$85:$EF$85) -> 0 | E23: =SUMIF(①통합_CF!$E$7:$EF$7,E$3,①통합_CF!$E$85:$EF$85) -> 0 | F23: =SUMIF(①통합_CF!$E$7:$EF$7,F$3,①통합_CF!$E$85:$EF$85) -> 0 | G23: =SUMIF(①통합_CF!$E$7:$EF$7,G$3,①통합_CF!$E$85:$EF$85) -> 0 | H23: =SUMIF(①통합_CF!$E$7:$EF$7,H$3,①통합_CF!$E$85:$EF$85) -> 0 | I23: =SUMIF(①통합_CF!$E$7:$EF$7,I$3,①통합_CF!$E$85:$EF$85) -> 0 | J23: =SUMIF(①통합_CF!$E$7:$EF$7,J$3,①통합_CF!$E$85:$EF$85) -> 0 | ... M23: =SUMIF(①통합_CF!$E$7:$EF$7,M$3,①통합_CF!$E$85:$EF$85) -> 941952
A24: PF 인출 | B24: =SUM(C24:M24) -> 632619.29 | C24: =SUMIF(①통합_CF!$E$7:$EF$7,C$3,①통합_CF!$E$116:$EF$116) -> 0 | D24: =SUMIF(①통합_CF!$E$7:$EF$7,D$3,①통합_CF!$E$116:$EF$116) -> 0 | E24: =SUMIF(①통합_CF!$E$7:$EF$7,E$3,①통합_CF!$E$116:$EF$116) -> 108087.92 | F24: =SUMIF(①통합_CF!$E$7:$EF$7,F$3,①통합_CF!$E$116:$EF$116) -> 345404.15 | G24: =SUMIF(①통합_CF!$E$7:$EF$7,G$3,①통합_CF!$E$116:$EF$116) -> 169838.35 | H24: =SUMIF(①통합_CF!$E$7:$EF$7,H$3,①통합_CF!$E$116:$EF$116) -> 9288.8612 | I24: =SUMIF(①통합_CF!$E$7:$EF$7,I$3,①통합_CF!$E$116:$EF$116) -> 0 | J24: =SUMIF(①통합_CF!$E$7:$EF$7,J$3,①통합_CF!$E$116:$EF$116) -> 0 | ... M24: =SUMIF(①통합_CF!$E$7:$EF$7,M$3,①통합_CF!$E$116:$EF$116) -> 0
A25: PF 상환 | B25: =SUM(C25:M25) -> 632619.29 | C25: =SUMIF(①통합_CF!$E$7:$EF$7,C$3,①통합_CF!$E$120:$EF$120) -> 0 | D25: =SUMIF(①통합_CF!$E$7:$EF$7,D$3,①통합_CF!$E$120:$EF$120) -> 0 | E25: =SUMIF(①통합_CF!$E$7:$EF$7,E$3,①통합_CF!$E$120:$EF$120) -> 0 | F25: =SUMIF(①통합_CF!$E$7:$EF$7,F$3,①통합_CF!$E$120:$EF$120) -> 0 | G25: =SUMIF(①통합_CF!$E$7:$EF$7,G$3,①통합_CF!$E$120:$EF$120) -> 0 | H25: =SUMIF(①통합_CF!$E$7:$EF$7,H$3,①통합_CF!$E$120:$EF$120) -> 632619.29 | I25: =SUMIF(①통합_CF!$E$7:$EF$7,I$3,①통합_CF!$E$120:$EF$120) -> 0 | J25: =SUMIF(①통합_CF!$E$7:$EF$7,J$3,①통합_CF!$E$120:$EF$120) -> 0 | ... M25: =SUMIF(①통합_CF!$E$7:$EF$7,M$3,①통합_CF!$E$120:$EF$120) -> 0
A26: 담보대출 인출 | B26: =SUM(C26:M26) -> 759668.28 | C26: =SUMIF(①통합_CF!$E$7:$EF$7,C$3,①통합_CF!$E$127:$EF$127) -> 0 | D26: =SUMIF(①통합_CF!$E$7:$EF$7,D$3,①통합_CF!$E$127:$EF$127) -> 0 | E26: =SUMIF(①통합_CF!$E$7:$EF$7,E$3,①통합_CF!$E$127:$EF$127) -> 0 | F26: =SUMIF(①통합_CF!$E$7:$EF$7,F$3,①통합_CF!$E$127:$EF$127) -> 0 | G26: =SUMIF(①통합_CF!$E$7:$EF$7,G$3,①통합_CF!$E$127:$EF$127) -> 0 | H26: =SUMIF(①통합_CF!$E$7:$EF$7,H$3,①통합_CF!$E$127:$EF$127) -> 759668.28 | I26: =SUMIF(①통합_CF!$E$7:$EF$7,I$3,①통합_CF!$E$127:$EF$127) -> 0 | J26: =SUMIF(①통합_CF!$E$7:$EF$7,J$3,①통합_CF!$E$127:$EF$127) -> 0 | ... M26: =SUMIF(①통합_CF!$E$7:$EF$7,M$3,①통합_CF!$E$127:$EF$127) -> 0
A27: 담보대출 상환 | B27: =SUM(C27:M27) -> 759668.28 | C27: =SUMIF(①통합_CF!$E$7:$EF$7,C$3,①통합_CF!$E$130:$EF$130) -> 0 | D27: =SUMIF(①통합_CF!$E$7:$EF$7,D$3,①통합_CF!$E$130:$EF$130) -> 0 | E27: =SUMIF(①통합_CF!$E$7:$EF$7,E$3,①통합_CF!$E$130:$EF$130) -> 0 | F27: =SUMIF(①통합_CF!$E$7:$EF$7,F$3,①통합_CF!$E$130:$EF$130) -> 0 | G27: =SUMIF(①통합_CF!$E$7:$EF$7,G$3,①통합_CF!$E$130:$EF$130) -> 0 | H27: =SUMIF(①통합_CF!$E$7:$EF$7,H$3,①통합_CF!$E$130:$EF$130) -> 0 | I27: =SUMIF(①통합_CF!$E$7:$EF$7,I$3,①통합_CF!$E$130:$EF$130) -> 0 | J27: =SUMIF(①통합_CF!$E$7:$EF$7,J$3,①통합_CF!$E$130:$EF$130) -> 0 | ... M27: =SUMIF(①통합_CF!$E$7:$EF$7,M$3,①통합_CF!$E$130:$EF$130) -> 759668.28
A28: 매각대금 | B28: =SUM(C28:M28) -> 1824235.9 | C28: =SUMIF(①통합_CF!$E$7:$EF$7,C$3,①통합_CF!$E$145:$EF$145) -> 0 | D28: =SUMIF(①통합_CF!$E$7:$EF$7,D$3,①통합_CF!$E$145:$EF$145) -> 0 | E28: =SUMIF(①통합_CF!$E$7:$EF$7,E$3,①통합_CF!$E$145:$EF$145) -> 0 | F28: =SUMIF(①통합_CF!$E$7:$EF$7,F$3,①통합_CF!$E$145:$EF$145) -> 0 | G28: =SUMIF(①통합_CF!$E$7:$EF$7,G$3,①통합_CF!$E$145:$EF$145) -> 0 | H28: =SUMIF(①통합_CF!$E$7:$EF$7,H$3,①통합_CF!$E$145:$EF$145) -> 0 | I28: =SUMIF(①통합_CF!$E$7:$EF$7,I$3,①통합_CF!$E$145:$EF$145) -> 0 | J28: =SUMIF(①통합_CF!$E$7:$EF$7,J$3,①통합_CF!$E$145:$EF$145) -> 0 | ... M28: =SUMIF(①통합_CF!$E$7:$EF$7,M$3,①통합_CF!$E$145:$EF$145) -> 1824235.9
A29: 분배
A30: 우선주 배당 | B30: =SUM(C30:M30) -> 91331.559 | C30: =SUMIF(①통합_CF!$E$7:$EF$7,C$3,①통합_CF!$E$165:$EF$165) -> 0 | D30: =SUMIF(①통합_CF!$E$7:$EF$7,D$3,①통합_CF!$E$165:$EF$165) -> 0 | E30: =SUMIF(①통합_CF!$E$7:$EF$7,E$3,①통합_CF!$E$165:$EF$165) -> 0 | F30: =SUMIF(①통합_CF!$E$7:$EF$7,F$3,①통합_CF!$E$165:$EF$165) -> 0 | G30: =SUMIF(①통합_CF!$E$7:$EF$7,G$3,①통합_CF!$E$165:$EF$165) -> 0 | H30: =SUMIF(①통합_CF!$E$7:$EF$7,H$3,①통합_CF!$E$165:$EF$165) -> 13776.401 | I30: =SUMIF(①통합_CF!$E$7:$EF$7,I$3,①통합_CF!$E$165:$EF$165) -> 24599.06 | J30: =SUMIF(①통합_CF!$E$7:$EF$7,J$3,①통합_CF!$E$165:$EF$165) -> 28910.077 | ... M30: =SUMIF(①통합_CF!$E$7:$EF$7,M$3,①통합_CF!$E$165:$EF$165) -> 4117.9416
A31: 우선주 원금상환 | B31: =SUM(C31:M31) -> 201164.87 | C31: =SUMIF(①통합_CF!$E$7:$EF$7,C$3,①통합_CF!$E$166:$EF$166) -> 0 | D31: =SUMIF(①통합_CF!$E$7:$EF$7,D$3,①통합_CF!$E$166:$EF$166) -> 0 | E31: =SUMIF(①통합_CF!$E$7:$EF$7,E$3,①통합_CF!$E$166:$EF$166) -> 0 | F31: =SUMIF(①통합_CF!$E$7:$EF$7,F$3,①통합_CF!$E$166:$EF$166) -> 0 | G31: =SUMIF(①통합_CF!$E$7:$EF$7,G$3,①통합_CF!$E$166:$EF$166) -> 0 | H31: =SUMIF(①통합_CF!$E$7:$EF$7,H$3,①통합_CF!$E$166:$EF$166) -> 0 | I31: =SUMIF(①통합_CF!$E$7:$EF$7,I$3,①통합_CF!$E$166:$EF$166) -> 0 | J31: =SUMIF(①통합_CF!$E$7:$EF$7,J$3,①통합_CF!$E$166:$EF$166) -> 0 | ... M31: =SUMIF(①통합_CF!$E$7:$EF$7,M$3,①통합_CF!$E$166:$EF$166) -> 201164.87
A32: 보통주 분배 | B32: =SUM(C32:M32) -> 443763.15 | C32: =SUMIF(①통합_CF!$E$7:$EF$7,C$3,①통합_CF!$E$168:$EF$168) -> 0 | D32: =SUMIF(①통합_CF!$E$7:$EF$7,D$3,①통합_CF!$E$168:$EF$168) -> 0 | E32: =SUMIF(①통합_CF!$E$7:$EF$7,E$3,①통합_CF!$E$168:$EF$168) -> 0 | F32: =SUMIF(①통합_CF!$E$7:$EF$7,F$3,①통합_CF!$E$168:$EF$168) -> 0 | G32: =SUMIF(①통합_CF!$E$7:$EF$7,G$3,①통합_CF!$E$168:$EF$168) -> 0 | H32: =SUMIF(①통합_CF!$E$7:$EF$7,H$3,①통합_CF!$E$168:$EF$168) -> 0 | I32: =SUMIF(①통합_CF!$E$7:$EF$7,I$3,①통합_CF!$E$168:$EF$168) -> 0 | J32: =SUMIF(①통합_CF!$E$7:$EF$7,J$3,①통합_CF!$E$168:$EF$168) -> 0 | ... M32: =SUMIF(①통합_CF!$E$7:$EF$7,M$3,①통합_CF!$E$168:$EF$168) -> 402141.85
A33: 보통주 CF | B33: =SUM(C33:M33) -> 357549.63 | C33: =SUMIF(①통합_CF!$E$7:$EF$7,C$3,①통합_CF!$E$171:$EF$171) -> -15820.18 | D33: =SUMIF(①통합_CF!$E$7:$EF$7,D$3,①통합_CF!$E$171:$EF$171) -> -70393.336 | E33: =SUMIF(①통합_CF!$E$7:$EF$7,E$3,①통합_CF!$E$171:$EF$171) -> 0 | F33: =SUMIF(①통합_CF!$E$7:$EF$7,F$3,①통합_CF!$E$171:$EF$171) -> 0 | G33: =SUMIF(①통합_CF!$E$7:$EF$7,G$3,①통합_CF!$E$171:$EF$171) -> 0 | H33: =SUMIF(①통합_CF!$E$7:$EF$7,H$3,①통합_CF!$E$171:$EF$171) -> 0 | I33: =SUMIF(①통합_CF!$E$7:$EF$7,I$3,①통합_CF!$E$171:$EF$171) -> 0 | J33: =SUMIF(①통합_CF!$E$7:$EF$7,J$3,①통합_CF!$E$171:$EF$171) -> 0 | ... M33: =SUMIF(①통합_CF!$E$7:$EF$7,M$3,①통합_CF!$E$171:$EF$171) -> 402141.85
A34: 우선주 CF | B34: =SUM(C34:M34) -> 91331.559 | C34: =SUMIF(①통합_CF!$E$7:$EF$7,C$3,①통합_CF!$E$172:$EF$172) -> 0 | D34: =SUMIF(①통합_CF!$E$7:$EF$7,D$3,①통합_CF!$E$172:$EF$172) -> -201164.87 | E34: =SUMIF(①통합_CF!$E$7:$EF$7,E$3,①통합_CF!$E$172:$EF$172) -> 0 | F34: =SUMIF(①통합_CF!$E$7:$EF$7,F$3,①통합_CF!$E$172:$EF$172) -> 0 | G34: =SUMIF(①통합_CF!$E$7:$EF$7,G$3,①통합_CF!$E$172:$EF$172) -> 0 | H34: =SUMIF(①통합_CF!$E$7:$EF$7,H$3,①통합_CF!$E$172:$EF$172) -> 13776.401 | I34: =SUMIF(①통합_CF!$E$7:$EF$7,I$3,①통합_CF!$E$172:$EF$172) -> 24599.06 | J34: =SUMIF(①통합_CF!$E$7:$EF$7,J$3,①통합_CF!$E$172:$EF$172) -> 28910.077 | ... M34: =SUMIF(①통합_CF!$E$7:$EF$7,M$3,①통합_CF!$E$172:$EF$172) -> 205282.81
A35: 전체 Equity CF | B35: =SUM(C35:M35) -> 448881.19 | C35: =SUMIF(①통합_CF!$E$7:$EF$7,C$3,①통합_CF!$E$173:$EF$173) -> -15820.18 | D35: =SUMIF(①통합_CF!$E$7:$EF$7,D$3,①통합_CF!$E$173:$EF$173) -> -271558.21 | E35: =SUMIF(①통합_CF!$E$7:$EF$7,E$3,①통합_CF!$E$173:$EF$173) -> 0 | F35: =SUMIF(①통합_CF!$E$7:$EF$7,F$3,①통합_CF!$E$173:$EF$173) -> 0 | G35: =SUMIF(①통합_CF!$E$7:$EF$7,G$3,①통합_CF!$E$173:$EF$173) -> 0 | H35: =SUMIF(①통합_CF!$E$7:$EF$7,H$3,①통합_CF!$E$173:$EF$173) -> 13776.401 | I35: =SUMIF(①통합_CF!$E$7:$EF$7,I$3,①통합_CF!$E$173:$EF$173) -> 24599.06 | J35: =SUMIF(①통합_CF!$E$7:$EF$7,J$3,①통합_CF!$E$173:$EF$173) -> 28910.077 | ... M35: =SUMIF(①통합_CF!$E$7:$EF$7,M$3,①통합_CF!$E$173:$EF$173) -> 607424.66
A36: 기말현금 | C36: =SUMIF(①통합_CF!$E$6:$EF$6,MIN(DATE(C$3,12,31),①통합_가정!$E$24),①통합_CF!$E$159:$EF$159)*(C$3<=YEAR(①통합_가정!$E$24)) -> 2084.0179 | D36: =SUMIF(①통합_CF!$E$6:$EF$6,MIN(DATE(D$3,12,31),①통합_가정!$E$24),①통합_CF!$E$159:$EF$159)*(D$3<=YEAR(①통합_가정!$E$24)) -> 76511.599 | E36: =SUMIF(①통합_CF!$E$6:$EF$6,MIN(DATE(E$3,12,31),①통합_가정!$E$24),①통합_CF!$E$159:$EF$159)*(E$3<=YEAR(①통합_가정!$E$24)) -> 500 | F36: =SUMIF(①통합_CF!$E$6:$EF$6,MIN(DATE(F$3,12,31),①통합_가정!$E$24),①통합_CF!$E$159:$EF$159)*(F$3<=YEAR(①통합_가정!$E$24)) -> 500 | G36: =SUMIF(①통합_CF!$E$6:$EF$6,MIN(DATE(G$3,12,31),①통합_가정!$E$24),①통합_CF!$E$159:$EF$159)*(G$3<=YEAR(①통합_가정!$E$24)) -> 500 | H36: =SUMIF(①통합_CF!$E$6:$EF$6,MIN(DATE(H$3,12,31),①통합_가정!$E$24),①통합_CF!$E$159:$EF$159)*(H$3<=YEAR(①통합_가정!$E$24)) -> 288275.69 | I36: =SUMIF(①통합_CF!$E$6:$EF$6,MIN(DATE(I$3,12,31),①통합_가정!$E$24),①통합_CF!$E$159:$EF$159)*(I$3<=YEAR(①통합_가정!$E$24)) -> 471626.09 | J36: =SUMIF(①통합_CF!$E$6:$EF$6,MIN(DATE(J$3,12,31),①통합_가정!$E$24),①통합_CF!$E$159:$EF$159)*(J$3<=YEAR(①통합_가정!$E$24)) -> 484826.09 | ... M36: =SUMIF(①통합_CF!$E$6:$EF$6,MIN(DATE(M$3,12,31),①통합_가정!$E$24),①통합_CF!$E$159:$EF$159)*(M$3<=YEAR(①통합_가정!$E$24)) -> 0
A38: IRR (보통주) | B38: =①통합_CF!$C$171 -> 0.20392787
A39: IRR (우선주) | B39: =①통합_CF!$C$172 -> 0.05
A40: IRR (전체) | B40: =①통합_CF!$C$173 -> 0.12111635

Sheet ②시니어_가정
B1: 센텀C부지 복합개발사업 재무모델 | I1: 입력값 | J1: 파란 글씨 = 입력(하드코딩)
B2: ② 시니어 레지던스 Vehicle — Assumption (단위: 백만원) | I2: 수식 | J2: 검정 = 계산 수식
C3: =IF(ABS(②시니어_CF!$C$159)<1,"OK","Error") -> Error | D3: =IF(SUMPRODUCT(ABS($F$560:$F$569))<1,"OK","Run Macro") -> OK | E3: =IF(MIN(②시니어_CF!$E$159:$EF$159)>-0.5,"OK","Shortage") -> Shortage | F3: =IF(SUM(②시니어_CF!$E$153:$EF$153)-SUM(②시니어_CF!$E$116:$EF$116)<1,"OK","PF한도부족") -> OK | I3: 연결 | J3: 초록 = CF 시트 연결
C4: Balance Check | D4: Macro Check | E4: Shortage Check | F4: Cash Check | I4: Macro | J4: 노랑 = Macro Paste 값(순환참조 차단)
A6: 프로젝트 일정 (계획)
B8: 리츠설립일 | D8: Date | E8: 46112
B9: 매매계약체결 준비기간 | D9: Months | E9: 3
B10: 토지매매계약체결일 | D10: Date | E10: =EOMONTH($E$8,$E$9) -> 46203
B11: 인허가 준비기간 | D11: Months | E11: 14
B12: 인허가 완료일 | D12: Date | E12: =EOMONTH($E$10,$E$11) -> 46630
B13: 공사준비기간 | D13: Months | E13: 1
B14: 착공일 | D14: Date | E14: =EOMONTH($E$12,$E$13) -> 46660
B15: 공사기간 | D15: Months | E15: 42
B16: 준공일 | D16: Date | E16: =EOMONTH($E$14,$E$15-1) -> 47907
B17: 운영준비기간 | D17: Months | E17: 1
B18: 운영개시일 | D18: Date | E18: =EOMONTH($E$16,$E$17) -> 47938
B19: 운영기간 | D19: Months | E19: 60
B20: 운영종료일 | D20: Date | E20: =EOMONTH($E$18,$E$19-1) -> 49734
B21: 처분준비기간 | D21: Months | E21: 0
B22: 처분일 | D22: Date | E22: =EOMONTH($E$20,$E$21) -> 49734
B23: 청산준비기간 | D23: Months | E23: 3
B24: 리츠청산일 | D24: Date | E24: =EOMONTH($E$22,$E$23) -> 49826
B25: 개발기간(설립~준공) | D25: Years | E25: =((YEAR($E$16)-YEAR($E$8))*12+MONTH($E$16)-MONTH($E$8)+1)/12 -> 5
B26: 리츠운용기간(운영개시~청산) | D26: Years | E26: =((YEAR($E$24)-YEAR($E$18))*12+MONTH($E$24)-MONTH($E$18)+1)/12 -> 5.25
A28: Results
B30: IRR On Equity (보통주) | E30: =②시니어_CF!$C$171 -> -0.1050309
B31: IRR On Equity (우선주) | E31: =②시니어_CF!$C$172 -> -0.14547119
B32: IRR On Equity (전체) | E32: =②시니어_CF!$C$173 -> -0.12979711
A34: Vehicle 설정 (용도별 포함여부: 1=포함, 0=제외)
B36: 구분 | C36: 항목 | D36: 시니어 레지던스 | E36: 레지던스 | F36: 호텔 | G36: 오피스 | H36: 부대시설 | I36: Vehicle 합계/비율
B37: Vehicle명 | C37: ② 시니어 레지던스 Vehicle
B38: 포함여부 | C38: 1 / 0 | D38: 1 | E38: 0 | F38: 0 | G38: 0 | H38: 0
B39: 연면적 | C39: 평 | D39: =$E$60 -> 23008.174 | E39: =$E$61 -> 13519.908 | F39: =$E$62 -> 21288.226 | G39: =$E$63 -> 14046.004 | H39: =$E$64 -> 9949.1131 | I39: =SUMPRODUCT(D38:H38,D39:H39) -> 23008.174
C40: 시니어 포함 연면적 | I40: =$D$38*$E$60 -> 23008.174
C41: 연면적 비중(전체 대비) | I41: =$I$39/$C$69 -> 0.28123425
B42: 토지 지분 | C42: Ratio | D42: =$C$85 -> 0.28123425 | E42: =$C$86 -> 0.16525697 | F42: =$C$87 -> 0.26021092 | G42: =$C$88 -> 0.17168756 | H42: =$C$89 -> 0.12161031 | I42: =SUMPRODUCT(D38:H38,D42:H42) -> 0.28123425
C43: 분양홍보비 지분 | I43: =IFERROR(SUMPRODUCT($D$38:$H$38,$P$325:$T$325)/SUM($P$325:$T$325),0) -> 0.33333333
C44: 보존등기비 지분(건물분 취득세 기준) | I44: =IFERROR(SUMPRODUCT($D$38:$H$38,$P$323:$T$323)/SUM($P$323:$T$323),0) -> 0.22102942
C45: 리츠 고정비 적용비율 | I45: 1
B46: ※ 토지비·공사비·보증금·운영수입·담보대출은 포함 용도만 반영, 리츠 고정비는 Vehicle별로 별도 발생, VAT 공통공제비율은 Vehicle 내 과세면적 비중으로 재계산
A48: 사업개요
B50: (1) 사 업 명 | D50: 센텀C부지 복합개발사업
B51: (2) 대 지 위 치 | D51: 부산광역시 해운대 우동 1492
B52: (3) 지 역 지 구 | D52: 중심상업지역/지구단위계획구역
B53: (4) 용 도 | D53: 관광숙박시설(호텔, 콘도), 노유자시설(시니어레지던스), 문화집회시설(공연장 등), 판매시설
B54: (5) 건축연면적 | E54: 평 환산계수 | F54: 0.3025
B56: 연면적 | C56: 지상연면적 | D56: 178919.43 | E56: =$D$56*$F$54 -> 54123.128
C57: 지하연면적 | D57: 91531.54 | E57: =$D$57*$F$54 -> 27688.291
C58: 전체연면적 | D58: =$D$56+$D$57 -> 270450.97 | E58: =$D$58*$F$54 -> 81811.418 | F58: =ABS($D$58-$C$70)<1 -> TRUE | G58: =ABS($D$58*$F$54-$C$69)<1 -> TRUE
B60: 용도별 연면적 | C60: 시니어 레지던스 | D60: =SUMIF($D$67:$W$67,"시니어 레지던스",$D$70:$W$70) -> 76060.08 | E60: =SUMIF($D$67:$W$67,"시니어 레지던스",$D$69:$W$69) -> 23008.174
C61: 레지던스 | D61: =SUMIF($D$67:$W$67,"레지던스",$D$70:$W$70) -> 44693.91 | E61: =SUMIF($D$67:$W$67,"레지던스",$D$69:$W$69) -> 13519.908
C62: 호텔 | D62: =SUMIF($D$67:$W$67,"호텔",$D$70:$W$70) -> 70374.3 | E62: =SUMIF($D$67:$W$67,"호텔",$D$69:$W$69) -> 21288.226
C63: 오피스 | D63: =SUMIF($D$67:$W$67,"오피스",$D$70:$W$70) -> 46433.07 | E63: =SUMIF($D$67:$W$67,"오피스",$D$69:$W$69) -> 14046.004
C64: 부대시설 | D64: =SUMIF($D$67:$W$67,"부대시설",$D$70:$W$70) -> 32889.63 | E64: =SUMIF($D$67:$W$67,"부대시설",$D$69:$W$69) -> 9949.1131
C65: 합계 | D65: =SUM(D60:D64) -> 270450.99 | E65: =SUM(E60:E64) -> 81811.424 | F65: =ABS(D65-$D$58)<1 -> TRUE | G65: =ABS(E65-$C$69)<0.1 -> TRUE
D67: 시니어 레지던스 | E67: 시니어 레지던스 | F67: 부대시설 | G67: 부대시설 | H67: 시니어 레지던스 | J67: 레지던스 | K67: 레지던스 | L67: 호텔 | M67: 호텔 | N67: 호텔 | O67: 호텔 | P67: 호텔 | Q67: 호텔 | R67: 오피스 | S67: 호텔 | U67: 부대시설 | V67: 부대시설 | W67: 부대시설
B68: 구분 | C68: 총계 | D68: 시니어 | E68: 시니어 부대 | F68: 국제학교 | G68: 영어유치원 | H68: SSZ | I68: B동 계 | J68: 가족호텔 | K68: 가족호텔 부대 멤버전용 | L68: 호텔 | M68: 컨벤션 | N68: 호텔부대_피트니스&수영장 | O68: 호텔부대_파인다이닝 | P68: 호텔부대_휴게 | Q68: 호텔 BOH | R68: 오피스 | S68: SSZ | T68: A동 계 | U68: 메디컬 | V68: 스파2.0 | W68: 판매시설 | X68: 부대시설 계 | Y68: MEP | Z68: 주차장
B69: 연면적(평) | C69: =I69+T69+X69 -> 81811.424 | D69: =D70*$F$54 -> 20475.245 | E69: =E70*$F$54 -> 2338.198 | F69: =F70*$F$54 -> 1425.6281 | G69: =G70*$F$54 -> 597.16525 | H69: =H70*$F$54 -> 194.73135 | I69: =SUM(D69:H69) -> 25030.967 | J69: =J70*$F$54 -> 10714.913 | K69: =K70*$F$54 -> 2804.9948 | L69: =L70*$F$54 -> 11246.593 | M69: =M70*$F$54 -> 2165.776 | N69: =N70*$F$54 -> 1829.3446 | O69: =O70*$F$54 -> 1274.2329 | P69: =P70*$F$54 -> 1063.9651 | Q69: =Q70*$F$54 -> 3250.7679 | ... S69: =S70*$F$54 -> 457.54638 | T69: =SUM(J69:S69) -> 48854.137 | U69: =U70*$F$54 -> 1673.7446 | V69: =V70*$F$54 -> 2443.3318 | W69: =W70*$F$54 -> 3809.2434 | X69: =SUM(U69:W69) -> 7926.3198
B70: 연면적(㎡) | C70: =I70+T70+X70 -> 270450.99 | D70: 67686.76 | E70: 7729.58 | F70: 4712.82 | G70: 1974.1 | H70: 643.74 | I70: =SUM(D70:H70) -> 82747 | J70: 35421.2 | K70: 9272.71 | L70: 37178.82 | M70: 7159.59 | N70: 6047.42 | O70: 4212.34 | P70: 3517.24 | Q70: 10746.34 | R70: 46433.07 | S70: 1512.55 | T70: =SUM(J70:S70) -> 161501.28 | U70: 5533.04 | V70: 8077.13 | W70: 12592.54 | X70: =SUM(U70:W70) -> 26202.71
B71: 구성비 | C71: =C69/$C$69 -> 1 | D71: =D69/$C$69 -> 0.25027366 | E71: =E69/$C$69 -> 0.028580335 | F71: =F69/$C$69 -> 0.017425782 | G71: =G69/$C$69 -> 0.0072992892 | H71: =H69/$C$69 -> 0.0023802464 | I71: =I69/$C$69 -> 0.30595932 | J71: =J69/$C$69 -> 0.13097086 | ... X71: =X69/$C$69 -> 0.096885243
B72: 전용면적 | C72: =I72+T72+X72 -> 40534.76 | D72: 10848.89 | E72: 1218.17 | F72: 591.99 | G72: 213.87 | H72: 0 | I72: =SUM(D72:H72) -> 12872.92 | J72: 5174.57 | K72: 1462.29 | L72: 5186.06 | M72: 847 | N72: 910.53 | O72: 535.43 | P72: 514.25 | Q72: 1870.66 | R72: 7377.98 | S72: 0 | T72: =SUM(J72:S72) -> 23878.77 | U72: 948.64 | V72: 1270.5 | W72: 1563.93 | X72: =SUM(U72:W72) -> 3783.07
B73: 공용면적 | C73: =I73+T73+X73 -> 18313.26 | D73: 3879.26 | E73: 463.73 | F73: 433.48 | G73: 215.68 | H73: 140.07 | I73: =SUM(D73:H73) -> 5132.22 | J73: 2532.63 | K73: 555.39 | L73: 2903.78 | M73: 710.88 | N73: 405.35 | O73: 381.15 | P73: 251.08 | Q73: 467.67 | R73: 2725.53 | S73: 329.12 | T73: =SUM(J73:S73) -> 11262.58 | U73: 255.31 | V73: 487.03 | W73: 1176.12 | X73: =SUM(U73:W73) -> 1918.46
B74: 시설면적 | C74: =I74+T74+X74+Y74+Z74 -> 81811.424 | D74: =D72+D73 -> 14728.15 | E74: =E72+E73 -> 1681.9 | F74: =F72+F73 -> 1025.47 | G74: =G72+G73 -> 429.55 | H74: =H72+H73 -> 140.07 | I74: =SUM(D74:H74) -> 18005.14 | J74: =J72+J73 -> 7707.2 | K74: =K72+K73 -> 2017.68 | L74: =L72+L73 -> 8089.84 | M74: =M72+M73 -> 1557.88 | N74: =N72+N73 -> 1315.88 | O74: =O72+O73 -> 916.58 | P74: =P72+P73 -> 765.33 | Q74: =Q72+Q73 -> 2338.33 | ... S74: =S72+S73 -> 329.12 | T74: =SUM(J74:S74) -> 35141.35 | U74: =U72+U73 -> 1203.95 | V74: =V72+V73 -> 1757.53 | W74: =W72+W73 -> 2740.05 | X74: =SUM(U74:W74) -> 5701.53 | Y74: 1585.81 | Z74: =$C$69-($I$74+$T$74+$X$74)-$Y$74 -> 21377.594
B75: 구성비 | C75: =C74/$C$74 -> 1 | D75: =D74/$C$74 -> 0.18002559 | E75: =E74/$C$74 -> 0.020558253 | F75: =F74/$C$74 -> 0.012534557 | G75: =G74/$C$74 -> 0.0052504892 | H75: =H74/$C$74 -> 0.0017121081 | I75: =I74/$C$74 -> 0.220081 | J75: =J74/$C$74 -> 0.094206892 | ... Z75: =Z74/$C$74 -> 0.26130329
B76: 주차장 배분 | C76: =I76+T76+X76 -> 21377.594 | D76: =$Z$74*D74/($I$74+$T$74+$X$74) -> 5350.2636 | E76: =$Z$74*E74/($I$74+$T$74+$X$74) -> 610.98022 | F76: =$Z$74*F74/($I$74+$T$74+$X$74) -> 372.5203 | G76: =$Z$74*G74/($I$74+$T$74+$X$74) -> 156.04171 | H76: =$Z$74*H74/($I$74+$T$74+$X$74) -> 50.88293 | I76: =SUM(D76:H76) -> 6540.6887 | J76: =$Z$74*J74/($I$74+$T$74+$X$74) -> 2799.7781 | K76: =$Z$74*K74/($I$74+$T$74+$X$74) -> 732.9583 | L76: =$Z$74*L74/($I$74+$T$74+$X$74) -> 2938.7789 | M76: =$Z$74*M74/($I$74+$T$74+$X$74) -> 565.92774 | N76: =$Z$74*N74/($I$74+$T$74+$X$74) -> 478.01692 | O76: =$Z$74*O74/($I$74+$T$74+$X$74) -> 332.96406 | P76: =$Z$74*P74/($I$74+$T$74+$X$74) -> 278.01979 | Q76: =$Z$74*Q74/($I$74+$T$74+$X$74) -> 849.44014 | ... S76: =$Z$74*S74/($I$74+$T$74+$X$74) -> 119.55872 | T76: =SUM(J76:S76) -> 12765.723 | U76: =$Z$74*U74/($I$74+$T$74+$X$74) -> 437.35634 | V76: =$Z$74*V74/($I$74+$T$74+$X$74) -> 638.45417 | W76: =$Z$74*W74/($I$74+$T$74+$X$74) -> 995.37211 | X76: =SUM(U76:W76) -> 2071.1826
B77: 기계실 배분 | C77: =I77+T77+X77 -> 1585.81 | D77: =$Y$74*D74/($I$74+$T$74+$X$74) -> 396.88757 | E77: =$Y$74*E74/($I$74+$T$74+$X$74) -> 45.323085 | F77: =$Y$74*F74/($I$74+$T$74+$X$74) -> 27.633905 | G77: =$Y$74*G74/($I$74+$T$74+$X$74) -> 11.57532 | H77: =$Y$74*H74/($I$74+$T$74+$X$74) -> 3.7745434 | I77: =SUM(D77:H77) -> 485.19442 | J77: =$Y$74*J74/($I$74+$T$74+$X$74) -> 207.69016 | K77: =$Y$74*K74/($I$74+$T$74+$X$74) -> 54.371534 | L77: =$Y$74*L74/($I$74+$T$74+$X$74) -> 218.00137 | M77: =$Y$74*M74/($I$74+$T$74+$X$74) -> 41.98105 | N77: =$Y$74*N74/($I$74+$T$74+$X$74) -> 35.459743 | O77: =$Y$74*O74/($I$74+$T$74+$X$74) -> 24.699586 | P77: =$Y$74*P74/($I$74+$T$74+$X$74) -> 20.623769 | Q77: =$Y$74*Q74/($I$74+$T$74+$X$74) -> 63.012266 | ... S77: =$Y$74*S74/($I$74+$T$74+$X$74) -> 8.8689779 | T77: =SUM(J77:S77) -> 946.97331 | U77: =$Y$74*U74/($I$74+$T$74+$X$74) -> 32.443504 | V77: =$Y$74*V74/($I$74+$T$74+$X$74) -> 47.361129 | W77: =$Y$74*W74/($I$74+$T$74+$X$74) -> 73.837636 | X77: =SUM(U77:W77) -> 153.64227
B78: 전체 공용면적 | C78: =I78+T78+X78 -> 41276.664 | D78: =D73+D76+D77 -> 9626.4111 | E78: =E73+E76+E77 -> 1120.0333 | F78: =F73+F76+F77 -> 833.6342 | G78: =G73+G76+G77 -> 383.29703 | H78: =H73+H76+H77 -> 194.72747 | I78: =SUM(D78:H78) -> 12158.103 | J78: =J73+J76+J77 -> 5540.0982 | K78: =K73+K76+K77 -> 1342.7198 | L78: =L73+L76+L77 -> 6060.5603 | M78: =M73+M76+M77 -> 1318.7888 | N78: =N73+N76+N77 -> 918.82666 | O78: =O73+O76+O77 -> 738.81364 | P78: =P73+P76+P77 -> 549.72356 | Q78: =Q73+Q76+Q77 -> 1380.1224 | ... S78: =S73+S76+S77 -> 457.5477 | T78: =SUM(J78:S78) -> 24975.276 | U78: =U73+U76+U77 -> 725.10985 | V78: =V73+V76+V77 -> 1172.8453 | W78: =W73+W76+W77 -> 2245.3297 | X78: =SUM(U78:W78) -> 4143.2849
B79: 전용률 | C79: =C72/C69 -> 0.49546576 | D79: =IF(D69=0,0,D72/D69) -> 0.52985398 | E79: =IF(E69=0,0,E72/E69) -> 0.52098669 | F79: =IF(F69=0,0,F72/F69) -> 0.41524856 | G79: =IF(G69=0,0,G72/G69) -> 0.35814207 | H79: =IF(H69=0,0,H72/H69) -> 0 | I79: =IF(I69=0,0,I72/I69) -> 0.51427976 | J79: =IF(J69=0,0,J72/J69) -> 0.48293159 | K79: =IF(K69=0,0,K72/K69) -> 0.52131648 | ... X79: =IF(X69=0,0,X72/X69) -> 0.47727951
B80: 비고 | D80: 270세대 | J80: 92세대 | L80: 257실
B82: (6) 대지면적 | D82: 16515 | E82: =$D$82*$F$54 -> 4995.7875
B84: 구분 | C84: Ratio | D84: 토지면적(㎡) | E84: 토지면적(평)
B85: 시니어 레지던스 | C85: =$E$60/$C$69 -> 0.28123425 | D85: =C85*$D$82 -> 4644.5836 | E85: =C85*$E$82 -> 1404.9865
B86: 서비스드 레지던스 | C86: =$E$61/$C$69 -> 0.16525697 | D86: =C86*$D$82 -> 2729.2188 | E86: =C86*$E$82 -> 825.58868
B87: 호텔 | C87: =$E$62/$C$69 -> 0.26021092 | D87: =C87*$D$82 -> 4297.3833 | E87: =C87*$E$82 -> 1299.9584
B88: 오피스 | C88: =$E$63/$C$69 -> 0.17168756 | D88: =C88*$D$82 -> 2835.42 | E88: =C88*$E$82 -> 857.71456
B89: 부대시설 | C89: =$E$64/$C$69 -> 0.12161031 | D89: =C89*$D$82 -> 2008.3943 | E89: =C89*$E$82 -> 607.53929
B90: 합계 | C90: =SUM(C85:C89) -> 1 | D90: =SUM(D85:D89) -> 16515 | E90: =SUM(E85:E89) -> 4995.7875
A92: Operation
B93: ※ 운영기간 시계열(Index: 운영기간 누적, 입주모집률, OCC, 공실률, 리징비용, 상승률 등)은 CF 시트에서 월별로 계산
A95: 시니어 레지던스
B96: 운영수입 | C96: 세대수 | D96: 세대 | E96: 270 | G96: 보증금 | H96: 일자 | I96: 비중 | J96: 월Key
C97: 보증금 | D97: 백만원/세대 | E97: 2000 | G97: 계약금 | H97: 46477 | I97: 0.1 | J97: =EOMONTH(H97,0) -> 46477
C98: 보증금(100% 기준) | D98: 백만원 | E98: =$E$96*$E$97 -> 540000 | G98: 중도금(1차) | H98: 46842 | I98: 0.2 | J98: =EOMONTH(H98,0) -> 46843
C99: 월임대료 | D99: 천원/세대,월 | E99: 0 | G99: 중도금(2차) | H99: 47208 | I99: 0.2 | J99: =EOMONTH(H99,0) -> 47208
C100: 이용료수익 | D100: 천원/세대,월 | E100: 6000 | G100: 중도금(3차) | H100: 47573 | I100: 0.2 | J100: =EOMONTH(H100,0) -> 47573
C101: 보증금 및 임대료상승률 | D101: % | E101: 0.02 | G101: 잔금 | H101: 47938 | I101: 0.3 | J101: =EOMONTH(H101,0) -> 47938
C102: 보증금 및 임대료상승주기 | D102: 개월 | E102: 12 | G102: 합계 | I102: =SUM(I97:I101) -> 1
C103: 물가상승률 | D103: % | E103: 0.02
C104: 입주모집률 | D104: Y+1 | E104: 0.8
D105: Y+2 | E105: 1
D106: Y+3 이후 | E106: 1
C107: 추가수입(세대관리비등) | D107: 매출액 대비 | E107: 0.15
B108: 운영비용 | C108: ADR | D108: 천원/일 | E108: 200
C109: OCC | D109: % | E109: 0.9
C110: 일반운영비 | D110: 매출대비 % | E110: 0.75
C111: 소모품비 | D111: 매출대비 % | E111: 0.04
A113: 시니어 부대시설
B114: 운영수입 | C114: 보증금 | D114: 백만원 | E114: 1500
C115: 월임대료(전용면적당) | D115: 천원/평,월 | E115: 120
C116: 전용면적 | D116: 평 | E116: =$E$72 -> 1218.17
...

Sheet ②시니어_CF
A1: 월별 현금흐름 (CF) — 단위: 백만원
A3: ※ 월말 기준. 모든 입력은 Assumption 시트 연결. C열 = 기간 합계(잔액행은 최대값/최종값, IRR행은 연환산 IRR)
A5: 구분 | B5: 단위 | C5: 합계
A6: 월말일자 | E6: =EOMONTH(②시니어_가정!$E$8,0) -> 46112 | F6: =EOMONTH(E6,1) -> 46142 | G6: =EOMONTH(F6,1) -> 46173 | H6: =EOMONTH(G6,1) -> 46203 | I6: =EOMONTH(H6,1) -> 46234 | J6: =EOMONTH(I6,1) -> 46265 | K6: =EOMONTH(J6,1) -> 46295 | L6: =EOMONTH(K6,1) -> 46326 | M6: =EOMONTH(L6,1) -> 46356 | ... EF6: =EOMONTH(EE6,1) -> 50099
A7: 연도 | E7: =YEAR(E6) -> 2026 | F7: =YEAR(F6) -> 2026 | G7: =YEAR(G6) -> 2026 | H7: =YEAR(H6) -> 2026 | I7: =YEAR(I6) -> 2026 | J7: =YEAR(J6) -> 2026 | K7: =YEAR(K6) -> 2026 | L7: =YEAR(L6) -> 2026 | ... EF7: =YEAR(EF6) -> 2037
A8: 월차 | E8: =1 -> 1 | F8: =E8+1 -> 2 | G8: =F8+1 -> 3 | H8: =G8+1 -> 4 | I8: =H8+1 -> 5 | J8: =I8+1 -> 6 | K8: =J8+1 -> 7 | L8: =K8+1 -> 8 | M8: =L8+1 -> 9 | ... EF8: =EE8+1 -> 132
A9: 모델기간 Flag | E9: =IF(E6<=②시니어_가정!$E$24,1,0) -> 1 | F9: =IF(F6<=②시니어_가정!$E$24,1,0) -> 1 | G9: =IF(G6<=②시니어_가정!$E$24,1,0) -> 1 | H9: =IF(H6<=②시니어_가정!$E$24,1,0) -> 1 | I9: =IF(I6<=②시니어_가정!$E$24,1,0) -> 1 | J9: =IF(J6<=②시니어_가정!$E$24,1,0) -> 1 | K9: =IF(K6<=②시니어_가정!$E$24,1,0) -> 1 | L9: =IF(L6<=②시니어_가정!$E$24,1,0) -> 1 | ... EF9: =IF(EF6<=②시니어_가정!$E$24,1,0) -> 0
A10: 개발기간 Flag(설립~준공) | E10: =IF(E6<=②시니어_가정!$E$16,1,0) -> 1 | F10: =IF(F6<=②시니어_가정!$E$16,1,0) -> 1 | G10: =IF(G6<=②시니어_가정!$E$16,1,0) -> 1 | H10: =IF(H6<=②시니어_가정!$E$16,1,0) -> 1 | I10: =IF(I6<=②시니어_가정!$E$16,1,0) -> 1 | J10: =IF(J6<=②시니어_가정!$E$16,1,0) -> 1 | K10: =IF(K6<=②시니어_가정!$E$16,1,0) -> 1 | L10: =IF(L6<=②시니어_가정!$E$16,1,0) -> 1 | ... EF10: =IF(EF6<=②시니어_가정!$E$16,1,0) -> 0
A11: 공사기간 Flag | E11: =IF(AND(E6>=②시니어_가정!$E$14,E6<=②시니어_가정!$E$16),1,0) -> 0 | F11: =IF(AND(F6>=②시니어_가정!$E$14,F6<=②시니어_가정!$E$16),1,0) -> 0 | G11: =IF(AND(G6>=②시니어_가정!$E$14,G6<=②시니어_가정!$E$16),1,0) -> 0 | H11: =IF(AND(H6>=②시니어_가정!$E$14,H6<=②시니어_가정!$E$16),1,0) -> 0 | I11: =IF(AND(I6>=②시니어_가정!$E$14,I6<=②시니어_가정!$E$16),1,0) -> 0 | J11: =IF(AND(J6>=②시니어_가정!$E$14,J6<=②시니어_가정!$E$16),1,0) -> 0 | K11: =IF(AND(K6>=②시니어_가정!$E$14,K6<=②시니어_가정!$E$16),1,0) -> 0 | L11: =IF(AND(L6>=②시니어_가정!$E$14,L6<=②시니어_가정!$E$16),1,0) -> 0 | ... EF11: =IF(AND(EF6>=②시니어_가정!$E$14,EF6<=②시니어_가정!$E$16),1,0) -> 0
A12: 공사 월차 | E12: =IF(E11=1,(YEAR(E6)-YEAR(②시니어_가정!$E$14))*12+MONTH(E6)-MONTH(②시니어_가정!$E$14)+1,0) -> 0 | F12: =IF(F11=1,(YEAR(F6)-YEAR(②시니어_가정!$E$14))*12+MONTH(F6)-MONTH(②시니어_가정!$E$14)+1,0) -> 0 | G12: =IF(G11=1,(YEAR(G6)-YEAR(②시니어_가정!$E$14))*12+MONTH(G6)-MONTH(②시니어_가정!$E$14)+1,0) -> 0 | H12: =IF(H11=1,(YEAR(H6)-YEAR(②시니어_가정!$E$14))*12+MONTH(H6)-MONTH(②시니어_가정!$E$14)+1,0) -> 0 | I12: =IF(I11=1,(YEAR(I6)-YEAR(②시니어_가정!$E$14))*12+MONTH(I6)-MONTH(②시니어_가정!$E$14)+1,0) -> 0 | J12: =IF(J11=1,(YEAR(J6)-YEAR(②시니어_가정!$E$14))*12+MONTH(J6)-MONTH(②시니어_가정!$E$14)+1,0) -> 0 | K12: =IF(K11=1,(YEAR(K6)-YEAR(②시니어_가정!$E$14))*12+MONTH(K6)-MONTH(②시니어_가정!$E$14)+1,0) -> 0 | L12: =IF(L11=1,(YEAR(L6)-YEAR(②시니어_가정!$E$14))*12+MONTH(L6)-MONTH(②시니어_가정!$E$14)+1,0) -> 0 | ... EF12: =IF(EF11=1,(YEAR(EF6)-YEAR(②시니어_가정!$E$14))*12+MONTH(EF6)-MONTH(②시니어_가정!$E$14)+1,0) -> 0
A13: S-curve 집행률 | B13: % | C13: =SUM(E13:EF13) -> 1 | E13: =IF(E12>0,(COS(PI()*(E12-1)/②시니어_가정!$E$15)-COS(PI()*E12/②시니어_가정!$E$15))/2,0) -> 0 | F13: =IF(F12>0,(COS(PI()*(F12-1)/②시니어_가정!$E$15)-COS(PI()*F12/②시니어_가정!$E$15))/2,0) -> 0 | G13: =IF(G12>0,(COS(PI()*(G12-1)/②시니어_가정!$E$15)-COS(PI()*G12/②시니어_가정!$E$15))/2,0) -> 0 | H13: =IF(H12>0,(COS(PI()*(H12-1)/②시니어_가정!$E$15)-COS(PI()*H12/②시니어_가정!$E$15))/2,0) -> 0 | I13: =IF(I12>0,(COS(PI()*(I12-1)/②시니어_가정!$E$15)-COS(PI()*I12/②시니어_가정!$E$15))/2,0) -> 0 | J13: =IF(J12>0,(COS(PI()*(J12-1)/②시니어_가정!$E$15)-COS(PI()*J12/②시니어_가정!$E$15))/2,0) -> 0 | K13: =IF(K12>0,(COS(PI()*(K12-1)/②시니어_가정!$E$15)-COS(PI()*K12/②시니어_가정!$E$15))/2,0) -> 0 | L13: =IF(L12>0,(COS(PI()*(L12-1)/②시니어_가정!$E$15)-COS(PI()*L12/②시니어_가정!$E$15))/2,0) -> 0 | ... EF13: =IF(EF12>0,(COS(PI()*(EF12-1)/②시니어_가정!$E$15)-COS(PI()*EF12/②시니어_가정!$E$15))/2,0) -> 0
A14: 운영기간 Flag | E14: =IF(AND(E6>=②시니어_가정!$E$18,E6<=②시니어_가정!$E$20),1,0) -> 0 | F14: =IF(AND(F6>=②시니어_가정!$E$18,F6<=②시니어_가정!$E$20),1,0) -> 0 | G14: =IF(AND(G6>=②시니어_가정!$E$18,G6<=②시니어_가정!$E$20),1,0) -> 0 | H14: =IF(AND(H6>=②시니어_가정!$E$18,H6<=②시니어_가정!$E$20),1,0) -> 0 | I14: =IF(AND(I6>=②시니어_가정!$E$18,I6<=②시니어_가정!$E$20),1,0) -> 0 | J14: =IF(AND(J6>=②시니어_가정!$E$18,J6<=②시니어_가정!$E$20),1,0) -> 0 | K14: =IF(AND(K6>=②시니어_가정!$E$18,K6<=②시니어_가정!$E$20),1,0) -> 0 | L14: =IF(AND(L6>=②시니어_가정!$E$18,L6<=②시니어_가정!$E$20),1,0) -> 0 | ... EF14: =IF(AND(EF6>=②시니어_가정!$E$18,EF6<=②시니어_가정!$E$20),1,0) -> 0
A15: 운영 월차 | E15: =IF(E14=1,(YEAR(E6)-YEAR(②시니어_가정!$E$18))*12+MONTH(E6)-MONTH(②시니어_가정!$E$18)+1,0) -> 0 | F15: =IF(F14=1,(YEAR(F6)-YEAR(②시니어_가정!$E$18))*12+MONTH(F6)-MONTH(②시니어_가정!$E$18)+1,0) -> 0 | G15: =IF(G14=1,(YEAR(G6)-YEAR(②시니어_가정!$E$18))*12+MONTH(G6)-MONTH(②시니어_가정!$E$18)+1,0) -> 0 | H15: =IF(H14=1,(YEAR(H6)-YEAR(②시니어_가정!$E$18))*12+MONTH(H6)-MONTH(②시니어_가정!$E$18)+1,0) -> 0 | I15: =IF(I14=1,(YEAR(I6)-YEAR(②시니어_가정!$E$18))*12+MONTH(I6)-MONTH(②시니어_가정!$E$18)+1,0) -> 0 | J15: =IF(J14=1,(YEAR(J6)-YEAR(②시니어_가정!$E$18))*12+MONTH(J6)-MONTH(②시니어_가정!$E$18)+1,0) -> 0 | K15: =IF(K14=1,(YEAR(K6)-YEAR(②시니어_가정!$E$18))*12+MONTH(K6)-MONTH(②시니어_가정!$E$18)+1,0) -> 0 | L15: =IF(L14=1,(YEAR(L6)-YEAR(②시니어_가정!$E$18))*12+MONTH(L6)-MONTH(②시니어_가정!$E$18)+1,0) -> 0 | ... EF15: =IF(EF14=1,(YEAR(EF6)-YEAR(②시니어_가정!$E$18))*12+MONTH(EF6)-MONTH(②시니어_가정!$E$18)+1,0) -> 0
A16: 운영 연차 | E16: =IF(E15>0,INT((E15-1)/12)+1,0) -> 0 | F16: =IF(F15>0,INT((F15-1)/12)+1,0) -> 0 | G16: =IF(G15>0,INT((G15-1)/12)+1,0) -> 0 | H16: =IF(H15>0,INT((H15-1)/12)+1,0) -> 0 | I16: =IF(I15>0,INT((I15-1)/12)+1,0) -> 0 | J16: =IF(J15>0,INT((J15-1)/12)+1,0) -> 0 | K16: =IF(K15>0,INT((K15-1)/12)+1,0) -> 0 | L16: =IF(L15>0,INT((L15-1)/12)+1,0) -> 0 | ... EF16: =IF(EF15>0,INT((EF15-1)/12)+1,0) -> 0
A17: 리츠운용기간 Flag(운영개시~청산) | E17: =IF(AND(E6>=②시니어_가정!$E$18,E6<=②시니어_가정!$E$24),1,0) -> 0 | F17: =IF(AND(F6>=②시니어_가정!$E$18,F6<=②시니어_가정!$E$24),1,0) -> 0 | G17: =IF(AND(G6>=②시니어_가정!$E$18,G6<=②시니어_가정!$E$24),1,0) -> 0 | H17: =IF(AND(H6>=②시니어_가정!$E$18,H6<=②시니어_가정!$E$24),1,0) -> 0 | I17: =IF(AND(I6>=②시니어_가정!$E$18,I6<=②시니어_가정!$E$24),1,0) -> 0 | J17: =IF(AND(J6>=②시니어_가정!$E$18,J6<=②시니어_가정!$E$24),1,0) -> 0 | K17: =IF(AND(K6>=②시니어_가정!$E$18,K6<=②시니어_가정!$E$24),1,0) -> 0 | L17: =IF(AND(L6>=②시니어_가정!$E$18,L6<=②시니어_가정!$E$24),1,0) -> 0 | ... EF17: =IF(AND(EF6>=②시니어_가정!$E$18,EF6<=②시니어_가정!$E$24),1,0) -> 0
A18: 일수 | B18: 일 | E18: =DAY(E6) -> 31 | F18: =DAY(F6) -> 30 | G18: =DAY(G6) -> 31 | H18: =DAY(H6) -> 30 | I18: =DAY(I6) -> 31 | J18: =DAY(J6) -> 31 | K18: =DAY(K6) -> 30 | L18: =DAY(L6) -> 31 | ... EF18: =DAY(EF6) -> 28
A20: 운영수입
A21: 시니어 레지던스 이용료·임대료 | B21: 백만원 | C21: =SUM(E21:EF21) -> 97278.541 | E21: =(E14=1)*②시니어_가정!$D$38*②시니어_가정!$E$96*CHOOSE(MIN(MAX(E16,1),3),②시니어_가정!$E$104,②시니어_가정!$E$105,②시니어_가정!$E$106)*(②시니어_가정!$E$100+②시니어_가정!$E$99)/1000*(1+②시니어_가정!$E$101)^INT((E15-1)/②시니어_가정!$E$102) -> 0 | F21: =(F14=1)*②시니어_가정!$D$38*②시니어_가정!$E$96*CHOOSE(MIN(MAX(F16,1),3),②시니어_가정!$E$104,②시니어_가정!$E$105,②시니어_가정!$E$106)*(②시니어_가정!$E$100+②시니어_가정!$E$99)/1000*(1+②시니어_가정!$E$101)^INT((F15-1)/②시니어_가정!$E$102) -> 0 | G21: =(G14=1)*②시니어_가정!$D$38*②시니어_가정!$E$96*CHOOSE(MIN(MAX(G16,1),3),②시니어_가정!$E$104,②시니어_가정!$E$105,②시니어_가정!$E$106)*(②시니어_가정!$E$100+②시니어_가정!$E$99)/1000*(1+②시니어_가정!$E$101)^INT((G15-1)/②시니어_가정!$E$102) -> 0 | H21: =(H14=1)*②시니어_가정!$D$38*②시니어_가정!$E$96*CHOOSE(MIN(MAX(H16,1),3),②시니어_가정!$E$104,②시니어_가정!$E$105,②시니어_가정!$E$106)*(②시니어_가정!$E$100+②시니어_가정!$E$99)/1000*(1+②시니어_가정!$E$101)^INT((H15-1)/②시니어_가정!$E$102) -> 0 | I21: =(I14=1)*②시니어_가정!$D$38*②시니어_가정!$E$96*CHOOSE(MIN(MAX(I16,1),3),②시니어_가정!$E$104,②시니어_가정!$E$105,②시니어_가정!$E$106)*(②시니어_가정!$E$100+②시니어_가정!$E$99)/1000*(1+②시니어_가정!$E$101)^INT((I15-1)/②시니어_가정!$E$102) -> 0 | J21: =(J14=1)*②시니어_가정!$D$38*②시니어_가정!$E$96*CHOOSE(MIN(MAX(J16,1),3),②시니어_가정!$E$104,②시니어_가정!$E$105,②시니어_가정!$E$106)*(②시니어_가정!$E$100+②시니어_가정!$E$99)/1000*(1+②시니어_가정!$E$101)^INT((J15-1)/②시니어_가정!$E$102) -> 0 | K21: =(K14=1)*②시니어_가정!$D$38*②시니어_가정!$E$96*CHOOSE(MIN(MAX(K16,1),3),②시니어_가정!$E$104,②시니어_가정!$E$105,②시니어_가정!$E$106)*(②시니어_가정!$E$100+②시니어_가정!$E$99)/1000*(1+②시니어_가정!$E$101)^INT((K15-1)/②시니어_가정!$E$102) -> 0 | L21: =(L14=1)*②시니어_가정!$D$38*②시니어_가정!$E$96*CHOOSE(MIN(MAX(L16,1),3),②시니어_가정!$E$104,②시니어_가정!$E$105,②시니어_가정!$E$106)*(②시니어_가정!$E$100+②시니어_가정!$E$99)/1000*(1+②시니어_가정!$E$101)^INT((L15-1)/②시니어_가정!$E$102) -> 0 | ... EF21: =(EF14=1)*②시니어_가정!$D$38*②시니어_가정!$E$96*CHOOSE(MIN(MAX(EF16,1),3),②시니어_가정!$E$104,②시니어_가정!$E$105,②시니어_가정!$E$106)*(②시니어_가정!$E$100+②시니어_가정!$E$99)/1000*(1+②시니어_가정!$E$101)^INT((EF15-1)/②시니어_가정!$E$102) -> 0
A22: 시니어 추가수입(세대관리비 등) | B22: 백만원 | C22: =SUM(E22:EF22) -> 14591.781 | E22: =E21*②시니어_가정!$E$107 -> 0 | F22: =F21*②시니어_가정!$E$107 -> 0 | G22: =G21*②시니어_가정!$E$107 -> 0 | H22: =H21*②시니어_가정!$E$107 -> 0 | I22: =I21*②시니어_가정!$E$107 -> 0 | J22: =J21*②시니어_가정!$E$107 -> 0 | K22: =K21*②시니어_가정!$E$107 -> 0 | L22: =L21*②시니어_가정!$E$107 -> 0 | ... EF22: =EF21*②시니어_가정!$E$107 -> 0
A23: 시니어 부대시설 임대료 | B23: 백만원 | C23: =SUM(E23:EF23) -> 9128.7441 | E23: =(E14=1)*②시니어_가정!$D$38*②시니어_가정!$E$115*②시니어_가정!$E$116/1000*(1+②시니어_가정!$E$118)^INT((E15-1)/②시니어_가정!$E$119) -> 0 | F23: =(F14=1)*②시니어_가정!$D$38*②시니어_가정!$E$115*②시니어_가정!$E$116/1000*(1+②시니어_가정!$E$118)^INT((F15-1)/②시니어_가정!$E$119) -> 0 | G23: =(G14=1)*②시니어_가정!$D$38*②시니어_가정!$E$115*②시니어_가정!$E$116/1000*(1+②시니어_가정!$E$118)^INT((G15-1)/②시니어_가정!$E$119) -> 0 | H23: =(H14=1)*②시니어_가정!$D$38*②시니어_가정!$E$115*②시니어_가정!$E$116/1000*(1+②시니어_가정!$E$118)^INT((H15-1)/②시니어_가정!$E$119) -> 0 | I23: =(I14=1)*②시니어_가정!$D$38*②시니어_가정!$E$115*②시니어_가정!$E$116/1000*(1+②시니어_가정!$E$118)^INT((I15-1)/②시니어_가정!$E$119) -> 0 | J23: =(J14=1)*②시니어_가정!$D$38*②시니어_가정!$E$115*②시니어_가정!$E$116/1000*(1+②시니어_가정!$E$118)^INT((J15-1)/②시니어_가정!$E$119) -> 0 | K23: =(K14=1)*②시니어_가정!$D$38*②시니어_가정!$E$115*②시니어_가정!$E$116/1000*(1+②시니어_가정!$E$118)^INT((K15-1)/②시니어_가정!$E$119) -> 0 | L23: =(L14=1)*②시니어_가정!$D$38*②시니어_가정!$E$115*②시니어_가정!$E$116/1000*(1+②시니어_가정!$E$118)^INT((L15-1)/②시니어_가정!$E$119) -> 0 | ... EF23: =(EF14=1)*②시니어_가정!$D$38*②시니어_가정!$E$115*②시니어_가정!$E$116/1000*(1+②시니어_가정!$E$118)^INT((EF15-1)/②시니어_가정!$E$119) -> 0
A24: 레지던스 객실매출 | B24: 백만원 | C24: =SUM(E24:EF24) -> 0 | E24: =(E14=1)*②시니어_가정!$E$38*②시니어_가정!$G$129*CHOOSE(MIN(MAX(E16,1),3),②시니어_가정!$E$136,②시니어_가정!$E$137,②시니어_가정!$E$138)*E18/1000000*(1+②시니어_가정!$E$132)^(MAX(E16,1)-1) -> 0 | F24: =(F14=1)*②시니어_가정!$E$38*②시니어_가정!$G$129*CHOOSE(MIN(MAX(F16,1),3),②시니어_가정!$E$136,②시니어_가정!$E$137,②시니어_가정!$E$138)*F18/1000000*(1+②시니어_가정!$E$132)^(MAX(F16,1)-1) -> 0 | G24: =(G14=1)*②시니어_가정!$E$38*②시니어_가정!$G$129*CHOOSE(MIN(MAX(G16,1),3),②시니어_가정!$E$136,②시니어_가정!$E$137,②시니어_가정!$E$138)*G18/1000000*(1+②시니어_가정!$E$132)^(MAX(G16,1)-1) -> 0 | H24: =(H14=1)*②시니어_가정!$E$38*②시니어_가정!$G$129*CHOOSE(MIN(MAX(H16,1),3),②시니어_가정!$E$136,②시니어_가정!$E$137,②시니어_가정!$E$138)*H18/1000000*(1+②시니어_가정!$E$132)^(MAX(H16,1)-1) -> 0 | I24: =(I14=1)*②시니어_가정!$E$38*②시니어_가정!$G$129*CHOOSE(MIN(MAX(I16,1),3),②시니어_가정!$E$136,②시니어_가정!$E$137,②시니어_가정!$E$138)*I18/1000000*(1+②시니어_가정!$E$132)^(MAX(I16,1)-1) -> 0 | J24: =(J14=1)*②시니어_가정!$E$38*②시니어_가정!$G$129*CHOOSE(MIN(MAX(J16,1),3),②시니어_가정!$E$136,②시니어_가정!$E$137,②시니어_가정!$E$138)*J18/1000000*(1+②시니어_가정!$E$132)^(MAX(J16,1)-1) -> 0 | K24: =(K14=1)*②시니어_가정!$E$38*②시니어_가정!$G$129*CHOOSE(MIN(MAX(K16,1),3),②시니어_가정!$E$136,②시니어_가정!$E$137,②시니어_가정!$E$138)*K18/1000000*(1+②시니어_가정!$E$132)^(MAX(K16,1)-1) -> 0 | L24: =(L14=1)*②시니어_가정!$E$38*②시니어_가정!$G$129*CHOOSE(MIN(MAX(L16,1),3),②시니어_가정!$E$136,②시니어_가정!$E$137,②시니어_가정!$E$138)*L18/1000000*(1+②시니어_가정!$E$132)^(MAX(L16,1)-1) -> 0 | ... EF24: =(EF14=1)*②시니어_가정!$E$38*②시니어_가정!$G$129*CHOOSE(MIN(MAX(EF16,1),3),②시니어_가정!$E$136,②시니어_가정!$E$137,②시니어_가정!$E$138)*EF18/1000000*(1+②시니어_가정!$E$132)^(MAX(EF16,1)-1) -> 0
A25: 레지던스 객실외매출 | B25: 백만원 | C25: =SUM(E25:EF25) -> 0 | E25: =E24*②시니어_가정!$E$139 -> 0 | F25: =F24*②시니어_가정!$E$139 -> 0 | G25: =G24*②시니어_가정!$E$139 -> 0 | H25: =H24*②시니어_가정!$E$139 -> 0 | I25: =I24*②시니어_가정!$E$139 -> 0 | J25: =J24*②시니어_가정!$E$139 -> 0 | K25: =K24*②시니어_가정!$E$139 -> 0 | L25: =L24*②시니어_가정!$E$139 -> 0 | ... EF25: =EF24*②시니어_가정!$E$139 -> 0
A26: 레지던스 멤버전용 매출 | B26: 백만원 | C26: =SUM(E26:EF26) -> 0 | E26: =E24*②시니어_가정!$E$144 -> 0 | F26: =F24*②시니어_가정!$E$144 -> 0 | G26: =G24*②시니어_가정!$E$144 -> 0 | H26: =H24*②시니어_가정!$E$144 -> 0 | I26: =I24*②시니어_가정!$E$144 -> 0 | J26: =J24*②시니어_가정!$E$144 -> 0 | K26: =K24*②시니어_가정!$E$144 -> 0 | L26: =L24*②시니어_가정!$E$144 -> 0 | ... EF26: =EF24*②시니어_가정!$E$144 -> 0
A27: 호텔 객실매출 | B27: 백만원 | C27: =SUM(E27:EF27) -> 0 | E27: =(E14=1)*②시니어_가정!$F$38*②시니어_가정!$E$148*②시니어_가정!$E$159*CHOOSE(MIN(MAX(E16,1),3),②시니어_가정!$E$160,②시니어_가정!$E$161,②시니어_가정!$E$162)*E18/1000000*(1+②시니어_가정!$E$155)^(MAX(E16,1)-1) -> 0 | F27: =(F14=1)*②시니어_가정!$F$38*②시니어_가정!$E$148*②시니어_가정!$E$159*CHOOSE(MIN(MAX(F16,1),3),②시니어_가정!$E$160,②시니어_가정!$E$161,②시니어_가정!$E$162)*F18/1000000*(1+②시니어_가정!$E$155)^(MAX(F16,1)-1) -> 0 | G27: =(G14=1)*②시니어_가정!$F$38*②시니어_가정!$E$148*②시니어_가정!$E$159*CHOOSE(MIN(MAX(G16,1),3),②시니어_가정!$E$160,②시니어_가정!$E$161,②시니어_가정!$E$162)*G18/1000000*(1+②시니어_가정!$E$155)^(MAX(G16,1)-1) -> 0 | H27: =(H14=1)*②시니어_가정!$F$38*②시니어_가정!$E$148*②시니어_가정!$E$159*CHOOSE(MIN(MAX(H16,1),3),②시니어_가정!$E$160,②시니어_가정!$E$161,②시니어_가정!$E$162)*H18/1000000*(1+②시니어_가정!$E$155)^(MAX(H16,1)-1) -> 0 | I27: =(I14=1)*②시니어_가정!$F$38*②시니어_가정!$E$148*②시니어_가정!$E$159*CHOOSE(MIN(MAX(I16,1),3),②시니어_가정!$E$160,②시니어_가정!$E$161,②시니어_가정!$E$162)*I18/1000000*(1+②시니어_가정!$E$155)^(MAX(I16,1)-1) -> 0 | J27: =(J14=1)*②시니어_가정!$F$38*②시니어_가정!$E$148*②시니어_가정!$E$159*CHOOSE(MIN(MAX(J16,1),3),②시니어_가정!$E$160,②시니어_가정!$E$161,②시니어_가정!$E$162)*J18/1000000*(1+②시니어_가정!$E$155)^(MAX(J16,1)-1) -> 0 | K27: =(K14=1)*②시니어_가정!$F$38*②시니어_가정!$E$148*②시니어_가정!$E$159*CHOOSE(MIN(MAX(K16,1),3),②시니어_가정!$E$160,②시니어_가정!$E$161,②시니어_가정!$E$162)*K18/1000000*(1+②시니어_가정!$E$155)^(MAX(K16,1)-1) -> 0 | L27: =(L14=1)*②시니어_가정!$F$38*②시니어_가정!$E$148*②시니어_가정!$E$159*CHOOSE(MIN(MAX(L16,1),3),②시니어_가정!$E$160,②시니어_가정!$E$161,②시니어_가정!$E$162)*L18/1000000*(1+②시니어_가정!$E$155)^(MAX(L16,1)-1) -> 0 | ... EF27: =(EF14=1)*②시니어_가정!$F$38*②시니어_가정!$E$148*②시니어_가정!$E$159*CHOOSE(MIN(MAX(EF16,1),3),②시니어_가정!$E$160,②시니어_가정!$E$161,②시니어_가정!$E$162)*EF18/1000000*(1+②시니어_가정!$E$155)^(MAX(EF16,1)-1) -> 0
A28: 호텔 객실외매출(식음) | B28: 백만원 | C28: =SUM(E28:EF28) -> 0 | E28: =E27*②시니어_가정!$E$163 -> 0 | F28: =F27*②시니어_가정!$E$163 -> 0 | G28: =G27*②시니어_가정!$E$163 -> 0 | H28: =H27*②시니어_가정!$E$163 -> 0 | I28: =I27*②시니어_가정!$E$163 -> 0 | J28: =J27*②시니어_가정!$E$163 -> 0 | K28: =K27*②시니어_가정!$E$163 -> 0 | L28: =L27*②시니어_가정!$E$163 -> 0 | ... EF28: =EF27*②시니어_가정!$E$163 -> 0
A29: 호텔 객실외매출(기타) | B29: 백만원 | C29: =SUM(E29:EF29) -> 0 | E29: =E27*②시니어_가정!$E$164 -> 0 | F29: =F27*②시니어_가정!$E$164 -> 0 | G29: =G27*②시니어_가정!$E$164 -> 0 | H29: =H27*②시니어_가정!$E$164 -> 0 | I29: =I27*②시니어_가정!$E$164 -> 0 | J29: =J27*②시니어_가정!$E$164 -> 0 | K29: =K27*②시니어_가정!$E$164 -> 0 | L29: =L27*②시니어_가정!$E$164 -> 0 | ... EF29: =EF27*②시니어_가정!$E$164 -> 0
A30: 컨벤션(연회장) | B30: 백만원 | C30: =SUM(E30:EF30) -> 0 | E30: =E27*②시니어_가정!$E$169 -> 0 | F30: =F27*②시니어_가정!$E$169 -> 0 | G30: =G27*②시니어_가정!$E$169 -> 0 | H30: =H27*②시니어_가정!$E$169 -> 0 | I30: =I27*②시니어_가정!$E$169 -> 0 | J30: =J27*②시니어_가정!$E$169 -> 0 | K30: =K27*②시니어_가정!$E$169 -> 0 | L30: =L27*②시니어_가정!$E$169 -> 0 | ... EF30: =EF27*②시니어_가정!$E$169 -> 0
A31: 스파&수영장&피트니스 | B31: 백만원 | C31: =SUM(E31:EF31) -> 0 | E31: =E27*②시니어_가정!$E$170 -> 0 | F31: =F27*②시니어_가정!$E$170 -> 0 | G31: =G27*②시니어_가정!$E$170 -> 0 | H31: =H27*②시니어_가정!$E$170 -> 0 | I31: =I27*②시니어_가정!$E$170 -> 0 | J31: =J27*②시니어_가정!$E$170 -> 0 | K31: =K27*②시니어_가정!$E$170 -> 0 | L31: =L27*②시니어_가정!$E$170 -> 0 | ... EF31: =EF27*②시니어_가정!$E$170 -> 0
A32: 파인다이닝/ADD | B32: 백만원 | C32: =SUM(E32:EF32) -> 0 | E32: =E27*②시니어_가정!$E$171 -> 0 | F32: =F27*②시니어_가정!$E$171 -> 0 | G32: =G27*②시니어_가정!$E$171 -> 0 | H32: =H27*②시니어_가정!$E$171 -> 0 | I32: =I27*②시니어_가정!$E$171 -> 0 | J32: =J27*②시니어_가정!$E$171 -> 0 | K32: =K27*②시니어_가정!$E$171 -> 0 | L32: =L27*②시니어_가정!$E$171 -> 0 | ... EF32: =EF27*②시니어_가정!$E$171 -> 0
A33: 휴게시설 | B33: 백만원 | C33: =SUM(E33:EF33) -> 0 | E33: =E27*②시니어_가정!$E$172 -> 0 | F33: =F27*②시니어_가정!$E$172 -> 0 | G33: =G27*②시니어_가정!$E$172 -> 0 | H33: =H27*②시니어_가정!$E$172 -> 0 | I33: =I27*②시니어_가정!$E$172 -> 0 | J33: =J27*②시니어_가정!$E$172 -> 0 | K33: =K27*②시니어_가정!$E$172 -> 0 | L33: =L27*②시니어_가정!$E$172 -> 0 | ... EF33: =EF27*②시니어_가정!$E$172 -> 0
A34: BOH | B34: 백만원 | C34: =SUM(E34:EF34) -> 0 | E34: =E33*②시니어_가정!$E$173 -> 0 | F34: =F33*②시니어_가정!$E$173 -> 0 | G34: =G33*②시니어_가정!$E$173 -> 0 | H34: =H33*②시니어_가정!$E$173 -> 0 | I34: =I33*②시니어_가정!$E$173 -> 0 | J34: =J33*②시니어_가정!$E$173 -> 0 | K34: =K33*②시니어_가정!$E$173 -> 0 | L34: =L33*②시니어_가정!$E$173 -> 0 | ... EF34: =EF33*②시니어_가정!$E$173 -> 0
A35: 오피스 임대료 | B35: 백만원 | C35: =SUM(E35:EF35) -> 0 | E35: =(E14=1)*②시니어_가정!$G$38*②시니어_가정!$E$183*②시니어_가정!$E$184/1000*(1+②시니어_가정!$E$186)^INT((E15-1)/②시니어_가정!$E$187)*(1-CHOOSE(MIN(MAX(E16,1),3),②시니어_가정!$E$189,②시니어_가정!$E$190,②시니어_가정!$E$191)) -> 0 | F35: =(F14=1)*②시니어_가정!$G$38*②시니어_가정!$E$183*②시니어_가정!$E$184/1000*(1+②시니어_가정!$E$186)^INT((F15-1)/②시니어_가정!$E$187)*(1-CHOOSE(MIN(MAX(F16,1),3),②시니어_가정!$E$189,②시니어_가정!$E$190,②시니어_가정!$E$191)) -> 0 | G35: =(G14=1)*②시니어_가정!$G$38*②시니어_가정!$E$183*②시니어_가정!$E$184/1000*(1+②시니어_가정!$E$186)^INT((G15-1)/②시니어_가정!$E$187)*(1-CHOOSE(MIN(MAX(G16,1),3),②시니어_가정!$E$189,②시니어_가정!$E$190,②시니어_가정!$E$191)) -> 0 | H35: =(H14=1)*②시니어_가정!$G$38*②시니어_가정!$E$183*②시니어_가정!$E$184/1000*(1+②시니어_가정!$E$186)^INT((H15-1)/②시니어_가정!$E$187)*(1-CHOOSE(MIN(MAX(H16,1),3),②시니어_가정!$E$189,②시니어_가정!$E$190,②시니어_가정!$E$191)) -> 0 | I35: =(I14=1)*②시니어_가정!$G$38*②시니어_가정!$E$183*②시니어_가정!$E$184/1000*(1+②시니어_가정!$E$186)^INT((I15-1)/②시니어_가정!$E$187)*(1-CHOOSE(MIN(MAX(I16,1),3),②시니어_가정!$E$189,②시니어_가정!$E$190,②시니어_가정!$E$191)) -> 0 | J35: =(J14=1)*②시니어_가정!$G$38*②시니어_가정!$E$183*②시니어_가정!$E$184/1000*(1+②시니어_가정!$E$186)^INT((J15-1)/②시니어_가정!$E$187)*(1-CHOOSE(MIN(MAX(J16,1),3),②시니어_가정!$E$189,②시니어_가정!$E$190,②시니어_가정!$E$191)) -> 0 | K35: =(K14=1)*②시니어_가정!$G$38*②시니어_가정!$E$183*②시니어_가정!$E$184/1000*(1+②시니어_가정!$E$186)^INT((K15-1)/②시니어_가정!$E$187)*(1-CHOOSE(MIN(MAX(K16,1),3),②시니어_가정!$E$189,②시니어_가정!$E$190,②시니어_가정!$E$191)) -> 0 | L35: =(L14=1)*②시니어_가정!$G$38*②시니어_가정!$E$183*②시니어_가정!$E$184/1000*(1+②시니어_가정!$E$186)^INT((L15-1)/②시니어_가정!$E$187)*(1-CHOOSE(MIN(MAX(L16,1),3),②시니어_가정!$E$189,②시니어_가정!$E$190,②시니어_가정!$E$191)) -> 0 | ... EF35: =(EF14=1)*②시니어_가정!$G$38*②시니어_가정!$E$183*②시니어_가정!$E$184/1000*(1+②시니어_가정!$E$186)^INT((EF15-1)/②시니어_가정!$E$187)*(1-CHOOSE(MIN(MAX(EF16,1),3),②시니어_가정!$E$189,②시니어_가정!$E$190,②시니어_가정!$E$191)) -> 0
A36: 메디컬 임대료 | B36: 백만원 | C36: =SUM(E36:EF36) -> 0 | E36: =(E14=1)*②시니어_가정!$H$38*②시니어_가정!$E$201*②시니어_가정!$E$202/1000*(1+②시니어_가정!$E$204)^INT((E15-1)/②시니어_가정!$E$205)*(1-CHOOSE(MIN(MAX(E16,1),3),②시니어_가정!$E$207,②시니어_가정!$E$208,②시니어_가정!$E$209)) -> 0 | F36: =(F14=1)*②시니어_가정!$H$38*②시니어_가정!$E$201*②시니어_가정!$E$202/1000*(1+②시니어_가정!$E$204)^INT((F15-1)/②시니어_가정!$E$205)*(1-CHOOSE(MIN(MAX(F16,1),3),②시니어_가정!$E$207,②시니어_가정!$E$208,②시니어_가정!$E$209)) -> 0 | G36: =(G14=1)*②시니어_가정!$H$38*②시니어_가정!$E$201*②시니어_가정!$E$202/1000*(1+②시니어_가정!$E$204)^INT((G15-1)/②시니어_가정!$E$205)*(1-CHOOSE(MIN(MAX(G16,1),3),②시니어_가정!$E$207,②시니어_가정!$E$208,②시니어_가정!$E$209)) -> 0 | H36: =(H14=1)*②시니어_가정!$H$38*②시니어_가정!$E$201*②시니어_가정!$E$202/1000*(1+②시니어_가정!$E$204)^INT((H15-1)/②시니어_가정!$E$205)*(1-CHOOSE(MIN(MAX(H16,1),3),②시니어_가정!$E$207,②시니어_가정!$E$208,②시니어_가정!$E$209)) -> 0 | I36: =(I14=1)*②시니어_가정!$H$38*②시니어_가정!$E$201*②시니어_가정!$E$202/1000*(1+②시니어_가정!$E$204)^INT((I15-1)/②시니어_가정!$E$205)*(1-CHOOSE(MIN(MAX(I16,1),3),②시니어_가정!$E$207,②시니어_가정!$E$208,②시니어_가정!$E$209)) -> 0 | J36: =(J14=1)*②시니어_가정!$H$38*②시니어_가정!$E$201*②시니어_가정!$E$202/1000*(1+②시니어_가정!$E$204)^INT((J15-1)/②시니어_가정!$E$205)*(1-CHOOSE(MIN(MAX(J16,1),3),②시니어_가정!$E$207,②시니어_가정!$E$208,②시니어_가정!$E$209)) -> 0 | K36: =(K14=1)*②시니어_가정!$H$38*②시니어_가정!$E$201*②시니어_가정!$E$202/1000*(1+②시니어_가정!$E$204)^INT((K15-1)/②시니어_가정!$E$205)*(1-CHOOSE(MIN(MAX(K16,1),3),②시니어_가정!$E$207,②시니어_가정!$E$208,②시니어_가정!$E$209)) -> 0 | L36: =(L14=1)*②시니어_가정!$H$38*②시니어_가정!$E$201*②시니어_가정!$E$202/1000*(1+②시니어_가정!$E$204)^INT((L15-1)/②시니어_가정!$E$205)*(1-CHOOSE(MIN(MAX(L16,1),3),②시니어_가정!$E$207,②시니어_가정!$E$208,②시니어_가정!$E$209)) -> 0 | ... EF36: =(EF14=1)*②시니어_가정!$H$38*②시니어_가정!$E$201*②시니어_가정!$E$202/1000*(1+②시니어_가정!$E$204)^INT((EF15-1)/②시니어_가정!$E$205)*(1-CHOOSE(MIN(MAX(EF16,1),3),②시니어_가정!$E$207,②시니어_가정!$E$208,②시니어_가정!$E$209)) -> 0
A37: 스파2.0 임대료 | B37: 백만원 | C37: =SUM(E37:EF37) -> 0 | E37: =(E14=1)*②시니어_가정!$H$38*②시니어_가정!$E$214*②시니어_가정!$E$215/1000*(1+②시니어_가정!$E$217)^INT((E15-1)/②시니어_가정!$E$218)*(1-CHOOSE(MIN(MAX(E16,1),3),②시니어_가정!$E$220,②시니어_가정!$E$221,②시니어_가정!$E$222)) -> 0 | F37: =(F14=1)*②시니어_가정!$H$38*②시니어_가정!$E$214*②시니어_가정!$E$215/1000*(1+②시니어_가정!$E$217)^INT((F15-1)/②시니어_가정!$E$218)*(1-CHOOSE(MIN(MAX(F16,1),3),②시니어_가정!$E$220,②시니어_가정!$E$221,②시니어_가정!$E$222)) -> 0 | G37: =(G14=1)*②시니어_가정!$H$38*②시니어_가정!$E$214*②시니어_가정!$E$215/1000*(1+②시니어_가정!$E$217)^INT((G15-1)/②시니어_가정!$E$218)*(1-CHOOSE(MIN(MAX(G16,1),3),②시니어_가정!$E$220,②시니어_가정!$E$221,②시니어_가정!$E$222)) -> 0 | H37: =(H14=1)*②시니어_가정!$H$38*②시니어_가정!$E$214*②시니어_가정!$E$215/1000*(1+②시니어_가정!$E$217)^INT((H15-1)/②시니어_가정!$E$218)*(1-CHOOSE(MIN(MAX(H16,1),3),②시니어_가정!$E$220,②시니어_가정!$E$221,②시니어_가정!$E$222)) -> 0 | I37: =(I14=1)*②시니어_가정!$H$38*②시니어_가정!$E$214*②시니어_가정!$E$215/1000*(1+②시니어_가정!$E$217)^INT((I15-1)/②시니어_가정!$E$218)*(1-CHOOSE(MIN(MAX(I16,1),3),②시니어_가정!$E$220,②시니어_가정!$E$221,②시니어_가정!$E$222)) -> 0 | J37: =(J14=1)*②시니어_가정!$H$38*②시니어_가정!$E$214*②시니어_가정!$E$215/1000*(1+②시니어_가정!$E$217)^INT((J15-1)/②시니어_가정!$E$218)*(1-CHOOSE(MIN(MAX(J16,1),3),②시니어_가정!$E$220,②시니어_가정!$E$221,②시니어_가정!$E$222)) -> 0 | K37: =(K14=1)*②시니어_가정!$H$38*②시니어_가정!$E$214*②시니어_가정!$E$215/1000*(1+②시니어_가정!$E$217)^INT((K15-1)/②시니어_가정!$E$218)*(1-CHOOSE(MIN(MAX(K16,1),3),②시니어_가정!$E$220,②시니어_가정!$E$221,②시니어_가정!$E$222)) -> 0 | L37: =(L14=1)*②시니어_가정!$H$38*②시니어_가정!$E$214*②시니어_가정!$E$215/1000*(1+②시니어_가정!$E$217)^INT((L15-1)/②시니어_가정!$E$218)*(1-CHOOSE(MIN(MAX(L16,1),3),②시니어_가정!$E$220,②시니어_가정!$E$221,②시니어_가정!$E$222)) -> 0 | ... EF37: =(EF14=1)*②시니어_가정!$H$38*②시니어_가정!$E$214*②시니어_가정!$E$215/1000*(1+②시니어_가정!$E$217)^INT((EF15-1)/②시니어_가정!$E$218)*(1-CHOOSE(MIN(MAX(EF16,1),3),②시니어_가정!$E$220,②시니어_가정!$E$221,②시니어_가정!$E$222)) -> 0
A38: 판매시설 임대료 | B38: 백만원 | C38: =SUM(E38:EF38) -> 0 | E38: =(E14=1)*②시니어_가정!$H$38*②시니어_가정!$E$227*②시니어_가정!$E$228/1000*(1+②시니어_가정!$E$230)^INT((E15-1)/②시니어_가정!$E$231)*(1-CHOOSE(MIN(MAX(E16,1),3),②시니어_가정!$E$233,②시니어_가정!$E$234,②시니어_가정!$E$235)) -> 0 | F38: =(F14=1)*②시니어_가정!$H$38*②시니어_가정!$E$227*②시니어_가정!$E$228/1000*(1+②시니어_가정!$E$230)^INT((F15-1)/②시니어_가정!$E$231)*(1-CHOOSE(MIN(MAX(F16,1),3),②시니어_가정!$E$233,②시니어_가정!$E$234,②시니어_가정!$E$235)) -> 0 | G38: =(G14=1)*②시니어_가정!$H$38*②시니어_가정!$E$227*②시니어_가정!$E$228/1000*(1+②시니어_가정!$E$230)^INT((G15-1)/②시니어_가정!$E$231)*(1-CHOOSE(MIN(MAX(G16,1),3),②시니어_가정!$E$233,②시니어_가정!$E$234,②시니어_가정!$E$235)) -> 0 | H38: =(H14=1)*②시니어_가정!$H$38*②시니어_가정!$E$227*②시니어_가정!$E$228/1000*(1+②시니어_가정!$E$230)^INT((H15-1)/②시니어_가정!$E$231)*(1-CHOOSE(MIN(MAX(H16,1),3),②시니어_가정!$E$233,②시니어_가정!$E$234,②시니어_가정!$E$235)) -> 0 | I38: =(I14=1)*②시니어_가정!$H$38*②시니어_가정!$E$227*②시니어_가정!$E$228/1000*(1+②시니어_가정!$E$230)^INT((I15-1)/②시니어_가정!$E$231)*(1-CHOOSE(MIN(MAX(I16,1),3),②시니어_가정!$E$233,②시니어_가정!$E$234,②시니어_가정!$E$235)) -> 0 | J38: =(J14=1)*②시니어_가정!$H$38*②시니어_가정!$E$227*②시니어_가정!$E$228/1000*(1+②시니어_가정!$E$230)^INT((J15-1)/②시니어_가정!$E$231)*(1-CHOOSE(MIN(MAX(J16,1),3),②시니어_가정!$E$233,②시니어_가정!$E$234,②시니어_가정!$E$235)) -> 0 | K38: =(K14=1)*②시니어_가정!$H$38*②시니어_가정!$E$227*②시니어_가정!$E$228/1000*(1+②시니어_가정!$E$230)^INT((K15-1)/②시니어_가정!$E$231)*(1-CHOOSE(MIN(MAX(K16,1),3),②시니어_가정!$E$233,②시니어_가정!$E$234,②시니어_가정!$E$235)) -> 0 | L38: =(L14=1)*②시니어_가정!$H$38*②시니어_가정!$E$227*②시니어_가정!$E$228/1000*(1+②시니어_가정!$E$230)^INT((L15-1)/②시니어_가정!$E$231)*(1-CHOOSE(MIN(MAX(L16,1),3),②시니어_가정!$E$233,②시니어_가정!$E$234,②시니어_가정!$E$235)) -> 0 | ... EF38: =(EF14=1)*②시니어_가정!$H$38*②시니어_가정!$E$227*②시니어_가정!$E$228/1000*(1+②시니어_가정!$E$230)^INT((EF15-1)/②시니어_가정!$E$231)*(1-CHOOSE(MIN(MAX(EF16,1),3),②시니어_가정!$E$233,②시니어_가정!$E$234,②시니어_가정!$E$235)) -> 0
A39: 국제학교 임대료 | B39: 백만원 | C39: =SUM(E39:EF39) -> 0 | E39: =(E14=1)*②시니어_가정!$H$38*②시니어_가정!$E$240*②시니어_가정!$E$241/1000*(1+②시니어_가정!$E$243)^INT((E15-1)/②시니어_가정!$E$244)*(1-CHOOSE(MIN(MAX(E16,1),3),②시니어_가정!$E$246,②시니어_가정!$E$247,②시니어_가정!$E$248)) -> 0 | F39: =(F14=1)*②시니어_가정!$H$38*②시니어_가정!$E$240*②시니어_가정!$E$241/1000*(1+②시니어_가정!$E$243)^INT((F15-1)/②시니어_가정!$E$244)*(1-CHOOSE(MIN(MAX(F16,1),3),②시니어_가정!$E$246,②시니어_가정!$E$247,②시니어_가정!$E$248)) -> 0 | G39: =(G14=1)*②시니어_가정!$H$38*②시니어_가정!$E$240*②시니어_가정!$E$241/1000*(1+②시니어_가정!$E$243)^INT((G15-1)/②시니어_가정!$E$244)*(1-CHOOSE(MIN(MAX(G16,1),3),②시니어_가정!$E$246,②시니어_가정!$E$247,②시니어_가정!$E$248)) -> 0 | H39: =(H14=1)*②시니어_가정!$H$38*②시니어_가정!$E$240*②시니어_가정!$E$241/1000*(1+②시니어_가정!$E$243)^INT((H15-1)/②시니어_가정!$E$244)*(1-CHOOSE(MIN(MAX(H16,1),3),②시니어_가정!$E$246,②시니어_가정!$E$247,②시니어_가정!$E$248)) -> 0 | I39: =(I14=1)*②시니어_가정!$H$38*②시니어_가정!$E$240*②시니어_가정!$E$241/1000*(1+②시니어_가정!$E$243)^INT((I15-1)/②시니어_가정!$E$244)*(1-CHOOSE(MIN(MAX(I16,1),3),②시니어_가정!$E$246,②시니어_가정!$E$247,②시니어_가정!$E$248)) -> 0 | J39: =(J14=1)*②시니어_가정!$H$38*②시니어_가정!$E$240*②시니어_가정!$E$241/1000*(1+②시니어_가정!$E$243)^INT((J15-1)/②시니어_가정!$E$244)*(1-CHOOSE(MIN(MAX(J16,1),3),②시니어_가정!$E$246,②시니어_가정!$E$247,②시니어_가정!$E$248)) -> 0 | K39: =(K14=1)*②시니어_가정!$H$38*②시니어_가정!$E$240*②시니어_가정!$E$241/1000*(1+②시니어_가정!$E$243)^INT((K15-1)/②시니어_가정!$E$244)*(1-CHOOSE(MIN(MAX(K16,1),3),②시니어_가정!$E$246,②시니어_가정!$E$247,②시니어_가정!$E$248)) -> 0 | L39: =(L14=1)*②시니어_가정!$H$38*②시니어_가정!$E$240*②시니어_가정!$E$241/1000*(1+②시니어_가정!$E$243)^INT((L15-1)/②시니어_가정!$E$244)*(1-CHOOSE(MIN(MAX(L16,1),3),②시니어_가정!$E$246,②시니어_가정!$E$247,②시니어_가정!$E$248)) -> 0 | ... EF39: =(EF14=1)*②시니어_가정!$H$38*②시니어_가정!$E$240*②시니어_가정!$E$241/1000*(1+②시니어_가정!$E$243)^INT((EF15-1)/②시니어_가정!$E$244)*(1-CHOOSE(MIN(MAX(EF16,1),3),②시니어_가정!$E$246,②시니어_가정!$E$247,②시니어_가정!$E$248)) -> 0
A40: 영어유치원 임대료 | B40: 백만원 | C40: =SUM(E40:EF40) -> 0 | E40: =(E14=1)*②시니어_가정!$H$38*②시니어_가정!$E$253*②시니어_가정!$E$254/1000*(1+②시니어_가정!$E$256)^INT((E15-1)/②시니어_가정!$E$257)*(1-CHOOSE(MIN(MAX(E16,1),3),②시니어_가정!$E$259,②시니어_가정!$E$260,②시니어_가정!$E$261)) -> 0 | F40: =(F14=1)*②시니어_가정!$H$38*②시니어_가정!$E$253*②시니어_가정!$E$254/1000*(1+②시니어_가정!$E$256)^INT((F15-1)/②시니어_가정!$E$257)*(1-CHOOSE(MIN(MAX(F16,1),3),②시니어_가정!$E$259,②시니어_가정!$E$260,②시니어_가정!$E$261)) -> 0 | G40: =(G14=1)*②시니어_가정!$H$38*②시니어_가정!$E$253*②시니어_가정!$E$254/1000*(1+②시니어_가정!$E$256)^INT((G15-1)/②시니어_가정!$E$257)*(1-CHOOSE(MIN(MAX(G16,1),3),②시니어_가정!$E$259,②시니어_가정!$E$260,②시니어_가정!$E$261)) -> 0 | H40: =(H14=1)*②시니어_가정!$H$38*②시니어_가정!$E$253*②시니어_가정!$E$254/1000*(1+②시니어_가정!$E$256)^INT((H15-1)/②시니어_가정!$E$257)*(1-CHOOSE(MIN(MAX(H16,1),3),②시니어_가정!$E$259,②시니어_가정!$E$260,②시니어_가정!$E$261)) -> 0 | I40: =(I14=1)*②시니어_가정!$H$38*②시니어_가정!$E$253*②시니어_가정!$E$254/1000*(1+②시니어_가정!$E$256)^INT((I15-1)/②시니어_가정!$E$257)*(1-CHOOSE(MIN(MAX(I16,1),3),②시니어_가정!$E$259,②시니어_가정!$E$260,②시니어_가정!$E$261)) -> 0 | J40: =(J14=1)*②시니어_가정!$H$38*②시니어_가정!$E$253*②시니어_가정!$E$254/1000*(1+②시니어_가정!$E$256)^INT((J15-1)/②시니어_가정!$E$257)*(1-CHOOSE(MIN(MAX(J16,1),3),②시니어_가정!$E$259,②시니어_가정!$E$260,②시니어_가정!$E$261)) -> 0 | K40: =(K14=1)*②시니어_가정!$H$38*②시니어_가정!$E$253*②시니어_가정!$E$254/1000*(1+②시니어_가정!$E$256)^INT((K15-1)/②시니어_가정!$E$257)*(1-CHOOSE(MIN(MAX(K16,1),3),②시니어_가정!$E$259,②시니어_가정!$E$260,②시니어_가정!$E$261)) -> 0 | L40: =(L14=1)*②시니어_가정!$H$38*②시니어_가정!$E$253*②시니어_가정!$E$254/1000*(1+②시니어_가정!$E$256)^INT((L15-1)/②시니어_가정!$E$257)*(1-CHOOSE(MIN(MAX(L16,1),3),②시니어_가정!$E$259,②시니어_가정!$E$260,②시니어_가정!$E$261)) -> 0 | ... EF40: =(EF14=1)*②시니어_가정!$H$38*②시니어_가정!$E$253*②시니어_가정!$E$254/1000*(1+②시니어_가정!$E$256)^INT((EF15-1)/②시니어_가정!$E$257)*(1-CHOOSE(MIN(MAX(EF16,1),3),②시니어_가정!$E$259,②시니어_가정!$E$260,②시니어_가정!$E$261)) -> 0
A41: 운영수입 합계 | B41: 백만원 | C41: =SUM(E41:EF41) -> 120999.07 | E41: =SUM(E21:E40) -> 0 | F41: =SUM(F21:F40) -> 0 | G41: =SUM(G21:G40) -> 0 | H41: =SUM(H21:H40) -> 0 | I41: =SUM(I21:I40) -> 0 | J41: =SUM(J21:J40) -> 0 | K41: =SUM(K21:K40) -> 0 | L41: =SUM(L21:L40) -> 0 | ... EF41: =SUM(EF21:EF40) -> 0
A43: 직접운영비용
A44: 시니어 운영비(일반+소모품) | B44: 백만원 | C44: =SUM(E44:EF44) -> 88377.554 | E44: =(E21+E22)*(②시니어_가정!$E$110+②시니어_가정!$E$111) -> 0 | F44: =(F21+F22)*(②시니어_가정!$E$110+②시니어_가정!$E$111) -> 0 | G44: =(G21+G22)*(②시니어_가정!$E$110+②시니어_가정!$E$111) -> 0 | H44: =(H21+H22)*(②시니어_가정!$E$110+②시니어_가정!$E$111) -> 0 | I44: =(I21+I22)*(②시니어_가정!$E$110+②시니어_가정!$E$111) -> 0 | J44: =(J21+J22)*(②시니어_가정!$E$110+②시니어_가정!$E$111) -> 0 | K44: =(K21+K22)*(②시니어_가정!$E$110+②시니어_가정!$E$111) -> 0 | L44: =(L21+L22)*(②시니어_가정!$E$110+②시니어_가정!$E$111) -> 0 | ... EF44: =(EF21+EF22)*(②시니어_가정!$E$110+②시니어_가정!$E$111) -> 0
A45: 레지던스 운영비(일반+소모품) | B45: 백만원 | C45: =SUM(E45:EF45) -> 0 | E45: =(E24+E25)*(②시니어_가정!$E$140+②시니어_가정!$E$141) -> 0 | F45: =(F24+F25)*(②시니어_가정!$E$140+②시니어_가정!$E$141) -> 0 | G45: =(G24+G25)*(②시니어_가정!$E$140+②시니어_가정!$E$141) -> 0 | H45: =(H24+H25)*(②시니어_가정!$E$140+②시니어_가정!$E$141) -> 0 | I45: =(I24+I25)*(②시니어_가정!$E$140+②시니어_가정!$E$141) -> 0 | J45: =(J24+J25)*(②시니어_가정!$E$140+②시니어_가정!$E$141) -> 0 | K45: =(K24+K25)*(②시니어_가정!$E$140+②시니어_가정!$E$141) -> 0 | L45: =(L24+L25)*(②시니어_가정!$E$140+②시니어_가정!$E$141) -> 0 | ... EF45: =(EF24+EF25)*(②시니어_가정!$E$140+②시니어_가정!$E$141) -> 0
A46: 레지던스 멤버전용 운영비 | B46: 백만원 | C46: =SUM(E46:EF46) -> 0 | E46: =E26*②시니어_가정!$E$145 -> 0 | F46: =F26*②시니어_가정!$E$145 -> 0 | G46: =G26*②시니어_가정!$E$145 -> 0 | H46: =H26*②시니어_가정!$E$145 -> 0 | I46: =I26*②시니어_가정!$E$145 -> 0 | J46: =J26*②시니어_가정!$E$145 -> 0 | K46: =K26*②시니어_가정!$E$145 -> 0 | L46: =L26*②시니어_가정!$E$145 -> 0 | ... EF46: =EF26*②시니어_가정!$E$145 -> 0
A47: 호텔 운영비(일반+소모품) | B47: 백만원 | C47: =SUM(E47:EF47) -> 0 | E47: =(E27+E28+E29)*(②시니어_가정!$E$165+②시니어_가정!$E$166) -> 0 | F47: =(F27+F28+F29)*(②시니어_가정!$E$165+②시니어_가정!$E$166) -> 0 | G47: =(G27+G28+G29)*(②시니어_가정!$E$165+②시니어_가정!$E$166) -> 0 | H47: =(H27+H28+H29)*(②시니어_가정!$E$165+②시니어_가정!$E$166) -> 0 | I47: =(I27+I28+I29)*(②시니어_가정!$E$165+②시니어_가정!$E$166) -> 0 | J47: =(J27+J28+J29)*(②시니어_가정!$E$165+②시니어_가정!$E$166) -> 0 | K47: =(K27+K28+K29)*(②시니어_가정!$E$165+②시니어_가정!$E$166) -> 0 | L47: =(L27+L28+L29)*(②시니어_가정!$E$165+②시니어_가정!$E$166) -> 0 | ... EF47: =(EF27+EF28+EF29)*(②시니어_가정!$E$165+②시니어_가정!$E$166) -> 0
A48: 컨벤션 운영비 | B48: 백만원 | C48: =SUM(E48:EF48) -> 0 | E48: =E30*②시니어_가정!$E$175 -> 0 | F48: =F30*②시니어_가정!$E$175 -> 0 | G48: =G30*②시니어_가정!$E$175 -> 0 | H48: =H30*②시니어_가정!$E$175 -> 0 | I48: =I30*②시니어_가정!$E$175 -> 0 | J48: =J30*②시니어_가정!$E$175 -> 0 | K48: =K30*②시니어_가정!$E$175 -> 0 | L48: =L30*②시니어_가정!$E$175 -> 0 | ... EF48: =EF30*②시니어_가정!$E$175 -> 0
A49: 스파&수영장&피트니스 운영비 | B49: 백만원 | C49: =SUM(E49:EF49) -> 0 | E49: =E31*②시니어_가정!$E$176 -> 0 | F49: =F31*②시니어_가정!$E$176 -> 0 | G49: =G31*②시니어_가정!$E$176 -> 0 | H49: =H31*②시니어_가정!$E$176 -> 0 | I49: =I31*②시니어_가정!$E$176 -> 0 | J49: =J31*②시니어_가정!$E$176 -> 0 | K49: =K31*②시니어_가정!$E$176 -> 0 | L49: =L31*②시니어_가정!$E$176 -> 0 | ... EF49: =EF31*②시니어_가정!$E$176 -> 0
A50: 파인다이닝/ADD 운영비 | B50: 백만원 | C50: =SUM(E50:EF50) -> 0 | E50: =E32*②시니어_가정!$E$177 -> 0 | F50: =F32*②시니어_가정!$E$177 -> 0 | G50: =G32*②시니어_가정!$E$177 -> 0 | H50: =H32*②시니어_가정!$E$177 -> 0 | I50: =I32*②시니어_가정!$E$177 -> 0 | J50: =J32*②시니어_가정!$E$177 -> 0 | K50: =K32*②시니어_가정!$E$177 -> 0 | L50: =L32*②시니어_가정!$E$177 -> 0 | ... EF50: =EF32*②시니어_가정!$E$177 -> 0
A51: 휴게시설 운영비 | B51: 백만원 | C51: =SUM(E51:EF51) -> 0 | E51: =E33*②시니어_가정!$E$178 -> 0 | F51: =F33*②시니어_가정!$E$178 -> 0 | G51: =G33*②시니어_가정!$E$178 -> 0 | H51: =H33*②시니어_가정!$E$178 -> 0 | I51: =I33*②시니어_가정!$E$178 -> 0 | J51: =J33*②시니어_가정!$E$178 -> 0 | K51: =K33*②시니어_가정!$E$178 -> 0 | L51: =L33*②시니어_가정!$E$178 -> 0 | ... EF51: =EF33*②시니어_가정!$E$178 -> 0
A52: BOH 운영비 | B52: 백만원 | C52: =SUM(E52:EF52) -> 0 | E52: =E34*②시니어_가정!$E$179 -> 0 | F52: =F34*②시니어_가정!$E$179 -> 0 | G52: =G34*②시니어_가정!$E$179 -> 0 | H52: =H34*②시니어_가정!$E$179 -> 0 | I52: =I34*②시니어_가정!$E$179 -> 0 | J52: =J34*②시니어_가정!$E$179 -> 0 | K52: =K34*②시니어_가정!$E$179 -> 0 | L52: =L34*②시니어_가정!$E$179 -> 0 | ... EF52: =EF34*②시니어_가정!$E$179 -> 0
A53: 오피스 리징비용 | B53: 백만원 | C53: =SUM(E53:EF53) -> 0 | E53: =E35*CHOOSE(MIN(MAX(E16,1),3),②시니어_가정!$E$192,②시니어_가정!$E$193,②시니어_가정!$E$194) -> 0 | F53: =F35*CHOOSE(MIN(MAX(F16,1),3),②시니어_가정!$E$192,②시니어_가정!$E$193,②시니어_가정!$E$194) -> 0 | G53: =G35*CHOOSE(MIN(MAX(G16,1),3),②시니어_가정!$E$192,②시니어_가정!$E$193,②시니어_가정!$E$194) -> 0 | H53: =H35*CHOOSE(MIN(MAX(H16,1),3),②시니어_가정!$E$192,②시니어_가정!$E$193,②시니어_가정!$E$194) -> 0 | I53: =I35*CHOOSE(MIN(MAX(I16,1),3),②시니어_가정!$E$192,②시니어_가정!$E$193,②시니어_가정!$E$194) -> 0 | J53: =J35*CHOOSE(MIN(MAX(J16,1),3),②시니어_가정!$E$192,②시니어_가정!$E$193,②시니어_가정!$E$194) -> 0 | K53: =K35*CHOOSE(MIN(MAX(K16,1),3),②시니어_가정!$E$192,②시니어_가정!$E$193,②시니어_가정!$E$194) -> 0 | L53: =L35*CHOOSE(MIN(MAX(L16,1),3),②시니어_가정!$E$192,②시니어_가정!$E$193,②시니어_가정!$E$194) -> 0 | ... EF53: =EF35*CHOOSE(MIN(MAX(EF16,1),3),②시니어_가정!$E$192,②시니어_가정!$E$193,②시니어_가정!$E$194) -> 0
A54: 오피스 관리비용 | B54: 백만원 | C54: =SUM(E54:EF54) -> 0 | E54: =(E14=1)*②시니어_가정!$G$38*②시니어_가정!$E$195*②시니어_가정!$E$184/1000*(1+②시니어_가정!$E$188)^(MAX(E16,1)-1) -> 0 | F54: =(F14=1)*②시니어_가정!$G$38*②시니어_가정!$E$195*②시니어_가정!$E$184/1000*(1+②시니어_가정!$E$188)^(MAX(F16,1)-1) -> 0 | G54: =(G14=1)*②시니어_가정!$G$38*②시니어_가정!$E$195*②시니어_가정!$E$184/1000*(1+②시니어_가정!$E$188)^(MAX(G16,1)-1) -> 0 | H54: =(H14=1)*②시니어_가정!$G$38*②시니어_가정!$E$195*②시니어_가정!$E$184/1000*(1+②시니어_가정!$E$188)^(MAX(H16,1)-1) -> 0 | I54: =(I14=1)*②시니어_가정!$G$38*②시니어_가정!$E$195*②시니어_가정!$E$184/1000*(1+②시니어_가정!$E$188)^(MAX(I16,1)-1) -> 0 | J54: =(J14=1)*②시니어_가정!$G$38*②시니어_가정!$E$195*②시니어_가정!$E$184/1000*(1+②시니어_가정!$E$188)^(MAX(J16,1)-1) -> 0 | K54: =(K14=1)*②시니어_가정!$G$38*②시니어_가정!$E$195*②시니어_가정!$E$184/1000*(1+②시니어_가정!$E$188)^(MAX(K16,1)-1) -> 0 | L54: =(L14=1)*②시니어_가정!$G$38*②시니어_가정!$E$195*②시니어_가정!$E$184/1000*(1+②시니어_가정!$E$188)^(MAX(L16,1)-1) -> 0 | ... EF54: =(EF14=1)*②시니어_가정!$G$38*②시니어_가정!$E$195*②시니어_가정!$E$184/1000*(1+②시니어_가정!$E$188)^(MAX(EF16,1)-1) -> 0
A55: 부대시설 운영비 | B55: 백만원 | C55: =SUM(E55:EF55) -> 0 | E55: =E36*②시니어_가정!$E$210+E37*②시니어_가정!$E$223+E38*②시니어_가정!$E$236+E39*②시니어_가정!$E$249+E40*②시니어_가정!$E$262 -> 0 | F55: =F36*②시니어_가정!$E$210+F37*②시니어_가정!$E$223+F38*②시니어_가정!$E$236+F39*②시니어_가정!$E$249+F40*②시니어_가정!$E$262 -> 0 | G55: =G36*②시니어_가정!$E$210+G37*②시니어_가정!$E$223+G38*②시니어_가정!$E$236+G39*②시니어_가정!$E$249+G40*②시니어_가정!$E$262 -> 0 | H55: =H36*②시니어_가정!$E$210+H37*②시니어_가정!$E$223+H38*②시니어_가정!$E$236+H39*②시니어_가정!$E$249+H40*②시니어_가정!$E$262 -> 0 | I55: =I36*②시니어_가정!$E$210+I37*②시니어_가정!$E$223+I38*②시니어_가정!$E$236+I39*②시니어_가정!$E$249+I40*②시니어_가정!$E$262 -> 0 | J55: =J36*②시니어_가정!$E$210+J37*②시니어_가정!$E$223+J38*②시니어_가정!$E$236+J39*②시니어_가정!$E$249+J40*②시니어_가정!$E$262 -> 0 | K55: =K36*②시니어_가정!$E$210+K37*②시니어_가정!$E$223+K38*②시니어_가정!$E$236+K39*②시니어_가정!$E$249+K40*②시니어_가정!$E$262 -> 0 | L55: =L36*②시니어_가정!$E$210+L37*②시니어_가정!$E$223+L38*②시니어_가정!$E$236+L39*②시니어_가정!$E$249+L40*②시니어_가정!$E$262 -> 0 | ... EF55: =EF36*②시니어_가정!$E$210+EF37*②시니어_가정!$E$223+EF38*②시니어_가정!$E$236+EF39*②시니어_가정!$E$249+EF40*②시니어_가정!$E$262 -> 0
A56: 직접운영비용 합계 | B56: 백만원 | C56: =SUM(E56:EF56) -> 88377.554 | E56: =SUM(E44:E55) -> 0 | F56: =SUM(F44:F55) -> 0 | G56: =SUM(G44:G55) -> 0 | H56: =SUM(H44:H55) -> 0 | I56: =SUM(I44:I55) -> 0 | J56: =SUM(J44:J55) -> 0 | K56: =SUM(K44:K55) -> 0 | L56: =SUM(L44:L55) -> 0 | ... EF56: =SUM(EF44:EF55) -> 0
A58: 용도별 NOI
A59: NOI - 시니어 레지던스 | B59: 백만원 | C59: =SUM(E59:EF59) -> 32621.512 | E59: =E21+E22+E23-E44 -> 0 | F59: =F21+F22+F23-F44 -> 0 | G59: =G21+G22+G23-G44 -> 0 | H59: =H21+H22+H23-H44 -> 0 | I59: =I21+I22+I23-I44 -> 0 | J59: =J21+J22+J23-J44 -> 0 | K59: =K21+K22+K23-K44 -> 0 | L59: =L21+L22+L23-L44 -> 0 | ... EF59: =EF21+EF22+EF23-EF44 -> 0
A60: NOI - 레지던스 | B60: 백만원 | C60: =SUM(E60:EF60) -> 0 | E60: =E24+E25+E26-E45-E46 -> 0 | F60: =F24+F25+F26-F45-F46 -> 0 | G60: =G24+G25+G26-G45-G46 -> 0 | H60: =H24+H25+H26-H45-H46 -> 0 | I60: =I24+I25+I26-I45-I46 -> 0 | J60: =J24+J25+J26-J45-J46 -> 0 | K60: =K24+K25+K26-K45-K46 -> 0 | L60: =L24+L25+L26-L45-L46 -> 0 | ... EF60: =EF24+EF25+EF26-EF45-EF46 -> 0
A61: NOI - 호텔 | B61: 백만원 | C61: =SUM(E61:EF61) -> 0 | E61: =SUM(E27:E34)-SUM(E47:E52) -> 0 | F61: =SUM(F27:F34)-SUM(F47:F52) -> 0 | G61: =SUM(G27:G34)-SUM(G47:G52) -> 0 | H61: =SUM(H27:H34)-SUM(H47:H52) -> 0 | I61: =SUM(I27:I34)-SUM(I47:I52) -> 0 | J61: =SUM(J27:J34)-SUM(J47:J52) -> 0 | K61: =SUM(K27:K34)-SUM(K47:K52) -> 0 | L61: =SUM(L27:L34)-SUM(L47:L52) -> 0 | ... EF61: =SUM(EF27:EF34)-SUM(EF47:EF52) -> 0
A62: NOI - 오피스 | B62: 백만원 | C62: =SUM(E62:EF62) -> 0 | E62: =E35-E53-E54 -> 0 | F62: =F35-F53-F54 -> 0 | G62: =G35-G53-G54 -> 0 | H62: =H35-H53-H54 -> 0 | I62: =I35-I53-I54 -> 0 | J62: =J35-J53-J54 -> 0 | K62: =K35-K53-K54 -> 0 | L62: =L35-L53-L54 -> 0 | ... EF62: =EF35-EF53-EF54 -> 0
A63: NOI - 부대시설 | B63: 백만원 | C63: =SUM(E63:EF63) -> 0 | E63: =SUM(E36:E40)-E55 -> 0 | F63: =SUM(F36:F40)-F55 -> 0 | G63: =SUM(G36:G40)-G55 -> 0 | H63: =SUM(H36:H40)-H55 -> 0 | I63: =SUM(I36:I40)-I55 -> 0 | J63: =SUM(J36:J40)-J55 -> 0 | K63: =SUM(K36:K40)-K55 -> 0 | L63: =SUM(L36:L40)-L55 -> 0 | ... EF63: =SUM(EF36:EF40)-EF55 -> 0
A64: NOI 합계 | B64: 백만원 | C64: =SUM(E64:EF64) -> 32621.512 | E64: =SUM(E59:E63) -> 0 | F64: =SUM(F59:F63) -> 0 | G64: =SUM(G59:G63) -> 0 | H64: =SUM(H59:H63) -> 0 | I64: =SUM(I59:I63) -> 0 | J64: =SUM(J59:J63) -> 0 | K64: =SUM(K59:K63) -> 0 | L64: =SUM(L59:L63) -> 0 | ... EF64: =SUM(EF59:EF63) -> 0
A66: 기타공통비용 및 리츠운용비(운영)
A67: 수선비 | B67: 백만원 | C67: =SUM(E67:EF67) -> 2155.2383 | E67: =(E14=1)*②시니어_가정!$E$265*②시니어_가정!$I$39/1000000*(1+②시니어_가정!$E$270)^(MAX(E16,1)-1) -> 0 | F67: =(F14=1)*②시니어_가정!$E$265*②시니어_가정!$I$39/1000000*(1+②시니어_가정!$E$270)^(MAX(F16,1)-1) -> 0 | G67: =(G14=1)*②시니어_가정!$E$265*②시니어_가정!$I$39/1000000*(1+②시니어_가정!$E$270)^(MAX(G16,1)-1) -> 0 | H67: =(H14=1)*②시니어_가정!$E$265*②시니어_가정!$I$39/1000000*(1+②시니어_가정!$E$270)^(MAX(H16,1)-1) -> 0 | I67: =(I14=1)*②시니어_가정!$E$265*②시니어_가정!$I$39/1000000*(1+②시니어_가정!$E$270)^(MAX(I16,1)-1) -> 0 | J67: =(J14=1)*②시니어_가정!$E$265*②시니어_가정!$I$39/1000000*(1+②시니어_가정!$E$270)^(MAX(J16,1)-1) -> 0 | K67: =(K14=1)*②시니어_가정!$E$265*②시니어_가정!$I$39/1000000*(1+②시니어_가정!$E$270)^(MAX(K16,1)-1) -> 0 | L67: =(L14=1)*②시니어_가정!$E$265*②시니어_가정!$I$39/1000000*(1+②시니어_가정!$E$270)^(MAX(L16,1)-1) -> 0 | ... EF67: =(EF14=1)*②시니어_가정!$E$265*②시니어_가정!$I$39/1000000*(1+②시니어_가정!$E$270)^(MAX(EF16,1)-1) -> 0
A68: 보험료 | B68: 백만원 | C68: =SUM(E68:EF68) -> 2155.2383 | E68: =(E14=1)*②시니어_가정!$E$266*②시니어_가정!$I$39/1000000*(1+②시니어_가정!$E$270)^(MAX(E16,1)-1) -> 0 | F68: =(F14=1)*②시니어_가정!$E$266*②시니어_가정!$I$39/1000000*(1+②시니어_가정!$E$270)^(MAX(F16,1)-1) -> 0 | G68: =(G14=1)*②시니어_가정!$E$266*②시니어_가정!$I$39/1000000*(1+②시니어_가정!$E$270)^(MAX(G16,1)-1) -> 0 | H68: =(H14=1)*②시니어_가정!$E$266*②시니어_가정!$I$39/1000000*(1+②시니어_가정!$E$270)^(MAX(H16,1)-1) -> 0 | I68: =(I14=1)*②시니어_가정!$E$266*②시니어_가정!$I$39/1000000*(1+②시니어_가정!$E$270)^(MAX(I16,1)-1) -> 0 | J68: =(J14=1)*②시니어_가정!$E$266*②시니어_가정!$I$39/1000000*(1+②시니어_가정!$E$270)^(MAX(J16,1)-1) -> 0 | K68: =(K14=1)*②시니어_가정!$E$266*②시니어_가정!$I$39/1000000*(1+②시니어_가정!$E$270)^(MAX(K16,1)-1) -> 0 | L68: =(L14=1)*②시니어_가정!$E$266*②시니어_가정!$I$39/1000000*(1+②시니어_가정!$E$270)^(MAX(L16,1)-1) -> 0 | ... EF68: =(EF14=1)*②시니어_가정!$E$266*②시니어_가정!$I$39/1000000*(1+②시니어_가정!$E$270)^(MAX(EF16,1)-1) -> 0
A69: PM 수수료 | B69: 백만원 | C69: =SUM(E69:EF69) -> 2155.2383 | E69: =(E14=1)*②시니어_가정!$E$267*②시니어_가정!$I$39/1000000*(1+②시니어_가정!$E$270)^(MAX(E16,1)-1) -> 0 | F69: =(F14=1)*②시니어_가정!$E$267*②시니어_가정!$I$39/1000000*(1+②시니어_가정!$E$270)^(MAX(F16,1)-1) -> 0 | G69: =(G14=1)*②시니어_가정!$E$267*②시니어_가정!$I$39/1000000*(1+②시니어_가정!$E$270)^(MAX(G16,1)-1) -> 0 | H69: =(H14=1)*②시니어_가정!$E$267*②시니어_가정!$I$39/1000000*(1+②시니어_가정!$E$270)^(MAX(H16,1)-1) -> 0 | I69: =(I14=1)*②시니어_가정!$E$267*②시니어_가정!$I$39/1000000*(1+②시니어_가정!$E$270)^(MAX(I16,1)-1) -> 0 | J69: =(J14=1)*②시니어_가정!$E$267*②시니어_가정!$I$39/1000000*(1+②시니어_가정!$E$270)^(MAX(J16,1)-1) -> 0 | K69: =(K14=1)*②시니어_가정!$E$267*②시니어_가정!$I$39/1000000*(1+②시니어_가정!$E$270)^(MAX(K16,1)-1) -> 0 | L69: =(L14=1)*②시니어_가정!$E$267*②시니어_가정!$I$39/1000000*(1+②시니어_가정!$E$270)^(MAX(L16,1)-1) -> 0 | ... EF69: =(EF14=1)*②시니어_가정!$E$267*②시니어_가정!$I$39/1000000*(1+②시니어_가정!$E$270)^(MAX(EF16,1)-1) -> 0
A70: 교통유발부담금 | B70: 백만원 | C70: =SUM(E70:EF70) -> 2305.098 | E70: =(E14=1)*②시니어_가정!$E$268*②시니어_가정!$I$41/12*(1+②시니어_가정!$E$270)^(MAX(E16,1)-1) -> 0 | F70: =(F14=1)*②시니어_가정!$E$268*②시니어_가정!$I$41/12*(1+②시니어_가정!$E$270)^(MAX(F16,1)-1) -> 0 | G70: =(G14=1)*②시니어_가정!$E$268*②시니어_가정!$I$41/12*(1+②시니어_가정!$E$270)^(MAX(G16,1)-1) -> 0 | H70: =(H14=1)*②시니어_가정!$E$268*②시니어_가정!$I$41/12*(1+②시니어_가정!$E$270)^(MAX(H16,1)-1) -> 0 | I70: =(I14=1)*②시니어_가정!$E$268*②시니어_가정!$I$41/12*(1+②시니어_가정!$E$270)^(MAX(I16,1)-1) -> 0 | J70: =(J14=1)*②시니어_가정!$E$268*②시니어_가정!$I$41/12*(1+②시니어_가정!$E$270)^(MAX(J16,1)-1) -> 0 | K70: =(K14=1)*②시니어_가정!$E$268*②시니어_가정!$I$41/12*(1+②시니어_가정!$E$270)^(MAX(K16,1)-1) -> 0 | L70: =(L14=1)*②시니어_가정!$E$268*②시니어_가정!$I$41/12*(1+②시니어_가정!$E$270)^(MAX(L16,1)-1) -> 0 | ... EF70: =(EF14=1)*②시니어_가정!$E$268*②시니어_가정!$I$41/12*(1+②시니어_가정!$E$270)^(MAX(EF16,1)-1) -> 0
A71: 간주임대료 부가세 | B71: 백만원 | C71: =SUM(E71:EF71) -> 9028.5125 | E71: =(E14=1)*0*②시니어_가정!$E$269/12*②시니어_가정!$D$555 -> 0 | F71: =(F14=1)*E86*②시니어_가정!$E$269/12*②시니어_가정!$D$555 -> 0 | G71: =(G14=1)*F86*②시니어_가정!$E$269/12*②시니어_가정!$D$555 -> 0 | H71: =(H14=1)*G86*②시니어_가정!$E$269/12*②시니어_가정!$D$555 -> 0 | I71: =(I14=1)*H86*②시니어_가정!$E$269/12*②시니어_가정!$D$555 -> 0 | J71: =(J14=1)*I86*②시니어_가정!$E$269/12*②시니어_가정!$D$555 -> 0 | K71: =(K14=1)*J86*②시니어_가정!$E$269/12*②시니어_가정!$D$555 -> 0 | L71: =(L14=1)*K86*②시니어_가정!$E$269/12*②시니어_가정!$D$555 -> 0 | M71: =(M14=1)*L86*②시니어_가정!$E$269/12*②시니어_가정!$D$555 -> 0 | ... EF71: =(EF14=1)*EE86*②시니어_가정!$E$269/12*②시니어_가정!$D$555 -> 0
A72: 리츠운용비(운영) | B72: 백만원 | C72: =SUM(E72:EF72) -> 7420.875 | E72: =E17*②시니어_가정!$E$426 -> 0 | F72: =F17*②시니어_가정!$E$426 -> 0 | G72: =G17*②시니어_가정!$E$426 -> 0 | H72: =H17*②시니어_가정!$E$426 -> 0 | I72: =I17*②시니어_가정!$E$426 -> 0 | J72: =J17*②시니어_가정!$E$426 -> 0 | K72: =K17*②시니어_가정!$E$426 -> 0 | L72: =L17*②시니어_가정!$E$426 -> 0 | ... EF72: =EF17*②시니어_가정!$E$426 -> 0
A73: 자산관리 수수료(매각보수) | B73: 백만원 | C73: =SUM(E73:EF73) -> 959.822 | E73: =IF(E6=②시니어_가정!$E$22,②시니어_가정!$R$420,0) -> 0 | F73: =IF(F6=②시니어_가정!$E$22,②시니어_가정!$R$420,0) -> 0 | G73: =IF(G6=②시니어_가정!$E$22,②시니어_가정!$R$420,0) -> 0 | H73: =IF(H6=②시니어_가정!$E$22,②시니어_가정!$R$420,0) -> 0 | I73: =IF(I6=②시니어_가정!$E$22,②시니어_가정!$R$420,0) -> 0 | J73: =IF(J6=②시니어_가정!$E$22,②시니어_가정!$R$420,0) -> 0 | K73: =IF(K6=②시니어_가정!$E$22,②시니어_가정!$R$420,0) -> 0 | L73: =IF(L6=②시니어_가정!$E$22,②시니어_가정!$R$420,0) -> 0 | ... EF73: =IF(EF6=②시니어_가정!$E$22,②시니어_가정!$R$420,0) -> 0
A74: 공통비용 합계 | B74: 백만원 | C74: =SUM(E74:EF74) -> 26180.023 | E74: =SUM(E67:E73) -> 0 | F74: =SUM(F67:F73) -> 0 | G74: =SUM(G67:G73) -> 0 | H74: =SUM(H67:H73) -> 0 | I74: =SUM(I67:I73) -> 0 | J74: =SUM(J67:J73) -> 0 | K74: =SUM(K67:K73) -> 0 | L74: =SUM(L67:L73) -> 0 | ... EF74: =SUM(EF67:EF73) -> 0
A75: 운영현금흐름(NOI-공통비용) | B75: 백만원 | C75: =SUM(E75:EF75) -> 6441.4891 | E75: =E64-E74 -> 0 | F75: =F64-F74 -> 0 | G75: =G64-G74 -> 0 | H75: =H64-H74 -> 0 | I75: =I64-I74 -> 0 | J75: =J64-J74 -> 0 | K75: =K64-K74 -> 0 | L75: =L64-L74 -> 0 | ... EF75: =EF64-EF74 -> 0
A77: 임대·입주 보증금
A78: 시니어 레지던스 보증금 유입 | B78: 백만원 | C78: =SUM(E78:EF78) -> 540000 | E78: =②시니어_가정!$D$38*②시니어_가정!$E$98*(②시니어_가정!$E$104*SUMIF(②시니어_가정!$J$97:$J$101,E6,②시니어_가정!$I$97:$I$101)+IF(E15=13,②시니어_가정!$E$105-②시니어_가정!$E$104,0)+IF(E15=25,②시니어_가정!$E$106-②시니어_가정!$E$105,0)) -> 0 | F78: =②시니어_가정!$D$38*②시니어_가정!$E$98*(②시니어_가정!$E$104*SUMIF(②시니어_가정!$J$97:$J$101,F6,②시니어_가정!$I$97:$I$101)+IF(F15=13,②시니어_가정!$E$105-②시니어_가정!$E$104,0)+IF(F15=25,②시니어_가정!$E$106-②시니어_가정!$E$105,0)) -> 0 | G78: =②시니어_가정!$D$38*②시니어_가정!$E$98*(②시니어_가정!$E$104*SUMIF(②시니어_가정!$J$97:$J$101,G6,②시니어_가정!$I$97:$I$101)+IF(G15=13,②시니어_가정!$E$105-②시니어_가정!$E$104,0)+IF(G15=25,②시니어_가정!$E$106-②시니어_가정!$E$105,0)) -> 0 | H78: =②시니어_가정!$D$38*②시니어_가정!$E$98*(②시니어_가정!$E$104*SUMIF(②시니어_가정!$J$97:$J$101,H6,②시니어_가정!$I$97:$I$101)+IF(H15=13,②시니어_가정!$E$105-②시니어_가정!$E$104,0)+IF(H15=25,②시니어_가정!$E$106-②시니어_가정!$E$105,0)) -> 0 | I78: =②시니어_가정!$D$38*②시니어_가정!$E$98*(②시니어_가정!$E$104*SUMIF(②시니어_가정!$J$97:$J$101,I6,②시니어_가정!$I$97:$I$101)+IF(I15=13,②시니어_가정!$E$105-②시니어_가정!$E$104,0)+IF(I15=25,②시니어_가정!$E$106-②시니어_가정!$E$105,0)) -> 0 | J78: =②시니어_가정!$D$38*②시니어_가정!$E$98*(②시니어_가정!$E$104*SUMIF(②시니어_가정!$J$97:$J$101,J6,②시니어_가정!$I$97:$I$101)+IF(J15=13,②시니어_가정!$E$105-②시니어_가정!$E$104,0)+IF(J15=25,②시니어_가정!$E$106-②시니어_가정!$E$105,0)) -> 0 | K78: =②시니어_가정!$D$38*②시니어_가정!$E$98*(②시니어_가정!$E$104*SUMIF(②시니어_가정!$J$97:$J$101,K6,②시니어_가정!$I$97:$I$101)+IF(K15=13,②시니어_가정!$E$105-②시니어_가정!$E$104,0)+IF(K15=25,②시니어_가정!$E$106-②시니어_가정!$E$105,0)) -> 0 | L78: =②시니어_가정!$D$38*②시니어_가정!$E$98*(②시니어_가정!$E$104*SUMIF(②시니어_가정!$J$97:$J$101,L6,②시니어_가정!$I$97:$I$101)+IF(L15=13,②시니어_가정!$E$105-②시니어_가정!$E$104,0)+IF(L15=25,②시니어_가정!$E$106-②시니어_가정!$E$105,0)) -> 0 | ... EF78: =②시니어_가정!$D$38*②시니어_가정!$E$98*(②시니어_가정!$E$104*SUMIF(②시니어_가정!$J$97:$J$101,EF6,②시니어_가정!$I$97:$I$101)+IF(EF15=13,②시니어_가정!$E$105-②시니어_가정!$E$104,0)+IF(EF15=25,②시니어_가정!$E$106-②시니어_가정!$E$105,0)) -> 0
A79: 레지던스 보증금 유입 | B79: 백만원 | C79: =SUM(E79:EF79) -> 0 | E79: =②시니어_가정!$E$38*②시니어_가정!$E$129*(②시니어_가정!$E$133*SUMIF(②시니어_가정!$L$124:$L$128,E6,②시니어_가정!$K$124:$K$128)+IF(E15=13,②시니어_가정!$E$134-②시니어_가정!$E$133,0)+IF(E15=25,②시니어_가정!$E$135-②시니어_가정!$E$134,0)) -> 0 | F79: =②시니어_가정!$E$38*②시니어_가정!$E$129*(②시니어_가정!$E$133*SUMIF(②시니어_가정!$L$124:$L$128,F6,②시니어_가정!$K$124:$K$128)+IF(F15=13,②시니어_가정!$E$134-②시니어_가정!$E$133,0)+IF(F15=25,②시니어_가정!$E$135-②시니어_가정!$E$134,0)) -> 0 | G79: =②시니어_가정!$E$38*②시니어_가정!$E$129*(②시니어_가정!$E$133*SUMIF(②시니어_가정!$L$124:$L$128,G6,②시니어_가정!$K$124:$K$128)+IF(G15=13,②시니어_가정!$E$134-②시니어_가정!$E$133,0)+IF(G15=25,②시니어_가정!$E$135-②시니어_가정!$E$134,0)) -> 0 | H79: =②시니어_가정!$E$38*②시니어_가정!$E$129*(②시니어_가정!$E$133*SUMIF(②시니어_가정!$L$124:$L$128,H6,②시니어_가정!$K$124:$K$128)+IF(H15=13,②시니어_가정!$E$134-②시니어_가정!$E$133,0)+IF(H15=25,②시니어_가정!$E$135-②시니어_가정!$E$134,0)) -> 0 | I79: =②시니어_가정!$E$38*②시니어_가정!$E$129*(②시니어_가정!$E$133*SUMIF(②시니어_가정!$L$124:$L$128,I6,②시니어_가정!$K$124:$K$128)+IF(I15=13,②시니어_가정!$E$134-②시니어_가정!$E$133,0)+IF(I15=25,②시니어_가정!$E$135-②시니어_가정!$E$134,0)) -> 0 | J79: =②시니어_가정!$E$38*②시니어_가정!$E$129*(②시니어_가정!$E$133*SUMIF(②시니어_가정!$L$124:$L$128,J6,②시니어_가정!$K$124:$K$128)+IF(J15=13,②시니어_가정!$E$134-②시니어_가정!$E$133,0)+IF(J15=25,②시니어_가정!$E$135-②시니어_가정!$E$134,0)) -> 0 | K79: =②시니어_가정!$E$38*②시니어_가정!$E$129*(②시니어_가정!$E$133*SUMIF(②시니어_가정!$L$124:$L$128,K6,②시니어_가정!$K$124:$K$128)+IF(K15=13,②시니어_가정!$E$134-②시니어_가정!$E$133,0)+IF(K15=25,②시니어_가정!$E$135-②시니어_가정!$E$134,0)) -> 0 | L79: =②시니어_가정!$E$38*②시니어_가정!$E$129*(②시니어_가정!$E$133*SUMIF(②시니어_가정!$L$124:$L$128,L6,②시니어_가정!$K$124:$K$128)+IF(L15=13,②시니어_가정!$E$134-②시니어_가정!$E$133,0)+IF(L15=25,②시니어_가정!$E$135-②시니어_가정!$E$134,0)) -> 0 | ... EF79: =②시니어_가정!$E$38*②시니어_가정!$E$129*(②시니어_가정!$E$133*SUMIF(②시니어_가정!$L$124:$L$128,EF6,②시니어_가정!$K$124:$K$128)+IF(EF15=13,②시니어_가정!$E$134-②시니어_가정!$E$133,0)+IF(EF15=25,②시니어_가정!$E$135-②시니어_가정!$E$134,0)) -> 0
A80: 호텔 회원보증금 유입 | B80: 백만원 | C80: =SUM(E80:EF80) -> 0 | E80: =②시니어_가정!$F$38*②시니어_가정!$E$151*(IF(E15=1,②시니어_가정!$E$156,0)+IF(E15=13,②시니어_가정!$E$157-②시니어_가정!$E$156,0)+IF(E15=25,②시니어_가정!$E$158-②시니어_가정!$E$157,0)) -> 0 | F80: =②시니어_가정!$F$38*②시니어_가정!$E$151*(IF(F15=1,②시니어_가정!$E$156,0)+IF(F15=13,②시니어_가정!$E$157-②시니어_가정!$E$156,0)+IF(F15=25,②시니어_가정!$E$158-②시니어_가정!$E$157,0)) -> 0 | G80: =②시니어_가정!$F$38*②시니어_가정!$E$151*(IF(G15=1,②시니어_가정!$E$156,0)+IF(G15=13,②시니어_가정!$E$157-②시니어_가정!$E$156,0)+IF(G15=25,②시니어_가정!$E$158-②시니어_가정!$E$157,0)) -> 0 | H80: =②시니어_가정!$F$38*②시니어_가정!$E$151*(IF(H15=1,②시니어_가정!$E$156,0)+IF(H15=13,②시니어_가정!$E$157-②시니어_가정!$E$156,0)+IF(H15=25,②시니어_가정!$E$158-②시니어_가정!$E$157,0)) -> 0 | I80: =②시니어_가정!$F$38*②시니어_가정!$E$151*(IF(I15=1,②시니어_가정!$E$156,0)+IF(I15=13,②시니어_가정!$E$157-②시니어_가정!$E$156,0)+IF(I15=25,②시니어_가정!$E$158-②시니어_가정!$E$157,0)) -> 0 | J80: =②시니어_가정!$F$38*②시니어_가정!$E$151*(IF(J15=1,②시니어_가정!$E$156,0)+IF(J15=13,②시니어_가정!$E$157-②시니어_가정!$E$156,0)+IF(J15=25,②시니어_가정!$E$158-②시니어_가정!$E$157,0)) -> 0 | K80: =②시니어_가정!$F$38*②시니어_가정!$E$151*(IF(K15=1,②시니어_가정!$E$156,0)+IF(K15=13,②시니어_가정!$E$157-②시니어_가정!$E$156,0)+IF(K15=25,②시니어_가정!$E$158-②시니어_가정!$E$157,0)) -> 0 | L80: =②시니어_가정!$F$38*②시니어_가정!$E$151*(IF(L15=1,②시니어_가정!$E$156,0)+IF(L15=13,②시니어_가정!$E$157-②시니어_가정!$E$156,0)+IF(L15=25,②시니어_가정!$E$158-②시니어_가정!$E$157,0)) -> 0 | ... EF80: =②시니어_가정!$F$38*②시니어_가정!$E$151*(IF(EF15=1,②시니어_가정!$E$156,0)+IF(EF15=13,②시니어_가정!$E$157-②시니어_가정!$E$156,0)+IF(EF15=25,②시니어_가정!$E$158-②시니어_가정!$E$157,0)) -> 0
A81: 시니어 부대 임대보증금 | B81: 백만원 | C81: =SUM(E81:EF81) -> 1500 | E81: =IF(E15=1,②시니어_가정!$D$38*②시니어_가정!$E$114,0) -> 0 | F81: =IF(F15=1,②시니어_가정!$D$38*②시니어_가정!$E$114,0) -> 0 | G81: =IF(G15=1,②시니어_가정!$D$38*②시니어_가정!$E$114,0) -> 0 | H81: =IF(H15=1,②시니어_가정!$D$38*②시니어_가정!$E$114,0) -> 0 | I81: =IF(I15=1,②시니어_가정!$D$38*②시니어_가정!$E$114,0) -> 0 | J81: =IF(J15=1,②시니어_가정!$D$38*②시니어_가정!$E$114,0) -> 0 | K81: =IF(K15=1,②시니어_가정!$D$38*②시니어_가정!$E$114,0) -> 0 | L81: =IF(L15=1,②시니어_가정!$D$38*②시니어_가정!$E$114,0) -> 0 | ... EF81: =IF(EF15=1,②시니어_가정!$D$38*②시니어_가정!$E$114,0) -> 0
A82: 오피스 임대보증금 | B82: 백만원 | C82: =SUM(E82:EF82) -> 0 | E82: =IF(E15=1,②시니어_가정!$G$38*②시니어_가정!$E$182,0) -> 0 | F82: =IF(F15=1,②시니어_가정!$G$38*②시니어_가정!$E$182,0) -> 0 | G82: =IF(G15=1,②시니어_가정!$G$38*②시니어_가정!$E$182,0) -> 0 | H82: =IF(H15=1,②시니어_가정!$G$38*②시니어_가정!$E$182,0) -> 0 | I82: =IF(I15=1,②시니어_가정!$G$38*②시니어_가정!$E$182,0) -> 0 | J82: =IF(J15=1,②시니어_가정!$G$38*②시니어_가정!$E$182,0) -> 0 | K82: =IF(K15=1,②시니어_가정!$G$38*②시니어_가정!$E$182,0) -> 0 | L82: =IF(L15=1,②시니어_가정!$G$38*②시니어_가정!$E$182,0) -> 0 | ... EF82: =IF(EF15=1,②시니어_가정!$G$38*②시니어_가정!$E$182,0) -> 0
A83: 부대시설 임대보증금 | B83: 백만원 | C83: =SUM(E83:EF83) -> 0 | E83: =IF(E15=1,②시니어_가정!$H$38*(②시니어_가정!$E$200+②시니어_가정!$E$213+②시니어_가정!$E$226+②시니어_가정!$E$239+②시니어_가정!$E$252),0) -> 0 | F83: =IF(F15=1,②시니어_가정!$H$38*(②시니어_가정!$E$200+②시니어_가정!$E$213+②시니어_가정!$E$226+②시니어_가정!$E$239+②시니어_가정!$E$252),0) -> 0 | G83: =IF(G15=1,②시니어_가정!$H$38*(②시니어_가정!$E$200+②시니어_가정!$E$213+②시니어_가정!$E$226+②시니어_가정!$E$239+②시니어_가정!$E$252),0) -> 0 | H83: =IF(H15=1,②시니어_가정!$H$38*(②시니어_가정!$E$200+②시니어_가정!$E$213+②시니어_가정!$E$226+②시니어_가정!$E$239+②시니어_가정!$E$252),0) -> 0 | I83: =IF(I15=1,②시니어_가정!$H$38*(②시니어_가정!$E$200+②시니어_가정!$E$213+②시니어_가정!$E$226+②시니어_가정!$E$239+②시니어_가정!$E$252),0) -> 0 | J83: =IF(J15=1,②시니어_가정!$H$38*(②시니어_가정!$E$200+②시니어_가정!$E$213+②시니어_가정!$E$226+②시니어_가정!$E$239+②시니어_가정!$E$252),0) -> 0 | K83: =IF(K15=1,②시니어_가정!$H$38*(②시니어_가정!$E$200+②시니어_가정!$E$213+②시니어_가정!$E$226+②시니어_가정!$E$239+②시니어_가정!$E$252),0) -> 0 | L83: =IF(L15=1,②시니어_가정!$H$38*(②시니어_가정!$E$200+②시니어_가정!$E$213+②시니어_가정!$E$226+②시니어_가정!$E$239+②시니어_가정!$E$252),0) -> 0 | ... EF83: =IF(EF15=1,②시니어_가정!$H$38*(②시니어_가정!$E$200+②시니어_가정!$E$213+②시니어_가정!$E$226+②시니어_가정!$E$239+②시니어_가정!$E$252),0) -> 0
A84: 보증금 유입 합계 | B84: 백만원 | C84: =SUM(E84:EF84) -> 541500 | E84: =SUM(E78:E83) -> 0 | F84: =SUM(F78:F83) -> 0 | G84: =SUM(G78:G83) -> 0 | H84: =SUM(H78:H83) -> 0 | I84: =SUM(I78:I83) -> 0 | J84: =SUM(J78:J83) -> 0 | K84: =SUM(K78:K83) -> 0 | L84: =SUM(L78:L83) -> 0 | ... EF84: =SUM(EF78:EF83) -> 0
A85: 보증금 승계(처분시 매수인 인계) | B85: 백만원 | C85: =SUM(E85:EF85) -> 541500 | E85: =IF(E6=②시니어_가정!$E$22,0+E84,0) -> 0 | F85: =IF(F6=②시니어_가정!$E$22,E86+F84,0) -> 0 | G85: =IF(G6=②시니어_가정!$E$22,F86+G84,0) -> 0 | H85: =IF(H6=②시니어_가정!$E$22,G86+H84,0) -> 0 | I85: =IF(I6=②시니어_가정!$E$22,H86+I84,0) -> 0 | J85: =IF(J6=②시니어_가정!$E$22,I86+J84,0) -> 0 | K85: =IF(K6=②시니어_가정!$E$22,J86+K84,0) -> 0 | L85: =IF(L6=②시니어_가정!$E$22,K86+L84,0) -> 0 | M85: =IF(M6=②시니어_가정!$E$22,L86+M84,0) -> 0 | ... EF85: =IF(EF6=②시니어_가정!$E$22,EE86+EF84,0) -> 0
A86: 보증금 잔액 | B86: 백만원 | C86: =MAX(E86:EF86) -> 541500 | E86: =0+E84-E85 -> 0 | F86: =E86+F84-F85 -> 0 | G86: =F86+G84-G85 -> 0 | H86: =G86+H84-H85 -> 0 | I86: =H86+I84-I85 -> 0 | J86: =I86+J84-J85 -> 0 | K86: =J86+K84-K85 -> 0 | L86: =K86+L84-L85 -> 0 | M86: =L86+M84-M85 -> 0 | ... EF86: =EE86+EF84-EF85 -> 0
A88: 개발사업비 집행 (공제후 순액)
A89: 토지 계약금 | B89: 백만원 | C89: =SUM(E89:EF89) -> 3093.5767 | E89: =IF(E6=②시니어_가정!$E$10,②시니어_가정!$R$358*②시니어_가정!$D$554,0) -> 0 | F89: =IF(F6=②시니어_가정!$E$10,②시니어_가정!$R$358*②시니어_가정!$D$554,0) -> 0 | G89: =IF(G6=②시니어_가정!$E$10,②시니어_가정!$R$358*②시니어_가정!$D$554,0) -> 0 | H89: =IF(H6=②시니어_가정!$E$10,②시니어_가정!$R$358*②시니어_가정!$D$554,0) -> 3093.5767 | I89: =IF(I6=②시니어_가정!$E$10,②시니어_가정!$R$358*②시니어_가정!$D$554,0) -> 0 | J89: =IF(J6=②시니어_가정!$E$10,②시니어_가정!$R$358*②시니어_가정!$D$554,0) -> 0 | K89: =IF(K6=②시니어_가정!$E$10,②시니어_가정!$R$358*②시니어_가정!$D$554,0) -> 0 | L89: =IF(L6=②시니어_가정!$E$10,②시니어_가정!$R$358*②시니어_가정!$D$554,0) -> 0 | ... EF89: =IF(EF6=②시니어_가정!$E$10,②시니어_가정!$R$358*②시니어_가정!$D$554,0) -> 0
A90: 토지 잔금·취득세·임차료·등기 | B90: 백만원 | C90: =SUM(E90:EF90) -> 62242.763 | E90: =IF(E6=②시니어_가정!$E$14,②시니어_가정!$R$358*(1-②시니어_가정!$D$554)+②시니어_가정!$R$359+②시니어_가정!$R$360+②시니어_가정!$R$361,0) -> 0 | F90: =IF(F6=②시니어_가정!$E$14,②시니어_가정!$R$358*(1-②시니어_가정!$D$554)+②시니어_가정!$R$359+②시니어_가정!$R$360+②시니어_가정!$R$361,0) -> 0 | G90: =IF(G6=②시니어_가정!$E$14,②시니어_가정!$R$358*(1-②시니어_가정!$D$554)+②시니어_가정!$R$359+②시니어_가정!$R$360+②시니어_가정!$R$361,0) -> 0 | H90: =IF(H6=②시니어_가정!$E$14,②시니어_가정!$R$358*(1-②시니어_가정!$D$554)+②시니어_가정!$R$359+②시니어_가정!$R$360+②시니어_가정!$R$361,0) -> 0 | I90: =IF(I6=②시니어_가정!$E$14,②시니어_가정!$R$358*(1-②시니어_가정!$D$554)+②시니어_가정!$R$359+②시니어_가정!$R$360+②시니어_가정!$R$361,0) -> 0 | J90: =IF(J6=②시니어_가정!$E$14,②시니어_가정!$R$358*(1-②시니어_가정!$D$554)+②시니어_가정!$R$359+②시니어_가정!$R$360+②시니어_가정!$R$361,0) -> 0 | K90: =IF(K6=②시니어_가정!$E$14,②시니어_가정!$R$358*(1-②시니어_가정!$D$554)+②시니어_가정!$R$359+②시니어_가정!$R$360+②시니어_가정!$R$361,0) -> 0 | L90: =IF(L6=②시니어_가정!$E$14,②시니어_가정!$R$358*(1-②시니어_가정!$D$554)+②시니어_가정!$R$359+②시니어_가정!$R$360+②시니어_가정!$R$361,0) -> 0 | ... EF90: =IF(EF6=②시니어_가정!$E$14,②시니어_가정!$R$358*(1-②시니어_가정!$D$554)+②시니어_가정!$R$359+②시니어_가정!$R$360+②시니어_가정!$R$361,0) -> 0
A91: 토지보유세(건설기간) | B91: 백만원 | C91: =SUM(E91:EF91) -> 1497.2911 | E91: =E11*②시니어_가정!$R$362/②시니어_가정!$E$15 -> 0 | F91: =F11*②시니어_가정!$R$362/②시니어_가정!$E$15 -> 0 | G91: =G11*②시니어_가정!$R$362/②시니어_가정!$E$15 -> 0 | H91: =H11*②시니어_가정!$R$362/②시니어_가정!$E$15 -> 0 | I91: =I11*②시니어_가정!$R$362/②시니어_가정!$E$15 -> 0 | J91: =J11*②시니어_가정!$R$362/②시니어_가정!$E$15 -> 0 | K91: =K11*②시니어_가정!$R$362/②시니어_가정!$E$15 -> 0 | L91: =L11*②시니어_가정!$R$362/②시니어_가정!$E$15 -> 0 | ... EF91: =EF11*②시니어_가정!$R$362/②시니어_가정!$E$15 -> 0
A92: 직접공사비(유보금 제외, S-curve) | B92: 백만원 | C92: =SUM(E92:EF92) -> 174534.72 | E92: =E13*(②시니어_가정!$R$367-②시니어_가정!$E$433) -> 0 | F92: =F13*(②시니어_가정!$R$367-②시니어_가정!$E$433) -> 0 | G92: =G13*(②시니어_가정!$R$367-②시니어_가정!$E$433) -> 0 | H92: =H13*(②시니어_가정!$R$367-②시니어_가정!$E$433) -> 0 | I92: =I13*(②시니어_가정!$R$367-②시니어_가정!$E$433) -> 0 | J92: =J13*(②시니어_가정!$R$367-②시니어_가정!$E$433) -> 0 | K92: =K13*(②시니어_가정!$R$367-②시니어_가정!$E$433) -> 0 | L92: =L13*(②시니어_가정!$R$367-②시니어_가정!$E$433) -> 0 | ... EF92: =EF13*(②시니어_가정!$R$367-②시니어_가정!$E$433) -> 0
A93: 공사비 유보금 지급 | B93: 백만원 | C93: =SUM(E93:EF93) -> 17453.472 | E93: =IF(E6=②시니어_가정!$E$18,②시니어_가정!$E$433,0) -> 0 | F93: =IF(F6=②시니어_가정!$E$18,②시니어_가정!$E$433,0) -> 0 | G93: =IF(G6=②시니어_가정!$E$18,②시니어_가정!$E$433,0) -> 0 | H93: =IF(H6=②시니어_가정!$E$18,②시니어_가정!$E$433,0) -> 0 | I93: =IF(I6=②시니어_가정!$E$18,②시니어_가정!$E$433,0) -> 0 | J93: =IF(J6=②시니어_가정!$E$18,②시니어_가정!$E$433,0) -> 0 | K93: =IF(K6=②시니어_가정!$E$18,②시니어_가정!$E$433,0) -> 0 | L93: =IF(L6=②시니어_가정!$E$18,②시니어_가정!$E$433,0) -> 0 | ... EF93: =IF(EF6=②시니어_가정!$E$18,②시니어_가정!$E$433,0) -> 0
A94: 간접공사비(S-curve) | B94: 백만원 | C94: =SUM(E94:EF94) -> 118414.72 | E94: =E13*②시니어_가정!$R$381 -> 0 | F94: =F13*②시니어_가정!$R$381 -> 0 | G94: =G13*②시니어_가정!$R$381 -> 0 | H94: =H13*②시니어_가정!$R$381 -> 0 | I94: =I13*②시니어_가정!$R$381 -> 0 | J94: =J13*②시니어_가정!$R$381 -> 0 | K94: =K13*②시니어_가정!$R$381 -> 0 | L94: =L13*②시니어_가정!$R$381 -> 0 | ... EF94: =EF13*②시니어_가정!$R$381 -> 0
A95: 판매비 | B95: 백만원 | C95: =SUM(E95:EF95) -> 11000 | E95: =E11*②시니어_가정!$R$386/②시니어_가정!$E$15 -> 0 | F95: =F11*②시니어_가정!$R$386/②시니어_가정!$E$15 -> 0 | G95: =G11*②시니어_가정!$R$386/②시니어_가정!$E$15 -> 0 | H95: =H11*②시니어_가정!$R$386/②시니어_가정!$E$15 -> 0 | I95: =I11*②시니어_가정!$R$386/②시니어_가정!$E$15 -> 0 | J95: =J11*②시니어_가정!$R$386/②시니어_가정!$E$15 -> 0 | K95: =K11*②시니어_가정!$R$386/②시니어_가정!$E$15 -> 0 | L95: =L11*②시니어_가정!$R$386/②시니어_가정!$E$15 -> 0 | ... EF95: =EF11*②시니어_가정!$R$386/②시니어_가정!$E$15 -> 0
A96: 부대비용(보존등기비 등) | B96: 백만원 | C96: =SUM(E96:EF96) -> 6542.0982 | E96: =IF(E6=②시니어_가정!$E$16,②시니어_가정!$R$389,0) -> 0 | F96: =IF(F6=②시니어_가정!$E$16,②시니어_가정!$R$389,0) -> 0 | G96: =IF(G6=②시니어_가정!$E$16,②시니어_가정!$R$389,0) -> 0 | H96: =IF(H6=②시니어_가정!$E$16,②시니어_가정!$R$389,0) -> 0 | I96: =IF(I6=②시니어_가정!$E$16,②시니어_가정!$R$389,0) -> 0 | J96: =IF(J6=②시니어_가정!$E$16,②시니어_가정!$R$389,0) -> 0 | K96: =IF(K6=②시니어_가정!$E$16,②시니어_가정!$R$389,0) -> 0 | L96: =IF(L6=②시니어_가정!$E$16,②시니어_가정!$R$389,0) -> 0 | ... EF96: =IF(EF6=②시니어_가정!$E$16,②시니어_가정!$R$389,0) -> 0
A97: 리츠운용비(일시: 등록면허세·실사·예비비) | B97: 백만원 | C97: =SUM(E97:EF97) -> 926.82246 | E97: =IF(E6=②시니어_가정!$E$8,②시니어_가정!$R$409+②시니어_가정!$R$410+②시니어_가정!$R$411,0) -> 926.82246 | F97: =IF(F6=②시니어_가정!$E$8,②시니어_가정!$R$409+②시니어_가정!$R$410+②시니어_가정!$R$411,0) -> 0 | G97: =IF(G6=②시니어_가정!$E$8,②시니어_가정!$R$409+②시니어_가정!$R$410+②시니어_가정!$R$411,0) -> 0 | H97: =IF(H6=②시니어_가정!$E$8,②시니어_가정!$R$409+②시니어_가정!$R$410+②시니어_가정!$R$411,0) -> 0 | I97: =IF(I6=②시니어_가정!$E$8,②시니어_가정!$R$409+②시니어_가정!$R$410+②시니어_가정!$R$411,0) -> 0 | J97: =IF(J6=②시니어_가정!$E$8,②시니어_가정!$R$409+②시니어_가정!$R$410+②시니어_가정!$R$411,0) -> 0 | K97: =IF(K6=②시니어_가정!$E$8,②시니어_가정!$R$409+②시니어_가정!$R$410+②시니어_가정!$R$411,0) -> 0 | L97: =IF(L6=②시니어_가정!$E$8,②시니어_가정!$R$409+②시니어_가정!$R$410+②시니어_가정!$R$411,0) -> 0 | ... EF97: =IF(EF6=②시니어_가정!$E$8,②시니어_가정!$R$409+②시니어_가정!$R$410+②시니어_가정!$R$411,0) -> 0
A98: 리츠운용비(매입보수) | B98: 백만원 | C98: =SUM(E98:EF98) -> 1437.3995 | E98: =IF(E6=②시니어_가정!$E$14,②시니어_가정!$R$404,0) -> 0 | F98: =IF(F6=②시니어_가정!$E$14,②시니어_가정!$R$404,0) -> 0 | G98: =IF(G6=②시니어_가정!$E$14,②시니어_가정!$R$404,0) -> 0 | H98: =IF(H6=②시니어_가정!$E$14,②시니어_가정!$R$404,0) -> 0 | I98: =IF(I6=②시니어_가정!$E$14,②시니어_가정!$R$404,0) -> 0 | J98: =IF(J6=②시니어_가정!$E$14,②시니어_가정!$R$404,0) -> 0 | K98: =IF(K6=②시니어_가정!$E$14,②시니어_가정!$R$404,0) -> 0 | L98: =IF(L6=②시니어_가정!$E$14,②시니어_가정!$R$404,0) -> 0 | ... EF98: =IF(EF6=②시니어_가정!$E$14,②시니어_가정!$R$404,0) -> 0
A99: 리츠운용비(개발기간 정기) | B99: 백만원 | C99: =SUM(E99:EF99) -> 5967.5 | E99: =E10*(②시니어_가정!$R$403+②시니어_가정!$R$405+②시니어_가정!$R$406+②시니어_가정!$R$407+②시니어_가정!$R$408)/(②시니어_가정!$E$25*12) -> 99.458333 | F99: =F10*(②시니어_가정!$R$403+②시니어_가정!$R$405+②시니어_가정!$R$406+②시니어_가정!$R$407+②시니어_가정!$R$408)/(②시니어_가정!$E$25*12) -> 99.458333 | G99: =G10*(②시니어_가정!$R$403+②시니어_가정!$R$405+②시니어_가정!$R$406+②시니어_가정!$R$407+②시니어_가정!$R$408)/(②시니어_가정!$E$25*12) -> 99.458333 | H99: =H10*(②시니어_가정!$R$403+②시니어_가정!$R$405+②시니어_가정!$R$406+②시니어_가정!$R$407+②시니어_가정!$R$408)/(②시니어_가정!$E$25*12) -> 99.458333 | I99: =I10*(②시니어_가정!$R$403+②시니어_가정!$R$405+②시니어_가정!$R$406+②시니어_가정!$R$407+②시니어_가정!$R$408)/(②시니어_가정!$E$25*12) -> 99.458333 | J99: =J10*(②시니어_가정!$R$403+②시니어_가정!$R$405+②시니어_가정!$R$406+②시니어_가정!$R$407+②시니어_가정!$R$408)/(②시니어_가정!$E$25*12) -> 99.458333 | K99: =K10*(②시니어_가정!$R$403+②시니어_가정!$R$405+②시니어_가정!$R$406+②시니어_가정!$R$407+②시니어_가정!$R$408)/(②시니어_가정!$E$25*12) -> 99.458333 | L99: =L10*(②시니어_가정!$R$403+②시니어_가정!$R$405+②시니어_가정!$R$406+②시니어_가정!$R$407+②시니어_가정!$R$408)/(②시니어_가정!$E$25*12) -> 99.458333 | ... EF99: =EF10*(②시니어_가정!$R$403+②시니어_가정!$R$405+②시니어_가정!$R$406+②시니어_가정!$R$407+②시니어_가정!$R$408)/(②시니어_가정!$E$25*12) -> 0
A100: 개발사업비 집행 합계 | B100: 백만원 | C100: =SUM(E100:EF100) -> 403110.36 | E100: =SUM(E89:E99) -> 1026.2808 | F100: =SUM(F89:F99) -> 99.458333 | G100: =SUM(G89:G99) -> 99.458333 | H100: =SUM(H89:H99) -> 3193.035 | I100: =SUM(I89:I99) -> 99.458333 | J100: =SUM(J89:J99) -> 99.458333 | K100: =SUM(K89:K99) -> 99.458333 | L100: =SUM(L89:L99) -> 99.458333 | ... EF100: =SUM(EF89:EF99) -> 0
A102: PF (개발기간)
A103: Tr.A 취급수수료 | B103: 백만원 | C103: =SUM(E103:EF103) -> 2267.6022 | E103: =IF(E6=②시니어_가정!$E$14,②시니어_가정!$E$452*②시니어_가정!$J$483,0) -> 0 | F103: =IF(F6=②시니어_가정!$E$14,②시니어_가정!$E$452*②시니어_가정!$J$483,0) -> 0 | G103: =IF(G6=②시니어_가정!$E$14,②시니어_가정!$E$452*②시니어_가정!$J$483,0) -> 0 | H103: =IF(H6=②시니어_가정!$E$14,②시니어_가정!$E$452*②시니어_가정!$J$483,0) -> 0 | I103: =IF(I6=②시니어_가정!$E$14,②시니어_가정!$E$452*②시니어_가정!$J$483,0) -> 0 | J103: =IF(J6=②시니어_가정!$E$14,②시니어_가정!$E$452*②시니어_가정!$J$483,0) -> 0 | K103: =IF(K6=②시니어_가정!$E$14,②시니어_가정!$E$452*②시니어_가정!$J$483,0) -> 0 | L103: =IF(L6=②시니어_가정!$E$14,②시니어_가정!$E$452*②시니어_가정!$J$483,0) -> 0 | ... EF103: =IF(EF6=②시니어_가정!$E$14,②시니어_가정!$E$452*②시니어_가정!$J$483,0) -> 0
A104: Tr.B 취급수수료 | B104: 백만원 | C104: =SUM(E104:EF104) -> 453.64743 | E104: =IF(E6=②시니어_가정!$E$14,②시니어_가정!$E$453*②시니어_가정!$J$484,0) -> 0 | F104: =IF(F6=②시니어_가정!$E$14,②시니어_가정!$E$453*②시니어_가정!$J$484,0) -> 0 | G104: =IF(G6=②시니어_가정!$E$14,②시니어_가정!$E$453*②시니어_가정!$J$484,0) -> 0 | H104: =IF(H6=②시니어_가정!$E$14,②시니어_가정!$E$453*②시니어_가정!$J$484,0) -> 0 | I104: =IF(I6=②시니어_가정!$E$14,②시니어_가정!$E$453*②시니어_가정!$J$484,0) -> 0 | J104: =IF(J6=②시니어_가정!$E$14,②시니어_가정!$E$453*②시니어_가정!$J$484,0) -> 0 | K104: =IF(K6=②시니어_가정!$E$14,②시니어_가정!$E$453*②시니어_가정!$J$484,0) -> 0 | L104: =IF(L6=②시니어_가정!$E$14,②시니어_가정!$E$453*②시니어_가정!$J$484,0) -> 0 | ... EF104: =IF(EF6=②시니어_가정!$E$14,②시니어_가정!$E$453*②시니어_가정!$J$484,0) -> 0
A105: Tr.C 취급수수료 | B105: 백만원 | C105: =SUM(E105:EF105) -> 453.32997 | E105: =IF(E6=②시니어_가정!$E$14,②시니어_가정!$E$454*②시니어_가정!$J$485,0) -> 0 | F105: =IF(F6=②시니어_가정!$E$14,②시니어_가정!$E$454*②시니어_가정!$J$485,0) -> 0 | G105: =IF(G6=②시니어_가정!$E$14,②시니어_가정!$E$454*②시니어_가정!$J$485,0) -> 0 | H105: =IF(H6=②시니어_가정!$E$14,②시니어_가정!$E$454*②시니어_가정!$J$485,0) -> 0 | I105: =IF(I6=②시니어_가정!$E$14,②시니어_가정!$E$454*②시니어_가정!$J$485,0) -> 0 | J105: =IF(J6=②시니어_가정!$E$14,②시니어_가정!$E$454*②시니어_가정!$J$485,0) -> 0 | K105: =IF(K6=②시니어_가정!$E$14,②시니어_가정!$E$454*②시니어_가정!$J$485,0) -> 0 | L105: =IF(L6=②시니어_가정!$E$14,②시니어_가정!$E$454*②시니어_가정!$J$485,0) -> 0 | ... EF105: =IF(EF6=②시니어_가정!$E$14,②시니어_가정!$E$454*②시니어_가정!$J$485,0) -> 0
A106: Tr.A 이자비용 | B106: 백만원 | C106: =SUM(E106:EF106) -> 0 | E106: =0*②시니어_가정!$K$483/12 -> 0 | F106: =E121*②시니어_가정!$K$483/12 -> 0 | G106: =F121*②시니어_가정!$K$483/12 -> 0 | H106: =G121*②시니어_가정!$K$483/12 -> 0 | I106: =H121*②시니어_가정!$K$483/12 -> 0 | J106: =I121*②시니어_가정!$K$483/12 -> 0 | K106: =J121*②시니어_가정!$K$483/12 -> 0 | L106: =K121*②시니어_가정!$K$483/12 -> 0 | M106: =L121*②시니어_가정!$K$483/12 -> 0 | ... EF106: =EE121*②시니어_가정!$K$483/12 -> 0
A107: Tr.B 이자비용 | B107: 백만원 | C107: =SUM(E107:EF107) -> 0 | E107: =0*②시니어_가정!$K$484/12 -> 0 | F107: =E122*②시니어_가정!$K$484/12 -> 0 | G107: =F122*②시니어_가정!$K$484/12 -> 0 | H107: =G122*②시니어_가정!$K$484/12 -> 0 | I107: =H122*②시니어_가정!$K$484/12 -> 0 | J107: =I122*②시니어_가정!$K$484/12 -> 0 | K107: =J122*②시니어_가정!$K$484/12 -> 0 | L107: =K122*②시니어_가정!$K$484/12 -> 0 | M107: =L122*②시니어_가정!$K$484/12 -> 0 | ... EF107: =EE122*②시니어_가정!$K$484/12 -> 0
A108: Tr.C 이자비용 | B108: 백만원 | C108: =SUM(E108:EF108) -> 2582.1886 | E108: =0*②시니어_가정!$K$485/12 -> 0 | F108: =E123*②시니어_가정!$K$485/12 -> 0 | G108: =F123*②시니어_가정!$K$485/12 -> 0 | H108: =G123*②시니어_가정!$K$485/12 -> 0 | I108: =H123*②시니어_가정!$K$485/12 -> 0 | J108: =I123*②시니어_가정!$K$485/12 -> 0 | K108: =J123*②시니어_가정!$K$485/12 -> 0 | L108: =K123*②시니어_가정!$K$485/12 -> 0 | M108: =L123*②시니어_가정!$K$485/12 -> 0 | ... EF108: =EE123*②시니어_가정!$K$485/12 -> 0
A109: Tr.A 미인출수수료 | B109: 백만원 | C109: =SUM(E109:EF109) -> 3968.3039 | E109: =E11*MAX(0,②시니어_가정!$E$452-0)*②시니어_가정!$O$483/12 -> 0 | F109: =F11*MAX(0,②시니어_가정!$E$452-E121)*②시니어_가정!$O$483/12 -> 0 | G109: =G11*MAX(0,②시니어_가정!$E$452-F121)*②시니어_가정!$O$483/12 -> 0 | H109: =H11*MAX(0,②시니어_가정!$E$452-G121)*②시니어_가정!$O$483/12 -> 0 | I109: =I11*MAX(0,②시니어_가정!$E$452-H121)*②시니어_가정!$O$483/12 -> 0 | J109: =J11*MAX(0,②시니어_가정!$E$452-I121)*②시니어_가정!$O$483/12 -> 0 | K109: =K11*MAX(0,②시니어_가정!$E$452-J121)*②시니어_가정!$O$483/12 -> 0 | L109: =L11*MAX(0,②시니어_가정!$E$452-K121)*②시니어_가정!$O$483/12 -> 0 | M109: =M11*MAX(0,②시니어_가정!$E$452-L121)*②시니어_가정!$O$483/12 -> 0 | ... EF109: =EF11*MAX(0,②시니어_가정!$E$452-EE121)*②시니어_가정!$O$483/12 -> 0
...

Sheet ②시니어_연도별
A1: 연도별 요약 (CF 시트 집계) — 단위: 백만원
A3: 구분 | B3: 합계 | C3: =YEAR(②시니어_가정!$E$8) -> 2026 | D3: =C3+1 -> 2027 | E3: =D3+1 -> 2028 | F3: =E3+1 -> 2029 | G3: =F3+1 -> 2030 | H3: =G3+1 -> 2031 | I3: =H3+1 -> 2032 | J3: =I3+1 -> 2033 | K3: =J3+1 -> 2034 | ... M3: =L3+1 -> 2036
A4: 운영
A5: 운영수입 합계 | B5: =SUM(C5:M5) -> 120999.07 | C5: =SUMIF(②시니어_CF!$E$7:$EF$7,C$3,②시니어_CF!$E$41:$EF$41) -> 0 | D5: =SUMIF(②시니어_CF!$E$7:$EF$7,D$3,②시니어_CF!$E$41:$EF$41) -> 0 | E5: =SUMIF(②시니어_CF!$E$7:$EF$7,E$3,②시니어_CF!$E$41:$EF$41) -> 0 | F5: =SUMIF(②시니어_CF!$E$7:$EF$7,F$3,②시니어_CF!$E$41:$EF$41) -> 0 | G5: =SUMIF(②시니어_CF!$E$7:$EF$7,G$3,②시니어_CF!$E$41:$EF$41) -> 0 | H5: =SUMIF(②시니어_CF!$E$7:$EF$7,H$3,②시니어_CF!$E$41:$EF$41) -> 16365.804 | I5: =SUMIF(②시니어_CF!$E$7:$EF$7,I$3,②시니어_CF!$E$41:$EF$41) -> 23766.801 | J5: =SUMIF(②시니어_CF!$E$7:$EF$7,J$3,②시니어_CF!$E$41:$EF$41) -> 25002.241 | ... M5: =SUMIF(②시니어_CF!$E$7:$EF$7,M$3,②시니어_CF!$E$41:$EF$41) -> 4349.603
A6: 직접운영비용 | B6: =SUM(C6:M6) -> 88377.554 | C6: =SUMIF(②시니어_CF!$E$7:$EF$7,C$3,②시니어_CF!$E$56:$EF$56) -> 0 | D6: =SUMIF(②시니어_CF!$E$7:$EF$7,D$3,②시니어_CF!$E$56:$EF$56) -> 0 | E6: =SUMIF(②시니어_CF!$E$7:$EF$7,E$3,②시니어_CF!$E$56:$EF$56) -> 0 | F6: =SUMIF(②시니어_CF!$E$7:$EF$7,F$3,②시니어_CF!$E$56:$EF$56) -> 0 | G6: =SUMIF(②시니어_CF!$E$7:$EF$7,G$3,②시니어_CF!$E$56:$EF$56) -> 0 | H6: =SUMIF(②시니어_CF!$E$7:$EF$7,H$3,②시니어_CF!$E$56:$EF$56) -> 11774.16 | I6: =SUMIF(②시니어_CF!$E$7:$EF$7,I$3,②시니어_CF!$E$56:$EF$56) -> 17366.886 | J6: =SUMIF(②시니어_CF!$E$7:$EF$7,J$3,②시니어_CF!$E$56:$EF$56) -> 18314.706 | ... M6: =SUMIF(②시니어_CF!$E$7:$EF$7,M$3,②시니어_CF!$E$56:$EF$56) -> 3186.1824
A7: NOI - 시니어 레지던스 | B7: =SUM(C7:M7) -> 32621.512 | C7: =SUMIF(②시니어_CF!$E$7:$EF$7,C$3,②시니어_CF!$E$59:$EF$59) -> 0 | D7: =SUMIF(②시니어_CF!$E$7:$EF$7,D$3,②시니어_CF!$E$59:$EF$59) -> 0 | E7: =SUMIF(②시니어_CF!$E$7:$EF$7,E$3,②시니어_CF!$E$59:$EF$59) -> 0 | F7: =SUMIF(②시니어_CF!$E$7:$EF$7,F$3,②시니어_CF!$E$59:$EF$59) -> 0 | G7: =SUMIF(②시니어_CF!$E$7:$EF$7,G$3,②시니어_CF!$E$59:$EF$59) -> 0 | H7: =SUMIF(②시니어_CF!$E$7:$EF$7,H$3,②시니어_CF!$E$59:$EF$59) -> 4591.644 | I7: =SUMIF(②시니어_CF!$E$7:$EF$7,I$3,②시니어_CF!$E$59:$EF$59) -> 6399.9149 | J7: =SUMIF(②시니어_CF!$E$7:$EF$7,J$3,②시니어_CF!$E$59:$EF$59) -> 6687.535 | ... M7: =SUMIF(②시니어_CF!$E$7:$EF$7,M$3,②시니어_CF!$E$59:$EF$59) -> 1163.4206
A8: NOI - 레지던스 | B8: =SUM(C8:M8) -> 0 | C8: =SUMIF(②시니어_CF!$E$7:$EF$7,C$3,②시니어_CF!$E$60:$EF$60) -> 0 | D8: =SUMIF(②시니어_CF!$E$7:$EF$7,D$3,②시니어_CF!$E$60:$EF$60) -> 0 | E8: =SUMIF(②시니어_CF!$E$7:$EF$7,E$3,②시니어_CF!$E$60:$EF$60) -> 0 | F8: =SUMIF(②시니어_CF!$E$7:$EF$7,F$3,②시니어_CF!$E$60:$EF$60) -> 0 | G8: =SUMIF(②시니어_CF!$E$7:$EF$7,G$3,②시니어_CF!$E$60:$EF$60) -> 0 | H8: =SUMIF(②시니어_CF!$E$7:$EF$7,H$3,②시니어_CF!$E$60:$EF$60) -> 0 | I8: =SUMIF(②시니어_CF!$E$7:$EF$7,I$3,②시니어_CF!$E$60:$EF$60) -> 0 | J8: =SUMIF(②시니어_CF!$E$7:$EF$7,J$3,②시니어_CF!$E$60:$EF$60) -> 0 | ... M8: =SUMIF(②시니어_CF!$E$7:$EF$7,M$3,②시니어_CF!$E$60:$EF$60) -> 0
A9: NOI - 호텔 | B9: =SUM(C9:M9) -> 0 | C9: =SUMIF(②시니어_CF!$E$7:$EF$7,C$3,②시니어_CF!$E$61:$EF$61) -> 0 | D9: =SUMIF(②시니어_CF!$E$7:$EF$7,D$3,②시니어_CF!$E$61:$EF$61) -> 0 | E9: =SUMIF(②시니어_CF!$E$7:$EF$7,E$3,②시니어_CF!$E$61:$EF$61) -> 0 | F9: =SUMIF(②시니어_CF!$E$7:$EF$7,F$3,②시니어_CF!$E$61:$EF$61) -> 0 | G9: =SUMIF(②시니어_CF!$E$7:$EF$7,G$3,②시니어_CF!$E$61:$EF$61) -> 0 | H9: =SUMIF(②시니어_CF!$E$7:$EF$7,H$3,②시니어_CF!$E$61:$EF$61) -> 0 | I9: =SUMIF(②시니어_CF!$E$7:$EF$7,I$3,②시니어_CF!$E$61:$EF$61) -> 0 | J9: =SUMIF(②시니어_CF!$E$7:$EF$7,J$3,②시니어_CF!$E$61:$EF$61) -> 0 | ... M9: =SUMIF(②시니어_CF!$E$7:$EF$7,M$3,②시니어_CF!$E$61:$EF$61) -> 0
A10: NOI - 오피스 | B10: =SUM(C10:M10) -> 0 | C10: =SUMIF(②시니어_CF!$E$7:$EF$7,C$3,②시니어_CF!$E$62:$EF$62) -> 0 | D10: =SUMIF(②시니어_CF!$E$7:$EF$7,D$3,②시니어_CF!$E$62:$EF$62) -> 0 | E10: =SUMIF(②시니어_CF!$E$7:$EF$7,E$3,②시니어_CF!$E$62:$EF$62) -> 0 | F10: =SUMIF(②시니어_CF!$E$7:$EF$7,F$3,②시니어_CF!$E$62:$EF$62) -> 0 | G10: =SUMIF(②시니어_CF!$E$7:$EF$7,G$3,②시니어_CF!$E$62:$EF$62) -> 0 | H10: =SUMIF(②시니어_CF!$E$7:$EF$7,H$3,②시니어_CF!$E$62:$EF$62) -> 0 | I10: =SUMIF(②시니어_CF!$E$7:$EF$7,I$3,②시니어_CF!$E$62:$EF$62) -> 0 | J10: =SUMIF(②시니어_CF!$E$7:$EF$7,J$3,②시니어_CF!$E$62:$EF$62) -> 0 | ... M10: =SUMIF(②시니어_CF!$E$7:$EF$7,M$3,②시니어_CF!$E$62:$EF$62) -> 0
A11: NOI - 부대시설 | B11: =SUM(C11:M11) -> 0 | C11: =SUMIF(②시니어_CF!$E$7:$EF$7,C$3,②시니어_CF!$E$63:$EF$63) -> 0 | D11: =SUMIF(②시니어_CF!$E$7:$EF$7,D$3,②시니어_CF!$E$63:$EF$63) -> 0 | E11: =SUMIF(②시니어_CF!$E$7:$EF$7,E$3,②시니어_CF!$E$63:$EF$63) -> 0 | F11: =SUMIF(②시니어_CF!$E$7:$EF$7,F$3,②시니어_CF!$E$63:$EF$63) -> 0 | G11: =SUMIF(②시니어_CF!$E$7:$EF$7,G$3,②시니어_CF!$E$63:$EF$63) -> 0 | H11: =SUMIF(②시니어_CF!$E$7:$EF$7,H$3,②시니어_CF!$E$63:$EF$63) -> 0 | I11: =SUMIF(②시니어_CF!$E$7:$EF$7,I$3,②시니어_CF!$E$63:$EF$63) -> 0 | J11: =SUMIF(②시니어_CF!$E$7:$EF$7,J$3,②시니어_CF!$E$63:$EF$63) -> 0 | ... M11: =SUMIF(②시니어_CF!$E$7:$EF$7,M$3,②시니어_CF!$E$63:$EF$63) -> 0
A12: NOI 합계 | B12: =SUM(C12:M12) -> 32621.512 | C12: =SUMIF(②시니어_CF!$E$7:$EF$7,C$3,②시니어_CF!$E$64:$EF$64) -> 0 | D12: =SUMIF(②시니어_CF!$E$7:$EF$7,D$3,②시니어_CF!$E$64:$EF$64) -> 0 | E12: =SUMIF(②시니어_CF!$E$7:$EF$7,E$3,②시니어_CF!$E$64:$EF$64) -> 0 | F12: =SUMIF(②시니어_CF!$E$7:$EF$7,F$3,②시니어_CF!$E$64:$EF$64) -> 0 | G12: =SUMIF(②시니어_CF!$E$7:$EF$7,G$3,②시니어_CF!$E$64:$EF$64) -> 0 | H12: =SUMIF(②시니어_CF!$E$7:$EF$7,H$3,②시니어_CF!$E$64:$EF$64) -> 4591.644 | I12: =SUMIF(②시니어_CF!$E$7:$EF$7,I$3,②시니어_CF!$E$64:$EF$64) -> 6399.9149 | J12: =SUMIF(②시니어_CF!$E$7:$EF$7,J$3,②시니어_CF!$E$64:$EF$64) -> 6687.535 | ... M12: =SUMIF(②시니어_CF!$E$7:$EF$7,M$3,②시니어_CF!$E$64:$EF$64) -> 1163.4206
A13: 공통비용·리츠운용비 | B13: =SUM(C13:M13) -> 26180.023 | C13: =SUMIF(②시니어_CF!$E$7:$EF$7,C$3,②시니어_CF!$E$74:$EF$74) -> 0 | D13: =SUMIF(②시니어_CF!$E$7:$EF$7,D$3,②시니어_CF!$E$74:$EF$74) -> 0 | E13: =SUMIF(②시니어_CF!$E$7:$EF$7,E$3,②시니어_CF!$E$74:$EF$74) -> 0 | F13: =SUMIF(②시니어_CF!$E$7:$EF$7,F$3,②시니어_CF!$E$74:$EF$74) -> 0 | G13: =SUMIF(②시니어_CF!$E$7:$EF$7,G$3,②시니어_CF!$E$74:$EF$74) -> 0 | H13: =SUMIF(②시니어_CF!$E$7:$EF$7,H$3,②시니어_CF!$E$74:$EF$74) -> 3808.542 | I13: =SUMIF(②시니어_CF!$E$7:$EF$7,I$3,②시니어_CF!$E$74:$EF$74) -> 4927.7251 | J13: =SUMIF(②시니어_CF!$E$7:$EF$7,J$3,②시니어_CF!$E$74:$EF$74) -> 5056.4946 | ... M13: =SUMIF(②시니어_CF!$E$7:$EF$7,M$3,②시니어_CF!$E$74:$EF$74) -> 2168.7079
A14: 운영현금흐름 | B14: =SUM(C14:M14) -> 6441.4891 | C14: =SUMIF(②시니어_CF!$E$7:$EF$7,C$3,②시니어_CF!$E$75:$EF$75) -> 0 | D14: =SUMIF(②시니어_CF!$E$7:$EF$7,D$3,②시니어_CF!$E$75:$EF$75) -> 0 | E14: =SUMIF(②시니어_CF!$E$7:$EF$7,E$3,②시니어_CF!$E$75:$EF$75) -> 0 | F14: =SUMIF(②시니어_CF!$E$7:$EF$7,F$3,②시니어_CF!$E$75:$EF$75) -> 0 | G14: =SUMIF(②시니어_CF!$E$7:$EF$7,G$3,②시니어_CF!$E$75:$EF$75) -> 0 | H14: =SUMIF(②시니어_CF!$E$7:$EF$7,H$3,②시니어_CF!$E$75:$EF$75) -> 783.10205 | I14: =SUMIF(②시니어_CF!$E$7:$EF$7,I$3,②시니어_CF!$E$75:$EF$75) -> 1472.1898 | J14: =SUMIF(②시니어_CF!$E$7:$EF$7,J$3,②시니어_CF!$E$75:$EF$75) -> 1631.0404 | ... M14: =SUMIF(②시니어_CF!$E$7:$EF$7,M$3,②시니어_CF!$E$75:$EF$75) -> -1005.2873
A15: 개발 및 금융
A16: 개발사업비 집행 | B16: =SUM(C16:M16) -> 403110.36 | C16: =SUMIF(②시니어_CF!$E$7:$EF$7,C$3,②시니어_CF!$E$100:$EF$100) -> 5014.9825 | D16: =SUMIF(②시니어_CF!$E$7:$EF$7,D$3,②시니어_CF!$E$100:$EF$100) -> 72571.342 | E16: =SUMIF(②시니어_CF!$E$7:$EF$7,E$3,②시니어_CF!$E$100:$EF$100) -> 91218.189 | F16: =SUMIF(②시니어_CF!$E$7:$EF$7,F$3,②시니어_CF!$E$100:$EF$100) -> 131514.74 | G16: =SUMIF(②시니어_CF!$E$7:$EF$7,G$3,②시니어_CF!$E$100:$EF$100) -> 76365.512 | H16: =SUMIF(②시니어_CF!$E$7:$EF$7,H$3,②시니어_CF!$E$100:$EF$100) -> 26425.597 | I16: =SUMIF(②시니어_CF!$E$7:$EF$7,I$3,②시니어_CF!$E$100:$EF$100) -> 0 | J16: =SUMIF(②시니어_CF!$E$7:$EF$7,J$3,②시니어_CF!$E$100:$EF$100) -> 0 | ... M16: =SUMIF(②시니어_CF!$E$7:$EF$7,M$3,②시니어_CF!$E$100:$EF$100) -> 0
A17: PF 금융비용 | B17: =SUM(C17:M17) -> 11165.567 | C17: =SUMIF(②시니어_CF!$E$7:$EF$7,C$3,②시니어_CF!$E$112:$EF$112) -> 0 | D17: =SUMIF(②시니어_CF!$E$7:$EF$7,D$3,②시니어_CF!$E$112:$EF$112) -> 3703.6763 | E17: =SUMIF(②시니어_CF!$E$7:$EF$7,E$3,②시니어_CF!$E$112:$EF$112) -> 1587.2898 | F17: =SUMIF(②시니어_CF!$E$7:$EF$7,F$3,②시니어_CF!$E$112:$EF$112) -> 1587.2898 | G17: =SUMIF(②시니어_CF!$E$7:$EF$7,G$3,②시니어_CF!$E$112:$EF$112) -> 3646.3955 | H17: =SUMIF(②시니어_CF!$E$7:$EF$7,H$3,②시니어_CF!$E$112:$EF$112) -> 640.91596 | I17: =SUMIF(②시니어_CF!$E$7:$EF$7,I$3,②시니어_CF!$E$112:$EF$112) -> 0 | J17: =SUMIF(②시니어_CF!$E$7:$EF$7,J$3,②시니어_CF!$E$112:$EF$112) -> 0 | ... M17: =SUMIF(②시니어_CF!$E$7:$EF$7,M$3,②시니어_CF!$E$112:$EF$112) -> 0
A18: 담보대출 이자 | B18: =SUM(C18:M18) -> 12812.877 | C18: =SUMIF(②시니어_CF!$E$7:$EF$7,C$3,②시니어_CF!$E$129:$EF$129) -> 0 | D18: =SUMIF(②시니어_CF!$E$7:$EF$7,D$3,②시니어_CF!$E$129:$EF$129) -> 0 | E18: =SUMIF(②시니어_CF!$E$7:$EF$7,E$3,②시니어_CF!$E$129:$EF$129) -> 0 | F18: =SUMIF(②시니어_CF!$E$7:$EF$7,F$3,②시니어_CF!$E$129:$EF$129) -> 0 | G18: =SUMIF(②시니어_CF!$E$7:$EF$7,G$3,②시니어_CF!$E$129:$EF$129) -> 0 | H18: =SUMIF(②시니어_CF!$E$7:$EF$7,H$3,②시니어_CF!$E$129:$EF$129) -> 2135.4795 | I18: =SUMIF(②시니어_CF!$E$7:$EF$7,I$3,②시니어_CF!$E$129:$EF$129) -> 2562.5754 | J18: =SUMIF(②시니어_CF!$E$7:$EF$7,J$3,②시니어_CF!$E$129:$EF$129) -> 2562.5754 | ... M18: =SUMIF(②시니어_CF!$E$7:$EF$7,M$3,②시니어_CF!$E$129:$EF$129) -> 427.0959
A19: 담보대출 취급수수료 | B19: =SUM(C19:M19) -> 474.551 | C19: =SUMIF(②시니어_CF!$E$7:$EF$7,C$3,②시니어_CF!$E$128:$EF$128) -> 0 | D19: =SUMIF(②시니어_CF!$E$7:$EF$7,D$3,②시니어_CF!$E$128:$EF$128) -> 0 | E19: =SUMIF(②시니어_CF!$E$7:$EF$7,E$3,②시니어_CF!$E$128:$EF$128) -> 0 | F19: =SUMIF(②시니어_CF!$E$7:$EF$7,F$3,②시니어_CF!$E$128:$EF$128) -> 0 | G19: =SUMIF(②시니어_CF!$E$7:$EF$7,G$3,②시니어_CF!$E$128:$EF$128) -> 0 | H19: =SUMIF(②시니어_CF!$E$7:$EF$7,H$3,②시니어_CF!$E$128:$EF$128) -> 474.551 | I19: =SUMIF(②시니어_CF!$E$7:$EF$7,I$3,②시니어_CF!$E$128:$EF$128) -> 0 | J19: =SUMIF(②시니어_CF!$E$7:$EF$7,J$3,②시니어_CF!$E$128:$EF$128) -> 0 | ... M19: =SUMIF(②시니어_CF!$E$7:$EF$7,M$3,②시니어_CF!$E$128:$EF$128) -> 0
A20: 자금 유출입
A21: Equity 납입 | B21: =SUM(C21:M21) -> 79364.491 | C21: =SUMIF(②시니어_CF!$E$7:$EF$7,C$3,②시니어_CF!$E$142:$EF$142) -> 4369.0152 | D21: =SUMIF(②시니어_CF!$E$7:$EF$7,D$3,②시니어_CF!$E$142:$EF$142) -> 74995.476 | E21: =SUMIF(②시니어_CF!$E$7:$EF$7,E$3,②시니어_CF!$E$142:$EF$142) -> 0 | F21: =SUMIF(②시니어_CF!$E$7:$EF$7,F$3,②시니어_CF!$E$142:$EF$142) -> 0 | G21: =SUMIF(②시니어_CF!$E$7:$EF$7,G$3,②시니어_CF!$E$142:$EF$142) -> 0 | H21: =SUMIF(②시니어_CF!$E$7:$EF$7,H$3,②시니어_CF!$E$142:$EF$142) -> 0 | I21: =SUMIF(②시니어_CF!$E$7:$EF$7,I$3,②시니어_CF!$E$142:$EF$142) -> 0 | J21: =SUMIF(②시니어_CF!$E$7:$EF$7,J$3,②시니어_CF!$E$142:$EF$142) -> 0 | ... M21: =SUMIF(②시니어_CF!$E$7:$EF$7,M$3,②시니어_CF!$E$142:$EF$142) -> 0
A22: 보증금 유입 | B22: =SUM(C22:M22) -> 541500 | C22: =SUMIF(②시니어_CF!$E$7:$EF$7,C$3,②시니어_CF!$E$84:$EF$84) -> 0 | D22: =SUMIF(②시니어_CF!$E$7:$EF$7,D$3,②시니어_CF!$E$84:$EF$84) -> 43200 | E22: =SUMIF(②시니어_CF!$E$7:$EF$7,E$3,②시니어_CF!$E$84:$EF$84) -> 86400 | F22: =SUMIF(②시니어_CF!$E$7:$EF$7,F$3,②시니어_CF!$E$84:$EF$84) -> 86400 | G22: =SUMIF(②시니어_CF!$E$7:$EF$7,G$3,②시니어_CF!$E$84:$EF$84) -> 86400 | H22: =SUMIF(②시니어_CF!$E$7:$EF$7,H$3,②시니어_CF!$E$84:$EF$84) -> 131100 | I22: =SUMIF(②시니어_CF!$E$7:$EF$7,I$3,②시니어_CF!$E$84:$EF$84) -> 108000 | J22: =SUMIF(②시니어_CF!$E$7:$EF$7,J$3,②시니어_CF!$E$84:$EF$84) -> 0 | ... M22: =SUMIF(②시니어_CF!$E$7:$EF$7,M$3,②시니어_CF!$E$84:$EF$84) -> 0
A23: 보증금 승계(처분) | B23: =SUM(C23:M23) -> 541500 | C23: =SUMIF(②시니어_CF!$E$7:$EF$7,C$3,②시니어_CF!$E$85:$EF$85) -> 0 | D23: =SUMIF(②시니어_CF!$E$7:$EF$7,D$3,②시니어_CF!$E$85:$EF$85) -> 0 | E23: =SUMIF(②시니어_CF!$E$7:$EF$7,E$3,②시니어_CF!$E$85:$EF$85) -> 0 | F23: =SUMIF(②시니어_CF!$E$7:$EF$7,F$3,②시니어_CF!$E$85:$EF$85) -> 0 | G23: =SUMIF(②시니어_CF!$E$7:$EF$7,G$3,②시니어_CF!$E$85:$EF$85) -> 0 | H23: =SUMIF(②시니어_CF!$E$7:$EF$7,H$3,②시니어_CF!$E$85:$EF$85) -> 0 | I23: =SUMIF(②시니어_CF!$E$7:$EF$7,I$3,②시니어_CF!$E$85:$EF$85) -> 0 | J23: =SUMIF(②시니어_CF!$E$7:$EF$7,J$3,②시니어_CF!$E$85:$EF$85) -> 0 | ... M23: =SUMIF(②시니어_CF!$E$7:$EF$7,M$3,②시니어_CF!$E$85:$EF$85) -> 541500
A24: PF 인출 | B24: =SUM(C24:M24) -> 27207.3 | C24: =SUMIF(②시니어_CF!$E$7:$EF$7,C$3,②시니어_CF!$E$116:$EF$116) -> 0 | D24: =SUMIF(②시니어_CF!$E$7:$EF$7,D$3,②시니어_CF!$E$116:$EF$116) -> 0 | E24: =SUMIF(②시니어_CF!$E$7:$EF$7,E$3,②시니어_CF!$E$116:$EF$116) -> 0 | F24: =SUMIF(②시니어_CF!$E$7:$EF$7,F$3,②시니어_CF!$E$116:$EF$116) -> 7885.8249 | G24: =SUMIF(②시니어_CF!$E$7:$EF$7,G$3,②시니어_CF!$E$116:$EF$116) -> 19321.475 | H24: =SUMIF(②시니어_CF!$E$7:$EF$7,H$3,②시니어_CF!$E$116:$EF$116) -> 0 | I24: =SUMIF(②시니어_CF!$E$7:$EF$7,I$3,②시니어_CF!$E$116:$EF$116) -> 0 | J24: =SUMIF(②시니어_CF!$E$7:$EF$7,J$3,②시니어_CF!$E$116:$EF$116) -> 0 | ... M24: =SUMIF(②시니어_CF!$E$7:$EF$7,M$3,②시니어_CF!$E$116:$EF$116) -> 0
A25: PF 상환 | B25: =SUM(C25:M25) -> 27207.3 | C25: =SUMIF(②시니어_CF!$E$7:$EF$7,C$3,②시니어_CF!$E$120:$EF$120) -> 0 | D25: =SUMIF(②시니어_CF!$E$7:$EF$7,D$3,②시니어_CF!$E$120:$EF$120) -> 0 | E25: =SUMIF(②시니어_CF!$E$7:$EF$7,E$3,②시니어_CF!$E$120:$EF$120) -> 0 | F25: =SUMIF(②시니어_CF!$E$7:$EF$7,F$3,②시니어_CF!$E$120:$EF$120) -> 0 | G25: =SUMIF(②시니어_CF!$E$7:$EF$7,G$3,②시니어_CF!$E$120:$EF$120) -> 0 | H25: =SUMIF(②시니어_CF!$E$7:$EF$7,H$3,②시니어_CF!$E$120:$EF$120) -> 27207.3 | I25: =SUMIF(②시니어_CF!$E$7:$EF$7,I$3,②시니어_CF!$E$120:$EF$120) -> 0 | J25: =SUMIF(②시니어_CF!$E$7:$EF$7,J$3,②시니어_CF!$E$120:$EF$120) -> 0 | ... M25: =SUMIF(②시니어_CF!$E$7:$EF$7,M$3,②시니어_CF!$E$120:$EF$120) -> 0
A26: 담보대출 인출 | B26: =SUM(C26:M26) -> 47455.1 | C26: =SUMIF(②시니어_CF!$E$7:$EF$7,C$3,②시니어_CF!$E$127:$EF$127) -> 0 | D26: =SUMIF(②시니어_CF!$E$7:$EF$7,D$3,②시니어_CF!$E$127:$EF$127) -> 0 | E26: =SUMIF(②시니어_CF!$E$7:$EF$7,E$3,②시니어_CF!$E$127:$EF$127) -> 0 | F26: =SUMIF(②시니어_CF!$E$7:$EF$7,F$3,②시니어_CF!$E$127:$EF$127) -> 0 | G26: =SUMIF(②시니어_CF!$E$7:$EF$7,G$3,②시니어_CF!$E$127:$EF$127) -> 0 | H26: =SUMIF(②시니어_CF!$E$7:$EF$7,H$3,②시니어_CF!$E$127:$EF$127) -> 47455.1 | I26: =SUMIF(②시니어_CF!$E$7:$EF$7,I$3,②시니어_CF!$E$127:$EF$127) -> 0 | J26: =SUMIF(②시니어_CF!$E$7:$EF$7,J$3,②시니어_CF!$E$127:$EF$127) -> 0 | ... M26: =SUMIF(②시니어_CF!$E$7:$EF$7,M$3,②시니어_CF!$E$127:$EF$127) -> 0
A27: 담보대출 상환 | B27: =SUM(C27:M27) -> 47455.1 | C27: =SUMIF(②시니어_CF!$E$7:$EF$7,C$3,②시니어_CF!$E$130:$EF$130) -> 0 | D27: =SUMIF(②시니어_CF!$E$7:$EF$7,D$3,②시니어_CF!$E$130:$EF$130) -> 0 | E27: =SUMIF(②시니어_CF!$E$7:$EF$7,E$3,②시니어_CF!$E$130:$EF$130) -> 0 | F27: =SUMIF(②시니어_CF!$E$7:$EF$7,F$3,②시니어_CF!$E$130:$EF$130) -> 0 | G27: =SUMIF(②시니어_CF!$E$7:$EF$7,G$3,②시니어_CF!$E$130:$EF$130) -> 0 | H27: =SUMIF(②시니어_CF!$E$7:$EF$7,H$3,②시니어_CF!$E$130:$EF$130) -> 0 | I27: =SUMIF(②시니어_CF!$E$7:$EF$7,I$3,②시니어_CF!$E$130:$EF$130) -> 0 | J27: =SUMIF(②시니어_CF!$E$7:$EF$7,J$3,②시니어_CF!$E$130:$EF$130) -> 0 | ... M27: =SUMIF(②시니어_CF!$E$7:$EF$7,M$3,②시니어_CF!$E$130:$EF$130) -> 47455.1
A28: 매각대금 | B28: =SUM(C28:M28) -> 174513.09 | C28: =SUMIF(②시니어_CF!$E$7:$EF$7,C$3,②시니어_CF!$E$145:$EF$145) -> 0 | D28: =SUMIF(②시니어_CF!$E$7:$EF$7,D$3,②시니어_CF!$E$145:$EF$145) -> 0 | E28: =SUMIF(②시니어_CF!$E$7:$EF$7,E$3,②시니어_CF!$E$145:$EF$145) -> 0 | F28: =SUMIF(②시니어_CF!$E$7:$EF$7,F$3,②시니어_CF!$E$145:$EF$145) -> 0 | G28: =SUMIF(②시니어_CF!$E$7:$EF$7,G$3,②시니어_CF!$E$145:$EF$145) -> 0 | H28: =SUMIF(②시니어_CF!$E$7:$EF$7,H$3,②시니어_CF!$E$145:$EF$145) -> 0 | I28: =SUMIF(②시니어_CF!$E$7:$EF$7,I$3,②시니어_CF!$E$145:$EF$145) -> 0 | J28: =SUMIF(②시니어_CF!$E$7:$EF$7,J$3,②시니어_CF!$E$145:$EF$145) -> 0 | ... M28: =SUMIF(②시니어_CF!$E$7:$EF$7,M$3,②시니어_CF!$E$145:$EF$145) -> 174513.09
A29: 분배
A30: 우선주 배당 | B30: =SUM(C30:M30) -> 23865.04 | C30: =SUMIF(②시니어_CF!$E$7:$EF$7,C$3,②시니어_CF!$E$165:$EF$165) -> 0 | D30: =SUMIF(②시니어_CF!$E$7:$EF$7,D$3,②시니어_CF!$E$165:$EF$165) -> 0 | E30: =SUMIF(②시니어_CF!$E$7:$EF$7,E$3,②시니어_CF!$E$165:$EF$165) -> 0 | F30: =SUMIF(②시니어_CF!$E$7:$EF$7,F$3,②시니어_CF!$E$165:$EF$165) -> 0 | G30: =SUMIF(②시니어_CF!$E$7:$EF$7,G$3,②시니어_CF!$E$165:$EF$165) -> 0 | H30: =SUMIF(②시니어_CF!$E$7:$EF$7,H$3,②시니어_CF!$E$165:$EF$165) -> 7741.9238 | I30: =SUMIF(②시니어_CF!$E$7:$EF$7,I$3,②시니어_CF!$E$165:$EF$165) -> 5706.6878 | J30: =SUMIF(②시니어_CF!$E$7:$EF$7,J$3,②시니어_CF!$E$165:$EF$165) -> 4757.9651 | ... M30: =SUMIF(②시니어_CF!$E$7:$EF$7,M$3,②시니어_CF!$E$165:$EF$165) -> 226.33853
A31: 우선주 원금상환 | B31: =SUM(C31:M31) -> 0 | C31: =SUMIF(②시니어_CF!$E$7:$EF$7,C$3,②시니어_CF!$E$166:$EF$166) -> 0 | D31: =SUMIF(②시니어_CF!$E$7:$EF$7,D$3,②시니어_CF!$E$166:$EF$166) -> 0 | E31: =SUMIF(②시니어_CF!$E$7:$EF$7,E$3,②시니어_CF!$E$166:$EF$166) -> 0 | F31: =SUMIF(②시니어_CF!$E$7:$EF$7,F$3,②시니어_CF!$E$166:$EF$166) -> 0 | G31: =SUMIF(②시니어_CF!$E$7:$EF$7,G$3,②시니어_CF!$E$166:$EF$166) -> 0 | H31: =SUMIF(②시니어_CF!$E$7:$EF$7,H$3,②시니어_CF!$E$166:$EF$166) -> 0 | I31: =SUMIF(②시니어_CF!$E$7:$EF$7,I$3,②시니어_CF!$E$166:$EF$166) -> 0 | J31: =SUMIF(②시니어_CF!$E$7:$EF$7,J$3,②시니어_CF!$E$166:$EF$166) -> 0 | ... M31: =SUMIF(②시니어_CF!$E$7:$EF$7,M$3,②시니어_CF!$E$166:$EF$166) -> 0
A32: 보통주 분배 | B32: =SUM(C32:M32) -> 10482.88 | C32: =SUMIF(②시니어_CF!$E$7:$EF$7,C$3,②시니어_CF!$E$168:$EF$168) -> 0 | D32: =SUMIF(②시니어_CF!$E$7:$EF$7,D$3,②시니어_CF!$E$168:$EF$168) -> 0 | E32: =SUMIF(②시니어_CF!$E$7:$EF$7,E$3,②시니어_CF!$E$168:$EF$168) -> 0 | F32: =SUMIF(②시니어_CF!$E$7:$EF$7,F$3,②시니어_CF!$E$168:$EF$168) -> 0 | G32: =SUMIF(②시니어_CF!$E$7:$EF$7,G$3,②시니어_CF!$E$168:$EF$168) -> 0 | H32: =SUMIF(②시니어_CF!$E$7:$EF$7,H$3,②시니어_CF!$E$168:$EF$168) -> 0 | I32: =SUMIF(②시니어_CF!$E$7:$EF$7,I$3,②시니어_CF!$E$168:$EF$168) -> 0 | J32: =SUMIF(②시니어_CF!$E$7:$EF$7,J$3,②시니어_CF!$E$168:$EF$168) -> 1917.5733 | ... M32: =SUMIF(②시니어_CF!$E$7:$EF$7,M$3,②시니어_CF!$E$168:$EF$168) -> 347.99116
A33: 보통주 CF | B33: =SUM(C33:M33) -> -13326.467 | C33: =SUMIF(②시니어_CF!$E$7:$EF$7,C$3,②시니어_CF!$E$171:$EF$171) -> -4369.0152 | D33: =SUMIF(②시니어_CF!$E$7:$EF$7,D$3,②시니어_CF!$E$171:$EF$171) -> -19440.332 | E33: =SUMIF(②시니어_CF!$E$7:$EF$7,E$3,②시니어_CF!$E$171:$EF$171) -> 0 | F33: =SUMIF(②시니어_CF!$E$7:$EF$7,F$3,②시니어_CF!$E$171:$EF$171) -> 0 | G33: =SUMIF(②시니어_CF!$E$7:$EF$7,G$3,②시니어_CF!$E$171:$EF$171) -> 0 | H33: =SUMIF(②시니어_CF!$E$7:$EF$7,H$3,②시니어_CF!$E$171:$EF$171) -> 0 | I33: =SUMIF(②시니어_CF!$E$7:$EF$7,I$3,②시니어_CF!$E$171:$EF$171) -> 0 | J33: =SUMIF(②시니어_CF!$E$7:$EF$7,J$3,②시니어_CF!$E$171:$EF$171) -> 1917.5733 | ... M33: =SUMIF(②시니어_CF!$E$7:$EF$7,M$3,②시니어_CF!$E$171:$EF$171) -> 347.99116
A34: 우선주 CF | B34: =SUM(C34:M34) -> -31690.104 | C34: =SUMIF(②시니어_CF!$E$7:$EF$7,C$3,②시니어_CF!$E$172:$EF$172) -> 0 | D34: =SUMIF(②시니어_CF!$E$7:$EF$7,D$3,②시니어_CF!$E$172:$EF$172) -> -55555.144 | E34: =SUMIF(②시니어_CF!$E$7:$EF$7,E$3,②시니어_CF!$E$172:$EF$172) -> 0 | F34: =SUMIF(②시니어_CF!$E$7:$EF$7,F$3,②시니어_CF!$E$172:$EF$172) -> 0 | G34: =SUMIF(②시니어_CF!$E$7:$EF$7,G$3,②시니어_CF!$E$172:$EF$172) -> 0 | H34: =SUMIF(②시니어_CF!$E$7:$EF$7,H$3,②시니어_CF!$E$172:$EF$172) -> 7741.9238 | I34: =SUMIF(②시니어_CF!$E$7:$EF$7,I$3,②시니어_CF!$E$172:$EF$172) -> 5706.6878 | J34: =SUMIF(②시니어_CF!$E$7:$EF$7,J$3,②시니어_CF!$E$172:$EF$172) -> 4757.9651 | ... M34: =SUMIF(②시니어_CF!$E$7:$EF$7,M$3,②시니어_CF!$E$172:$EF$172) -> 226.33853
A35: 전체 Equity CF | B35: =SUM(C35:M35) -> -45016.571 | C35: =SUMIF(②시니어_CF!$E$7:$EF$7,C$3,②시니어_CF!$E$173:$EF$173) -> -4369.0152 | D35: =SUMIF(②시니어_CF!$E$7:$EF$7,D$3,②시니어_CF!$E$173:$EF$173) -> -74995.476 | E35: =SUMIF(②시니어_CF!$E$7:$EF$7,E$3,②시니어_CF!$E$173:$EF$173) -> 0 | F35: =SUMIF(②시니어_CF!$E$7:$EF$7,F$3,②시니어_CF!$E$173:$EF$173) -> 0 | G35: =SUMIF(②시니어_CF!$E$7:$EF$7,G$3,②시니어_CF!$E$173:$EF$173) -> 0 | H35: =SUMIF(②시니어_CF!$E$7:$EF$7,H$3,②시니어_CF!$E$173:$EF$173) -> 7741.9238 | I35: =SUMIF(②시니어_CF!$E$7:$EF$7,I$3,②시니어_CF!$E$173:$EF$173) -> 5706.6878 | J35: =SUMIF(②시니어_CF!$E$7:$EF$7,J$3,②시니어_CF!$E$173:$EF$173) -> 6675.5384 | ... M35: =SUMIF(②시니어_CF!$E$7:$EF$7,M$3,②시니어_CF!$E$173:$EF$173) -> 574.32969
A36: 기말현금 | C36: =SUMIF(②시니어_CF!$E$6:$EF$6,MIN(DATE(C$3,12,31),②시니어_가정!$E$24),②시니어_CF!$E$159:$EF$159)*(C$3<=YEAR(②시니어_가정!$E$24)) -> -621.58057 | D36: =SUMIF(②시니어_CF!$E$6:$EF$6,MIN(DATE(D$3,12,31),②시니어_가정!$E$24),②시니어_CF!$E$159:$EF$159)*(D$3<=YEAR(②시니어_가정!$E$24)) -> 42291.183 | E36: =SUMIF(②시니어_CF!$E$6:$EF$6,MIN(DATE(E$3,12,31),②시니어_가정!$E$24),②시니어_CF!$E$159:$EF$159)*(E$3<=YEAR(②시니어_가정!$E$24)) -> 38062.047 | F36: =SUMIF(②시니어_CF!$E$6:$EF$6,MIN(DATE(F$3,12,31),②시니어_가정!$E$24),②시니어_CF!$E$159:$EF$159)*(F$3<=YEAR(②시니어_가정!$E$24)) -> 500 | G36: =SUMIF(②시니어_CF!$E$6:$EF$6,MIN(DATE(G$3,12,31),②시니어_가정!$E$24),②시니어_CF!$E$159:$EF$159)*(G$3<=YEAR(②시니어_가정!$E$24)) -> 27355.168 | H36: =SUMIF(②시니어_CF!$E$6:$EF$6,MIN(DATE(H$3,12,31),②시니어_가정!$E$24),②시니어_CF!$E$159:$EF$159)*(H$3<=YEAR(②시니어_가정!$E$24)) -> 145569.11 | I36: =SUMIF(②시니어_CF!$E$6:$EF$6,MIN(DATE(I$3,12,31),②시니어_가정!$E$24),②시니어_CF!$E$159:$EF$159)*(I$3<=YEAR(②시니어_가정!$E$24)) -> 253569.11 | J36: =SUMIF(②시니어_CF!$E$6:$EF$6,MIN(DATE(J$3,12,31),②시니어_가정!$E$24),②시니어_CF!$E$159:$EF$159)*(J$3<=YEAR(②시니어_가정!$E$24)) -> 253569.11 | ... M36: =SUMIF(②시니어_CF!$E$6:$EF$6,MIN(DATE(M$3,12,31),②시니어_가정!$E$24),②시니어_CF!$E$159:$EF$159)*(M$3<=YEAR(②시니어_가정!$E$24)) -> -161611.76
A38: IRR (보통주) | B38: =②시니어_CF!$C$171 -> -0.1050309
A39: IRR (우선주) | B39: =②시니어_CF!$C$172 -> -0.14547119
A40: IRR (전체) | B40: =②시니어_CF!$C$173 -> -0.12979711

Sheet ③기타_가정
B1: 센텀C부지 복합개발사업 재무모델 | I1: 입력값 | J1: 파란 글씨 = 입력(하드코딩)
B2: ③ 레지던스·호텔·오피스·부대시설 Vehicle — Assumption (단위: 백만원) | I2: 수식 | J2: 검정 = 계산 수식
C3: =IF(ABS(③기타_CF!$C$159)<1,"OK","Error") -> OK | D3: =IF(SUMPRODUCT(ABS($F$560:$F$569))<1,"OK","Run Macro") -> OK | E3: =IF(MIN(③기타_CF!$E$159:$EF$159)>-0.5,"OK","Shortage") -> OK | F3: =IF(SUM(③기타_CF!$E$153:$EF$153)-SUM(③기타_CF!$E$116:$EF$116)<1,"OK","PF한도부족") -> OK | I3: 연결 | J3: 초록 = CF 시트 연결
C4: Balance Check | D4: Macro Check | E4: Shortage Check | F4: Cash Check | I4: Macro | J4: 노랑 = Macro Paste 값(순환참조 차단)
A6: 프로젝트 일정 (계획)
B8: 리츠설립일 | D8: Date | E8: 46112
B9: 매매계약체결 준비기간 | D9: Months | E9: 3
B10: 토지매매계약체결일 | D10: Date | E10: =EOMONTH($E$8,$E$9) -> 46203
B11: 인허가 준비기간 | D11: Months | E11: 14
B12: 인허가 완료일 | D12: Date | E12: =EOMONTH($E$10,$E$11) -> 46630
B13: 공사준비기간 | D13: Months | E13: 1
B14: 착공일 | D14: Date | E14: =EOMONTH($E$12,$E$13) -> 46660
B15: 공사기간 | D15: Months | E15: 42
B16: 준공일 | D16: Date | E16: =EOMONTH($E$14,$E$15-1) -> 47907
B17: 운영준비기간 | D17: Months | E17: 1
B18: 운영개시일 | D18: Date | E18: =EOMONTH($E$16,$E$17) -> 47938
B19: 운영기간 | D19: Months | E19: 60
B20: 운영종료일 | D20: Date | E20: =EOMONTH($E$18,$E$19-1) -> 49734
B21: 처분준비기간 | D21: Months | E21: 0
B22: 처분일 | D22: Date | E22: =EOMONTH($E$20,$E$21) -> 49734
B23: 청산준비기간 | D23: Months | E23: 3
B24: 리츠청산일 | D24: Date | E24: =EOMONTH($E$22,$E$23) -> 49826
B25: 개발기간(설립~준공) | D25: Years | E25: =((YEAR($E$16)-YEAR($E$8))*12+MONTH($E$16)-MONTH($E$8)+1)/12 -> 5
B26: 리츠운용기간(운영개시~청산) | D26: Years | E26: =((YEAR($E$24)-YEAR($E$18))*12+MONTH($E$24)-MONTH($E$18)+1)/12 -> 5.25
A28: Results
B30: IRR On Equity (보통주) | E30: =③기타_CF!$C$171 -> 0.29508635
